Workbook

Sheet 每日指數值
A1: date | B1: price_index | C1: total_return_index | D1: price_daily_return | E1: tr_daily_return
A2: 2024-01-03 | B2: 100 | C2: 100
A3: 2024-01-04 | B3: 100.0275 | C3: 100.24659 | D3: 0.00027504329 | E3: 0.0024659266
A4: 2024-01-05 | B4: 99.387924 | C4: 99.605612 | D4: -0.0063940441 | E4: -0.0063940441
A5: 2024-01-08 | B5: 100.19869 | C5: 100.41815 | D5: 0.008157569 | E5: 0.008157569
A6: 2024-01-09 | B6: 100.66359 | C6: 100.88407 | D6: 0.0046398346 | E6: 0.0046398346
A7: 2024-01-10 | B7: 100.26211 | C7: 100.48171 | D7: -0.0039883706 | E7: -0.0039883706
A8: 2024-01-11 | B8: 100.55541 | C8: 100.77565 | D8: 0.0029253062 | E8: 0.0029253062
A9: 2024-01-12 | B9: 100.31816 | C9: 100.53789 | D9: -0.0023593448 | E9: -0.0023593448
A10: 2024-01-15 | B10: 100.53411 | C10: 100.75431 | D10: 0.002152634 | E10: 0.002152634
A11: 2024-01-16 | B11: 99.431372 | C11: 99.649154 | D11: -0.010968799 | E11: -0.010968799
A12: 2024-01-17 | B12: 99.328749 | C12: 99.546307 | D12: -0.0010320983 | E12: -0.0010320983
A13: 2024-01-18 | B13: 100.59853 | C13: 100.81887 | D13: 0.012783619 | E13: 0.012783619
A14: 2024-01-19 | B14: 106.34298 | C14: 106.5759 | D14: 0.05710274 | E14: 0.05710274
... A479: 2025-12-22 | B479: 240.42641 | C479: 250.01999 | D479: 0.024743515 | E479: 0.024743515

Sheet 投資後權重
A1: date | B1: 2308 | C1: 2317 | D1: 2330 | E1: 2454 | F1: 權重驗證 | G1: 2308 | H1: 2317 | I1: 2330 | J1: 2454 | K1: 2308 | L1: 2317 | M1: 2330 | N1: 2454 | O1: 現金股利殖利率
A2: 2024-01-03 | B2: 0 | C2: 0.080652758 | D2: 0.83447278 | E2: 0.084874462 | F2: =SUM(B2:E2) -> 1 | K2: =IFERROR(G3/每日收盤價!B2,0) -> 0 | L2: =IFERROR(H3/每日收盤價!C2,0) -> 0 | M2: =IFERROR(I3/每日收盤價!D2,0) -> 0 | N2: =IFERROR(J3/每日收盤價!E2,0) -> 0.025813221 | O2: =SUM(K2:N2) -> 0.025813221
A3: 2024-01-04 | B3: =B2*(1+$O2)*(1+每日報酬率!B3) -> 0 | C3: =C2*(1+每日報酬率!C3)*(1+$E2*$O2) -> 0.080442715 | D3: =D2*(1+每日報酬率!D3)*(1+$E2*$O2) -> 0.83919479 | E3: =E2*(1+每日報酬率!E3-O2)*(1+$E2*$O2) -> 0.080633344 | F3: =SUM(B3:E3) -> 1.0002708 | J3: 24.6 | K3: =IFERROR(G4/每日收盤價!B3,0) -> 0 | L3: =IFERROR(H4/每日收盤價!C3,0) -> 0 | M3: =IFERROR(I4/每日收盤價!D3,0) -> 0 | N3: =IFERROR(J4/每日收盤價!E3,0) -> 0 | O3: =SUM(K3:N3) -> 0
A4: 2024-01-05 | B4: =B3*(1+$CD$2)*(1+每日報酬率!B4) -> 0 | C4: =C3*(1+$CD$2)*(1+每日報酬率!C4) -> 0.080442715 | D4: =D3*(1+$CD$2)*(1+每日報酬率!D4) -> 0.83340724 | E4: =E3*(1+$CD$2)*(1+每日報酬率!E4) -> 0.080025118 | F4: =SUM(B4:E4) -> 0.99387507 | K4: =IFERROR(G5/每日收盤價!B4,0) -> 0 | L4: =IFERROR(H5/每日收盤價!C4,0) -> 0 | M4: =IFERROR(I5/每日收盤價!D4,0) -> 0 | N4: =IFERROR(J5/每日收盤價!E4,0) -> 0 | O4: =SUM(K4:N4) -> 0
A5: 2024-01-08 | B5: =B4*(1+$CD$2)*(1+每日報酬率!B5) -> 0 | C5: =C4*(1+$CD$2)*(1+每日報酬率!C5) -> 0.078508996 | D5: =D4*(1+$CD$2)*(1+每日報酬率!D5) -> 0.84353545 | E5: =E4*(1+$CD$2)*(1+每日報酬率!E5) -> 0.079938229 | F5: =SUM(B5:E5) -> 1.0019827 | K5: =IFERROR(G6/每日收盤價!B5,0) -> 0 | L5: =IFERROR(H6/每日收盤價!C5,0) -> 0 | M5: =IFERROR(I6/每日收盤價!D5,0) -> 0 | N5: =IFERROR(J6/每日收盤價!E5,0) -> 0 | O5: =SUM(K5:N5) -> 0
A6: 2024-01-09 | B6: =B5*(1+$CD$2)*(1+每日報酬率!B6) -> 0 | C6: =C5*(1+$CD$2)*(1+每日報酬率!C6) -> 0.078122252 | D6: =D5*(1+$CD$2)*(1+每日報酬率!D6) -> 0.84787611 | E6: =E5*(1+$CD$2)*(1+每日報酬率!E6) -> 0.080633344 | F6: =SUM(B6:E6) -> 1.0066317 | K6: =IFERROR(G7/每日收盤價!B6,0) -> 0 | L6: =IFERROR(H7/每日收盤價!C6,0) -> 0 | M6: =IFERROR(I7/每日收盤價!D6,0) -> 0 | N6: =IFERROR(J7/每日收盤價!E6,0) -> 0 | O6: =SUM(K6:N6) -> 0
A7: 2024-01-10 | B7: =B6*(1+$CD$2)*(1+每日報酬率!B7) -> 0 | C7: =C6*(1+$CD$2)*(1+每日報酬率!C7) -> 0.077348764 | D7: =D6*(1+$CD$2)*(1+每日報酬率!D7) -> 0.84498234 | E7: =E6*(1+$CD$2)*(1+每日報酬率!E7) -> 0.080285786 | F7: =SUM(B7:E7) -> 1.0026169 | K7: =IFERROR(G8/每日收盤價!B7,0) -> 0 | L7: =IFERROR(H8/每日收盤價!C7,0) -> 0 | M7: =IFERROR(I8/每日收盤價!D7,0) -> 0 | N7: =IFERROR(J8/每日收盤價!E7,0) -> 0 | O7: =SUM(K7:N7) -> 0
A8: 2024-01-11 | B8: =B7*(1+$CD$2)*(1+每日報酬率!B8) -> 0 | C8: =C7*(1+$CD$2)*(1+每日報酬率!C8) -> 0.077735508 | D8: =D7*(1+$CD$2)*(1+每日報酬率!D8) -> 0.84787611 | E8: =E7*(1+$CD$2)*(1+每日報酬率!E8) -> 0.079938229 | F8: =SUM(B8:E8) -> 1.0055498 | K8: =IFERROR(G9/每日收盤價!B8,0) -> 0 | L8: =IFERROR(H9/每日收盤價!C8,0) -> 0 | M8: =IFERROR(I9/每日收盤價!D8,0) -> 0 | N8: =IFERROR(J9/每日收盤價!E8,0) -> 0 | O8: =SUM(K8:N8) -> 0
A9: 2024-01-12 | B9: =B8*(1+$CD$2)*(1+每日報酬率!B9) -> 0 | C9: =C8*(1+$CD$2)*(1+每日報酬率!C9) -> 0.077735508 | D9: =D8*(1+$CD$2)*(1+每日報酬率!D9) -> 0.84498234 | E9: =E8*(1+$CD$2)*(1+每日報酬率!E9) -> 0.080459565 | F9: =SUM(B9:E9) -> 1.0031774 | K9: =IFERROR(G10/每日收盤價!B9,0) -> 0 | L9: =IFERROR(H10/每日收盤價!C9,0) -> 0 | M9: =IFERROR(I10/每日收盤價!D9,0) -> 0 | N9: =IFERROR(J10/每日收盤價!E9,0) -> 0 | O9: =SUM(K9:N9) -> 0
A10: 2024-01-15 | B10: =B9*(1+$CD$2)*(1+每日報酬率!B10) -> 0 | C10: =C9*(1+$CD$2)*(1+每日報酬率!C10) -> 0.077348764 | D10: =D9*(1+$CD$2)*(1+每日報酬率!D10) -> 0.84787611 | E10: =E9*(1+$CD$2)*(1+每日報酬率!E10) -> 0.080112007 | F10: =SUM(B10:E10) -> 1.0053369 | K10: =IFERROR(G11/每日收盤價!B10,0) -> 0 | L10: =IFERROR(H11/每日收盤價!C10,0) -> 0 | M10: =IFERROR(I11/每日收盤價!D10,0) -> 0 | N10: =IFERROR(J11/每日收盤價!E10,0) -> 0 | O10: =SUM(K10:N10) -> 0
A11: 2024-01-16 | B11: =B10*(1+$CD$2)*(1+每日報酬率!B11) -> 0 | C11: =C10*(1+$CD$2)*(1+每日報酬率!C11) -> 0.077348764 | D11: =D10*(1+$CD$2)*(1+每日報酬率!D11) -> 0.83919479 | E11: =E10*(1+$CD$2)*(1+每日報酬率!E11) -> 0.077765994 | F11: =SUM(B11:E11) -> 0.99430955 | K11: =IFERROR(G12/每日收盤價!B11,0) -> 0 | L11: =IFERROR(H12/每日收盤價!C11,0) -> 0 | M11: =IFERROR(I12/每日收盤價!D11,0) -> 0 | N11: =IFERROR(J12/每日收盤價!E11,0) -> 0 | O11: =SUM(K11:N11) -> 0
A12: 2024-01-17 | B12: =B11*(1+$CD$2)*(1+每日報酬率!B12) -> 0 | C12: =C11*(1+$CD$2)*(1+每日報酬率!C12) -> 0.076265882 | D12: =D11*(1+$CD$2)*(1+每日報酬率!D12) -> 0.84064167 | E12: =E11*(1+$CD$2)*(1+每日報酬率!E12) -> 0.076375764 | F12: =SUM(B12:E12) -> 0.99328332 | K12: =IFERROR(G13/每日收盤價!B12,0) -> 0 | L12: =IFERROR(H13/每日收盤價!C12,0) -> 0 | M12: =IFERROR(I13/每日收盤價!D12,0) -> 0 | N12: =IFERROR(J13/每日收盤價!E12,0) -> 0 | O12: =SUM(K12:N12) -> 0
A13: 2024-01-18 | B13: =B12*(1+$CD$2)*(1+每日報酬率!B13) -> 0 | C13: =C12*(1+$CD$2)*(1+每日報酬率!C13) -> 0.077271416 | D13: =D12*(1+$CD$2)*(1+每日報酬率!D13) -> 0.85076989 | E13: =E12*(1+$CD$2)*(1+每日報酬率!E13) -> 0.077939773 | F13: =SUM(B13:E13) -> 1.0059811 | K13: =IFERROR(G14/每日收盤價!B13,0) -> 0 | L13: =IFERROR(H14/每日收盤價!C13,0) -> 0 | M13: =IFERROR(I14/每日收盤價!D13,0) -> 0 | N13: =IFERROR(J14/每日收盤價!E13,0) -> 0 | O13: =SUM(K13:N13) -> 0
A14: 2024-01-19 | B14: =B13*(1+$CD$2)*(1+每日報酬率!B14) -> 0 | C14: =C13*(1+$CD$2)*(1+每日報酬率!C14) -> 0.077735508 | D14: =D13*(1+$CD$2)*(1+每日報酬率!D14) -> 0.90575162 | E14: =E13*(1+$CD$2)*(1+每日報酬率!E14) -> 0.079938229 | F14: =SUM(B14:E14) -> 1.0634254 | K14: =IFERROR(G15/每日收盤價!B14,0) -> 0 | L14: =IFERROR(H15/每日收盤價!C14,0) -> 0 | M14: =IFERROR(I15/每日收盤價!D14,0) -> 0 | N14: =IFERROR(J15/每日收盤價!E14,0) -> 0 | O14: =SUM(K14:N14) -> 0
A15: 2024-01-22 | B15: =B14*(1+$CD$2)*(1+每日報酬率!B15) -> 0 | C15: =C14*(1+$CD$2)*(1+每日報酬率!C15) -> 0.077271416 | D15: =D14*(1+$CD$2)*(1+每日報酬率!D15) -> 0.90575162 | E15: =E14*(1+$CD$2)*(1+每日報酬率!E15) -> 0.080112007 | F15: =SUM(B15:E15) -> 1.063135 | K15: =IFERROR(G16/每日收盤價!B15,0) -> 0 | L15: =IFERROR(H16/每日收盤價!C15,0) -> 0 | M15: =IFERROR(I16/每日收盤價!D15,0) -> 0 | N15: =IFERROR(J16/每日收盤價!E15,0) -> 0 | O15: =SUM(K15:N15) -> 0
... A46: 2024-03-15 | B46: =B45*(1+$CD$2)*(1+每日報酬率!B46) -> 0 | C46: =C45*(1+$CD$2)*(1+每日報酬率!C46) -> 0.10210037 | D46: =D45*(1+$CD$2)*(1+每日報酬率!D46) -> 1.0895063 | E46: =E45*(1+$CD$2)*(1+每日報酬率!E46) -> 0.098619445 | F46: =SUM(B46:E46) -> 1.2902262 | K46: =IFERROR(G47/每日收盤價!B46,0) -> 0 | L46: =IFERROR(H47/每日收盤價!C46,0) -> 0 | M46: =IFERROR(I47/每日收盤價!D46,0) -> 0.0046477951 | N46: =IFERROR(J47/每日收盤價!E46,0) -> 0 | O46: =SUM(K46:N46) -> 0.0046477951
A47: 2024-03-18 | B47: =B46*(1+$CD$2)*(1+每日報酬率!B47) -> 0 | C47: =C46*(1+$CD$2)*(1+每日報酬率!C47) -> 0.10519432 | D47: =D46*(1+$CD$2)*(1+每日報酬率!D47) -> 1.1054221 | E47: =E46*(1+$CD$2)*(1+每日報酬率!E47) -> 0.10166057 | F47: =SUM(B47:E47) -> 1.312277 | I47: 3.4997897 | K47: =IFERROR(G48/每日收盤價!B47,0) -> 0 | L47: =IFERROR(H48/每日收盤價!C47,0) -> 0 | M47: =IFERROR(I48/每日收盤價!D47,0) -> 0 | N47: =IFERROR(J48/每日收盤價!E47,0) -> 0 | O47: =SUM(K47:N47) -> 0
A48: 2024-03-19 | B48: =B47*(1+$CD$2)*(1+每日報酬率!B48) -> 0 | C48: =C47*(1+$CD$2)*(1+每日報酬率!C48) -> 0.10519432 | D48: =D47*(1+$CD$2)*(1+每日報酬率!D48) -> 1.1025283 | E48: =E47*(1+$CD$2)*(1+每日報酬率!E48) -> 0.099922786 | F48: =SUM(B48:E48) -> 1.3076454 | K48: =IFERROR(G49/每日收盤價!B48,0) -> 0 | L48: =IFERROR(H49/每日收盤價!C48,0) -> 0 | M48: =IFERROR(I49/每日收盤價!D48,0) -> 0 | N48: =IFERROR(J49/每日收盤價!E48,0) -> 0 | O48: =SUM(K48:N48) -> 0
A49: 2024-03-20 | B49: =B48*(1+$CD$2)*(1+每日報酬率!B49) -> 0 | C49: =C48*(1+$CD$2)*(1+每日報酬率!C49) -> 0.10674129 | D49: =D48*(1+$CD$2)*(1+每日報酬率!D49) -> 1.0967408 | E49: =E48*(1+$CD$2)*(1+每日報酬率!E49) -> 0.098184998 | F49: =SUM(B49:E49) -> 1.3016671 | K49: =IFERROR(G50/每日收盤價!B49,0) -> 0 | L49: =IFERROR(H50/每日收盤價!C49,0) -> 0 | M49: =IFERROR(I50/每日收盤價!D49,0) -> 0 | N49: =IFERROR(J50/每日收盤價!E49,0) -> 0 | O49: =SUM(K49:N49) -> 0
A50: 2024-03-21 | B50: =B49*(1+$CD$2)*(1+每日報酬率!B50) -> 0 | C50: =C49*(1+$CD$2)*(1+每日報酬率!C50) -> 0.11022199 | D50: =D49*(1+$CD$2)*(1+每日報酬率!D50) -> 1.1343599 | E50: =E49*(1+$CD$2)*(1+每日報酬率!E50) -> 0.099053892 | F50: =SUM(B50:E50) -> 1.3436357 | K50: =IFERROR(G51/每日收盤價!B50,0) -> 0 | L50: =IFERROR(H51/每日收盤價!C50,0) -> 0 | M50: =IFERROR(I51/每日收盤價!D50,0) -> 0 | N50: =IFERROR(J51/每日收盤價!E50,0) -> 0 | O50: =SUM(K50:N50) -> 0
A51: 2024-03-22 | B51: =B50*(1+$CD$2)*(1+每日報酬率!B51) -> 0 | C51: =C50*(1+$CD$2)*(1+每日報酬率!C51) -> 0.11254245 | D51: =D50*(1+$CD$2)*(1+每日報酬率!D51) -> 1.1358067 | E51: =E50*(1+$CD$2)*(1+每日報酬率!E51) -> 0.097750551 | F51: =SUM(B51:E51) -> 1.3460997 | K51: =IFERROR(G52/每日收盤價!B51,0) -> 0 | L51: =IFERROR(H52/每日收盤價!C51,0) -> 0 | M51: =IFERROR(I52/每日收盤價!D51,0) -> 0 | N51: =IFERROR(J52/每日收盤價!E51,0) -> 0 | O51: =SUM(K51:N51) -> 0
A52: 2024-03-25 | B52: =B51*(1+$CD$2)*(1+每日報酬率!B52) -> 0 | C52: =C51*(1+$CD$2)*(1+每日報酬率!C52) -> 0.11254245 | D52: =D51*(1+$CD$2)*(1+每日報酬率!D52) -> 1.1285723 | E52: =E51*(1+$CD$2)*(1+每日報酬率!E52) -> 0.097316104 | F52: =SUM(B52:E52) -> 1.3384309 | K52: =IFERROR(G53/每日收盤價!B52,0) -> 0 | L52: =IFERROR(H53/每日收盤價!C52,0) -> 0 | M52: =IFERROR(I53/每日收盤價!D52,0) -> 0 | N52: =IFERROR(J53/每日收盤價!E52,0) -> 0 | O52: =SUM(K52:N52) -> 0
A53: 2024-03-26 | B53: =B52*(1+$CD$2)*(1+每日報酬率!B53) -> 0 | C53: =C52*(1+$CD$2)*(1+每日報酬率!C53) -> 0.10983525 | D53: =D52*(1+$CD$2)*(1+每日報酬率!D53) -> 1.1314661 | E53: =E52*(1+$CD$2)*(1+每日報酬率!E53) -> 0.098184998 | F53: =SUM(B53:E53) -> 1.3394863 | K53: =IFERROR(G54/每日收盤價!B53,0) -> 0 | L53: =IFERROR(H54/每日收盤價!C53,0) -> 0 | M53: =IFERROR(I54/每日收盤價!D53,0) -> 0 | N53: =IFERROR(J54/每日收盤價!E53,0) -> 0 | O53: =SUM(K53:N53) -> 0
A54: 2024-03-27 | B54: =B53*(1+$CD$2)*(1+每日報酬率!B54) -> 0 | C54: =C53*(1+$CD$2)*(1+每日報酬率!C54) -> 0.11486292 | D54: =D53*(1+$CD$2)*(1+每日報酬率!D54) -> 1.1271254 | E54: =E53*(1+$CD$2)*(1+每日報酬率!E54) -> 0.10122613 | F54: =SUM(B54:E54) -> 1.3432145 | K54: =IFERROR(G55/每日收盤價!B54,0) -> 0 | L54: =IFERROR(H55/每日收盤價!C54,0) -> 0 | M54: =IFERROR(I55/每日收盤價!D54,0) -> 0 | N54: =IFERROR(J55/每日收盤價!E54,0) -> 0 | O54: =SUM(K54:N54) -> 0
A55: 2024-03-28 | B55: =B54*(1+$CD$2)*(1+每日報酬率!B55) -> 0 | C55: =C54*(1+$CD$2)*(1+每日報酬率!C55) -> 0.12027733 | D55: =D54*(1+$CD$2)*(1+每日報酬率!D55) -> 1.1126565 | E55: =E54*(1+$CD$2)*(1+每日報酬率!E55) -> 0.10079168 | F55: =SUM(B55:E55) -> 1.3337255 | K55: =IFERROR(G56/每日收盤價!B55,0) -> 0 | L55: =IFERROR(H56/每日收盤價!C55,0) -> 0 | M55: =IFERROR(I56/每日收盤價!D55,0) -> 0 | N55: =IFERROR(J56/每日收盤價!E55,0) -> 0 | O55: =SUM(K55:N55) -> 0
A56: 2024-03-29 | B56: =B55*(1+$CD$2)*(1+每日報酬率!B56) -> 0 | C56: =C55*(1+$CD$2)*(1+每日報酬率!C56) -> 0.11602315 | D56: =D55*(1+$CD$2)*(1+每日報酬率!D56) -> 1.1271254 | E56: =E55*(1+$CD$2)*(1+每日報酬率!E56) -> 0.10383281 | F56: =SUM(B56:E56) -> 1.3469814 | K56: =IFERROR(G57/每日收盤價!B56,0) -> 0 | L56: =IFERROR(H57/每日收盤價!C56,0) -> 0 | M56: =IFERROR(I57/每日收盤價!D56,0) -> 0 | N56: =IFERROR(J57/每日收盤價!E56,0) -> 0 | O56: =SUM(K56:N56) -> 0
A57: 2024-04-01 | B57: =B56*(1+$CD$2)*(1+每日報酬率!B57) -> 0 | C57: =C56*(1+$CD$2)*(1+每日報酬率!C57) -> 0.11640989 | D57: =D56*(1+$CD$2)*(1+每日報酬率!D57) -> 1.1141034 | E57: =E56*(1+$CD$2)*(1+每日報酬率!E57) -> 0.10079168 | F57: =SUM(B57:E57) -> 1.331305 | K57: =IFERROR(G58/每日收盤價!B57,0) -> 0 | L57: =IFERROR(H58/每日收盤價!C57,0) -> 0 | M57: =IFERROR(I58/每日收盤價!D57,0) -> 0 | N57: =IFERROR(J58/每日收盤價!E57,0) -> 0 | O57: =SUM(K57:N57) -> 0
A58: 2024-04-02 | B58: =B57*(1+$CD$2)*(1+每日報酬率!B58) -> 0 | C58: =C57*(1+$CD$2)*(1+每日報酬率!C58) -> 0.12298454 | D58: =D57*(1+$CD$2)*(1+每日報酬率!D58) -> 1.1430412 | E58: =E57*(1+$CD$2)*(1+每日報酬率!E58) -> 0.10122613 | F58: =SUM(B58:E58) -> 1.3672518 | K58: =IFERROR(G59/每日收盤價!B58,0) -> 0 | L58: =IFERROR(H59/每日收盤價!C58,0) -> 0 | M58: =IFERROR(I59/每日收盤價!D58,0) -> 0 | N58: =IFERROR(J59/每日收盤價!E58,0) -> 0 | O58: =SUM(K58:N58) -> 0
A59: 2024-04-03 | B59: =B58*(1+$CD$2)*(1+每日報酬率!B59) -> 0 | C59: =C58*(1+$CD$2)*(1+每日報酬率!C59) -> 0.12298454 | D59: =D58*(1+$CD$2)*(1+每日報酬率!D59) -> 1.1285723 | E59: =E58*(1+$CD$2)*(1+每日報酬率!E59) -> 0.10079168 | F59: =SUM(B59:E59) -> 1.3523485 | K59: =IFERROR(G60/每日收盤價!B59,0) -> 0 | L59: =IFERROR(H60/每日收盤價!C59,0) -> 0 | M59: =IFERROR(I60/每日收盤價!D59,0) -> 0 | N59: =IFERROR(J60/每日收盤價!E59,0) -> 0 | O59: =SUM(K59:N59) -> 0
... A105: 2024-06-12 | B105: =B104*(1+$CD$2)*(1+每日報酬率!B105) -> 0 | C105: =C104*(1+$CD$2)*(1+每日報酬率!C105) -> 0.14502893 | D105: =D104*(1+$CD$2)*(1+每日報酬率!D105) -> 1.3152208 | E105: =E104*(1+$CD$2)*(1+每日報酬率!E105) -> 0.11295619 | F105: =SUM(B105:E105) -> 1.5732059 | K105: =IFERROR(G106/每日收盤價!B105,0) -> 0 | L105: =IFERROR(H106/每日收盤價!C105,0) -> 0 | M105: =IFERROR(I106/每日收盤價!D105,0) -> 0.0038501537 | N105: =IFERROR(J106/每日收盤價!E105,0) -> 0 | O105: =SUM(K105:N105) -> 0.0038501537
A106: 2024-06-13 | B106: =B105*(1+$CD$2)*(1+每日報酬率!B106) -> 0 | C106: =C105*(1+$CD$2)*(1+每日報酬率!C106) -> 0.14850963 | D106: =D105*(1+$CD$2)*(1+每日報酬率!D106) -> 1.3296897 | E106: =E105*(1+$CD$2)*(1+每日報酬率!E106) -> 0.12034179 | F106: =SUM(B106:E106) -> 1.5985411 | I106: 3.4997897 | K106: =IFERROR(G107/每日收盤價!B106,0) -> 0 | L106: =IFERROR(H107/每日收盤價!C106,0) -> 0 | M106: =IFERROR(I107/每日收盤價!D106,0) -> 0 | N106: =IFERROR(J107/每日收盤價!E106,0) -> 0 | O106: =SUM(K106:N106) -> 0
A107: 2024-06-14 | B107: =B106*(1+$CD$2)*(1+每日報酬率!B107) -> 0 | C107: =C106*(1+$CD$2)*(1+每日報酬率!C107) -> 0.15315055 | D107: =D106*(1+$CD$2)*(1+每日報酬率!D107) -> 1.3340303 | E107: =E106*(1+$CD$2)*(1+每日報酬率!E107) -> 0.12121068 | F107: =SUM(B107:E107) -> 1.6083916 | K107: =IFERROR(G108/每日收盤價!B107,0) -> 0 | L107: =IFERROR(H108/每日收盤價!C107,0) -> 0 | M107: =IFERROR(I108/每日收盤價!D107,0) -> 0 | N107: =IFERROR(J108/每日收盤價!E107,0) -> 0 | O107: =SUM(K107:N107) -> 0
A108: 2024-06-17 | B108: =B107*(1+$CD$2)*(1+每日報酬率!B108) -> 0 | C108: =C107*(1+$CD$2)*(1+每日報酬率!C108) -> 0.15469753 | D108: =D107*(1+$CD$2)*(1+每日報酬率!D108) -> 1.3325834 | E108: =E107*(1+$CD$2)*(1+每日報酬率!E108) -> 0.11990734 | F108: =SUM(B108:E108) -> 1.6071883 | K108: =IFERROR(G109/每日收盤價!B108,0) -> 0 | L108: =IFERROR(H109/每日收盤價!C108,0) -> 0 | M108: =IFERROR(I109/每日收盤價!D108,0) -> 0 | N108: =IFERROR(J109/每日收盤價!E108,0) -> 0 | O108: =SUM(K108:N108) -> 0
A109: 2024-06-18 | B109: =B108*(1+$CD$2)*(1+每日報酬率!B109) -> 0 | C109: =C108*(1+$CD$2)*(1+每日報酬率!C109) -> 0.1535373 | D109: =D108*(1+$CD$2)*(1+每日報酬率!D109) -> 1.364415 | E109: =E108*(1+$CD$2)*(1+每日報酬率!E109) -> 0.12207958 | F109: =SUM(B109:E109) -> 1.6400318 | G109: 6.43 | K109: =IFERROR(G110/每日收盤價!B109,0) -> 0 | L109: =IFERROR(H110/每日收盤價!C109,0) -> 0 | M109: =IFERROR(I110/每日收盤價!D109,0) -> 0 | N109: =IFERROR(J110/每日收盤價!E109,0) -> 0 | O109: =SUM(K109:N109) -> 0
A110: 2024-06-19 | B110: =B109*(1+$CD$2)*(1+每日報酬率!B110) -> 0 | C110: =C109*(1+$CD$2)*(1+每日報酬率!C110) -> 0.15701799 | D110: =D109*(1+$CD$2)*(1+每日報酬率!D110) -> 1.4193967 | E110: =E109*(1+$CD$2)*(1+每日報酬率!E110) -> 0.12903073 | F110: =SUM(B110:E110) -> 1.7054454 | K110: =IFERROR(G111/每日收盤價!B110,0) -> 0 | L110: =IFERROR(H111/每日收盤價!C110,0) -> 0 | M110: =IFERROR(I111/每日收盤價!D110,0) -> 0 | N110: =IFERROR(J111/每日收盤價!E110,0) -> 0 | O110: =SUM(K110:N110) -> 0
A111: 2024-06-20 | B111: =B110*(1+$CD$2)*(1+每日報酬率!B111) -> 0 | C111: =C110*(1+$CD$2)*(1+每日報酬率!C111) -> 0.16823356 | D111: =D110*(1+$CD$2)*(1+每日報酬率!D111) -> 1.4193967 | E111: =E110*(1+$CD$2)*(1+每日報酬率!E111) -> 0.13033407 | F111: =SUM(B111:E111) -> 1.7179643 | K111: =IFERROR(G112/每日收盤價!B111,0) -> 0 | L111: =IFERROR(H112/每日收盤價!C111,0) -> 0 | M111: =IFERROR(I112/每日收盤價!D111,0) -> 0 | N111: =IFERROR(J112/每日收盤價!E111,0) -> 0 | O111: =SUM(K111:N111) -> 0
A112: 2024-06-21 | B112: =B111*(1+$CD$2)*(1+每日報酬率!B112) -> 0 | C112: =C111*(1+$CD$2)*(1+每日報酬率!C112) -> 0.16397938 | D112: =D111*(1+$CD$2)*(1+每日報酬率!D112) -> 1.4034809 | E112: =E111*(1+$CD$2)*(1+每日報酬率!E112) -> 0.12946517 | F112: =SUM(B112:E112) -> 1.6969255 | K112: =IFERROR(G113/每日收盤價!B112,0) -> 0 | L112: =IFERROR(H113/每日收盤價!C112,0) -> 0 | M112: =IFERROR(I113/每日收盤價!D112,0) -> 0 | N112: =IFERROR(J113/每日收盤價!E112,0) -> 0 | O112: =SUM(K112:N112) -> 0
A113: 2024-06-24 | B113: =B112*(1+$CD$2)*(1+每日報酬率!B113) -> 0 | C113: =C112*(1+$CD$2)*(1+每日報酬率!C113) -> 0.15933845 | D113: =D112*(1+$CD$2)*(1+每日報酬率!D113) -> 1.3600743 | E113: =E112*(1+$CD$2)*(1+每日報酬率!E113) -> 0.12251402 | F113: =SUM(B113:E113) -> 1.6419268 | K113: =IFERROR(G114/每日收盤價!B113,0) -> 0 | L113: =IFERROR(H114/每日收盤價!C113,0) -> 0 | M113: =IFERROR(I114/每日收盤價!D113,0) -> 0 | N113: =IFERROR(J114/每日收盤價!E113,0) -> 0 | O113: =SUM(K113:N113) -> 0
A114: 2024-06-25 | B114: =B113*(1+$CD$2)*(1+每日報酬率!B114) -> 0 | C114: =C113*(1+$CD$2)*(1+每日報酬率!C114) -> 0.16320589 | D114: =D113*(1+$CD$2)*(1+每日報酬率!D114) -> 1.3673087 | E114: =E113*(1+$CD$2)*(1+每日報酬率!E114) -> 0.12034179 | F114: =SUM(B114:E114) -> 1.6508564 | K114: =IFERROR(G115/每日收盤價!B114,0) -> 0 | L114: =IFERROR(H115/每日收盤價!C114,0) -> 0 | M114: =IFERROR(I115/每日收盤價!D114,0) -> 0 | N114: =IFERROR(J115/每日收盤價!E114,0) -> 0 | O114: =SUM(K114:N114) -> 0
A115: 2024-06-26 | B115: =B114*(1+$CD$2)*(1+每日報酬率!B115) -> 0 | C115: =C114*(1+$CD$2)*(1+每日報酬率!C115) -> 0.16243241 | D115: =D114*(1+$CD$2)*(1+每日報酬率!D115) -> 1.3890121 | E115: =E114*(1+$CD$2)*(1+每日報酬率!E115) -> 0.12207958 | F115: =SUM(B115:E115) -> 1.673524 | K115: =IFERROR(G116/每日收盤價!B115,0) -> 0 | L115: =IFERROR(H116/每日收盤價!C115,0) -> 0 | M115: =IFERROR(I116/每日收盤價!D115,0) -> 0 | N115: =IFERROR(J116/每日收盤價!E115,0) -> 0 | O115: =SUM(K115:N115) -> 0
A116: 2024-06-27 | B116: =B115*(1+$CD$2)*(1+每日報酬率!B116) -> 0 | C116: =C115*(1+$CD$2)*(1+每日報酬率!C116) -> 0.16436612 | D116: =D115*(1+$CD$2)*(1+每日報酬率!D116) -> 1.3890121 | E116: =E115*(1+$CD$2)*(1+每日報酬率!E116) -> 0.12121068 | F116: =SUM(B116:E116) -> 1.6745889 | K116: =IFERROR(G117/每日收盤價!B116,0) -> 0 | L116: =IFERROR(H117/每日收盤價!C116,0) -> 0 | M116: =IFERROR(I117/每日收盤價!D116,0) -> 0 | N116: =IFERROR(J117/每日收盤價!E116,0) -> 0 | O116: =SUM(K116:N116) -> 0
A117: 2024-06-28 | B117: =B116*(1+$CD$2)*(1+每日報酬率!B117) -> 0 | C117: =C116*(1+$CD$2)*(1+每日報酬率!C117) -> 0.16552636 | D117: =D116*(1+$CD$2)*(1+每日報酬率!D117) -> 1.3976934 | E117: =E116*(1+$CD$2)*(1+每日報酬率!E117) -> 0.12164513 | F117: =SUM(B117:E117) -> 1.6848649 | K117: =IFERROR(G118/每日收盤價!B117,0) -> 0 | L117: =IFERROR(H118/每日收盤價!C117,0) -> 0 | M117: =IFERROR(I118/每日收盤價!D117,0) -> 0 | N117: =IFERROR(J118/每日收盤價!E117,0) -> 0 | O117: =SUM(K117:N117) -> 0
A118: 2024-07-01 | B118: =B117*(1+$CD$2)*(1+每日報酬率!B118) -> 0 | C118: =C117*(1+$CD$2)*(1+每日報酬率!C118) -> 0.16707333 | D118: =D117*(1+$CD$2)*(1+每日報酬率!D118) -> 1.4005872 | E118: =E117*(1+$CD$2)*(1+每日報酬率!E118) -> 0.12294847 | F118: =SUM(B118:E118) -> 1.690609 | K118: =IFERROR(G119/每日收盤價!B118,0) -> 0 | L118: =IFERROR(H119/每日收盤價!C118,0) -> 0.025 | M118: =IFERROR(I119/每日收盤價!D118,0) -> 0 | N118: =IFERROR(J119/每日收盤價!E118,0) -> 0 | O118: =SUM(K118:N118) -> 0.025
A119: 2024-07-02 | B119: =B118*(1+$CD$2)*(1+每日報酬率!B119) -> 0 | C119: =C118*(1+$CD$2)*(1+每日報酬率!C119) -> 0.15817822 | D119: =D118*(1+$CD$2)*(1+每日報酬率!D119) -> 1.3890121 | E119: =E118*(1+$CD$2)*(1+每日報酬率!E119) -> 0.12251402 | F119: =SUM(B119:E119) -> 1.6697043 | H119: 5.4 | K119: =IFERROR(G120/每日收盤價!B119,0) -> 0 | L119: =IFERROR(H120/每日收盤價!C119,0) -> 0 | M119: =IFERROR(I120/每日收盤價!D119,0) -> 0 | N119: =IFERROR(J120/每日收盤價!E119,0) -> 0 | O119: =SUM(K119:N119) -> 0
A120: 2024-07-03 | B120: =B119*(1+$CD$2)*(1+每日報酬率!B120) -> 0 | C120: =C119*(1+$CD$2)*(1+每日報酬率!C120) -> 0.15701799 | D120: =D119*(1+$CD$2)*(1+每日報酬率!D120) -> 1.4165029 | E120: =E119*(1+$CD$2)*(1+每日報酬率!E120) -> 0.12207958 | F120: =SUM(B120:E120) -> 1.6956005 | K120: =IFERROR(G121/每日收盤價!B120,0) -> 0 | L120: =IFERROR(H121/每日收盤價!C120,0) -> 0 | M120: =IFERROR(I121/每日收盤價!D120,0) -> 0 | N120: =IFERROR(J121/每日收盤價!E120,0) -> 0.021640789 | O120: =SUM(K120:N120) -> 0.021640789
A121: 2024-07-04 | B121: =B120*(1+$CD$2)*(1+每日報酬率!B121) -> 0 | C121: =C120*(1+$CD$2)*(1+每日報酬率!C121) -> 0.1659131 | D121: =D120*(1+$CD$2)*(1+每日報酬率!D121) -> 1.454122 | E121: =E120*(1+$CD$2)*(1+每日報酬率!E121) -> 0.1194729 | F121: =SUM(B121:E121) -> 1.739508 | J121: 30.405309 | K121: =IFERROR(G122/每日收盤價!B121,0) -> 0 | L121: =IFERROR(H122/每日收盤價!C121,0) -> 0 | M121: =IFERROR(I122/每日收盤價!D121,0) -> 0 | N121: =IFERROR(J122/每日收盤價!E121,0) -> 0 | O121: =SUM(K121:N121) -> 0
A122: 2024-07-05 | B122: =B121*(1+$CD$2)*(1+每日報酬率!B122) -> 0 | C122: =C121*(1+$CD$2)*(1+每日報酬率!C122) -> 0.1659131 | D122: =D121*(1+$CD$2)*(1+每日報酬率!D122) -> 1.454122 | E122: =E121*(1+$CD$2)*(1+每日報酬率!E122) -> 0.11730066 | F122: =SUM(B122:E122) -> 1.7373358 | K122: =IFERROR(G123/每日收盤價!B122,0) -> 0 | L122: =IFERROR(H123/每日收盤價!C122,0) -> 0 | M122: =IFERROR(I123/每日收盤價!D122,0) -> 0 | N122: =IFERROR(J123/每日收盤價!E122,0) -> 0 | O122: =SUM(K122:N122) -> 0
A123: 2024-07-08 | B123: =B122*(1+$CD$2)*(1+每日報酬率!B123) -> 0 | C123: =C122*(1+$CD$2)*(1+每日報酬率!C123) -> 0.17519495 | D123: =D122*(1+$CD$2)*(1+每日報酬率!D123) -> 1.4975286 | E123: =E122*(1+$CD$2)*(1+每日報酬率!E123) -> 0.12338292 | F123: =SUM(B123:E123) -> 1.7961065 | K123: =IFERROR(G124/每日收盤價!B123,0) -> 0 | L123: =IFERROR(H124/每日收盤價!C123,0) -> 0 | M123: =IFERROR(I124/每日收盤價!D123,0) -> 0 | N123: =IFERROR(J124/每日收盤價!E123,0) -> 0 | O123: =SUM(K123:N123) -> 0
A124: 2024-07-09 | B124: =B123*(1+$CD$2)*(1+每日報酬率!B124) -> 0 | C124: =C123*(1+$CD$2)*(1+每日報酬率!C124) -> 0.17442146 | D124: =D123*(1+$CD$2)*(1+每日報酬率!D124) -> 1.5047631 | E124: =E123*(1+$CD$2)*(1+每日報酬率!E124) -> 0.12685849 | F124: =SUM(B124:E124) -> 1.806043 | K124: =IFERROR(G125/每日收盤價!B124,0) -> 0 | L124: =IFERROR(H125/每日收盤價!C124,0) -> 0 | M124: =IFERROR(I125/每日收盤價!D124,0) -> 0 | N124: =IFERROR(J125/每日收盤價!E124,0) -> 0 | O124: =SUM(K124:N124) -> 0
A125: 2024-07-10 | B125: =B124*(1+$CD$2)*(1+每日報酬率!B125) -> 0 | C125: =C124*(1+$CD$2)*(1+每日報酬率!C125) -> 0.17287449 | D125: =D124*(1+$CD$2)*(1+每日報酬率!D125) -> 1.5119975 | E125: =E124*(1+$CD$2)*(1+每日報酬率!E125) -> 0.12468626 | F125: =SUM(B125:E125) -> 1.8095583 | K125: =IFERROR(G126/每日收盤價!B125,0) -> 0 | L125: =IFERROR(H126/每日收盤價!C125,0) -> 0 | M125: =IFERROR(I126/每日收盤價!D125,0) -> 0 | N125: =IFERROR(J126/每日收盤價!E125,0) -> 0 | O125: =SUM(K125:N125) -> 0
A126: 2024-07-11 | B126: =B125*(1+$CD$2)*(1+每日報酬率!B126) -> 0 | C126: =C125*(1+$CD$2)*(1+每日報酬率!C126) -> 0.17442146 | D126: =D125*(1+$CD$2)*(1+每日報酬率!D126) -> 1.5626386 | E126: =E125*(1+$CD$2)*(1+每日報酬率!E126) -> 0.12338292 | F126: =SUM(B126:E126) -> 1.860443 | K126: =IFERROR(G127/每日收盤價!B126,0) -> 0 | L126: =IFERROR(H127/每日收盤價!C126,0) -> 0 | M126: =IFERROR(I127/每日收盤價!D126,0) -> 0 | N126: =IFERROR(J127/每日收盤價!E126,0) -> 0 | O126: =SUM(K126:N126) -> 0
A127: 2024-07-12 | B127: =B126*(1+$CD$2)*(1+每日報酬率!B127) -> 0 | C127: =C126*(1+$CD$2)*(1+每日報酬率!C127) -> 0.16707333 | D127: =D126*(1+$CD$2)*(1+每日報酬率!D127) -> 1.5047631 | E127: =E126*(1+$CD$2)*(1+每日報酬率!E127) -> 0.11816956 | F127: =SUM(B127:E127) -> 1.790006 | K127: =IFERROR(G128/每日收盤價!B127,0) -> 0 | L127: =IFERROR(H128/每日收盤價!C127,0) -> 0 | M127: =IFERROR(I128/每日收盤價!D127,0) -> 0 | N127: =IFERROR(J128/每日收盤價!E127,0) -> 0 | O127: =SUM(K127:N127) -> 0
A128: 2024-07-15 | B128: =B127*(1+$CD$2)*(1+每日報酬率!B128) -> 0 | C128: =C127*(1+$CD$2)*(1+每日報酬率!C128) -> 0.16746007 | D128: =D127*(1+$CD$2)*(1+每日報酬率!D128) -> 1.5047631 | E128: =E127*(1+$CD$2)*(1+每日報酬率!E128) -> 0.11773511 | F128: =SUM(B128:E128) -> 1.7899583 | K128: =IFERROR(G129/每日收盤價!B128,0) -> 0 | L128: =IFERROR(H129/每日收盤價!C128,0) -> 0 | M128: =IFERROR(I129/每日收盤價!D128,0) -> 0 | N128: =IFERROR(J129/每日收盤價!E128,0) -> 0 | O128: =SUM(K128:N128) -> 0
A129: 2024-07-16 | B129: =B128*(1+$CD$2)*(1+每日報酬率!B129) -> 0 | C129: =C128*(1+$CD$2)*(1+每日報酬率!C129) -> 0.16475287 | D129: =D128*(1+$CD$2)*(1+每日報酬率!D129) -> 1.5264664 | E129: =E128*(1+$CD$2)*(1+每日報酬率!E129) -> 0.11686621 | F129: =SUM(B129:E129) -> 1.8080855 | K129: =IFERROR(G130/每日收盤價!B129,0) -> 0 | L129: =IFERROR(H130/每日收盤價!C129,0) -> 0 | M129: =IFERROR(I130/每日收盤價!D129,0) -> 0 | N129: =IFERROR(J130/每日收盤價!E129,0) -> 0 | O129: =SUM(K129:N129) -> 0
A130: 2024-07-17 | B130: =B129*(1+$CD$2)*(1+每日報酬率!B130) -> 0 | C130: =C129*(1+$CD$2)*(1+每日報酬率!C130) -> 0.16397938 | D130: =D129*(1+$CD$2)*(1+每日報酬率!D130) -> 1.4902942 | E130: =E129*(1+$CD$2)*(1+每日報酬率!E130) -> 0.11512843 | F130: =SUM(B130:E130) -> 1.769402 | K130: =IFERROR(G131/每日收盤價!B130,0) -> 0 | L130: =IFERROR(H131/每日收盤價!C130,0) -> 0 | M130: =IFERROR(I131/每日收盤價!D130,0) -> 0 | N130: =IFERROR(J131/每日收盤價!E130,0) -> 0 | O130: =SUM(K130:N130) -> 0
A131: 2024-07-18 | B131: =B130*(1+$CD$2)*(1+每日報酬率!B131) -> 0 | C131: =C130*(1+$CD$2)*(1+每日報酬率!C131) -> 0.15779148 | D131: =D130*(1+$CD$2)*(1+每日報酬率!D131) -> 1.454122 | E131: =E130*(1+$CD$2)*(1+每日報酬率!E131) -> 0.11121841 | F131: =SUM(B131:E131) -> 1.7231319 | K131: =IFERROR(G132/每日收盤價!B131,0) -> 0 | L131: =IFERROR(H132/每日收盤價!C131,0) -> 0 | M131: =IFERROR(I132/每日收盤價!D131,0) -> 0 | N131: =IFERROR(J132/每日收盤價!E131,0) -> 0 | O131: =SUM(K131:N131) -> 0
A132: 2024-07-19 | B132: =B131*(1+$CD$2)*(1+每日報酬率!B132) -> 0 | C132: =C131*(1+$CD$2)*(1+每日報酬率!C132) -> 0.15779148 | D132: =D131*(1+$CD$2)*(1+每日報酬率!D132) -> 1.4034809 | E132: =E131*(1+$CD$2)*(1+每日報酬率!E132) -> 0.10948062 | F132: =SUM(B132:E132) -> 1.670753 | K132: =IFERROR(G133/每日收盤價!B132,0) -> 0 | L132: =IFERROR(H133/每日收盤價!C132,0) -> 0 | M132: =IFERROR(I133/每日收盤價!D132,0) -> 0 | N132: =IFERROR(J133/每日收盤價!E132,0) -> 0 | O132: =SUM(K132:N132) -> 0
A133: 2024-07-22 | B133: =B132*(1+$CD$2)*(1+每日報酬率!B133) -> 0 | C133: =C132*(1+$CD$2)*(1+每日報酬率!C133) -> 0.14889637 | D133: =D132*(1+$CD$2)*(1+每日報酬率!D133) -> 1.3586274 | E133: =E132*(1+$CD$2)*(1+每日報酬率!E133) -> 0.10643949 | F133: =SUM(B133:E133) -> 1.6139633 | K133: =IFERROR(G134/每日收盤價!B133,0) -> 0 | L133: =IFERROR(H134/每日收盤價!C133,0) -> 0 | M133: =IFERROR(I134/每日收盤價!D133,0) -> 0 | N133: =IFERROR(J134/每日收盤價!E133,0) -> 0 | O133: =SUM(K133:N133) -> 0
... A168: 2024-09-11 | B168: =B167*(1+$CD$2)*(1+每日報酬率!B168) -> 0 | C168: =C167*(1+$CD$2)*(1+每日報酬率!C168) -> 0.13110616 | D168: =D167*(1+$CD$2)*(1+每日報酬率!D168) -> 1.3036457 | E168: =E167*(1+$CD$2)*(1+每日報酬率!E168) -> 0.096447211 | F168: =SUM(B168:E168) -> 1.5311991 | K168: =IFERROR(G169/每日收盤價!B168,0) -> 0 | L168: =IFERROR(H169/每日收盤價!C168,0) -> 0 | M168: =IFERROR(I169/每日收盤價!D168,0) -> 0.004439665 | N168: =IFERROR(J169/每日收盤價!E168,0) -> 0 | O168: =SUM(K168:N168) -> 0.004439665
A169: 2024-09-12 | B169: =B168*(1+$CD$2)*(1+每日報酬率!B169) -> 0 | C169: =C168*(1+$CD$2)*(1+每日報酬率!C169) -> 0.13729406 | D169: =D168*(1+$CD$2)*(1+每日報酬率!D169) -> 1.3600743 | E169: =E168*(1+$CD$2)*(1+每日報酬率!E169) -> 0.10035723 | F169: =SUM(B169:E169) -> 1.5977256 | I169: 4.0001382 | K169: =IFERROR(G170/每日收盤價!B169,0) -> 0 | L169: =IFERROR(H170/每日收盤價!C169,0) -> 0 | M169: =IFERROR(I170/每日收盤價!D169,0) -> 0 | N169: =IFERROR(J170/每日收盤價!E169,0) -> 0 | O169: =SUM(K169:N169) -> 0
A170: 2024-09-13 | B170: =B169*(1+$CD$2)*(1+每日報酬率!B170) -> 0 | C170: =C169*(1+$CD$2)*(1+每日報酬率!C170) -> 0.13613383 | D170: =D169*(1+$CD$2)*(1+每日報酬率!D170) -> 1.3702025 | E170: =E169*(1+$CD$2)*(1+每日報酬率!E170) -> 0.097750551 | F170: =SUM(B170:E170) -> 1.6040869 | K170: =IFERROR(G171/每日收盤價!B170,0) -> 0 | L170: =IFERROR(H171/每日收盤價!C170,0) -> 0 | M170: =IFERROR(I171/每日收盤價!D170,0) -> 0 | N170: =IFERROR(J171/每日收盤價!E170,0) -> 0 | O170: =SUM(K170:N170) -> 0
A171: 2024-09-16 | B171: =B170*(1+$CD$2)*(1+每日報酬率!B171) -> 0 | C171: =C170*(1+$CD$2)*(1+每日報酬率!C171) -> 0.14000126 | D171: =D170*(1+$CD$2)*(1+每日報酬率!D171) -> 1.3702025 | E171: =E170*(1+$CD$2)*(1+每日報酬率!E171) -> 0.098184998 | F171: =SUM(B171:E171) -> 1.6083888 | K171: =IFERROR(G172/每日收盤價!B171,0) -> 0 | L171: =IFERROR(H172/每日收盤價!C171,0) -> 0 | M171: =IFERROR(I172/每日收盤價!D171,0) -> 0 | N171: =IFERROR(J172/每日收盤價!E171,0) -> 0 | O171: =SUM(K171:N171) -> 0
A172: 2024-09-18 | B172: =B171*(1+$CD$2)*(1+每日報酬率!B172) -> 0 | C172: =C171*(1+$CD$2)*(1+每日報酬率!C172) -> 0.13458685 | D172: =D171*(1+$CD$2)*(1+每日報酬率!D172) -> 1.3615212 | E172: =E171*(1+$CD$2)*(1+每日報酬率!E172) -> 0.096012764 | F172: =SUM(B172:E172) -> 1.5921208 | K172: =IFERROR(G173/每日收盤價!B172,0) -> 0 | L172: =IFERROR(H173/每日收盤價!C172,0) -> 0 | M172: =IFERROR(I173/每日收盤價!D172,0) -> 0 | N172: =IFERROR(J173/每日收盤價!E172,0) -> 0 | O172: =SUM(K172:N172) -> 0
A173: 2024-09-19 | B173: =B172*(1+$CD$2)*(1+每日報酬率!B173) -> 0 | C173: =C172*(1+$CD$2)*(1+每日報酬率!C173) -> 0.13652057 | D173: =D172*(1+$CD$2)*(1+每日報酬率!D173) -> 1.3890121 | E173: =E172*(1+$CD$2)*(1+每日報酬率!E173) -> 0.097316104 | F173: =SUM(B173:E173) -> 1.6228487 | K173: =IFERROR(G174/每日收盤價!B173,0) -> 0 | L173: =IFERROR(H174/每日收盤價!C173,0) -> 0 | M173: =IFERROR(I174/每日收盤價!D173,0) -> 0 | N173: =IFERROR(J174/每日收盤價!E173,0) -> 0 | O173: =SUM(K173:N173) -> 0
A174: 2024-09-20 | B174: =B173*(1+$CD$2)*(1+每日報酬率!B174) -> 0 | C174: =C173*(1+$CD$2)*(1+每日報酬率!C174) -> 0.13690731 | D174: =D173*(1+$CD$2)*(1+每日報酬率!D174) -> 1.4078216 | E174: =E173*(1+$CD$2)*(1+每日報酬率!E174) -> 0.097750551 | F174: =SUM(B174:E174) -> 1.6424795 | K174: =IFERROR(G175/每日收盤價!B174,0) -> 0 | L174: =IFERROR(H175/每日收盤價!C174,0) -> 0 | M174: =IFERROR(I175/每日收盤價!D174,0) -> 0 | N174: =IFERROR(J175/每日收盤價!E174,0) -> 0 | O174: =SUM(K174:N174) -> 0
A175: 2024-09-23 | B175: =B174*(1+$CD$2)*(1+每日報酬率!B175) -> 0 | C175: =C174*(1+$CD$2)*(1+每日報酬率!C175) -> 0.13922778 | D175: =D174*(1+$CD$2)*(1+每日報酬率!D175) -> 1.4136092 | E175: =E174*(1+$CD$2)*(1+每日報酬率!E175) -> 0.099488339 | F175: =SUM(B175:E175) -> 1.6523253 | K175: =IFERROR(G176/每日收盤價!B175,0) -> 0 | L175: =IFERROR(H176/每日收盤價!C175,0) -> 0 | M175: =IFERROR(I176/每日收盤價!D175,0) -> 0 | N175: =IFERROR(J176/每日收盤價!E175,0) -> 0 | O175: =SUM(K175:N175) -> 0
A176: 2024-09-24 | B176: =B175*(1+$CD$2)*(1+每日報酬率!B176) -> 0 | C176: =C175*(1+$CD$2)*(1+每日報酬率!C176) -> 0.14154824 | D176: =D175*(1+$CD$2)*(1+每日報酬率!D176) -> 1.428078 | E176: =E175*(1+$CD$2)*(1+每日報酬率!E176) -> 0.10383281 | F176: =SUM(B176:E176) -> 1.6734591 | K176: =IFERROR(G177/每日收盤價!B176,0) -> 0 | L176: =IFERROR(H177/每日收盤價!C176,0) -> 0 | M176: =IFERROR(I177/每日收盤價!D176,0) -> 0 | N176: =IFERROR(J177/每日收盤價!E176,0) -> 0 | O176: =SUM(K176:N176) -> 0
A177: 2024-09-25 | B177: =B176*(1+$CD$2)*(1+每日報酬率!B177) -> 0 | C177: =C176*(1+$CD$2)*(1+每日報酬率!C177) -> 0.14580242 | D177: =D176*(1+$CD$2)*(1+每日報酬率!D177) -> 1.454122 | E177: =E176*(1+$CD$2)*(1+每日報酬率!E177) -> 0.10643949 | F177: =SUM(B177:E177) -> 1.7063639 | K177: =IFERROR(G178/每日收盤價!B177,0) -> 0 | L177: =IFERROR(H178/每日收盤價!C177,0) -> 0 | M177: =IFERROR(I178/每日收盤價!D177,0) -> 0 | N177: =IFERROR(J178/每日收盤價!E177,0) -> 0 | O177: =SUM(K177:N177) -> 0
A178: 2024-09-26 | B178: =B177*(1+$CD$2)*(1+每日報酬率!B178) -> 0 | C178: =C177*(1+$CD$2)*(1+每日報酬率!C178) -> 0.14657591 | D178: =D177*(1+$CD$2)*(1+每日報酬率!D178) -> 1.4685909 | E178: =E177*(1+$CD$2)*(1+每日報酬率!E178) -> 0.11034951 | F178: =SUM(B178:E178) -> 1.7255163 | K178: =IFERROR(G179/每日收盤價!B178,0) -> 0 | L178: =IFERROR(H179/每日收盤價!C178,0) -> 0 | M178: =IFERROR(I179/每日收盤價!D178,0) -> 0 | N178: =IFERROR(J179/每日收盤價!E178,0) -> 0 | O178: =SUM(K178:N178) -> 0
A179: 2024-09-27 | B179: =B178*(1+$CD$2)*(1+每日報酬率!B179) -> 0 | C179: =C178*(1+$CD$2)*(1+每日報酬率!C179) -> 0.14773614 | D179: =D178*(1+$CD$2)*(1+每日報酬率!D179) -> 1.4468876 | E179: =E178*(1+$CD$2)*(1+每日報酬率!E179) -> 0.10948062 | F179: =SUM(B179:E179) -> 1.7041043 | K179: =IFERROR(G180/每日收盤價!B179,0) -> 0 | L179: =IFERROR(H180/每日收盤價!C179,0) -> 0 | M179: =IFERROR(I180/每日收盤價!D179,0) -> 0 | N179: =IFERROR(J180/每日收盤價!E179,0) -> 0 | O179: =SUM(K179:N179) -> 0
A180: 2024-09-30 | B180: =B179*(1+$CD$2)*(1+每日報酬率!B180) -> 0 | C180: =C179*(1+$CD$2)*(1+每日報酬率!C180) -> 0.14502893 | D180: =D179*(1+$CD$2)*(1+每日報酬率!D180) -> 1.3846714 | E180: =E179*(1+$CD$2)*(1+每日報酬率!E180) -> 0.10209502 | F180: =SUM(B180:E180) -> 1.6317954 | K180: =IFERROR(G181/每日收盤價!B180,0) -> 0 | L180: =IFERROR(H181/每日收盤價!C180,0) -> 0 | M180: =IFERROR(I181/每日收盤價!D180,0) -> 0 | N180: =IFERROR(J181/每日收盤價!E180,0) -> 0 | O180: =SUM(K180:N180) -> 0
A181: 2024-10-01 | B181: =B180*(1+$CD$2)*(1+每日報酬率!B181) -> 0 | C181: =C180*(1+$CD$2)*(1+每日報酬率!C181) -> 0.14464219 | D181: =D180*(1+$CD$2)*(1+每日報酬率!D181) -> 1.4063747 | E181: =E180*(1+$CD$2)*(1+每日報酬率!E181) -> 0.10513615 | F181: =SUM(B181:E181) -> 1.6561531 | K181: =IFERROR(G182/每日收盤價!B181,0) -> 0 | L181: =IFERROR(H182/每日收盤價!C181,0) -> 0 | M181: =IFERROR(I182/每日收盤價!D181,0) -> 0 | N181: =IFERROR(J182/每日收盤價!E181,0) -> 0 | O181: =SUM(K181:N181) -> 0
... A228: 2024-12-11 | B228: =B227*(1+$CD$2)*(1+每日報酬率!B228) -> 0 | C228: =C227*(1+$CD$2)*(1+每日報酬率!C228) -> 0.14618916 | D228: =D227*(1+$CD$2)*(1+每日報酬率!D228) -> 1.5119975 | E228: =E227*(1+$CD$2)*(1+每日報酬率!E228) -> 0.11730066 | F228: =SUM(B228:E228) -> 1.7754873 | K228: =IFERROR(G229/每日收盤價!B228,0) -> 0 | L228: =IFERROR(H229/每日收盤價!C228,0) -> 0 | M228: =IFERROR(I229/每日收盤價!D228,0) -> 0.0038274039 | N228: =IFERROR(J229/每日收盤價!E228,0) -> 0 | O228: =SUM(K228:N228) -> 0.0038274039
A229: 2024-12-12 | B229: =B228*(1+$CD$2)*(1+每日報酬率!B229) -> 0 | C229: =C228*(1+$CD$2)*(1+每日報酬率!C229) -> 0.14580242 | D229: =D228*(1+$CD$2)*(1+每日報酬率!D229) -> 1.5337008 | E229: =E228*(1+$CD$2)*(1+每日報酬率!E229) -> 0.11990734 | F229: =SUM(B229:E229) -> 1.7994106 | I229: 3.9996371 | K229: =IFERROR(G230/每日收盤價!B229,0) -> 0 | L229: =IFERROR(H230/每日收盤價!C229,0) -> 0 | M229: =IFERROR(I230/每日收盤價!D229,0) -> 0 | N229: =IFERROR(J230/每日收盤價!E229,0) -> 0 | O229: =SUM(K229:N229) -> 0
A230: 2024-12-13 | B230: =B229*(1+$CD$2)*(1+每日報酬率!B230) -> 0 | C230: =C229*(1+$CD$2)*(1+每日報酬率!C230) -> 0.14425545 | D230: =D229*(1+$CD$2)*(1+每日報酬率!D230) -> 1.5409353 | E230: =E229*(1+$CD$2)*(1+每日報酬率!E230) -> 0.12251402 | F230: =SUM(B230:E230) -> 1.8077047 | K230: =IFERROR(G231/每日收盤價!B230,0) -> 0 | L230: =IFERROR(H231/每日收盤價!C230,0) -> 0 | M230: =IFERROR(I231/每日收盤價!D230,0) -> 0 | N230: =IFERROR(J231/每日收盤價!E230,0) -> 0 | O230: =SUM(K230:N230) -> 0
A231: 2024-12-16 | B231: =B230*(1+$CD$2)*(1+每日報酬率!B231) -> 0 | C231: =C230*(1+$CD$2)*(1+每日報酬率!C231) -> 0.14077475 | D231: =D230*(1+$CD$2)*(1+每日報酬率!D231) -> 1.569873 | E231: =E230*(1+$CD$2)*(1+每日報酬率!E231) -> 0.12034179 | F231: =SUM(B231:E231) -> 1.8309895 | K231: =IFERROR(G232/每日收盤價!B231,0) -> 0 | L231: =IFERROR(H232/每日收盤價!C231,0) -> 0 | M231: =IFERROR(I232/每日收盤價!D231,0) -> 0 | N231: =IFERROR(J232/每日收盤價!E231,0) -> 0 | O231: =SUM(K231:N231) -> 0
A232: 2024-12-17 | B232: =B231*(1+$CD$2)*(1+每日報酬率!B232) -> 0 | C232: =C231*(1+$CD$2)*(1+每日報酬率!C232) -> 0.14154824 | D232: =D231*(1+$CD$2)*(1+每日報酬率!D232) -> 1.5554041 | E232: =E231*(1+$CD$2)*(1+每日報酬率!E232) -> 0.12381737 | F232: =SUM(B232:E232) -> 1.8207697 | K232: =IFERROR(G233/每日收盤價!B232,0) -> 0 | L232: =IFERROR(H233/每日收盤價!C232,0) -> 0 | M232: =IFERROR(I233/每日收盤價!D232,0) -> 0 | N232: =IFERROR(J233/每日收盤價!E232,0) -> 0 | O232: =SUM(K232:N232) -> 0
A233: 2024-12-18 | B233: =B232*(1+$CD$2)*(1+每日報酬率!B233) -> 0 | C233: =C232*(1+$CD$2)*(1+每日報酬率!C233) -> 0.14270847 | D233: =D232*(1+$CD$2)*(1+每日報酬率!D233) -> 1.569873 | E233: =E232*(1+$CD$2)*(1+每日報酬率!E233) -> 0.12338292 | F233: =SUM(B233:E233) -> 1.8359644 | K233: =IFERROR(G234/每日收盤價!B233,0) -> 0 | L233: =IFERROR(H234/每日收盤價!C233,0) -> 0 | M233: =IFERROR(I234/每日收盤價!D233,0) -> 0 | N233: =IFERROR(J234/每日收盤價!E233,0) -> 0 | O233: =SUM(K233:N233) -> 0
A234: 2024-12-19 | B234: =B233*(1+$CD$2)*(1+每日報酬率!B234) -> 0 | C234: =C233*(1+$CD$2)*(1+每日報酬率!C234) -> 0.14000126 | D234: =D233*(1+$CD$2)*(1+每日報酬率!D234) -> 1.5481697 | E234: =E233*(1+$CD$2)*(1+每日報酬率!E234) -> 0.12338292 | F234: =SUM(B234:E234) -> 1.8115539 | K234: =IFERROR(G235/每日收盤價!B234,0) -> 0 | L234: =IFERROR(H235/每日收盤價!C234,0) -> 0 | M234: =IFERROR(I235/每日收盤價!D234,0) -> 0 | N234: =IFERROR(J235/每日收盤價!E234,0) -> 0 | O234: =SUM(K234:N234) -> 0
A235: 2024-12-20 | B235: =B234*(1+$CD$2)*(1+每日報酬率!B235) -> 0 | C235: =C234*(1+$CD$2)*(1+每日報酬率!C235) -> 0.14000126 | D235: =D234*(1+$CD$2)*(1+每日報酬率!D235) -> 1.4975286 | E235: =E234*(1+$CD$2)*(1+每日報酬率!E235) -> 0.12077624 | F235: =SUM(B235:E235) -> 1.7583061 | K235: =IFERROR(G236/每日收盤價!B235,0) -> 0 | L235: =IFERROR(H236/每日收盤價!C235,0) -> 0 | M235: =IFERROR(I236/每日收盤價!D235,0) -> 0 | N235: =IFERROR(J236/每日收盤價!E235,0) -> 0 | O235: =SUM(K235:N235) -> 0
A236: 2024-12-23 | B236: =B235*(1+$CD$2)*(1+每日報酬率!B236) -> 0 | C236: =C235*(1+$CD$2)*(1+每日報酬率!C236) -> 0.14348196 | D236: =D235*(1+$CD$2)*(1+每日報酬率!D236) -> 1.5626386 | E236: =E235*(1+$CD$2)*(1+每日報酬率!E236) -> 0.12251402 | F236: =SUM(B236:E236) -> 1.8286346 | K236: =IFERROR(G237/每日收盤價!B236,0) -> 0 | L236: =IFERROR(H237/每日收盤價!C236,0) -> 0 | M236: =IFERROR(I237/每日收盤價!D236,0) -> 0 | N236: =IFERROR(J237/每日收盤價!E236,0) -> 0 | O236: =SUM(K236:N236) -> 0
A237: 2024-12-24 | B237: =B236*(1+$CD$2)*(1+每日報酬率!B237) -> 0 | C237: =C236*(1+$CD$2)*(1+每日報酬率!C237) -> 0.14348196 | D237: =D236*(1+$CD$2)*(1+每日報酬率!D237) -> 1.5626386 | E237: =E236*(1+$CD$2)*(1+每日報酬率!E237) -> 0.12207958 | F237: =SUM(B237:E237) -> 1.8282001 | K237: =IFERROR(G238/每日收盤價!B237,0) -> 0 | L237: =IFERROR(H238/每日收盤價!C237,0) -> 0 | M237: =IFERROR(I238/每日收盤價!D237,0) -> 0 | N237: =IFERROR(J238/每日收盤價!E237,0) -> 0 | O237: =SUM(K237:N237) -> 0
A238: 2024-12-25 | B238: =B237*(1+$CD$2)*(1+每日報酬率!B238) -> 0 | C238: =C237*(1+$CD$2)*(1+每日報酬率!C238) -> 0.14425545 | D238: =D237*(1+$CD$2)*(1+每日報酬率!D238) -> 1.569873 | E238: =E237*(1+$CD$2)*(1+每日報酬率!E238) -> 0.12251402 | F238: =SUM(B238:E238) -> 1.8366425 | K238: =IFERROR(G239/每日收盤價!B238,0) -> 0 | L238: =IFERROR(H239/每日收盤價!C238,0) -> 0 | M238: =IFERROR(I239/每日收盤價!D238,0) -> 0 | N238: =IFERROR(J239/每日收盤價!E238,0) -> 0 | O238: =SUM(K238:N238) -> 0
A239: 2024-12-26 | B239: =B238*(1+$CD$2)*(1+每日報酬率!B239) -> 0 | C239: =C238*(1+$CD$2)*(1+每日報酬率!C239) -> 0.14502893 | D239: =D238*(1+$CD$2)*(1+每日報酬率!D239) -> 1.569873 | E239: =E238*(1+$CD$2)*(1+每日報酬率!E239) -> 0.12338292 | F239: =SUM(B239:E239) -> 1.8382849 | K239: =IFERROR(G240/每日收盤價!B239,0) -> 0 | L239: =IFERROR(H240/每日收盤價!C239,0) -> 0 | M239: =IFERROR(I240/每日收盤價!D239,0) -> 0 | N239: =IFERROR(J240/每日收盤價!E239,0) -> 0 | O239: =SUM(K239:N239) -> 0
A240: 2024-12-27 | B240: =B239*(1+$CD$2)*(1+每日報酬率!B240) -> 0 | C240: =C239*(1+$CD$2)*(1+每日報酬率!C240) -> 0.14425545 | D240: =D239*(1+$CD$2)*(1+每日報酬率!D240) -> 1.5771074 | E240: =E239*(1+$CD$2)*(1+每日報酬率!E240) -> 0.12425181 | F240: =SUM(B240:E240) -> 1.8456147 | K240: =IFERROR(G241/每日收盤價!B240,0) -> 0 | L240: =IFERROR(H241/每日收盤價!C240,0) -> 0 | M240: =IFERROR(I241/每日收盤價!D240,0) -> 0 | N240: =IFERROR(J241/每日收盤價!E240,0) -> 0 | O240: =SUM(K240:N240) -> 0
A241: 2024-12-30 | B241: =B240*(1+$CD$2)*(1+每日報酬率!B241) -> 0 | C241: =C240*(1+$CD$2)*(1+每日報酬率!C241) -> 0.14309521 | D241: =D240*(1+$CD$2)*(1+每日報酬率!D241) -> 1.5771074 | E241: =E240*(1+$CD$2)*(1+每日報酬率!E241) -> 0.12338292 | F241: =SUM(B241:E241) -> 1.8435856 | K241: =IFERROR(G242/每日收盤價!B241,0) -> 0 | L241: =IFERROR(H242/每日收盤價!C241,0) -> 0 | M241: =IFERROR(I242/每日收盤價!D241,0) -> 0 | N241: =IFERROR(J242/每日收盤價!E241,0) -> 0 | O241: =SUM(K241:N241) -> 0
A242: 2024-12-31 | B242: =B241*(1+$CD$2)*(1+每日報酬率!B242) -> 0 | C242: =C241*(1+$CD$2)*(1+每日報酬率!C242) -> 0.14232173 | D242: =D241*(1+$CD$2)*(1+每日報酬率!D242) -> 1.5554041 | E242: =E241*(1+$CD$2)*(1+每日報酬率!E242) -> 0.12294847 | F242: =SUM(B242:E242) -> 1.8206743 | K242: =IFERROR(G243/每日收盤價!B242,0) -> 0 | L242: =IFERROR(H243/每日收盤價!C242,0) -> 0 | M242: =IFERROR(I243/每日收盤價!D242,0) -> 0 | N242: =IFERROR(J243/每日收盤價!E242,0) -> 0.0204947 | O242: =SUM(K242:N242) -> 0.0204947
A243: 2025-01-02 | B243: =B242*(1+$CD$2)*(1+每日報酬率!B243) -> 0 | C243: =C242*(1+$CD$2)*(1+每日報酬率!C243) -> 0.14116149 | D243: =D242*(1+$CD$2)*(1+每日報酬率!D243) -> 1.5409353 | E243: =E242*(1+$CD$2)*(1+每日報酬率!E243) -> 0.11730066 | F243: =SUM(B243:E243) -> 1.7993974 | J243: 29 | K243: =IFERROR(G244/每日收盤價!B243,0) -> 0 | L243: =IFERROR(H244/每日收盤價!C243,0) -> 0 | M243: =IFERROR(I244/每日收盤價!D243,0) -> 0 | N243: =IFERROR(J244/每日收盤價!E243,0) -> 0 | O243: =SUM(K243:N243) -> 0
A244: 2025-01-03 | B244: =B243*(1+$CD$2)*(1+每日報酬率!B244) -> 0 | C244: =C243*(1+$CD$2)*(1+每日報酬率!C244) -> 0.14000126 | D244: =D243*(1+$CD$2)*(1+每日報酬率!D244) -> 1.5554041 | E244: =E243*(1+$CD$2)*(1+每日報酬率!E244) -> 0.118604 | F244: =SUM(B244:E244) -> 1.8140094 | K244: =IFERROR(G245/每日收盤價!B244,0) -> 0 | L244: =IFERROR(H245/每日收盤價!C244,0) -> 0 | M244: =IFERROR(I245/每日收盤價!D244,0) -> 0 | N244: =IFERROR(J245/每日收盤價!E244,0) -> 0 | O244: =SUM(K244:N244) -> 0
A245: 2025-01-06 | B245: =B244*(1+$CD$2)*(1+每日報酬率!B245) -> 0 | C245: =C244*(1+$CD$2)*(1+每日報酬率!C245) -> 0.14270847 | D245: =D244*(1+$CD$2)*(1+每日報酬率!D245) -> 1.6277485 | E245: =E244*(1+$CD$2)*(1+每日報酬率!E245) -> 0.12381737 | F245: =SUM(B245:E245) -> 1.8942743 | K245: =IFERROR(G246/每日收盤價!B245,0) -> 0 | L245: =IFERROR(H246/每日收盤價!C245,0) -> 0 | M245: =IFERROR(I246/每日收盤價!D245,0) -> 0 | N245: =IFERROR(J246/每日收盤價!E245,0) -> 0 | O245: =SUM(K245:N245) -> 0
A246: 2025-01-07 | B246: =B245*(1+$CD$2)*(1+每日報酬率!B246) -> 0 | C246: =C245*(1+$CD$2)*(1+每日報酬率!C246) -> 0.14696265 | D246: =D245*(1+$CD$2)*(1+每日報酬率!D246) -> 1.6349829 | E246: =E245*(1+$CD$2)*(1+每日報酬率!E246) -> 0.12946517 | F246: =SUM(B246:E246) -> 1.9114108 | K246: =IFERROR(G247/每日收盤價!B246,0) -> 0 | L246: =IFERROR(H247/每日收盤價!C246,0) -> 0 | M246: =IFERROR(I247/每日收盤價!D246,0) -> 0 | N246: =IFERROR(J247/每日收盤價!E246,0) -> 0 | O246: =SUM(K246:N246) -> 0
A247: 2025-01-08 | B247: =B246*(1+$CD$2)*(1+每日報酬率!B247) -> 0 | C247: =C246*(1+$CD$2)*(1+每日報酬率!C247) -> 0.14541568 | D247: =D246*(1+$CD$2)*(1+每日報酬率!D247) -> 1.5988108 | E247: =E246*(1+$CD$2)*(1+每日報酬率!E247) -> 0.12772739 | F247: =SUM(B247:E247) -> 1.8719538 | K247: =IFERROR(G248/每日收盤價!B247,0) -> 0 | L247: =IFERROR(H248/每日收盤價!C247,0) -> 0 | M247: =IFERROR(I248/每日收盤價!D247,0) -> 0 | N247: =IFERROR(J248/每日收盤價!E247,0) -> 0 | O247: =SUM(K247:N247) -> 0
A248: 2025-01-09 | B248: =B247*(1+$CD$2)*(1+每日報酬率!B248) -> 0 | C248: =C247*(1+$CD$2)*(1+每日報酬率!C248) -> 0.14154824 | D248: =D247*(1+$CD$2)*(1+每日報酬率!D248) -> 1.5915763 | E248: =E247*(1+$CD$2)*(1+每日報酬率!E248) -> 0.12512071 | F248: =SUM(B248:E248) -> 1.8582453 | K248: =IFERROR(G249/每日收盤價!B248,0) -> 0 | L248: =IFERROR(H249/每日收盤價!C248,0) -> 0 | M248: =IFERROR(I249/每日收盤價!D248,0) -> 0 | N248: =IFERROR(J249/每日收盤價!E248,0) -> 0 | O248: =SUM(K248:N248) -> 0
A249: 2025-01-10 | B249: =B248*(1+$CD$2)*(1+每日報酬率!B249) -> 0 | C249: =C248*(1+$CD$2)*(1+每日報酬率!C249) -> 0.14038801 | D249: =D248*(1+$CD$2)*(1+每日報酬率!D249) -> 1.5915763 | E249: =E248*(1+$CD$2)*(1+每日報酬率!E249) -> 0.12729294 | F249: =SUM(B249:E249) -> 1.8592573 | K249: =IFERROR(G250/每日收盤價!B249,0) -> 0 | L249: =IFERROR(H250/每日收盤價!C249,0) -> 0 | M249: =IFERROR(I250/每日收盤價!D249,0) -> 0 | N249: =IFERROR(J250/每日收盤價!E249,0) -> 0 | O249: =SUM(K249:N249) -> 0
A250: 2025-01-13 | B250: =B249*(1+$CD$2)*(1+每日報酬率!B250) -> 0 | C250: =C249*(1+$CD$2)*(1+每日報酬率!C250) -> 0.13265313 | D250: =D249*(1+$CD$2)*(1+每日報酬率!D250) -> 1.5554041 | E250: =E249*(1+$CD$2)*(1+每日報酬率!E250) -> 0.12077624 | F250: =SUM(B250:E250) -> 1.8088335 | K250: =IFERROR(G251/每日收盤價!B250,0) -> 0 | L250: =IFERROR(H251/每日收盤價!C250,0) -> 0 | M250: =IFERROR(I251/每日收盤價!D250,0) -> 0 | N250: =IFERROR(J251/每日收盤價!E250,0) -> 0 | O250: =SUM(K250:N250) -> 0
A251: 2025-01-14 | B251: =B250*(1+$CD$2)*(1+每日報酬率!B251) -> 0 | C251: =C250*(1+$CD$2)*(1+每日報酬率!C251) -> 0.13497359 | D251: =D250*(1+$CD$2)*(1+每日報酬率!D251) -> 1.5771074 | E251: =E250*(1+$CD$2)*(1+每日報酬率!E251) -> 0.12164513 | F251: =SUM(B251:E251) -> 1.8337262 | K251: =IFERROR(G252/每日收盤價!B251,0) -> 0 | L251: =IFERROR(H252/每日收盤價!C251,0) -> 0 | M251: =IFERROR(I252/每日收盤價!D251,0) -> 0 | N251: =IFERROR(J252/每日收盤價!E251,0) -> 0 | O251: =SUM(K251:N251) -> 0
A252: 2025-01-15 | B252: =B251*(1+$CD$2)*(1+每日報酬率!B252) -> 0 | C252: =C251*(1+$CD$2)*(1+每日報酬率!C252) -> 0.13226639 | D252: =D251*(1+$CD$2)*(1+每日報酬率!D252) -> 1.5409353 | E252: =E251*(1+$CD$2)*(1+每日報酬率!E252) -> 0.12338292 | F252: =SUM(B252:E252) -> 1.7965846 | K252: =IFERROR(G253/每日收盤價!B252,0) -> 0 | L252: =IFERROR(H253/每日收盤價!C252,0) -> 0 | M252: =IFERROR(I253/每日收盤價!D252,0) -> 0 | N252: =IFERROR(J253/每日收盤價!E252,0) -> 0 | O252: =SUM(K252:N252) -> 0
A253: 2025-01-16 | B253: =B252*(1+$CD$2)*(1+每日報酬率!B253) -> 0 | C253: =C252*(1+$CD$2)*(1+每日報酬率!C253) -> 0.13420011 | D253: =D252*(1+$CD$2)*(1+每日報酬率!D253) -> 1.5988108 | E253: =E252*(1+$CD$2)*(1+每日報酬率!E253) -> 0.12685849 | F253: =SUM(B253:E253) -> 1.8598694 | K253: =IFERROR(G254/每日收盤價!B253,0) -> 0 | L253: =IFERROR(H254/每日收盤價!C253,0) -> 0 | M253: =IFERROR(I254/每日收盤價!D253,0) -> 0 | N253: =IFERROR(J254/每日收盤價!E253,0) -> 0 | O253: =SUM(K253:N253) -> 0
A254: 2025-01-17 | B254: =B253*(1+$CD$2)*(1+每日報酬率!B254) -> 0 | C254: =C253*(1+$CD$2)*(1+每日報酬率!C254) -> 0.13420011 | D254: =D253*(1+$CD$2)*(1+每日報酬率!D254) -> 1.6205141 | E254: =E253*(1+$CD$2)*(1+每日報酬率!E254) -> 0.12425181 | F254: =SUM(B254:E254) -> 1.878966 | K254: =IFERROR(G255/每日收盤價!B254,0) -> 0 | L254: =IFERROR(H255/每日收盤價!C254,0) -> 0 | M254: =IFERROR(I255/每日收盤價!D254,0) -> 0 | N254: =IFERROR(J255/每日收盤價!E254,0) -> 0 | O254: =SUM(K254:N254) -> 0
A255: 2025-01-20 | B255: =B254*(1+$CD$2)*(1+每日報酬率!B255) -> 0 | C255: =C254*(1+$CD$2)*(1+每日報酬率!C255) -> 0.1376808 | D255: =D254*(1+$CD$2)*(1+每日報酬率!D255) -> 1.6205141 | E255: =E254*(1+$CD$2)*(1+每日報酬率!E255) -> 0.12555515 | F255: =SUM(B255:E255) -> 1.88375 | K255: =IFERROR(G256/每日收盤價!B255,0) -> 0 | L255: =IFERROR(H256/每日收盤價!C255,0) -> 0 | M255: =IFERROR(I256/每日收盤價!D255,0) -> 0 | N255: =IFERROR(J256/每日收盤價!E255,0) -> 0 | O255: =SUM(K255:N255) -> 0
...

Sheet 標準化權重
A1: date | B1: 2308 | C1: 2317 | D1: 2330 | E1: 2454
A2: 2024-01-03
A3: 2024-01-04 | B3: =投資後權重!B3/投資後權重!$F3 -> 0 | C3: =投資後權重!C3/投資後權重!$F3 -> 0.080420933 | D3: =投資後權重!D3/投資後權重!$F3 -> 0.83896756 | E3: =投資後權重!E3/投資後權重!$F3 -> 0.08061151 | F3: =SUM(B3:E3) -> 1
A4: 2024-01-05 | B4: =投資後權重!B4/投資後權重!$F4 -> 0 | C4: =投資後權重!C4/投資後權重!$F4 -> 0.080938457 | D4: =投資後權重!D4/投資後權重!$F4 -> 0.83854326 | E4: =投資後權重!E4/投資後權重!$F4 -> 0.080518287 | F4: =SUM(B4:E4) -> 1
A5: 2024-01-08 | B5: =投資後權重!B5/投資後權重!$F5 -> 0 | C5: =投資後權重!C5/投資後權重!$F5 -> 0.078353646 | D5: =投資後權重!D5/投資後權重!$F5 -> 0.8418663 | E5: =投資後權重!E5/投資後權重!$F5 -> 0.079780051 | F5: =SUM(B5:E5) -> 1
A6: 2024-01-09 | B6: =投資後權重!B6/投資後權重!$F6 -> 0 | C6: =投資後權重!C6/投資後權重!$F6 -> 0.077607581 | D6: =投資後權重!D6/投資後權重!$F6 -> 0.84229029 | E6: =投資後權重!E6/投資後權重!$F6 -> 0.08010213 | F6: =SUM(B6:E6) -> 1
A7: 2024-01-10 | B7: =投資後權重!B7/投資後權重!$F7 -> 0 | C7: =投資後權重!C7/投資後權重!$F7 -> 0.07714688 | D7: =投資後權重!D7/投資後權重!$F7 -> 0.84277688 | E7: =投資後權重!E7/投資後權重!$F7 -> 0.080076236 | F7: =SUM(B7:E7) -> 1
A8: 2024-01-11 | B8: =投資後權重!B8/投資後權重!$F8 -> 0 | C8: =投資後權重!C8/投資後權重!$F8 -> 0.077306469 | D8: =投資後權重!D8/投資後權重!$F8 -> 0.8431965 | E8: =投資後權重!E8/投資後權重!$F8 -> 0.079497032 | F8: =SUM(B8:E8) -> 1
A9: 2024-01-12 | B9: =投資後權重!B9/投資後權重!$F9 -> 0 | C9: =投資後權重!C9/投資後權重!$F9 -> 0.077489293 | D9: =投資後權重!D9/投資後權重!$F9 -> 0.84230599 | E9: =投資後權重!E9/投資後權重!$F9 -> 0.080204722 | F9: =SUM(B9:E9) -> 1
A10: 2024-01-15 | B10: =投資後權重!B10/投資後權重!$F10 -> 0 | C10: =投資後權重!C10/投資後權重!$F10 -> 0.076938154 | D10: =投資後權重!D10/投資後權重!$F10 -> 0.84337512 | E10: =投資後權重!E10/投資後權重!$F10 -> 0.079686729 | F10: =SUM(B10:E10) -> 1
A11: 2024-01-16 | B11: =投資後權重!B11/投資後權重!$F11 -> 0 | C11: =投資後權重!C11/投資後權重!$F11 -> 0.077791433 | D11: =投資後權重!D11/投資後權重!$F11 -> 0.84399752 | E11: =投資後權重!E11/投資後權重!$F11 -> 0.078211051 | F11: =SUM(B11:E11) -> 1
A12: 2024-01-17 | B12: =投資後權重!B12/投資後權重!$F12 -> 0 | C12: =投資後權重!C12/投資後權重!$F12 -> 0.076781599 | D12: =投資後權重!D12/投資後權重!$F12 -> 0.84632618 | E12: =投資後權重!E12/投資後權重!$F12 -> 0.076892225 | F12: =SUM(B12:E12) -> 1
A13: 2024-01-18 | B13: =投資後權重!B13/投資後權重!$F13 -> 0 | C13: =投資後權重!C13/投資後權重!$F13 -> 0.076811997 | D13: =投資後權重!D13/投資後權重!$F13 -> 0.84571162 | E13: =投資後權重!E13/投資後權重!$F13 -> 0.077476381 | F13: =SUM(B13:E13) -> 1
A14: 2024-01-19 | B14: =投資後權重!B14/投資後權重!$F14 -> 0 | C14: =投資後權重!C14/投資後權重!$F14 -> 0.073099168 | D14: =投資後權重!D14/投資後權重!$F14 -> 0.85173032 | E14: =投資後權重!E14/投資後權重!$F14 -> 0.075170512 | F14: =SUM(B14:E14) -> 1
... A479: 2025-12-22 | B479: =投資後權重!B479/投資後權重!$F479 -> 0 | C479: =投資後權重!C479/投資後權重!$F479 -> 0.07194995 | D479: =投資後權重!D479/投資後權重!$F479 -> 0.88024083 | E479: =投資後權重!E479/投資後權重!$F479 -> 0.047809221 | F479: =SUM(B479:E479) -> 1

Sheet 驗證 
A1: date | B1: 2308 | C1: 2317 | D1: 2330 | E1: 2454
A2: 2024-01-03
A3: 2024-01-04 | B3: =標準化權重!B3-每日權重!B3 -> 0 | C3: =標準化權重!C3-每日權重!C3 -> 0 | D3: =標準化權重!D3-每日權重!D3 -> 0 | E3: =標準化權重!E3-每日權重!E3 -> 0
A4: 2024-01-05 | B4: =標準化權重!B4-每日權重!B4 -> 0 | C4: =標準化權重!C4-每日權重!C4 -> 0 | D4: =標準化權重!D4-每日權重!D4 -> 0 | E4: =標準化權重!E4-每日權重!E4 -> 0
A5: 2024-01-08 | B5: =標準化權重!B5-每日權重!B5 -> 0 | C5: =標準化權重!C5-每日權重!C5 -> 0 | D5: =標準化權重!D5-每日權重!D5 -> 0 | E5: =標準化權重!E5-每日權重!E5 -> 0
A6: 2024-01-09 | B6: =標準化權重!B6-每日權重!B6 -> 0 | C6: =標準化權重!C6-每日權重!C6 -> 0 | D6: =標準化權重!D6-每日權重!D6 -> 0 | E6: =標準化權重!E6-每日權重!E6 -> 0
A7: 2024-01-10 | B7: =標準化權重!B7-每日權重!B7 -> 0 | C7: =標準化權重!C7-每日權重!C7 -> 0 | D7: =標準化權重!D7-每日權重!D7 -> 0 | E7: =標準化權重!E7-每日權重!E7 -> 0
A8: 2024-01-11 | B8: =標準化權重!B8-每日權重!B8 -> 0 | C8: =標準化權重!C8-每日權重!C8 -> 0 | D8: =標準化權重!D8-每日權重!D8 -> 0 | E8: =標準化權重!E8-每日權重!E8 -> 0
A9: 2024-01-12 | B9: =標準化權重!B9-每日權重!B9 -> 0 | C9: =標準化權重!C9-每日權重!C9 -> 0 | D9: =標準化權重!D9-每日權重!D9 -> 0 | E9: =標準化權重!E9-每日權重!E9 -> 0
A10: 2024-01-15 | B10: =標準化權重!B10-每日權重!B10 -> 0 | C10: =標準化權重!C10-每日權重!C10 -> 0 | D10: =標準化權重!D10-每日權重!D10 -> 0 | E10: =標準化權重!E10-每日權重!E10 -> 0
A11: 2024-01-16 | B11: =標準化權重!B11-每日權重!B11 -> 0 | C11: =標準化權重!C11-每日權重!C11 -> 0 | D11: =標準化權重!D11-每日權重!D11 -> 0 | E11: =標準化權重!E11-每日權重!E11 -> 0
A12: 2024-01-17 | B12: =標準化權重!B12-每日權重!B12 -> 0 | C12: =標準化權重!C12-每日權重!C12 -> 0 | D12: =標準化權重!D12-每日權重!D12 -> 0 | E12: =標準化權重!E12-每日權重!E12 -> 0
A13: 2024-01-18 | B13: =標準化權重!B13-每日權重!B13 -> 0 | C13: =標準化權重!C13-每日權重!C13 -> 0 | D13: =標準化權重!D13-每日權重!D13 -> 0 | E13: =標準化權重!E13-每日權重!E13 -> 0
A14: 2024-01-19 | B14: =標準化權重!B14-每日權重!B14 -> 0 | C14: =標準化權重!C14-每日權重!C14 -> 0 | D14: =標準化權重!D14-每日權重!D14 -> 0 | E14: =標準化權重!E14-每日權重!E14 -> 0
... A479: 2025-12-22 | B479: =標準化權重!B479-每日權重!B479 -> -0.05720561 | C479: =標準化權重!C479-每日權重!C479 -> 0.0013164257 | D479: =標準化權重!D479-每日權重!D479 -> 0.0080799633 | E479: =標準化權重!E479-每日權重!E479 -> 0.047809221

Sheet 每日權重
A1: date | B1: 2308 | C1: 2317 | D1: 2330 | E1: 2454
A2: 2024-01-03 | C2: 0.080652758 | D2: 0.83447278 | E2: 0.084874462
A3: 2024-01-04 | C3: 0.080420933 | D3: 0.83896756 | E3: 0.08061151
A4: 2024-01-05 | C4: 0.080938457 | D4: 0.83854326 | E4: 0.080518287
A5: 2024-01-08 | C5: 0.078353646 | D5: 0.8418663 | E5: 0.079780051
A6: 2024-01-09 | C6: 0.077607581 | D6: 0.84229029 | E6: 0.08010213
A7: 2024-01-10 | C7: 0.07714688 | D7: 0.84277688 | E7: 0.080076236
A8: 2024-01-11 | C8: 0.077306469 | D8: 0.8431965 | E8: 0.079497032
A9: 2024-01-12 | C9: 0.077489293 | D9: 0.84230599 | E9: 0.080204722
A10: 2024-01-15 | C10: 0.076938154 | D10: 0.84337512 | E10: 0.079686729
A11: 2024-01-16 | C11: 0.077791433 | D11: 0.84399752 | E11: 0.078211051
A12: 2024-01-17 | C12: 0.076781599 | D12: 0.84632618 | E12: 0.076892225
A13: 2024-01-18 | C13: 0.076811997 | D13: 0.84571162 | E13: 0.077476381
... A427: 2025-10-07 | C427: 0.072445691 | D427: 0.88039854 | E427: 0.047155769
A428: 2025-10-08 | B428: 0.060389793 | C428: 0.072760251 | D428: 0.86684996
A429: 2025-10-09 | B429: 0.060571624 | C429: 0.070549607 | D429: 0.86887877
A430: 2025-10-13 | B430: 0.063461043 | C430: 0.068939277 | D430: 0.86759968
A431: 2025-10-14 | B431: 0.061026723 | C431: 0.066572174 | D431: 0.8724011
A432: 2025-10-15 | B432: 0.060855462 | C432: 0.065038529 | D432: 0.87410601
A433: 2025-10-16 | B433: 0.060384435 | C433: 0.069011766 | D433: 0.8706038
A434: 2025-10-17 | B434: 0.060113176 | C434: 0.071596127 | D434: 0.8682907
A435: 2025-10-20 | B435: 0.059719097 | C435: 0.073714464 | D435: 0.86656644
A436: 2025-10-21 | B436: 0.059986363 | C436: 0.07383587 | D436: 0.86617777
A437: 2025-10-22 | B437: 0.06063049 | C437: 0.075721601 | D437: 0.86364791
A438: 2025-10-23 | B438: 0.060496007 | C438: 0.075200439 | D438: 0.86430355
A439: 2025-10-27 | B439: 0.062597761 | C439: 0.075754612 | D439: 0.86164763
... A479: 2025-12-22 | B479: 0.05720561 | C479: 0.070633525 | D479: 0.87216086

Sheet 現金股利
A1: date | B1: 2308 | C1: 2317 | D1: 2330 | E1: 2454
A2: 45294
A3: 45295 | E3: 24.6
A4: 45299
A5: 45302
A6: 45306
A7: 45307
A8: 45308
A9: 45309
A10: 45310
A11: 45313
A12: 45316
A13: 45344
A14: 45348
A15: 45349
... A22: 45365
A23: 45369 | D23: 3.4997897
A24: 45370
A25: 45371
A26: 45372
A27: 45373
A28: 45376
A29: 45377
A30: 45378
A31: 45379
A32: 45380
A33: 45383
A34: 45384
A35: 45385
... A67: 45455
A68: 45456 | D68: 3.4997897
A69: 45457
A70: 45460
A71: 45461 | B71: 6.43
A72: 45462
A73: 45463
A74: 45464
A75: 45467
A76: 45468
A77: 45469
A78: 45470
A79: 45471
A80: 45474
A81: 45475 | C81: 5.4
A82: 45476
A83: 45477 | E83: 30.405309
A84: 45478
A85: 45481
A86: 45482
A87: 45483
A88: 45484
A89: 45485
A90: 45488
A91: 45489
A92: 45490
A93: 45491
A94: 45492
A95: 45495
... A129: 45545
A130: 45547 | D130: 4.0001382
A131: 45548
A132: 45551
A133: 45553
A134: 45554
A135: 45555
A136: 45558
A137: 45559
A138: 45560
A139: 45561
A140: 45566
A141: 45569
A142: 45572
... A174: 45637
A175: 45638 | D175: 3.9996371
A176: 45642
A177: 45643
A178: 45644
A179: 45645
A180: 45646
A181: 45650
A182: 45651
A183: 45652
A184: 45656
A185: 45657
A186: 45659 | E186: 29
A187: 45660
A188: 45663
A189: 45665
A190: 45667
A191: 45673
A192: 45674
A193: 45677
A194: 45678
A195: 45679
A196: 45693
A197: 45694
A198: 45699
... A216: 45733
A217: 45734 | D217: 4.5000204
A218: 45735
...

Sheet 每日收盤價
A1: date | B1: 2308 | C1: 2317 | D1: 2330 | E1: 2454
A2: 2024-01-03 | C2: 104.5 | D2: 578 | E2: 953
A3: 2024-01-04 | C3: 104 | D3: 580 | E3: 928
A4: 2024-01-05 | C4: 104 | D4: 576 | E4: 921
A5: 2024-01-08 | C5: 101.5 | D5: 583 | E5: 920
A6: 2024-01-09 | C6: 101 | D6: 586 | E6: 928
A7: 2024-01-10 | C7: 100 | D7: 584 | E7: 924
A8: 2024-01-11 | C8: 100.5 | D8: 586 | E8: 920
A9: 2024-01-12 | C9: 100.5 | D9: 584 | E9: 926
A10: 2024-01-15 | C10: 100 | D10: 586 | E10: 922
A11: 2024-01-16 | C11: 100 | D11: 580 | E11: 895
A12: 2024-01-17 | C12: 98.6 | D12: 581 | E12: 879
A13: 2024-01-18 | C13: 99.9 | D13: 588 | E13: 897
... A427: 2025-10-07 | C427: 228.5 | D427: 1435 | E427: 1325
A428: 2025-10-08 | B428: 981 | C428: 225 | D428: 1415
A429: 2025-10-09 | B429: 999 | C429: 221.5 | D429: 1440
A430: 2025-10-13 | B430: 1030 | C430: 213 | D430: 1415
A431: 2025-10-14 | B431: 992 | C431: 206 | D431: 1425
A432: 2025-10-15 | B432: 1015 | C432: 206.5 | D432: 1465
A433: 2025-10-16 | B433: 1025 | C433: 223 | D433: 1485
A434: 2025-10-17 | B434: 999 | C434: 226.5 | D434: 1450
A435: 2025-10-20 | B435: 1015 | C435: 238.5 | D435: 1480
A436: 2025-10-21 | B436: 1020 | C436: 239 | D436: 1480
A437: 2025-10-22 | B437: 1020 | C437: 242.5 | D437: 1460
A438: 2025-10-23 | B438: 1010 | C438: 239 | D438: 1450
A439: 2025-10-27 | B439: 1070 | C439: 246.5 | D439: 1480
... A479: 2025-12-22 | B479: 953 | C479: 224 | D479: 1465

Sheet 每日報酬率
A1: date | B1: 2308 | C1: 2317 | D1: 2330 | E1: 2454
A2: 2024-01-03 | C2: 0 | D2: 0 | E2: 0
A3: 2024-01-04 | C3: -0.004784689 | D3: 0.0034602076 | E3: -0.026232949
A4: 2024-01-05 | C4: 0 | D4: -0.0068965517 | E4: -0.0075431034
A5: 2024-01-08 | C5: -0.024038462 | D5: 0.012152778 | E5: -0.0010857763
A6: 2024-01-09 | C6: -0.0049261084 | D6: 0.0051457976 | E6: 0.0086956522
A7: 2024-01-10 | C7: -0.0099009901 | D7: -0.0034129693 | E7: -0.0043103448
A8: 2024-01-11 | C8: 0.005 | D8: 0.0034246575 | E8: -0.0043290043
A9: 2024-01-12 | C9: 0 | D9: -0.0034129693 | E9: 0.0065217391
A10: 2024-01-15 | C10: -0.0049751244 | D10: 0.0034246575 | E10: -0.0043196544
A11: 2024-01-16 | C11: 0 | D11: -0.010238908 | E11: -0.029284165
A12: 2024-01-17 | C12: -0.014 | D12: 0.0017241379 | E12: -0.017877095
A13: 2024-01-18 | C13: 0.013184584 | D13: 0.012048193 | E13: 0.020477816
... A427: 2025-10-07 | C427: 0.0088300221 | D427: 0.025 | E427: 0.0037878788
A428: 2025-10-08 | B428: -0.0060790274 | C428: -0.015317287 | D428: -0.013937282
A429: 2025-10-09 | B429: 0.018348624 | C429: -0.015555556 | D429: 0.017667845
A430: 2025-10-13 | B430: 0.031031031 | C430: -0.038374718 | D430: -0.017361111
A431: 2025-10-14 | B431: -0.036893204 | C431: -0.03286385 | D431: 0.0070671378
A432: 2025-10-15 | B432: 0.023185484 | C432: 0.0024271845 | D432: 0.028070175
A433: 2025-10-16 | B433: 0.0098522167 | C433: 0.079903148 | D433: 0.013651877
A434: 2025-10-17 | B434: -0.025365854 | C434: 0.015695067 | D434: -0.023569024
A435: 2025-10-20 | B435: 0.016016016 | C435: 0.052980132 | D435: 0.020689655
A436: 2025-10-21 | B436: 0.0049261084 | C436: 0.0020964361 | D436: 0
A437: 2025-10-22 | B437: 0 | C437: 0.014644351 | D437: -0.013513514
A438: 2025-10-23 | B438: -0.0098039216 | C438: -0.01443299 | D438: -0.0068493151
A439: 2025-10-27 | B439: 0.059405941 | C439: 0.031380753 | D439: 0.020689655
... A479: 2025-12-22 | B479: 0.046103183 | C479: 0.011286682 | D479: 0.024475524

Sheet 每日貢獻度
A1: date | B1: 2308 | C1: 2317 | D1: 2330 | E1: 2454 | F1: total
A2: 2024-01-03 | C2: 0 | D2: 0 | E2: 0 | F2: 0
A3: 2024-01-04 | C3: -0.00038589836 | D3: 0.0028874491 | E3: -0.0022265074 | F3: 0.00027504329
A4: 2024-01-05 | C4: 0 | D4: -0.0057859831 | E4: -0.00060806096 | F4: -0.0063940441
A5: 2024-01-08 | C5: -0.001945636 | D5: 0.01019063 | E5: -8.742485e-05 | F5: 0.008157569
A6: 2024-01-09 | C6: -0.00038597855 | D6: 0.0043320736 | E6: 0.00069373957 | F6: 0.0046398346
A7: 2024-01-10 | C7: -0.00076839189 | D7: -0.0028747109 | E7: -0.0003452678 | F7: -0.0039883706
A8: 2024-01-11 | C8: 0.0003857344 | D8: 0.0028862222 | E8: -0.00034665037 | F8: 0.0029253062
A9: 2024-01-12 | C9: 0 | D9: -0.0028778038 | E9: 0.0005184589 | F9: -0.0023593448
A10: 2024-01-15 | C10: -0.00038551887 | D10: 0.0028846095 | E10: -0.00034645668 | F10: 0.002152634
A11: 2024-01-16 | C11: 0 | D11: -0.0086352401 | E11: -0.0023335593 | F11: -0.010968799
A12: 2024-01-17 | C12: -0.0010890801 | D12: 0.0014551681 | E12: -0.0013981864 | F12: -0.0010320983
A13: 2024-01-18 | C13: 0.0010123335 | D13: 0.010196701 | E13: 0.0015745848 | F13: 0.012783619
... A427: 2025-10-07 | C427: 0.00064855102 | D427: 0.021962575 | E427: 0.00018200225 | F427: 0.022793128
A428: 2025-10-08 | B428: -0.00036434551 | C428: -0.0011164708 | D428: -0.012086071 | F428: -0.013566887
A429: 2025-10-09 | B429: 0.0011080696 | C429: -0.0011318261 | D429: 0.01531537 | F429: 0.015291614
A430: 2025-10-13 | B430: 0.0018796 | C430: -0.0027073213 | D430: -0.015084701 | F430: -0.015912422
A431: 2025-10-14 | B431: -0.0023412812 | C431: -0.00226561 | D431: 0.0061314465 | F431: 0.0015245553
A432: 2025-10-15 | B432: 0.0014149341 | C432: 0.00016158295 | D432: 0.024488452 | F432: 0.026064969
A433: 2025-10-16 | B433: 0.0005995612 | C433: 0.0051967832 | D433: 0.011933188 | F433: 0.017729532
A434: 2025-10-17 | B434: -0.0015317027 | C434: 0.0010831443 | D434: -0.020519281 | F434: -0.02096784
A435: 2025-10-20 | B435: 0.00096277359 | C435: 0.0037931723 | D435: 0.017964635 | F435: 0.022720581
A436: 2025-10-21 | B436: 0.00029418274 | C436: 0.00015453766 | D436: 0 | F436: 0.0004487204
A437: 2025-10-22 | B437: 0 | C437: 0.0010812784 | D437: -0.011705105 | F437: -0.010623827
A438: 2025-10-23 | B438: -0.00059441657 | C438: -0.0010928891 | D438: -0.0059153966 | F438: -0.0076027023
A439: 2025-10-27 | B439: 0.0035938222 | C439: 0.0023598464 | D439: 0.017882143 | F439: 0.023835811
... A479: 2025-12-22 | B479: 0.0025835103 | C479: 0.00080782641 | D479: 0.021352179 | F479: 0.024743515

Sheet 調倉摘要
A1: review_date | B1: effective_date | C1: total_stocks | D1: stocks_added | E1: stocks_removed | F1: stocks_maintained | G1: turnover
A2: 2024-01-03 | B2: 2024-01-03 | C2: 3 | D2: 0 | E2: 0 | F2: 3 | G2: 0
A3: 2024-03-29 | B3: 2024-04-09 | C3: 3 | D3: 0 | E3: 0 | F3: 3 | G3: 0.004579639
A4: 2024-06-28 | B4: 2024-07-05 | C4: 3 | D4: 0 | E4: 0 | F4: 3 | G4: 0.0011102038
A5: 2024-09-30 | B5: 2024-10-09 | C5: 3 | D5: 0 | E5: 0 | F5: 3 | G5: 0.0035705927
A6: 2024-12-31 | B6: 2025-01-08 | C6: 3 | D6: 0 | E6: 0 | F6: 3 | G6: 0.0039519779
A7: 2025-03-31 | B7: 2025-04-09 | C7: 3 | D7: 0 | E7: 0 | F7: 3 | G7: 0.0031541676
A8: 2025-06-30 | B8: 2025-07-07 | C8: 3 | D8: 0 | E8: 0 | F8: 3 | G8: 0.0022112385
A9: 2025-09-30 | B9: 2025-10-08 | C9: 3 | D9: 1 | E9: 1 | F9: 2 | G9: 0.057798385

Sheet 過渡期權重
A1: date | B1: portfolio_type | C1: stock_id | D1: weight
A2: 2024-03-29 | B2: old | C2: 2330 | D2: 0.83615071
A3: 2024-03-29 | B3: old | C3: 2454 | D3: 0.077382176
A4: 2024-03-29 | B4: old | C4: 2317 | D4: 0.086467117
A5: 2024-03-29 | B5: new | C5: 2330 | D5: 0.83736079
A6: 2024-03-29 | B6: new | C6: 2317 | D6: 0.082070491
A7: 2024-03-29 | B7: new | C7: 2454 | D7: 0.080568717
A8: 2024-04-01 | B8: old | C8: 2330 | D8: 0.83622279
A9: 2024-04-01 | B9: old | C9: 2454 | D9: 0.07600028
A10: 2024-04-01 | B10: old | C10: 2317 | D10: 0.087776931
A11: 2024-04-01 | B11: new | C11: 2330 | D11: 0.83753633
A12: 2024-04-01 | B12: new | C12: 2317 | D12: 0.083323987
A13: 2024-04-01 | B13: new | C13: 2454 | D13: 0.079139682
... A211: 2025-10-07 | B211: new | C211: 2308 | D211: 0.059934837
