Workbook

Sheet 每日指數值
A1: date | B1: price_index | C1: total_return_index | D1: price_daily_return | E1: tr_daily_return
A2: 2024-01-03 | B2: 100 | C2: 100
A3: 2024-01-04 | B3: 99.968476 | C3: 100.09495 | D3: -0.00031523592 | E3: 0.00094949081
A4: 2024-01-05 | B4: 99.615001 | C4: 99.741026 | D4: -0.0035358711 | E4: -0.0035358711
A5: 2024-01-08 | B5: 100.04105 | C5: 100.16762 | D5: 0.004276984 | E5: 0.004276984
A6: 2024-01-09 | B6: 99.944013 | C6: 100.07045 | D6: -0.00096999827 | E6: -0.00096999827
A7: 2024-01-10 | B7: 99.585939 | C7: 99.711927 | D7: -0.0035827468 | E7: -0.0035827468
A8: 2024-01-11 | B8: 100.00249 | C8: 100.129 | D8: 0.004182796 | E8: 0.004182796
A9: 2024-01-12 | B9: 99.934967 | C9: 100.0614 | D9: -0.00067517291 | E9: -0.00067517291
A10: 2024-01-15 | B10: 99.959929 | C10: 100.08639 | D10: 0.00024978174 | E10: 0.00024978174
A11: 2024-01-16 | B11: 98.648522 | C11: 98.773325 | D11: -0.01311933 | E11: -0.01311933
A12: 2024-01-17 | B12: 97.508968 | C12: 97.632329 | D12: -0.011551656 | E12: -0.011551656
A13: 2024-01-18 | B13: 98.045718 | C13: 98.169758 | D13: 0.0055046137 | E13: 0.0055046137
A14: 2024-01-19 | B14: 101.06611 | C14: 101.20521 | D14: 0.030805976 | E14: 0.030920483
... A479: 2025-12-22 | B479: 162.74254 | C479: 174.52565 | D479: 0.014328456 | E479: 0.014328456

Sheet 投資後權重
A1: date | B1: 1101 | C1: 1216 | D1: 1301 | E1: 1303 | F1: 1326 | G1: 1590 | H1: 2002 | I1: 2059 | J1: 2207 | K1: 2301 | L1: 2303 | M1: 2308 | N1: 2317 | O1: 2327 | P1: 2330 | Q1: 2345 | R1: 2357 | S1: 2360 | T1: 2379 | U1: 2382 | V1: 2383 | W1: 2395 | X1: 2408 | Y1: 2412 | Z1: 2454 | AA1: 2603 | AB1: 2609 | AC1: 2615 | AD1: 2618 | AE1: 2801 | AF1: 2880 | AG1: 2881 | AH1: 2882 | AI1: 2883 | AJ1: 2884 | AK1: 2885 | AL1: 2886 | AM1: 2887 | AN1: 2888 | AO1: 2890 | AP1: 2891 | AQ1: 2892 | AR1: 2912 | AS1: 3008 | AT1: 3017 | AU1: 3034 | AV1: 3037 | AW1: 3045 | AX1: 3231 | AY1: 3293 | AZ1: 3443 | BA1: 3529 | BB1: 3653 | BC1: 3661 | BD1: 3711 | BE1: 4904 | BF1: 4938 | BG1: 5871 | BH1: 5876 | BI1: 5880 | BJ1: 6488 | BK1: 6505 | BL1: 6669 | BM1: 6919 | BN1: 8069
A2: 2024-01-03 | B2: 0.0085195677 | C2: 0.013330686 | D2: 0.015977926 | E2: 0.016720322 | F2: 0.011509403 | H2: 0.013534765 | J2: 0.012264334 | K2: 0.0085076765 | L2: 0.020376065 | M2: 0.025419544 | N2: 0.046558253 | O2: 0.007859445 | P2: 0.3 | Q2: 0.0088252038 | R2: 0.011100602 | T2: 0.0074506446 | U2: 0.026565599 | W2: 0.0099233729 | X2: 0.0072787042 | Y2: 0.029917312 | Z2: 0.048995308 | AA2: 0.010596994 | AF2: 0.0096460185 | AG2: 0.029920205 | AH2: 0.023406395 | AI2: 0.0072803111 | AJ2: 0.012887497 | AK2: 0.010990368 | AL2: 0.017888553 | AM2: 0.0077887405 | AO2: 0.0076765775 | AP2: 0.018237576 | AQ2: 0.011818574 | AR2: 0.0089206549 | AS2: 0.011520008 | AU2: 0.0097684658 | AV2: 0.0083325222 | AW2: 0.011834001 | AX2: 0.0087136836 | AZ2: 0.0070627342 | BC2: 0.0082261441 | BD2: 0.017807886 | BE2: 0.0092009017 | BF2: 0.0073548722 | BG2: 0.010888489 | BH2: 0.0071871097 | BI2: 0.012456521 | BJ2: 0.0080310641 | BK2: 0.024400114 | BL2: 0.0095222857 | BO2: =24.6/每日收盤價!Z2 -> 0.025813221
A3: 2024-01-04 | B3: =B2*(1+$BO$2)*(1+每日報酬率!B3) -> 0.0087394852 | C3: =C2*(1+$BO$2)*(1+每日報酬率!C3) -> 0.013581131 | D3: =D2*(1+$BO$2)*(1+每日報酬率!D3) -> 0.01643234 | E3: =E2*(1+$BO$2)*(1+每日報酬率!E3) -> 0.017151928 | F3: =F2*(1+$BO$2)*(1+每日報酬率!F3) -> 0.011806498 | G3: =G2*(1+$BO$2)*(1+每日報酬率!G3) -> 0 | H3: =H2*(1+$BO$2)*(1+每日報酬率!H3) -> 0.01388414 | I3: =I2*(1+$BO$2)*(1+每日報酬率!I3) -> 0 | ... Y3: =Y2*(1+$BO$2)*(1+每日報酬率!Y3) -> 0.030433828 | Z3: =Z2*(1+每日報酬率!Z3) -> 0.047710016 | AA3: =AA2*(1+$BO$2)*(1+每日報酬率!AA3) -> 0.011291331 | AB3: =AB2*(1+$BO$2)*(1+每日報酬率!AB3) -> 0 | AC3: =AC2*(1+$BO$2)*(1+每日報酬率!AC3) -> 0 | AD3: =AD2*(1+$BO$2)*(1+每日報酬率!AD3) -> 0 | AE3: =AE2*(1+$BO$2)*(1+每日報酬率!AE3) -> 0 | AF3: =AF2*(1+$BO$2)*(1+每日報酬率!AF3) -> 0.0098950133 | AG3: =AG2*(1+$BO$2)*(1+每日報酬率!AG3) -> 0.030596176 | AH3: =AH2*(1+$BO$2)*(1+每日報酬率!AH3) -> 0.023877049 | ... BN3: =BN2*(1+$BO$2)*(1+每日報酬率!BN3) -> 0 | BT3: =SUM(B3:BN3) -> 1.0242583
A4: 2024-01-05 | B4: =B3*(1+每日報酬率!B4) -> 0.0087778163 | C4: =C3*(1+每日報酬率!C4) -> 0.013637328 | D4: =D3*(1+每日報酬率!D4) -> 0.016390367 | E4: =E3*(1+每日報酬率!E4) -> 0.017099635 | F4: =F3*(1+每日報酬率!F4) -> 0.011787174 | G4: =G3*(1+每日報酬率!G4) -> 0 | H4: =H3*(1+每日報酬率!H4) -> 0.01388414 | I4: =I3*(1+每日報酬率!I4) -> 0 | ... BN4: =BN3*(1+每日報酬率!BN4) -> 0 | BT4: =SUM(B4:BN4) -> 1.0206364
A5: 2024-01-08 | B5: =B4*(1+每日報酬率!B5) -> 0.0087522622 | C5: =C4*(1+每日報酬率!C5) -> 0.013674794 | D5: =D4*(1+每日報酬率!D5) -> 0.016390367 | E5: =E4*(1+每日報酬率!E5) -> 0.01720422 | F5: =F4*(1+每日報酬率!F5) -> 0.011787174 | G5: =G4*(1+每日報酬率!G5) -> 0 | H5: =H4*(1+每日報酬率!H5) -> 0.013780139 | I5: =I4*(1+每日報酬率!I5) -> 0 | ... BN5: =BN4*(1+每日報酬率!BN5) -> 0 | BT5: =SUM(B5:BN5) -> 1.0250013
A6: 2024-01-09 | B6: =B5*(1+每日報酬率!B6) -> 0.0087011541 | C6: =C5*(1+每日報酬率!C6) -> 0.013581131 | D6: =D5*(1+每日報酬率!D6) -> 0.016285435 | E6: =E5*(1+每日報酬率!E6) -> 0.017021197 | F6: =F5*(1+每日報酬率!F6) -> 0.011748528 | G6: =G5*(1+每日報酬率!G6) -> 0 | H6: =H5*(1+每日報酬率!H6) -> 0.013520137 | I6: =I5*(1+每日報酬率!I6) -> 0 | ... BN6: =BN5*(1+每日報酬率!BN6) -> 0 | BT6: =SUM(B6:BN6) -> 1.0240077
A7: 2024-01-10 | B7: =B6*(1+每日報酬率!B7) -> 0.0086117149 | C7: =C6*(1+每日報酬率!C7) -> 0.013581131 | D7: =D6*(1+每日報酬率!D7) -> 0.016159517 | E7: =E6*(1+每日報酬率!E7) -> 0.016864319 | F7: =F6*(1+每日報酬率!F7) -> 0.011651912 | G7: =G6*(1+每日報酬率!G7) -> 0 | H7: =H6*(1+每日報酬率!H7) -> 0.013442136 | I7: =I6*(1+每日報酬率!I7) -> 0 | ... BN7: =BN6*(1+每日報酬率!BN7) -> 0 | BT7: =SUM(B7:BN7) -> 1.0203389
A8: 2024-01-11 | B8: =B7*(1+每日報酬率!B8) -> 0.0086117149 | C8: =C7*(1+每日報酬率!C8) -> 0.013543666 | D8: =D7*(1+每日報酬率!D8) -> 0.015928667 | E8: =E7*(1+每日報酬率!E8) -> 0.016602857 | F8: =F7*(1+每日報酬率!F8) -> 0.011651912 | G8: =G7*(1+每日報酬率!G8) -> 0 | H8: =H7*(1+每日報酬率!H8) -> 0.013416136 | I8: =I7*(1+每日報酬率!I8) -> 0 | ... BN8: =BN7*(1+每日報酬率!BN8) -> 0 | BT8: =SUM(B8:BN8) -> 1.0246062
A9: 2024-01-12 | B9: =B8*(1+每日報酬率!B9) -> 0.008624492 | C9: =C8*(1+每日報酬率!C9) -> 0.013599863 | D9: =D8*(1+每日報酬率!D9) -> 0.015949653 | E9: =E8*(1+每日報酬率!E9) -> 0.016733588 | F9: =F8*(1+每日報酬率!F9) -> 0.011613265 | G9: =G8*(1+每日報酬率!G9) -> 0 | H9: =H8*(1+每日報酬率!H9) -> 0.013416136 | I9: =I8*(1+每日報酬率!I9) -> 0 | ... BN9: =BN8*(1+每日報酬率!BN9) -> 0 | BT9: =SUM(B9:BN9) -> 1.0239149
A10: 2024-01-15 | B10: =B9*(1+每日報酬率!B10) -> 0.0085989379 | C10: =C9*(1+每日報酬率!C10) -> 0.013524933 | D10: =D9*(1+每日報酬率!D10) -> 0.015844721 | E10: =E9*(1+每日報酬率!E10) -> 0.016629003 | F10: =F9*(1+每日報酬率!F10) -> 0.011535972 | G10: =G9*(1+每日報酬率!G10) -> 0 | H10: =H9*(1+每日報酬率!H10) -> 0.013416136 | I10: =I9*(1+每日報酬率!I10) -> 0 | ... BN10: =BN9*(1+每日報酬率!BN10) -> 0 | BT10: =SUM(B10:BN10) -> 1.0241703
A11: 2024-01-16 | B11: =B10*(1+每日報酬率!B11) -> 0.0084072825 | C11: =C10*(1+每日報酬率!C11) -> 0.013337607 | D11: =D10*(1+每日報酬率!D11) -> 0.01544598 | E11: =E10*(1+每日報酬率!E11) -> 0.016158371 | F11: =F10*(1+每日報酬率!F11) -> 0.011014245 | G11: =G10*(1+每日報酬率!G11) -> 0 | H11: =H10*(1+每日報酬率!H11) -> 0.013104133 | I11: =I10*(1+每日報酬率!I11) -> 0 | ... BN11: =BN10*(1+每日報酬率!BN11) -> 0 | BT11: =SUM(B11:BN11) -> 1.0107328
A12: 2024-01-17 | B12: =B11*(1+每日報酬率!B12) -> 0.0082284042 | C12: =C11*(1+每日報酬率!C12) -> 0.013169014 | D12: =D11*(1+每日報酬率!D12) -> 0.015068225 | E12: =E11*(1+每日報酬率!E12) -> 0.015713885 | F12: =F11*(1+每日報酬率!F12) -> 0.010782366 | G12: =G11*(1+每日報酬率!G12) -> 0 | H12: =H11*(1+每日報酬率!H12) -> 0.01289613 | I12: =I11*(1+每日報酬率!I12) -> 0 | ... BN12: =BN11*(1+每日報酬率!BN12) -> 0 | BT12: =SUM(B12:BN12) -> 0.99905678
A13: 2024-01-18 | B13: =B12*(1+每日報酬率!B13) -> 0.0081900731 | C13: =C12*(1+每日報酬率!C13) -> 0.013318874 | D13: =D12*(1+每日報酬率!D13) -> 0.01492132 | E13: =E12*(1+每日報酬率!E13) -> 0.015713885 | F13: =F12*(1+每日報酬率!F13) -> 0.010782366 | G13: =G12*(1+每日報酬率!G13) -> 0 | H13: =H12*(1+每日報酬率!H13) -> 0.01289613 | I13: =I12*(1+每日報酬率!I13) -> 0 | ... BN13: =BN12*(1+每日報酬率!BN13) -> 0 | BT13: =SUM(B13:BN13) -> 1.0045571
A14: 2024-01-19 | B14: =B13*(1+每日報酬率!B14) -> 0.0082795123 | C14: =C13*(1+每日報酬率!C14) -> 0.013393805 | D14: =D13*(1+每日報酬率!D14) -> 0.014942307 | E14: =E13*(1+每日報酬率!E14) -> 0.015687739 | F14: =F13*(1+每日報酬率!F14) -> 0.010801689 | G14: =G13*(1+每日報酬率!G14) -> 0 | H14: =H13*(1+每日報酬率!H14) -> 0.01281813 | I14: =I13*(1+每日報酬率!I14) -> 0 | ... BN14: =BN13*(1+每日報酬率!BN14) -> 0 | BT14: =SUM(B14:BN14) -> 1.0355032
A15: 2024-01-22 | B15: =B14*(1+每日報酬率!B15) -> 0.0082539582 | C15: =C14*(1+每日報酬率!C15) -> 0.013225211 | D15: =D14*(1+每日報酬率!D15) -> 0.014816388 | E15: =E14*(1+每日報酬率!E15) -> 0.015557008 | F15: =F14*(1+每日報酬率!F15) -> 0.01074372 | G15: =G14*(1+每日報酬率!G15) -> 0 | H15: =H14*(1+每日報酬率!H15) -> 0.01287013 | I15: =I14*(1+每日報酬率!I15) -> 0 | ... BN15: =BN14*(1+每日報酬率!BN15) -> 0 | BT15: =SUM(B15:BN15) -> 1.0418811
... A479: 2025-12-22 | B479: =B478*(1+每日報酬率!B479) -> 0.0063885126 | C479: =C478*(1+每日報酬率!C479) -> 0.014573958 | D479: =D478*(1+每日報酬率!D479) -> 0.0084260339 | E479: =E478*(1+每日報酬率!E479) -> 0.015792324 | F479: =F478*(1+每日報酬率!F479) -> 0.0051786274 | G479: =G478*(1+每日報酬率!G479) -> 0 | H479: =H478*(1+每日報酬率!H479) -> 0.0097760989 | I479: =I478*(1+每日報酬率!I479) -> 0 | ... BN479: =BN478*(1+每日報酬率!BN479) -> 0 | BT479: =SUM(B479:BN479) -> 1.7231352

Sheet 現金股利
A1: date | B1: 1101 | C1: 1216 | D1: 1301 | E1: 1303 | F1: 1326 | G1: 1590 | H1: 2002 | I1: 2059 | J1: 2207 | K1: 2301 | L1: 2303 | M1: 2308 | N1: 2317 | O1: 2327 | P1: 2330 | Q1: 2345 | R1: 2357 | S1: 2360 | T1: 2379 | U1: 2382 | V1: 2383 | W1: 2395 | X1: 2408 | Y1: 2412 | Z1: 2454 | AA1: 2603 | AB1: 2609 | AC1: 2615 | AD1: 2618 | AE1: 2801 | AF1: 2880 | AG1: 2881 | AH1: 2882 | AI1: 2883 | AJ1: 2884 | AK1: 2885 | AL1: 2886 | AM1: 2887 | AN1: 2888 | AO1: 2890 | AP1: 2891 | AQ1: 2892 | AR1: 2912 | AS1: 3008 | AT1: 3017 | AU1: 3034 | AV1: 3037 | AW1: 3045 | AX1: 3231 | AY1: 3293 | AZ1: 3443 | BA1: 3529 | BB1: 3653 | BC1: 3661 | BD1: 3711 | BE1: 4904 | BF1: 4938 | BG1: 5871 | BH1: 5876 | BI1: 5880 | BJ1: 6488 | BK1: 6505 | BL1: 6669 | BM1: 6919 | BN1: 8096 | BP1: date | BQ1: 1101 | BR1: 1216 | BS1: 1301 | BT1: 1303 | BU1: 1326 | BV1: 1590 | BW1: 2002 | BX1: 2059 | BY1: 2207 | BZ1: 2301 | CA1: 2303 | CB1: 2308 | CC1: 2317 | CD1: 2327 | CE1: 2330 | CF1: 2345 | CG1: 2357 | CH1: 2360 | CI1: 2379 | CJ1: 2382 | CK1: 2383 | CL1: 2395 | CM1: 2408 | CN1: 2412 | CO1: 2454 | CP1: 2603 | CQ1: 2609 | CR1: 2615 | CS1: 2618 | CT1: 2801 | CU1: 2880 | CV1: 2881 | CW1: 2882 | CX1: 2883 | CY1: 2884 | CZ1: 2885 | DA1: 2886 | DB1: 2887 | DC1: 2888 | DD1: 2890 | DE1: 2891 | DF1: 2892 | DG1: 2912 | DH1: 3008 | DI1: 3017 | DJ1: 3034 | DK1: 3037 | DL1: 3045 | DM1: 3231 | DN1: 3293 | DO1: 3443 | DP1: 3529 | DQ1: 3653 | DR1: 3661 | DS1: 3711 | DT1: 4904 | DU1: 4938 | DV1: 5871 | DW1: 5876 | DX1: 5880 | DY1: 6488 | DZ1: 6505 | EA1: 6669 | EB1: 6919 | EC1: 8096
A2: 41347 | BP2: 41347
A3: 41373 | BP3: 41373
A4: 41388 | BP4: 41388
A5: 41403 | BP5: 41403
A6: 41411 | BP6: 41411
A7: 41414 | BP7: 41414
A8: 41415 | BP8: 41415
A9: 41416 | BP9: 41416
A10: 41417 | BP10: 41417
A11: 41418 | BP11: 41418
A12: 41422 | BP12: 41422
A13: 41423 | BP13: 41423
... A17: 41431 | BP17: 41431
A18: 41432 | G18: 3.8 | BP18: 41432
A19: 41435 | BP19: 41435
A20: 41436 | BP20: 41436
A21: 41438 | BP21: 41438
A22: 41442 | BP22: 41442
A23: 41443 | BP23: 41443
A24: 41444 | BP24: 41444
A25: 41445 | BP25: 41445
A26: 41446 | BP26: 41446
A27: 41449 | BP27: 41449
A28: 41450 | BP28: 41450
A29: 41451 | BG29: 2 | BP29: 41451
A30: 41452 | BP30: 41452
A31: 41453 | BP31: 41453
A32: 41456 | AG32: 1 | BP32: 41456
A33: 41457 | BK33: 0.26 | BP33: 41457
A34: 41458 | P34: 2.9995522 | BP34: 41458
A35: 41459 | BA35: 2.7 | BP35: 41459
A36: 41460 | BP36: 41460
A37: 41463 | L37: 0.40639654 | M37: 5.291015 | S37: 2 | AC37: 0.8 | AW37: 5.5 | BP37: 41463
A38: 41464 | BB38: 2.0094496 | BP38: 41464
A39: 41465 | BP39: 41465
A40: 41466 | BP40: 41466
A41: 41467 | BP41: 41467
A42: 41470 | W42: 4.8858785 | BP42: 41470
A43: 41471 | Z43: 8.999811 | BP43: 41471
A44: 41472 | D44: 1.2 | J44: 9 | Y44: 5.35 | AP44: 0.71 | AZ44: 3 | BP44: 41472
A45: 41473 | Q45: 1.4935793 | BP45: 41473
A46: 41474 | AH46: 0.7 | BP46: 41474
A47: 41477 | F47: 0.65 | BP47: 41477
A48: 41478 | AK48: 0.55 | BP48: 41478
A49: 41479 | BE49: 3.5 | BP49: 41479
A50: 41480 | B50: 1.9 | AI50: 0.18 | AV50: 1.1 | BP50: 41480
A51: 41481 | H51: 0.4 | BP51: 41481
A52: 41484 | BP52: 41484
A53: 41485 | BP53: 41485
A54: 41486 | BP54: 41486
A55: 41487 | I55: 5.9428775 | U55: 3.9997862 | AX55: 1.5 | BP55: 41487
A56: 41488 | AQ56: 0.45 | BP56: 41488
A57: 41491 | BP57: 41491
A58: 41492 | BP58: 41492
A59: 41493 | E59: 0.3 | K59: 2.3406158 | AR59: 4.85 | BP59: 41493
A60: 41494 | C60: 1.4 | R60: 19.172968 | BP60: 41494
A61: 41495 | BP61: 41495
A62: 41498 | AM62: 0.22272568 | BP62: 41498
A63: 41499 | AL63: 1.1 | BP63: 41499
A64: 41500 | AO64: 0.33338378 | AY64: 5.5 | BI64: 0.4 | BP64: 41500
A65: 41501 | T65: 3.4 | AF65: 0.5 | AJ65: 0.3 | AU65: 5.5929359 | BP65: 41501
A66: 41502 | BP66: 41502
A67: 41505 | BP67: 41505
A68: 41506 | BP68: 41506
A69: 41507 | BP69: 41507
A70: 41508 | AE70: 0.1 | BP70: 41508
A71: 41509 | AS71: 17 | BP71: 41509
A72: 41512 | BP72: 41512
A73: 41513 | BN73: 1.5 | BP73: 41513
A74: 41514 | BP74: 41514
A75: 41515 | V75: 1.79406 | BP75: 41515
A76: 41516 | BP76: 41516
A77: 41519 | BP77: 41519
A78: 41520 | BP78: 41520
A79: 41521 | BP79: 41521
A80: 41522 | BP80: 41522
A81: 41523 | BP81: 41523
A82: 41526 | N82: 1.5 | BP82: 41526
A83: 41527 | AN83: 0.02915635 | BP83: 41527
A84: 41528 | BP84: 41528
A85: 41529 | BP85: 41529
A86: 41531 | BP86: 41531
A87: 41534 | BP87: 41534
A88: 41535 | BP88: 41535
A89: 41540 | BP89: 41540
A90: 41541 | AT90: 0.2 | BP90: 41541
A91: 41544 | BP91: 41544
A92: 41548 | BF92: 1.4811735 | BP92: 41548
A93: 41550 | BP93: 41550
A94: 41551 | BP94: 41551
A95: 41554 | BP95: 41554
A96: 41555 | BP96: 41555
A97: 41563 | BP97: 41563
A98: 41564 | BP98: 41564
A99: 41570 | BP99: 41570
A100: 41571 | BP100: 41571
A101: 41572 | BP101: 41572
A102: 41577 | BP102: 41577
A103: 41578 | BP103: 41578
...

Sheet 標準化後權重
A1: date | B1: 1101 | C1: 1216 | D1: 1301 | E1: 1303 | F1: 1326 | G1: 1590 | H1: 2002 | I1: 2059 | J1: 2207 | K1: 2301 | L1: 2303 | M1: 2308 | N1: 2317 | O1: 2327 | P1: 2330 | Q1: 2345 | R1: 2357 | S1: 2360 | T1: 2379 | U1: 2382 | V1: 2383 | W1: 2395 | X1: 2408 | Y1: 2412 | Z1: 2454 | AA1: 2603 | AB1: 2609 | AC1: 2615 | AD1: 2618 | AE1: 2801 | AF1: 2880 | AG1: 2881 | AH1: 2882 | AI1: 2883 | AJ1: 2884 | AK1: 2885 | AL1: 2886 | AM1: 2887 | AN1: 2888 | AO1: 2890 | AP1: 2891 | AQ1: 2892 | AR1: 2912 | AS1: 3008 | AT1: 3017 | AU1: 3034 | AV1: 3037 | AW1: 3045 | AX1: 3231 | AY1: 3293 | AZ1: 3443 | BA1: 3529 | BB1: 3653 | BC1: 3661 | BD1: 3711 | BE1: 4904 | BF1: 4938 | BG1: 5871 | BH1: 5876 | BI1: 5880 | BJ1: 6488 | BK1: 6505 | BL1: 6669 | BM1: 6919 | BN1: 8069
A2: 2024-01-03 | BO2: =SUM(B2:BN2) -> 0
A3: 2024-01-04 | B3: =投資後權重!B3/投資後權重!$BT3 -> 0.0085325012 | C3: =投資後權重!C3/投資後權重!$BT3 -> 0.013259478 | D3: =投資後權重!D3/投資後權重!$BT3 -> 0.01604316 | E3: =投資後權重!E3/投資後權重!$BT3 -> 0.016745706 | F3: =投資後權重!F3/投資後權重!$BT3 -> 0.011526875 | G3: =投資後權重!G3/投資後權重!$BT3 -> 0 | H3: =投資後權重!H3/投資後權重!$BT3 -> 0.013555312 | I3: =投資後權重!I3/投資後權重!$BT3 -> 0 | ... BN3: =投資後權重!BN3/投資後權重!$BT3 -> 0 | BO3: =SUM(B3:BN3) -> 1
A4: 2024-01-05 | B4: =投資後權重!B4/投資後權重!$BT4 -> 0.0086003364 | C4: =投資後權重!C4/投資後權重!$BT4 -> 0.013361593 | D4: =投資後權重!D4/投資後權重!$BT4 -> 0.016058968 | E4: =投資後權重!E4/投資後權重!$BT4 -> 0.016753895 | F4: =投資後權重!F4/投資後權重!$BT4 -> 0.011548848 | G4: =投資後權重!G4/投資後權重!$BT4 -> 0 | H4: =投資後權重!H4/投資後權重!$BT4 -> 0.013603415 | I4: =投資後權重!I4/投資後權重!$BT4 -> 0 | ... BN4: =投資後權重!BN4/投資後權重!$BT4 -> 0 | BO4: =SUM(B4:BN4) -> 1
A5: 2024-01-08 | B5: =投資後權重!B5/投資後權重!$BT5 -> 0.0085387817 | C5: =投資後權重!C5/投資後權重!$BT5 -> 0.013341245 | D5: =投資後權重!D5/投資後權重!$BT5 -> 0.015990582 | E5: =投資後權重!E5/投資後權重!$BT5 -> 0.016784584 | F5: =投資後權重!F5/投資後權重!$BT5 -> 0.011499668 | G5: =投資後權重!G5/投資後權重!$BT5 -> 0 | H5: =投資後權重!H5/投資後權重!$BT5 -> 0.013444022 | I5: =投資後權重!I5/投資後權重!$BT5 -> 0 | ... BN5: =投資後權重!BN5/投資後權重!$BT5 -> 0 | BO5: =SUM(B5:BN5) -> 1
A6: 2024-01-09 | B6: =投資後權重!B6/投資後權重!$BT6 -> 0.0084971572 | C6: =投資後權重!C6/投資後權重!$BT6 -> 0.013262724 | D6: =投資後權重!D6/投資後權重!$BT6 -> 0.015903626 | E6: =投資後權重!E6/投資後權重!$BT6 -> 0.016622138 | F6: =投資後權重!F6/投資後權重!$BT6 -> 0.011473086 | G6: =投資後權重!G6/投資後權重!$BT6 -> 0 | H6: =投資後權重!H6/投資後權重!$BT6 -> 0.01320316 | I6: =投資後權重!I6/投資後權重!$BT6 -> 0 | ... BN6: =投資後權重!BN6/投資後權重!$BT6 -> 0 | BO6: =SUM(B6:BN6) -> 1
A7: 2024-01-10 | B7: =投資後權重!B7/投資後權重!$BT7 -> 0.0084400539 | C7: =投資後權重!C7/投資後權重!$BT7 -> 0.013310412 | D7: =投資後權重!D7/投資後權重!$BT7 -> 0.015837402 | E7: =投資後權重!E7/投資後權重!$BT7 -> 0.016528156 | F7: =投資後權重!F7/投資後權重!$BT7 -> 0.011419649 | G7: =投資後權重!G7/投資後權重!$BT7 -> 0 | H7: =投資後權重!H7/投資後權重!$BT7 -> 0.013174188 | I7: =投資後權重!I7/投資後權重!$BT7 -> 0 | ... BN7: =投資後權重!BN7/投資後權重!$BT7 -> 0 | BO7: =SUM(B7:BN7) -> 1
A8: 2024-01-11 | B8: =投資後權重!B8/投資後權重!$BT8 -> 0.0084049025 | C8: =投資後權重!C8/投資後權重!$BT8 -> 0.013218411 | D8: =投資後權重!D8/投資後權重!$BT8 -> 0.015546136 | E8: =投資後權重!E8/投資後權重!$BT8 -> 0.016204135 | F8: =投資後權重!F8/投資後權重!$BT8 -> 0.011372088 | G8: =投資後權重!G8/投資後權重!$BT8 -> 0 | H8: =投資後權重!H8/投資後權重!$BT8 -> 0.013093944 | I8: =投資後權重!I8/投資後權重!$BT8 -> 0 | ... BN8: =投資後權重!BN8/投資後權重!$BT8 -> 0 | BO8: =SUM(B8:BN8) -> 1
A9: 2024-01-12 | B9: =投資後權重!B9/投資後權重!$BT9 -> 0.0084230558 | C9: =投資後權重!C9/投資後權重!$BT9 -> 0.013282221 | D9: =投資後權重!D9/投資後權重!$BT9 -> 0.015577128 | E9: =投資後權重!E9/投資後權重!$BT9 -> 0.016342754 | F9: =投資後權重!F9/投資後權重!$BT9 -> 0.011342022 | G9: =投資後權重!G9/投資後權重!$BT9 -> 0 | H9: =投資後權重!H9/投資後權重!$BT9 -> 0.013102785 | I9: =投資後權重!I9/投資後權重!$BT9 -> 0 | ... BN9: =投資後權重!BN9/投資後權重!$BT9 -> 0 | BO9: =SUM(B9:BN9) -> 1
A10: 2024-01-15 | B10: =投資後權重!B10/投資後權重!$BT10 -> 0.0083960039 | C10: =投資後權重!C10/投資後權重!$BT10 -> 0.013205746 | D10: =投資後權重!D10/投資後權重!$BT10 -> 0.015470788 | E10: =投資後權重!E10/投資後權重!$BT10 -> 0.016236561 | F10: =投資後權重!F10/投資後權重!$BT10 -> 0.011263725 | G10: =投資後權重!G10/投資後權重!$BT10 -> 0 | H10: =投資後權重!H10/投資後權重!$BT10 -> 0.013099516 | I10: =投資後權重!I10/投資後權重!$BT10 -> 0 | ... BN10: =投資後權重!BN10/投資後權重!$BT10 -> 0 | BO10: =SUM(B10:BN10) -> 1
A11: 2024-01-16 | B11: =投資後權重!B11/投資後權重!$BT11 -> 0.0083180068 | C11: =投資後權重!C11/投資後權重!$BT11 -> 0.013195977 | D11: =投資後權重!D11/投資後權重!$BT11 -> 0.015281961 | E11: =投資後權重!E11/投資後權重!$BT11 -> 0.015986788 | F11: =投資後權重!F11/投資後權重!$BT11 -> 0.010897286 | G11: =投資後權重!G11/投資後權重!$BT11 -> 0 | H11: =投資後權重!H11/投資後權重!$BT11 -> 0.012964982 | I11: =投資後權重!I11/投資後權重!$BT11 -> 0 | ... BN11: =投資後權重!BN11/投資後權重!$BT11 -> 0 | BO11: =SUM(B11:BN11) -> 1
A12: 2024-01-17 | B12: =投資後權重!B12/投資後權重!$BT12 -> 0.0082361727 | C12: =投資後權重!C12/投資後權重!$BT12 -> 0.013181447 | D12: =投資後權重!D12/投資後權重!$BT12 -> 0.015082451 | E12: =投資後權重!E12/投資後權重!$BT12 -> 0.015728721 | F12: =投資後權重!F12/投資後權重!$BT12 -> 0.010792546 | G12: =投資後權重!G12/投資後權重!$BT12 -> 0 | H12: =投資後權重!H12/投資後權重!$BT12 -> 0.012908306 | I12: =投資後權重!I12/投資後權重!$BT12 -> 0 | ... BN12: =投資後權重!BN12/投資後權重!$BT12 -> 0 | BO12: =SUM(B12:BN12) -> 1
A13: 2024-01-18 | B13: =投資後權重!B13/投資後權重!$BT13 -> 0.0081529191 | C13: =投資後權重!C13/投資後權重!$BT13 -> 0.013258454 | D13: =投資後權重!D13/投資後權重!$BT13 -> 0.01485363 | E13: =投資後權重!E13/投資後權重!$BT13 -> 0.0156426 | F13: =投資後權重!F13/投資後權重!$BT13 -> 0.010733452 | G13: =投資後權重!G13/投資後權重!$BT13 -> 0 | H13: =投資後權重!H13/投資後權重!$BT13 -> 0.012837628 | I13: =投資後權重!I13/投資後權重!$BT13 -> 0 | ... BN13: =投資後權重!BN13/投資後權重!$BT13 -> 0 | BO13: =SUM(B13:BN13) -> 1
A14: 2024-01-19 | B14: =投資後權重!B14/投資後權重!$BT14 -> 0.0079956416 | C14: =投資後權重!C14/投資後權重!$BT14 -> 0.012934586 | D14: =投資後權重!D14/投資後權重!$BT14 -> 0.014429996 | E14: =投資後權重!E14/投資後權重!$BT14 -> 0.01514987 | F14: =投資後權重!F14/投資後權重!$BT14 -> 0.010431343 | G14: =投資後權重!G14/投資後權重!$BT14 -> 0 | H14: =投資後權重!H14/投資後權重!$BT14 -> 0.012378648 | I14: =投資後權重!I14/投資後權重!$BT14 -> 0 | ... BN14: =投資後權重!BN14/投資後權重!$BT14 -> 0 | BO14: =SUM(B14:BN14) -> 1
... A60: 2024-04-08 | B60: =投資後權重!B60/投資後權重!$BT60 -> 0.0068722832 | C60: =投資後權重!C60/投資後權重!$BT60 -> 0.01176002 | D60: =投資後權重!D60/投資後權重!$BT60 -> 0.012301246 | E60: =投資後權重!E60/投資後權重!$BT60 -> 0.012560985 | F60: =投資後權重!F60/投資後權重!$BT60 -> 0.0088648267 | G60: =投資後權重!G60/投資後權重!$BT60 -> 0 | H60: =投資後權重!H60/投資後權重!$BT60 -> 0.010823969 | I60: =投資後權重!I60/投資後權重!$BT60 -> 0 | ... BN60: =投資後權重!BN60/投資後權重!$BT60 -> 0 | BO60: =SUM(B60:BN60) -> 1
A61: 2024-04-09 | B61: 0.0072467011 | C61: 0.012526012 | D61: 0.013081707 | E61: 0.013417859 | F61: 0.0093926758 | G61: 0.0066499733 | H61: 0.011721574 | J61: 0.010207682 | K61: 0.0066083935 | L61: 0.018721869 | M61: 0.024537704 | N61: 0.060022219 | O61: 0.0073615461 | P61: 0.31038466 | Q61: 0.0074754551 | R61: 0.0090950253 | T61: 0.0083204093 | U61: 0.033010142 | W61: 0.0095489591 | Y61: 0.027766589 | Z61: 0.054301986 | AA61: 0.010207572 | AF61: 0.0090895577 | AG61: 0.029230429 | AH61: 0.02294932 | AI61: 0.0074554494 | AJ61: 0.012192557 | AK61: 0.011249541 | AL61: 0.016651098 | AM61: 0.0070005865 | AO61: 0.0076118572 | AP61: 0.018746236 | AQ61: 0.010698261 | AR61: 0.0080926945 | AS61: 0.0090817807 | AU61: 0.010564784 | AV61: 0.0084273264 | AW61: 0.011107988 | AX61: 0.010756844 | BC61: 0.0071433209 | BD61: 0.020182121 | BE61: 0.0083375833 | BF61: 0.0077811782 | BG61: 0.0089739567 | BH61: 0.0064837742 | BI61: 0.011053333 | BJ61: 0.0071336697 | BK61: 0.020096206 | BL61: 0.012739126 | BN61: 0.007562708
A62: 2024-04-10 | B62: =投資後權重!B62/投資後權重!$BT62 -> 0.0068492456 | C62: =投資後權重!C62/投資後權重!$BT62 -> 0.01173077 | D62: =投資後權重!D62/投資後權重!$BT62 -> 0.012385267 | E62: =投資後權重!E62/投資後權重!$BT62 -> 0.012494328 | F62: =投資後權重!F62/投資後權重!$BT62 -> 0.0088854203 | G62: =投資後權重!G62/投資後權重!$BT62 -> 0 | H62: =投資後權重!H62/投資後權重!$BT62 -> 0.010911462 | I62: =投資後權重!I62/投資後權重!$BT62 -> 0 | ... BN62: =投資後權重!BN62/投資後權重!$BT62 -> 0 | BO62: =SUM(B62:BN62) -> 1
A63: 2024-04-11 | B63: =投資後權重!B63/投資後權重!$BT63 -> 0.006790513 | C63: =投資後權重!C63/投資後權重!$BT63 -> 0.011737865 | D63: =投資後權重!D63/投資後權重!$BT63 -> 0.012203424 | E63: =投資後權重!E63/投資後權重!$BT63 -> 0.012266 | F63: =投資後權重!F63/投資後權重!$BT63 -> 0.0087957056 | G63: =投資後權重!G63/投資後權重!$BT63 -> 0 | H63: =投資後權重!H63/投資後權重!$BT63 -> 0.010790115 | I63: =投資後權重!I63/投資後權重!$BT63 -> 0 | ... BN63: =投資後權重!BN63/投資後權重!$BT63 -> 0 | BO63: =SUM(B63:BN63) -> 1
A64: 2024-04-12 | B64: =投資後權重!B64/投資後權重!$BT64 -> 0.0067832448 | C64: =投資後權重!C64/投資後權重!$BT64 -> 0.0118599 | D64: =投資後權重!D64/投資後權重!$BT64 -> 0.012058473 | E64: =投資後權重!E64/投資後權重!$BT64 -> 0.012372084 | F64: =投資後權重!F64/投資後權重!$BT64 -> 0.0088090055 | G64: =投資後權重!G64/投資後權重!$BT64 -> 0 | H64: =投資後權重!H64/投資後權重!$BT64 -> 0.010652609 | I64: =投資後權重!I64/投資後權重!$BT64 -> 0 | ... BN64: =投資後權重!BN64/投資後權重!$BT64 -> 0 | BO64: =SUM(B64:BN64) -> 1
A65: 2024-04-15 | B65: =投資後權重!B65/投資後權重!$BT65 -> 0.0069139908 | C65: =投資後權重!C65/投資後權重!$BT65 -> 0.012016778 | D65: =投資後權重!D65/投資後權重!$BT65 -> 0.012216355 | E65: =投資後權重!E65/投資後權重!$BT65 -> 0.012508346 | F65: =投資後權重!F65/投資後權重!$BT65 -> 0.0088886811 | G65: =投資後權重!G65/投資後權重!$BT65 -> 0 | H65: =投資後權重!H65/投資後權重!$BT65 -> 0.010677117 | I65: =投資後權重!I65/投資後權重!$BT65 -> 0 | ... BN65: =投資後權重!BN65/投資後權重!$BT65 -> 0 | BO65: =SUM(B65:BN65) -> 1
A66: 2024-04-16 | B66: =投資後權重!B66/投資後權重!$BT66 -> 0.0071272133 | C66: =投資後權重!C66/投資後權重!$BT66 -> 0.011994979 | D66: =投資後權重!D66/投資後權重!$BT66 -> 0.012265687 | E66: =投資後權重!E66/投資後權重!$BT66 -> 0.012472324 | F66: =投資後權重!F66/投資後權重!$BT66 -> 0.0089518737 | G66: =投資後權重!G66/投資後權重!$BT66 -> 0 | H66: =投資後權重!H66/投資後權重!$BT66 -> 0.01083839 | I66: =投資後權重!I66/投資後權重!$BT66 -> 0 | ... BN66: =投資後權重!BN66/投資後權重!$BT66 -> 0 | BO66: =SUM(B66:BN66) -> 1
A67: 2024-04-17 | B67: =投資後權重!B67/投資後權重!$BT67 -> 0.0070802057 | C67: =投資後權重!C67/投資後權重!$BT67 -> 0.011985943 | D67: =投資後權重!D67/投資後權重!$BT67 -> 0.012074532 | E67: =投資後權重!E67/投資後權重!$BT67 -> 0.012203228 | F67: =投資後權重!F67/投資後權重!$BT67 -> 0.0087891648 | G67: =投資後權重!G67/投資後權重!$BT67 -> 0 | H67: =投資後權重!H67/投資後權重!$BT67 -> 0.010789208 | I67: =投資後權重!I67/投資後權重!$BT67 -> 0 | ... BN67: =投資後權重!BN67/投資後權重!$BT67 -> 0 | BO67: =SUM(B67:BN67) -> 1
A68: 2024-04-18 | B68: =投資後權重!B68/投資後權重!$BT68 -> 0.0070670773 | C68: =投資後權重!C68/投資後權重!$BT68 -> 0.012167224 | D68: =投資後權重!D68/投資後權重!$BT68 -> 0.012086961 | E68: =投資後權重!E68/投資後權重!$BT68 -> 0.012338877 | F68: =投資後權重!F68/投資後權重!$BT68 -> 0.0087594534 | G68: =投資後權重!G68/投資後權重!$BT68 -> 0 | H68: =投資後權重!H68/投資後權重!$BT68 -> 0.01090666 | I68: =投資後權重!I68/投資後權重!$BT68 -> 0 | ... BN68: =投資後權重!BN68/投資後權重!$BT68 -> 0 | BO68: =SUM(B68:BN68) -> 1
A69: 2024-04-19 | B69: =投資後權重!B69/投資後權重!$BT69 -> 0.0072061951 | C69: =投資後權重!C69/投資後權重!$BT69 -> 0.012546073 | D69: =投資後權重!D69/投資後權重!$BT69 -> 0.012409562 | E69: =投資後權重!E69/投資後權重!$BT69 -> 0.012672669 | F69: =投資後權重!F69/投資後權重!$BT69 -> 0.0089229293 | G69: =投資後權重!G69/投資後權重!$BT69 -> 0 | H69: =投資後權重!H69/投資後權重!$BT69 -> 0.011204253 | I69: =投資後權重!I69/投資後權重!$BT69 -> 0 | ... BN69: =投資後權重!BN69/投資後權重!$BT69 -> 0 | BO69: =SUM(B69:BN69) -> 1
A70: 2024-04-22 | B70: =投資後權重!B70/投資後權重!$BT70 -> 0.0073535769 | C70: =投資後權重!C70/投資後權重!$BT70 -> 0.013046566 | D70: =投資後權重!D70/投資後權重!$BT70 -> 0.012911947 | E70: =投資後權重!E70/投資後權重!$BT70 -> 0.013224675 | F70: =投資後權重!F70/投資後權重!$BT70 -> 0.0093983749 | G70: =投資後權重!G70/投資後權重!$BT70 -> 0 | H70: =投資後權重!H70/投資後權重!$BT70 -> 0.011337727 | I70: =投資後權重!I70/投資後權重!$BT70 -> 0 | ... BN70: =投資後權重!BN70/投資後權重!$BT70 -> 0 | BO70: =SUM(B70:BN70) -> 1
A71: 2024-04-23 | B71: =投資後權重!B71/投資後權重!$BT71 -> 0.0072400167 | C71: =投資後權重!C71/投資後權重!$BT71 -> 0.012862326 | D71: =投資後權重!D71/投資後權重!$BT71 -> 0.012700512 | E71: =投資後權重!E71/投資後權重!$BT71 -> 0.012983677 | F71: =投資後權重!F71/投資後權重!$BT71 -> 0.0092908993 | G71: =投資後權重!G71/投資後權重!$BT71 -> 0 | H71: =投資後權重!H71/投資後權重!$BT71 -> 0.011317218 | I71: =投資後權重!I71/投資後權重!$BT71 -> 0 | ... BN71: =投資後權重!BN71/投資後權重!$BT71 -> 0 | BO71: =SUM(B71:BN71) -> 1
A72: 2024-04-24 | B72: =投資後權重!B72/投資後權重!$BT72 -> 0.0069955766 | C72: =投資後權重!C72/投資後權重!$BT72 -> 0.012282066 | D72: =投資後權重!D72/投資後權重!$BT72 -> 0.012294444 | E72: =投資後權重!E72/投資後權重!$BT72 -> 0.012556569 | F72: =投資後權重!F72/投資後權重!$BT72 -> 0.0090166087 | G72: =投資後權重!G72/投資後權重!$BT72 -> 0 | H72: =投資後權重!H72/投資後權重!$BT72 -> 0.010958869 | I72: =投資後權重!I72/投資後權重!$BT72 -> 0 | ... BN72: =投資後權重!BN72/投資後權重!$BT72 -> 0 | BO72: =SUM(B72:BN72) -> 1
A73: 2024-04-25 | B73: =投資後權重!B73/投資後權重!$BT73 -> 0.0070821652 | C73: =投資後權重!C73/投資後權重!$BT73 -> 0.012346359 | D73: =投資後權重!D73/投資後權重!$BT73 -> 0.012341381 | E73: =投資後權重!E73/投資後權重!$BT73 -> 0.012635709 | F73: =投資後權重!F73/投資後權重!$BT73 -> 0.0090371182 | G73: =投資後權重!G73/投資後權重!$BT73 -> 0 | H73: =投資後權重!H73/投資後權重!$BT73 -> 0.011056446 | I73: =投資後權重!I73/投資後權重!$BT73 -> 0 | ... BN73: =投資後權重!BN73/投資後權重!$BT73 -> 0 | BO73: =SUM(B73:BN73) -> 1
... A121: 2024-07-04 | B121: =投資後權重!B121/投資後權重!$BT121 -> 0.0062645412 | C121: =投資後權重!C121/投資後權重!$BT121 -> 0.01132267 | D121: =投資後權重!D121/投資後權重!$BT121 -> 0.0086775865 | E121: =投資後權重!E121/投資後權重!$BT121 -> 0.0092814156 | F121: =投資後權重!F121/投資後權重!$BT121 -> 0.0068524463 | G121: =投資後權重!G121/投資後權重!$BT121 -> 0 | H121: =投資後權重!H121/投資後權重!$BT121 -> 0.008772319 | I121: =投資後權重!I121/投資後權重!$BT121 -> 0 | ... BN121: =投資後權重!BN121/投資後權重!$BT121 -> 0 | BO121: =SUM(B121:BN121) -> 1
A122: 2024-07-05 | B122: 0.0068137234 | C122: 0.012509133 | D122: 0.0096917117 | E122: 0.010256364 | F122: 0.0077101065 | H122: 0.0098051607 | J122: 0.0092313148 | K122: 0.0064925371 | L122: 0.016442934 | M122: 0.026545581 | N122: 0.076792897 | O122: 0.0082667184 | P122: 0.3088774 | Q122: 0.0085319311 | R122: 0.0090240685 | T122: 0.0077100644 | U122: 0.032470778 | W122: 0.0084757623 | Y122: 0.023440966 | Z122: 0.055809774 | AA122: 0.010346192 | AB122: 0.0065970366 | AC122: 0.0061447003 | AF122: 0.0097571526 | AG122: 0.033057337 | AH122: 0.025217321 | AI122: 0.0075245991 | AJ122: 0.012046902 | AK122: 0.011133655 | AL122: 0.016028816 | AM122: 0.0069207745 | AO122: 0.0086571285 | AP122: 0.021309867 | AQ122: 0.010296585 | AR122: 0.0076118212 | AS122: 0.010311216 | AT122: 0.0080170238 | AU122: 0.0099049416 | AV122: 0.0072306615 | AW122: 0.011483244 | AX122: 0.008277595 | BD122: 0.018494342 | BE122: 0.0086630328 | BF122: 0.0074036001 | BG122: 0.00734505 | BI122: 0.010286284 | BJ122: 0.0073427572 | BK122: 0.016485582 | BL122: 0.012988246 | BN122: 0.0082176151
A123: 2024-07-08 | B123: =投資後權重!B123/投資後權重!$BT123 -> 0.0062123906 | C123: =投資後權重!C123/投資後權重!$BT123 -> 0.011016567 | D123: =投資後權重!D123/投資後權重!$BT123 -> 0.0085524108 | E123: =投資後權重!E123/投資後權重!$BT123 -> 0.0090477012 | F123: =投資後權重!F123/投資後權重!$BT123 -> 0.0066730796 | G123: =投資後權重!G123/投資後權重!$BT123 -> 0 | H123: =投資後權重!H123/投資後權重!$BT123 -> 0.0085861508 | I123: =投資後權重!I123/投資後權重!$BT123 -> 0 | ... BN123: =投資後權重!BN123/投資後權重!$BT123 -> 0 | BO123: =SUM(B123:BN123) -> 1
A124: 2024-07-09 | B124: =投資後權重!B124/投資後權重!$BT124 -> 0.0060837826 | C124: =投資後權重!C124/投資後權重!$BT124 -> 0.011110059 | D124: =投資後權重!D124/投資後權重!$BT124 -> 0.0083762095 | E124: =投資後權重!E124/投資後權重!$BT124 -> 0.0088794459 | F124: =投資後權重!F124/投資後權重!$BT124 -> 0.0065623084 | G124: =投資後權重!G124/投資後權重!$BT124 -> 0 | H124: =投資後權重!H124/投資後權重!$BT124 -> 0.0084475495 | I124: =投資後權重!I124/投資後權重!$BT124 -> 0 | ... BN124: =投資後權重!BN124/投資後權重!$BT124 -> 0 | BO124: =SUM(B124:BN124) -> 1
A125: 2024-07-10 | B125: =投資後權重!B125/投資後權重!$BT125 -> 0.0060415624 | C125: =投資後權重!C125/投資後權重!$BT125 -> 0.011081848 | D125: =投資後權重!D125/投資後權重!$BT125 -> 0.0082816514 | E125: =投資後權重!E125/投資後權重!$BT125 -> 0.0087655906 | F125: =投資後權重!F125/投資後權重!$BT125 -> 0.0063499506 | G125: =投資後權重!G125/投資後權重!$BT125 -> 0 | H125: =投資後權重!H125/投資後權重!$BT125 -> 0.0083716201 | I125: =投資後權重!I125/投資後權重!$BT125 -> 0 | ... BN125: =投資後權重!BN125/投資後權重!$BT125 -> 0 | BO125: =SUM(B125:BN125) -> 1
A126: 2024-07-11 | B126: =投資後權重!B126/投資後權重!$BT126 -> 0.0059675111 | C126: =投資後權重!C126/投資後權重!$BT126 -> 0.010984503 | D126: =投資後權重!D126/投資後權重!$BT126 -> 0.008204061 | E126: =投資後權重!E126/投資後權重!$BT126 -> 0.0087328186 | F126: =投資後權重!F126/投資後權重!$BT126 -> 0.0063214197 | G126: =投資後權重!G126/投資後權重!$BT126 -> 0 | H126: =投資後權重!H126/投資後權重!$BT126 -> 0.0082204396 | I126: =投資後權重!I126/投資後權重!$BT126 -> 0 | ... BN126: =投資後權重!BN126/投資後權重!$BT126 -> 0 | BO126: =SUM(B126:BN126) -> 1
A127: 2024-07-12 | B127: =投資後權重!B127/投資後權重!$BT127 -> 0.0061484089 | C127: =投資後權重!C127/投資後權重!$BT127 -> 0.011277716 | D127: =投資後權重!D127/投資後權重!$BT127 -> 0.0085360832 | E127: =投資後權重!E127/投資後權重!$BT127 -> 0.0092021488 | F127: =投資後權重!F127/投資後權重!$BT127 -> 0.0066039707 | G127: =投資後權重!G127/投資後權重!$BT127 -> 0 | H127: =投資後權重!H127/投資後權重!$BT127 -> 0.0084384395 | I127: =投資後權重!I127/投資後權重!$BT127 -> 0 | ... BN127: =投資後權重!BN127/投資後權重!$BT127 -> 0 | BO127: =SUM(B127:BN127) -> 1
A128: 2024-07-15 | B128: =投資後權重!B128/投資後權重!$BT128 -> 0.0061396873 | C128: =投資後權重!C128/投資後權重!$BT128 -> 0.011416846 | D128: =投資後權重!D128/投資後權重!$BT128 -> 0.0084727502 | E128: =投資後權重!E128/投資後權重!$BT128 -> 0.0091466168 | F128: =投資後權重!F128/投資後權重!$BT128 -> 0.0065759595 | G128: =投資後權重!G128/投資後權重!$BT128 -> 0 | H128: =投資後權重!H128/投資後權重!$BT128 -> 0.008573452 | I128: =投資後權重!I128/投資後權重!$BT128 -> 0 | ... BN128: =投資後權重!BN128/投資後權重!$BT128 -> 0 | BO128: =SUM(B128:BN128) -> 1
A129: 2024-07-16 | B129: =投資後權重!B129/投資後權重!$BT129 -> 0.0061174412 | C129: =投資後權重!C129/投資後權重!$BT129 -> 0.011148719 | D129: =投資後權重!D129/投資後權重!$BT129 -> 0.0084149789 | E129: =投資後權重!E129/投資後權重!$BT129 -> 0.0089626681 | F129: =投資後權重!F129/投資後權重!$BT129 -> 0.0065560851 | G129: =投資後權重!G129/投資後權重!$BT129 -> 0 | H129: =投資後權重!H129/投資後權重!$BT129 -> 0.008420523 | I129: =投資後權重!I129/投資後權重!$BT129 -> 0 | ... BN129: =投資後權重!BN129/投資後權重!$BT129 -> 0 | BO129: =SUM(B129:BN129) -> 1
A130: 2024-07-17 | B130: =投資後權重!B130/投資後權重!$BT130 -> 0.0062511271 | C130: =投資後權重!C130/投資後權重!$BT130 -> 0.011263497 | D130: =投資後權重!D130/投資後權重!$BT130 -> 0.0089431726 | E130: =投資後權重!E130/投資後權重!$BT130 -> 0.0093437052 | F130: =投資後權重!F130/投資後權重!$BT130 -> 0.0068163588 | G130: =投資後權重!G130/投資後權重!$BT130 -> 0 | H130: =投資後權重!H130/投資後權重!$BT130 -> 0.0086094243 | I130: =投資後權重!I130/投資後權重!$BT130 -> 0 | ... BN130: =投資後權重!BN130/投資後權重!$BT130 -> 0 | BO130: =SUM(B130:BN130) -> 1
A131: 2024-07-18 | B131: =投資後權重!B131/投資後權重!$BT131 -> 0.0064103911 | C131: =投資後權重!C131/投資後權重!$BT131 -> 0.011801981 | D131: =投資後權重!D131/投資後權重!$BT131 -> 0.0091978594 | E131: =投資後權重!E131/投資後權重!$BT131 -> 0.0095557021 | F131: =投資後權重!F131/投資後權重!$BT131 -> 0.0071317378 | G131: =投資後權重!G131/投資後權重!$BT131 -> 0 | H131: =投資後權重!H131/投資後權重!$BT131 -> 0.008808889 | I131: =投資後權重!I131/投資後權重!$BT131 -> 0 | ... BN131: =投資後權重!BN131/投資後權重!$BT131 -> 0 | BO131: =SUM(B131:BN131) -> 1
A132: 2024-07-19 | B132: =投資後權重!B132/投資後權重!$BT132 -> 0.0065161833 | C132: =投資後權重!C132/投資後權重!$BT132 -> 0.011997069 | D132: =投資後權重!D132/投資後權重!$BT132 -> 0.0092954319 | E132: =投資後權重!E132/投資後權重!$BT132 -> 0.0097117409 | F132: =投資後權重!F132/投資後權重!$BT132 -> 0.0071916526 | G132: =投資後權重!G132/投資後權重!$BT132 -> 0 | H132: =投資後權重!H132/投資後權重!$BT132 -> 0.0089485377 | I132: =投資後權重!I132/投資後權重!$BT132 -> 0 | ... BN132: =投資後權重!BN132/投資後權重!$BT132 -> 0 | BO132: =SUM(B132:BN132) -> 1
A133: 2024-07-22 | B133: =投資後權重!B133/投資後權重!$BT133 -> 0.0066499439 | C133: =投資後權重!C133/投資後權重!$BT133 -> 0.012531127 | D133: =投資後權重!D133/投資後權重!$BT133 -> 0.0095711834 | E133: =投資後權重!E133/投資後權重!$BT133 -> 0.0099634233 | F133: =投資後權重!F133/投資後權重!$BT133 -> 0.0073926942 | G133: =投資後權重!G133/投資後權重!$BT133 -> 0 | H133: =投資後權重!H133/投資後權重!$BT133 -> 0.0091002058 | I133: =投資後權重!I133/投資後權重!$BT133 -> 0 | ... BN133: =投資後權重!BN133/投資後權重!$BT133 -> 0 | BO133: =SUM(B133:BN133) -> 1
A134: 2024-07-23 | B134: =投資後權重!B134/投資後權重!$BT134 -> 0.0065729706 | C134: =投資後權重!C134/投資後權重!$BT134 -> 0.012201015 | D134: =投資後權重!D134/投資後權重!$BT134 -> 0.0090817542 | E134: =投資後權重!E134/投資後權重!$BT134 -> 0.0096790304 | F134: =投資後權重!F134/投資後權重!$BT134 -> 0.0071816794 | G134: =投資後權重!G134/投資後權重!$BT134 -> 0 | H134: =投資後權重!H134/投資後權重!$BT134 -> 0.0088595874 | I134: =投資後權重!I134/投資後權重!$BT134 -> 0 | ... BN134: =投資後權重!BN134/投資後權重!$BT134 -> 0 | BO134: =SUM(B134:BN134) -> 1
... A184: 2024-10-08 | B184: =投資後權重!B184/投資後權重!$BT184 -> 0.0062801933 | C184: =投資後權重!C184/投資後權重!$BT184 -> 0.012160571 | D184: =投資後權重!D184/投資後權重!$BT184 -> 0.0079276263 | E184: =投資後權重!E184/投資後權重!$BT184 -> 0.0086810523 | F184: =投資後權重!F184/投資後權重!$BT184 -> 0.0060492812 | G184: =投資後權重!G184/投資後權重!$BT184 -> 0 | H184: =投資後權重!H184/投資後權重!$BT184 -> 0.0091642703 | I184: =投資後權重!I184/投資後權重!$BT184 -> 0 | ... BN184: =投資後權重!BN184/投資後權重!$BT184 -> 0 | BO184: =SUM(B184:BN184) -> 1
A185: 2024-10-09 | B185: 0.007189813 | C185: 0.013796082 | D185: 0.0088827191 | E185: 0.0096540504 | F185: 0.0066782155 | H185: 0.010105262 | J185: 0.010015739 | K185: 0.0066101049 | L185: 0.017912092 | M185: 0.026546528 | N185: 0.076267621 | O185: 0.0085809787 | P185: 0.30855903 | Q185: 0.0082515141 | R185: 0.011751373 | T185: 0.0066105513 | U185: 0.028354708 | W185: 0.0073646047 | Y185: 0.026550105 | Z185: 0.052369791 | AA185: 0.010564563 | AB185: 0.0058175729 | AC185: 0.0059794982 | AF185: 0.0097797094 | AG185: 0.038566055 | AH185: 0.030478495 | AI185: 0.0085457377 | AJ185: 0.012524072 | AK185: 0.011518166 | AL185: 0.01608408 | AM185: 0.0071750169 | AO185: 0.0085190636 | AP185: 0.019661288 | AQ185: 0.01043577 | AR185: 0.0086077185 | AS185: 0.0089274354 | AT185: 0.0061748981 | AU185: 0.0088766403 | AV185: 0.0059148417 | AW185: 0.011696106 | AX185: 0.0083188446 | AY185: 0.0078651679 | BD185: 0.018149946 | BE185: 0.0088970157 | BF185: 0.0074651197 | BG185: 0.008107613 | BI185: 0.010848764 | BK185: 0.013951126 | BL185: 0.008875456 | BN185: 0.0096233353
A186: 2024-10-11 | B186: =投資後權重!B186/投資後權重!$BT186 -> 0.0060603398 | C186: =投資後權重!C186/投資後權重!$BT186 -> 0.011837764 | D186: =投資後權重!D186/投資後權重!$BT186 -> 0.0075957943 | E186: =投資後權重!E186/投資後權重!$BT186 -> 0.0082899661 | F186: =投資後權重!F186/投資後權重!$BT186 -> 0.0058093957 | G186: =投資後權重!G186/投資後權重!$BT186 -> 0 | H186: =投資後權重!H186/投資後權重!$BT186 -> 0.0086136548 | I186: =投資後權重!I186/投資後權重!$BT186 -> 0 | ... BN186: =投資後權重!BN186/投資後權重!$BT186 -> 0 | BO186: =SUM(B186:BN186) -> 1
A187: 2024-10-14 | B187: =投資後權重!B187/投資後權重!$BT187 -> 0.0060572633 | C187: =投資後權重!C187/投資後權重!$BT187 -> 0.012004562 | D187: =投資後權重!D187/投資後權重!$BT187 -> 0.0076414077 | E187: =投資後權重!E187/投資後權重!$BT187 -> 0.0082063888 | F187: =投資後權重!F187/投資後權重!$BT187 -> 0.0056216314 | G187: =投資後權重!G187/投資後權重!$BT187 -> 0 | H187: =投資後權重!H187/投資後權重!$BT187 -> 0.0084635191 | I187: =投資後權重!I187/投資後權重!$BT187 -> 0 | ... BN187: =投資後權重!BN187/投資後權重!$BT187 -> 0 | BO187: =SUM(B187:BN187) -> 1
A188: 2024-10-15 | B188: =投資後權重!B188/投資後權重!$BT188 -> 0.0059395973 | C188: =投資後權重!C188/投資後權重!$BT188 -> 0.011856461 | D188: =投資後權重!D188/投資後權重!$BT188 -> 0.0072568479 | E188: =投資後權重!E188/投資後權重!$BT188 -> 0.0079752082 | F188: =投資後權重!F188/投資後權重!$BT188 -> 0.0055001792 | G188: =投資後權重!G188/投資後權重!$BT188 -> 0 | H188: =投資後權重!H188/投資後權重!$BT188 -> 0.008311878 | I188: =投資後權重!I188/投資後權重!$BT188 -> 0 | ... BN188: =投資後權重!BN188/投資後權重!$BT188 -> 0 | BO188: =SUM(B188:BN188) -> 1
A189: 2024-10-16 | B189: =投資後權重!B189/投資後權重!$BT189 -> 0.0059674537 | C189: =投資後權重!C189/投資後權重!$BT189 -> 0.012014535 | D189: =投資後權重!D189/投資後權重!$BT189 -> 0.00730928 | E189: =投資後權重!E189/投資後權重!$BT189 -> 0.008023875 | F189: =投資後權重!F189/投資後權重!$BT189 -> 0.0054738491 | G189: =投資後權重!G189/投資後權重!$BT189 -> 0 | H189: =投資後權重!H189/投資後權重!$BT189 -> 0.0083662301 | I189: =投資後權重!I189/投資後權重!$BT189 -> 0 | ... BN189: =投資後權重!BN189/投資後權重!$BT189 -> 0 | BO189: =SUM(B189:BN189) -> 1
A190: 2024-10-17 | B190: =投資後權重!B190/投資後權重!$BT190 -> 0.0060227412 | C190: =投資後權重!C190/投資後權重!$BT190 -> 0.012185447 | D190: =投資後權重!D190/投資後權重!$BT190 -> 0.0073660407 | E190: =投資後權重!E190/投資後權重!$BT190 -> 0.0081342496 | F190: =投資後權重!F190/投資後權重!$BT190 -> 0.005647237 | G190: =投資後權重!G190/投資後權重!$BT190 -> 0 | H190: =投資後權重!H190/投資後權重!$BT190 -> 0.0084659399 | I190: =投資後權重!I190/投資後權重!$BT190 -> 0 | ... BN190: =投資後權重!BN190/投資後權重!$BT190 -> 0 | BO190: =SUM(B190:BN190) -> 1
A191: 2024-10-18 | B191: =投資後權重!B191/投資後權重!$BT191 -> 0.0059294777 | C191: =投資後權重!C191/投資後權重!$BT191 -> 0.011905174 | D191: =投資後權重!D191/投資後權重!$BT191 -> 0.0071668791 | E191: =投資後權重!E191/投資後權重!$BT191 -> 0.0080119938 | F191: =投資後權重!F191/投資後權重!$BT191 -> 0.0054899657 | G191: =投資後權重!G191/投資後權重!$BT191 -> 0 | H191: =投資後權重!H191/投資後權重!$BT191 -> 0.0084554323 | I191: =投資後權重!I191/投資後權重!$BT191 -> 0 | ... BN191: =投資後權重!BN191/投資後權重!$BT191 -> 0 | BO191: =SUM(B191:BN191) -> 1
A192: 2024-10-21 | B192: =投資後權重!B192/投資後權重!$BT192 -> 0.0058558258 | C192: =投資後權重!C192/投資後權重!$BT192 -> 0.011894518 | D192: =投資後權重!D192/投資後權重!$BT192 -> 0.0070424646 | E192: =投資後權重!E192/投資後權重!$BT192 -> 0.0077630154 | F192: =投資後權重!F192/投資後權重!$BT192 -> 0.0053328007 | G192: =投資後權重!G192/投資後權重!$BT192 -> 0 | H192: =投資後權重!H192/投資後權重!$BT192 -> 0.0083376193 | I192: =投資後權重!I192/投資後權重!$BT192 -> 0 | ... BN192: =投資後權重!BN192/投資後權重!$BT192 -> 0 | BO192: =SUM(B192:BN192) -> 1
A193: 2024-10-22 | B193: =投資後權重!B193/投資後權重!$BT193 -> 0.0058212592 | C193: =投資後權重!C193/投資後權重!$BT193 -> 0.011786561 | D193: =投資後權重!D193/投資後權重!$BT193 -> 0.0069443364 | E193: =投資後權重!E193/投資後權重!$BT193 -> 0.0076605656 | F193: =投資後權重!F193/投資後權重!$BT193 -> 0.0052918264 | G193: =投資後權重!G193/投資後權重!$BT193 -> 0 | H193: =投資後權重!H193/投資後權重!$BT193 -> 0.0082533825 | I193: =投資後權重!I193/投資後權重!$BT193 -> 0 | ... BN193: =投資後權重!BN193/投資後權重!$BT193 -> 0 | BO193: =SUM(B193:BN193) -> 1
A194: 2024-10-23 | B194: =投資後權重!B194/投資後權重!$BT194 -> 0.0058905809 | C194: =投資後權重!C194/投資後權重!$BT194 -> 0.011814527 | D194: =投資後權重!D194/投資後權重!$BT194 -> 0.0069410014 | E194: =投資後權重!E194/投資後權重!$BT194 -> 0.0076648828 | F194: =投資後權重!F194/投資後權重!$BT194 -> 0.0052981122 | G194: =投資後權重!G194/投資後權重!$BT194 -> 0 | H194: =投資後權重!H194/投資後權重!$BT194 -> 0.008301472 | I194: =投資後權重!I194/投資後權重!$BT194 -> 0 | ... BN194: =投資後權重!BN194/投資後權重!$BT194 -> 0 | BO194: =SUM(B194:BN194) -> 1
A195: 2024-10-24 | B195: =投資後權重!B195/投資後權重!$BT195 -> 0.0058870903 | C195: =投資後權重!C195/投資後權重!$BT195 -> 0.012110588 | D195: =投資後權重!D195/投資後權重!$BT195 -> 0.0069802439 | E195: =投資後權重!E195/投資後權重!$BT195 -> 0.0077929235 | F195: =投資後權重!F195/投資後權重!$BT195 -> 0.0053628447 | G195: =投資後權重!G195/投資後權重!$BT195 -> 0 | H195: =投資後權重!H195/投資後權重!$BT195 -> 0.0083296878 | I195: =投資後權重!I195/投資後權重!$BT195 -> 0 | ... BN195: =投資後權重!BN195/投資後權重!$BT195 -> 0 | BO195: =SUM(B195:BN195) -> 1
A196: 2024-10-25 | B196: =投資後權重!B196/投資後權重!$BT196 -> 0.0058466189 | C196: =投資後權重!C196/投資後權重!$BT196 -> 0.011888216 | D196: =投資後權重!D196/投資後權重!$BT196 -> 0.0070188224 | E196: =投資後權重!E196/投資後權重!$BT196 -> 0.007717944 | F196: =投資後權重!F196/投資後權重!$BT196 -> 0.0053107714 | G196: =投資後權重!G196/投資後權重!$BT196 -> 0 | H196: =投資後權重!H196/投資後權重!$BT196 -> 0.0083708833 | I196: =投資後權重!I196/投資後權重!$BT196 -> 0 | ... BN196: =投資後權重!BN196/投資後權重!$BT196 -> 0 | BO196: =SUM(B196:BN196) -> 1
A197: 2024-10-28 | B197: =投資後權重!B197/投資後權重!$BT197 -> 0.0058952485 | C197: =投資後權重!C197/投資後權重!$BT197 -> 0.012070789 | D197: =投資後權重!D197/投資後權重!$BT197 -> 0.0073111935 | E197: =投資後權重!E197/投資後權重!$BT197 -> 0.0079361682 | F197: =投資後權重!F197/投資後權重!$BT197 -> 0.0054977433 | G197: =投資後權重!G197/投資後權重!$BT197 -> 0 | H197: =投資後權重!H197/投資後權重!$BT197 -> 0.0084888827 | I197: =投資後權重!I197/投資後權重!$BT197 -> 0 | ... BN197: =投資後權重!BN197/投資後權重!$BT197 -> 0 | BO197: =SUM(B197:BN197) -> 1
... A246: 2025-01-07 | B246: =投資後權重!B246/投資後權重!$BT246 -> 0.0056448046 | C246: =投資後權重!C246/投資後權重!$BT246 -> 0.010443442 | D246: =投資後權重!D246/投資後權重!$BT246 -> 0.0050846881 | E246: =投資後權重!E246/投資後權重!$BT246 -> 0.0054914185 | F246: =投資後權重!F246/投資後權重!$BT246 -> 0.0036315605 | G246: =投資後權重!G246/投資後權重!$BT246 -> 0 | H246: =投資後權重!H246/投資後權重!$BT246 -> 0.0069102787 | I246: =投資後權重!I246/投資後權重!$BT246 -> 0 | ... BN246: =投資後權重!BN246/投資後權重!$BT246 -> 0 | BO246: =SUM(B246:BN246) -> 1
A247: 2025-01-08 | B247: 0.0066687321 | C247: 0.012083592 | D247: 0.0057901838 | E247: 0.0063146121 | H247: 0.0080730562 | J247: 0.0094027041 | K247: 0.0064526618 | L247: 0.014655416 | M247: 0.030132856 | N247: 0.071058808 | O247: 0.0080792186 | P247: 0.30145781 | Q247: 0.011974436 | R247: 0.013105526 | T247: 0.007630604 | U247: 0.031063594 | W247: 0.0089549752 | Y247: 0.026102852 | Z247: 0.062805195 | AA247: 0.013533518 | AB247: 0.007462464 | AC247: 0.0064961713 | AD247: 0.0068044153 | AF247: 0.0099501526 | AG247: 0.037627925 | AH247: 0.030098429 | AI247: 0.0087281319 | AJ247: 0.011880107 | AK247: 0.012332926 | AL247: 0.015663471 | AM247: 0.0067001311 | AO247: 0.0078614856 | AP247: 0.02133062 | AQ247: 0.010572108 | AR247: 0.0073803549 | AS247: 0.0096217861 | AT247: 0.006407682 | AU247: 0.0084568403 | AW247: 0.011305906 | AX247: 0.0085184628 | AY247: 0.0076026636 | BA247: 0.0066794671 | BC247: 0.0069086457 | BD247: 0.02051 | BE247: 0.0085329228 | BF247: 0.0068970009 | BI247: 0.010265674 | BK247: 0.0089124643 | BL247: 0.014387689 | BN247: 0.0087635475
A248: 2025-01-09 | B248: =投資後權重!B248/投資後權重!$BT248 -> 0.0056512957 | C248: =投資後權重!C248/投資後權重!$BT248 -> 0.010572022 | D248: =投資後權重!D248/投資後權重!$BT248 -> 0.0048219777 | E248: =投資後權重!E248/投資後權重!$BT248 -> 0.0053692387 | F248: =投資後權重!F248/投資後權重!$BT248 -> 0.0037183669 | G248: =投資後權重!G248/投資後權重!$BT248 -> 0 | H248: =投資後權重!H248/投資後權重!$BT248 -> 0.0069447762 | I248: =投資後權重!I248/投資後權重!$BT248 -> 0 | ... BN248: =投資後權重!BN248/投資後權重!$BT248 -> 0 | BO248: =SUM(B248:BN248) -> 1
A249: 2025-01-10 | B249: =投資後權重!B249/投資後權重!$BT249 -> 0.0055697069 | C249: =投資後權重!C249/投資後權重!$BT249 -> 0.010595338 | D249: =投資後權重!D249/投資後權重!$BT249 -> 0.0047556022 | E249: =投資後權重!E249/投資後權重!$BT249 -> 0.0053314183 | F249: =投資後權重!F249/投資後權重!$BT249 -> 0.0037313147 | G249: =投資後權重!G249/投資後權重!$BT249 -> 0 | H249: =投資後權重!H249/投資後權重!$BT249 -> 0.0068565563 | I249: =投資後權重!I249/投資後權重!$BT249 -> 0 | ... BN249: =投資後權重!BN249/投資後權重!$BT249 -> 0 | BO249: =SUM(B249:BN249) -> 1
A250: 2025-01-13 | B250: =投資後權重!B250/投資後權重!$BT250 -> 0.0057408875 | C250: =投資後權重!C250/投資後權重!$BT250 -> 0.010762471 | D250: =投資後權重!D250/投資後權重!$BT250 -> 0.0050007067 | E250: =投資後權重!E250/投資後權重!$BT250 -> 0.0055272671 | F250: =投資後權重!F250/投資後權重!$BT250 -> 0.0038144692 | G250: =投資後權重!G250/投資後權重!$BT250 -> 0 | H250: =投資後權重!H250/投資後權重!$BT250 -> 0.0069327535 | I250: =投資後權重!I250/投資後權重!$BT250 -> 0 | ... BN250: =投資後權重!BN250/投資後權重!$BT250 -> 0 | BO250: =SUM(B250:BN250) -> 1
A251: 2025-01-14 | B251: =投資後權重!B251/投資後權重!$BT251 -> 0.0056847019 | C251: =投資後權重!C251/投資後權重!$BT251 -> 0.010758495 | D251: =投資後權重!D251/投資後權重!$BT251 -> 0.0053322605 | E251: =投資後權重!E251/投資後權重!$BT251 -> 0.0057879254 | F251: =投資後權重!F251/投資後權重!$BT251 -> 0.0037647938 | G251: =投資後權重!G251/投資後權重!$BT251 -> 0 | H251: =投資後權重!H251/投資後權重!$BT251 -> 0.0069369782 | I251: =投資後權重!I251/投資後權重!$BT251 -> 0 | ... BN251: =投資後權重!BN251/投資後權重!$BT251 -> 0 | BO251: =SUM(B251:BN251) -> 1
A252: 2025-01-15 | B252: =投資後權重!B252/投資後權重!$BT252 -> 0.0058004866 | C252: =投資後權重!C252/投資後權重!$BT252 -> 0.010726867 | D252: =投資後權重!D252/投資後權重!$BT252 -> 0.0054983353 | E252: =投資後權重!E252/投資後權重!$BT252 -> 0.005963809 | F252: =投資後權重!F252/投資後權重!$BT252 -> 0.0038165296 | G252: =投資後權重!G252/投資後權重!$BT252 -> 0 | H252: =投資後權重!H252/投資後權重!$BT252 -> 0.0071664374 | I252: =投資後權重!I252/投資後權重!$BT252 -> 0 | ... BN252: =投資後權重!BN252/投資後權重!$BT252 -> 0 | BO252: =SUM(B252:BN252) -> 1
A253: 2025-01-16 | B253: =投資後權重!B253/投資後權重!$BT253 -> 0.0056968426 | C253: =投資後權重!C253/投資後權重!$BT253 -> 0.010632563 | D253: =投資後權重!D253/投資後權重!$BT253 -> 0.0053512438 | E253: =投資後權重!E253/投資後權重!$BT253 -> 0.0059324417 | F253: =投資後權重!F253/投資後權重!$BT253 -> 0.0037301688 | G253: =投資後權重!G253/投資後權重!$BT253 -> 0 | H253: =投資後權重!H253/投資後權重!$BT253 -> 0.0070791866 | I253: =投資後權重!I253/投資後權重!$BT253 -> 0 | ... BN253: =投資後權重!BN253/投資後權重!$BT253 -> 0 | BO253: =SUM(B253:BN253) -> 1
A254: 2025-01-17 | B254: =投資後權重!B254/投資後權重!$BT254 -> 0.0058017797 | C254: =投資後權重!C254/投資後權重!$BT254 -> 0.010531975 | D254: =投資後權重!D254/投資後權重!$BT254 -> 0.0055914291 | E254: =投資後權重!E254/投資後權重!$BT254 -> 0.0061703067 | F254: =投資後權重!F254/投資後權重!$BT254 -> 0.0037090005 | G254: =投資後權重!G254/投資後權重!$BT254 -> 0 | H254: =投資後權重!H254/投資後權重!$BT254 -> 0.0072810955 | I254: =投資後權重!I254/投資後權重!$BT254 -> 0 | ... BN254: =投資後權重!BN254/投資後權重!$BT254 -> 0 | BO254: =SUM(B254:BN254) -> 1
A255: 2025-01-20 | B255: =投資後權重!B255/投資後權重!$BT255 -> 0.0058074211 | C255: =投資後權重!C255/投資後權重!$BT255 -> 0.010399002 | D255: =投資後權重!D255/投資後權重!$BT255 -> 0.0055255836 | E255: =投資後權重!E255/投資後權重!$BT255 -> 0.0060352814 | F255: =投資後權重!F255/投資後權重!$BT255 -> 0.0036951221 | G255: =投資後權重!G255/投資後權重!$BT255 -> 0 | H255: =投資後權重!H255/投資後權重!$BT255 -> 0.007253851 | I255: =投資後權重!I255/投資後權重!$BT255 -> 0 | ... BN255: =投資後權重!BN255/投資後權重!$BT255 -> 0 | BO255: =SUM(B255:BN255) -> 1
A256: 2025-01-21 | B256: =投資後權重!B256/投資後權重!$BT256 -> 0.005785574 | C256: =投資後權重!C256/投資後權重!$BT256 -> 0.010456193 | D256: =投資後權重!D256/投資後權重!$BT256 -> 0.0053789776 | E256: =投資後權重!E256/投資後權重!$BT256 -> 0.0059661851 | F256: =投資後權重!F256/投資後權重!$BT256 -> 0.0036870095 | G256: =投資後權重!G256/投資後權重!$BT256 -> 0 | H256: =投資後權重!H256/投資後權重!$BT256 -> 0.0074415496 | I256: =投資後權重!I256/投資後權重!$BT256 -> 0 | ... BN256: =投資後權重!BN256/投資後權重!$BT256 -> 0 | BO256: =SUM(B256:BN256) -> 1
A257: 2025-01-22 | B257: =投資後權重!B257/投資後權重!$BT257 -> 0.0057447974 | C257: =投資後權重!C257/投資後權重!$BT257 -> 0.010366198 | D257: =投資後權重!D257/投資後權重!$BT257 -> 0.0053697145 | E257: =投資後權重!E257/投資後權重!$BT257 -> 0.0059702006 | F257: =投資後權重!F257/投資後權重!$BT257 -> 0.0036552762 | G257: =投資後權重!G257/投資後權重!$BT257 -> 0 | H257: =投資後權重!H257/投資後權重!$BT257 -> 0.0073958538 | I257: =投資後權重!I257/投資後權重!$BT257 -> 0 | ... BN257: =投資後權重!BN257/投資後權重!$BT257 -> 0 | BO257: =SUM(B257:BN257) -> 1
A258: 2025-02-03 | B258: =投資後權重!B258/投資後權重!$BT258 -> 0.0059468433 | C258: =投資後權重!C258/投資後權重!$BT258 -> 0.010874421 | D258: =投資後權重!D258/投資後權重!$BT258 -> 0.005299195 | E258: =投資後權重!E258/投資後權重!$BT258 -> 0.0059888322 | F258: =投資後權重!F258/投資後權重!$BT258 -> 0.0037957508 | G258: =投資後權重!G258/投資後權重!$BT258 -> 0 | H258: =投資後權重!H258/投資後權重!$BT258 -> 0.0076229094 | I258: =投資後權重!I258/投資後權重!$BT258 -> 0 | ... BN258: =投資後權重!BN258/投資後權重!$BT258 -> 0 | BO258: =SUM(B258:BN258) -> 1
A259: 2025-02-04 | B259: =投資後權重!B259/投資後權重!$BT259 -> 0.005818126 | C259: =投資後權重!C259/投資後權重!$BT259 -> 0.010700088 | D259: =投資後權重!D259/投資後權重!$BT259 -> 0.0051986421 | E259: =投資後權重!E259/投資後權重!$BT259 -> 0.0058100825 | F259: =投資後權重!F259/投資後權重!$BT259 -> 0.0037730105 | G259: =投資後權重!G259/投資後權重!$BT259 -> 0 | H259: =投資後權重!H259/投資後權重!$BT259 -> 0.0074256959 | I259: =投資後權重!I259/投資後權重!$BT259 -> 0 | ... BN259: =投資後權重!BN259/投資後權重!$BT259 -> 0 | BO259: =SUM(B259:BN259) -> 1
... A301: 2025-04-08 | B301: =投資後權重!B301/投資後權重!$BT301 -> 0.0067306534 | C301: =投資後權重!C301/投資後權重!$BT301 -> 0.013029642 | D301: =投資後權重!D301/投資後權重!$BT301 -> 0.0065342908 | E301: =投資後權重!E301/投資後權重!$BT301 -> 0.0067008162 | F301: =投資後權重!F301/投資後權重!$BT301 -> 0.0046003137 | G301: =投資後權重!G301/投資後權重!$BT301 -> 0 | H301: =投資後權重!H301/投資後權重!$BT301 -> 0.0094465632 | I301: =投資後權重!I301/投資後權重!$BT301 -> 0 | ... BN301: =投資後權重!BN301/投資後權重!$BT301 -> 0 | BO301: =SUM(B301:BN301) -> 1
A302: 2025-04-09 | B302: 0.0077875531 | C302: 0.015060697 | D302: 0.0071047464 | E302: 0.007445623 | H302: 0.010545847 | J302: 0.01070243 | K302: 0.0056180665 | L302: 0.018145397 | M302: 0.025171751 | N302: 0.053533783 | O302: 0.0068329302 | P302: 0.30216633 | Q302: 0.0083273119 | R302: 0.011227546 | T302: 0.0077821454 | U302: 0.02320614 | W302: 0.0092132082 | Y302: 0.03490887 | Z302: 0.065067423 | AA302: 0.01319685 | AB302: 0.0070654845 | AC302: 0.0058934918 | AD302: 0.0062076712 | AF302: 0.012338311 | AG302: 0.038460819 | AH302: 0.027710532 | AI302: 0.0090522422 | AJ302: 0.014514667 | AK302: 0.012253921 | AL302: 0.019553819 | AM302: 0.0070579064 | AN302: 0.0063383704 | AO302: 0.0087155073 | AP302: 0.02414584 | AQ302: 0.012187759 | AR302: 0.0090796735 | AS302: 0.0085373523 | AU302: 0.0098105333 | AW302: 0.015338997 | AX302: 0.0074079711 | AY302: 0.0069816286 | BC302: 0.0052807062 | BD302: 0.017430316 | BE302: 0.011064599 | BF302: 0.0063026397 | BH302: 0.0078435105 | BI302: 0.012138162 | BK302: 0.010452712 | BL302: 0.01003794 | BN302: 0.0077522673
A303: 2025-04-10 | B303: =投資後權重!B303/投資後權重!$BT303 -> 0.0067616091 | C303: =投資後權重!C303/投資後權重!$BT303 -> 0.012637442 | D303: =投資後權重!D303/投資後權重!$BT303 -> 0.0062843749 | E303: =投資後權重!E303/投資後權重!$BT303 -> 0.0066370687 | F303: =投資後權重!F303/投資後權重!$BT303 -> 0.0044561506 | G303: =投資後權重!G303/投資後權重!$BT303 -> 0 | H303: =投資後權重!H303/投資後權重!$BT303 -> 0.0093518862 | I303: =投資後權重!I303/投資後權重!$BT303 -> 0 | ... BN303: =投資後權重!BN303/投資後權重!$BT303 -> 0 | BO303: =SUM(B303:BN303) -> 1
A304: 2025-04-11 | B304: =投資後權重!B304/投資後權重!$BT304 -> 0.0064041539 | C304: =投資後權重!C304/投資後權重!$BT304 -> 0.012205998 | D304: =投資後權重!D304/投資後權重!$BT304 -> 0.0061009526 | E304: =投資後權重!E304/投資後權重!$BT304 -> 0.0065744035 | F304: =投資後權重!F304/投資後權重!$BT304 -> 0.0043260887 | G304: =投資後權重!G304/投資後權重!$BT304 -> 0 | H304: =投資後權重!H304/投資後權重!$BT304 -> 0.008883453 | I304: =投資後權重!I304/投資後權重!$BT304 -> 0 | ... BN304: =投資後權重!BN304/投資後權重!$BT304 -> 0 | BO304: =SUM(B304:BN304) -> 1
A305: 2025-04-14 | B305: =投資後權重!B305/投資後權重!$BT305 -> 0.0064159904 | C305: =投資後權重!C305/投資後權重!$BT305 -> 0.012033505 | D305: =投資後權重!D305/投資後權重!$BT305 -> 0.0062295954 | E305: =投資後權重!E305/投資後權重!$BT305 -> 0.0067622713 | F305: =投資後權重!F305/投資後權重!$BT305 -> 0.0043485797 | G305: =投資後權重!G305/投資後權重!$BT305 -> 0 | H305: =投資後權重!H305/投資後權重!$BT305 -> 0.0092352973 | I305: =投資後權重!I305/投資後權重!$BT305 -> 0 | ... BN305: =投資後權重!BN305/投資後權重!$BT305 -> 0 | BO305: =SUM(B305:BN305) -> 1
A306: 2025-04-15 | B306: =投資後權重!B306/投資後權重!$BT306 -> 0.0063433765 | C306: =投資後權重!C306/投資後權重!$BT306 -> 0.011757345 | D306: =投資後權重!D306/投資後權重!$BT306 -> 0.0063681691 | E306: =投資後權重!E306/投資後權重!$BT306 -> 0.0069136613 | F306: =投資後權重!F306/投資後權重!$BT306 -> 0.0042993641 | G306: =投資後權重!G306/投資後權重!$BT306 -> 0 | H306: =投資後權重!H306/投資後權重!$BT306 -> 0.0092171186 | I306: =投資後權重!I306/投資後權重!$BT306 -> 0 | ... BN306: =投資後權重!BN306/投資後權重!$BT306 -> 0 | BO306: =SUM(B306:BN306) -> 1
A307: 2025-04-16 | B307: =投資後權重!B307/投資後權重!$BT307 -> 0.0063686542 | C307: =投資後權重!C307/投資後權重!$BT307 -> 0.012154163 | D307: =投資後權重!D307/投資後權重!$BT307 -> 0.0063472643 | E307: =投資後權重!E307/投資後權重!$BT307 -> 0.006880707 | F307: =投資後權重!F307/投資後權重!$BT307 -> 0.0043750253 | G307: =投資後權重!G307/投資後權重!$BT307 -> 0 | H307: =投資後權重!H307/投資後權重!$BT307 -> 0.009181633 | I307: =投資後權重!I307/投資後權重!$BT307 -> 0 | ... BN307: =投資後權重!BN307/投資後權重!$BT307 -> 0 | BO307: =SUM(B307:BN307) -> 1
A308: 2025-04-17 | B308: =投資後權重!B308/投資後權重!$BT308 -> 0.0063969934 | C308: =投資後權重!C308/投資後權重!$BT308 -> 0.012078911 | D308: =投資後權重!D308/投資後權重!$BT308 -> 0.0063543928 | E308: =投資後權重!E308/投資後權重!$BT308 -> 0.0068574441 | F308: =投資後權重!F308/投資後權重!$BT308 -> 0.0044169524 | G308: =投資後權重!G308/投資後權重!$BT308 -> 0 | H308: =投資後權重!H308/投資後權重!$BT308 -> 0.009092214 | I308: =投資後權重!I308/投資後權重!$BT308 -> 0 | ... BN308: =投資後權重!BN308/投資後權重!$BT308 -> 0 | BO308: =SUM(B308:BN308) -> 1
A309: 2025-04-18 | B309: =投資後權重!B309/投資後權重!$BT309 -> 0.0062892207 | C309: =投資後權重!C309/投資後權重!$BT309 -> 0.011928017 | D309: =投資後權重!D309/投資後權重!$BT309 -> 0.0063247361 | E309: =投資後權重!E309/投資後權重!$BT309 -> 0.0068128386 | F309: =投資後權重!F309/投資後權重!$BT309 -> 0.0044025387 | G309: =投資後權重!G309/投資後權重!$BT309 -> 0 | H309: =投資後權重!H309/投資後權重!$BT309 -> 0.0090183363 | I309: =投資後權重!I309/投資後權重!$BT309 -> 0 | ... BN309: =投資後權重!BN309/投資後權重!$BT309 -> 0 | BO309: =SUM(B309:BN309) -> 1
A310: 2025-04-21 | B310: =投資後權重!B310/投資後權重!$BT310 -> 0.0063034581 | C310: =投資後權重!C310/投資後權重!$BT310 -> 0.012026957 | D310: =投資後權重!D310/投資後權重!$BT310 -> 0.0062409539 | E310: =投資後權重!E310/投資後權重!$BT310 -> 0.0067529076 | F310: =投資後權重!F310/投資後權重!$BT310 -> 0.0044509416 | G310: =投資後權重!G310/投資後權重!$BT310 -> 0 | H310: =投資後權重!H310/投資後權重!$BT310 -> 0.0089387123 | I310: =投資後權重!I310/投資後權重!$BT310 -> 0 | ... BN310: =投資後權重!BN310/投資後權重!$BT310 -> 0 | BO310: =SUM(B310:BN310) -> 1
A311: 2025-04-22 | B311: =投資後權重!B311/投資後權重!$BT311 -> 0.0063980882 | C311: =投資後權重!C311/投資後權重!$BT311 -> 0.012364988 | D311: =投資後權重!D311/投資後權重!$BT311 -> 0.006365981 | E311: =投資後權重!E311/投資後權重!$BT311 -> 0.0069698085 | F311: =投資後權重!F311/投資後權重!$BT311 -> 0.0045335573 | G311: =投資後權重!G311/投資後權重!$BT311 -> 0 | H311: =投資後權重!H311/投資後權重!$BT311 -> 0.0091956737 | I311: =投資後權重!I311/投資後權重!$BT311 -> 0 | ... BN311: =投資後權重!BN311/投資後權重!$BT311 -> 0 | BO311: =SUM(B311:BN311) -> 1
A312: 2025-04-23 | B312: =投資後權重!B312/投資後權重!$BT312 -> 0.0062600928 | C312: =投資後權重!C312/投資後權重!$BT312 -> 0.012158914 | D312: =投資後權重!D312/投資後權重!$BT312 -> 0.0062660282 | E312: =投資後權重!E312/投資後權重!$BT312 -> 0.006843122 | F312: =投資後權重!F312/投資後權重!$BT312 -> 0.0043372037 | G312: =投資後權重!G312/投資後權重!$BT312 -> 0 | H312: =投資後權重!H312/投資後權重!$BT312 -> 0.0089933802 | I312: =投資後權重!I312/投資後權重!$BT312 -> 0 | ... BN312: =投資後權重!BN312/投資後權重!$BT312 -> 0 | BO312: =SUM(B312:BN312) -> 1
A313: 2025-04-24 | B313: =投資後權重!B313/投資後權重!$BT313 -> 0.0063356087 | C313: =投資後權重!C313/投資後權重!$BT313 -> 0.012146806 | D313: =投資後權重!D313/投資後權重!$BT313 -> 0.006056999 | E313: =投資後權重!E313/投資後權重!$BT313 -> 0.0067262117 | F313: =投資後權重!F313/投資後權重!$BT313 -> 0.0043895237 | G313: =投資後權重!G313/投資後權重!$BT313 -> 0 | H313: =投資後權重!H313/投資後權重!$BT313 -> 0.0090357526 | I313: =投資後權重!I313/投資後權重!$BT313 -> 0 | ... BN313: =投資後權重!BN313/投資後權重!$BT313 -> 0 | BO313: =SUM(B313:BN313) -> 1
A314: 2025-04-25 | B314: =投資後權重!B314/投資後權重!$BT314 -> 0.0062280802 | C314: =投資後權重!C314/投資後權重!$BT314 -> 0.011853299 | D314: =投資後權重!D314/投資後權重!$BT314 -> 0.0059426257 | E314: =投資後權重!E314/投資後權重!$BT314 -> 0.0066003814 | F314: =投資後權重!F314/投資後權重!$BT314 -> 0.0043003223 | G314: =投資後權重!G314/投資後權重!$BT314 -> 0 | H314: =投資後權重!H314/投資後權重!$BT314 -> 0.008765771 | I314: =投資後權重!I314/投資後權重!$BT314 -> 0 | ... BN314: =投資後權重!BN314/投資後權重!$BT314 -> 0 | BO314: =SUM(B314:BN314) -> 1
... A362: 2025-07-04 | B362: =投資後權重!B362/投資後權重!$BT362 -> 0.0046682575 | C362: =投資後權重!C362/投資後權重!$BT362 -> 0.011292937 | D362: =投資後權重!D362/投資後權重!$BT362 -> 0.0055667193 | E362: =投資後權重!E362/投資後權重!$BT362 -> 0.0055406682 | F362: =投資後權重!F362/投資後權重!$BT362 -> 0.0037841619 | G362: =投資後權重!G362/投資後權重!$BT362 -> 0 | H362: =投資後權重!H362/投資後權重!$BT362 -> 0.0073146494 | I362: =投資後權重!I362/投資後權重!$BT362 -> 0 | ... BN362: =投資後權重!BN362/投資後權重!$BT362 -> 0 | BO362: =SUM(B362:BN362) -> 1
A363: 2025-07-07 | C363: 0.013730373 | D363: 0.0064010079 | E363: 0.0063340119 | H363: 0.008523419 | J363: 0.0086352124 | K363: 0.0076421895 | L363: 0.015729105 | M363: 0.032898663 | N363: 0.06080139 | O363: 0.0071733838 | P363: 0.30587717 | Q363: 0.011932466 | R363: 0.013671103 | T363: 0.0084774935 | U363: 0.028317084 | V363: 0.0093441719 | W363: 0.0084902622 | Y363: 0.027719493 | Z363: 0.056492349 | AA363: 0.011843387 | AB363: 0.0072040232 | AC363: 0.0070593994 | AF363: 0.011203727 | AG363: 0.034801413 | AH363: 0.025268628 | AI363: 0.0070968966 | AJ363: 0.015643344 | AK363: 0.011372035 | AL363: 0.017957982 | AM363: 0.0064462183 | AO363: 0.0089620748 | AP363: 0.025701504 | AQ363: 0.012060864 | AR363: 0.0077940869 | AS363: 0.0085000724 | AT363: 0.0086169362 | AU363: 0.0096180554 | AW363: 0.012052352 | AX363: 0.01085417 | AY363: 0.0067619398 | BB363: 0.0060479458 | BC363: 0.0077656276 | BD363: 0.01740378 | BE363: 0.0092097119 | BG363: 0.0067870609 | BH363: 0.0061972298 | BI363: 0.010931244 | BK363: 0.010124723 | BL363: 0.013180093 | BN363: 0.0073431247
A364: 2025-07-08 | B364: =投資後權重!B364/投資後權重!$BT364 -> 0.004698374 | C364: =投資後權重!C364/投資後權重!$BT364 -> 0.011544889 | D364: =投資後權重!D364/投資後權重!$BT364 -> 0.0053402499 | E364: =投資後權重!E364/投資後權重!$BT364 -> 0.0053937374 | F364: =投資後權重!F364/投資後權重!$BT364 -> 0.0038085749 | G364: =投資後權重!G364/投資後權重!$BT364 -> 0 | H364: =投資後權重!H364/投資後權重!$BT364 -> 0.0071897439 | I364: =投資後權重!I364/投資後權重!$BT364 -> 0 | ... BN364: =投資後權重!BN364/投資後權重!$BT364 -> 0 | BO364: =SUM(B364:BN364) -> 1
A365: 2025-07-09 | B365: =投資後權重!B365/投資後權重!$BT365 -> 0.0046633378 | C365: =投資後權重!C365/投資後權重!$BT365 -> 0.011417776 | D365: =投資後權重!D365/投資後權重!$BT365 -> 0.0052391506 | E365: =投資後權重!E365/投資後權重!$BT365 -> 0.0052390022 | F365: =投資後權重!F365/投資後權重!$BT365 -> 0.003780174 | G365: =投資後權重!G365/投資後權重!$BT365 -> 0 | H365: =投資後權重!H365/投資後權重!$BT365 -> 0.0071740875 | I365: =投資後權重!I365/投資後權重!$BT365 -> 0 | ... BN365: =投資後權重!BN365/投資後權重!$BT365 -> 0 | BO365: =SUM(B365:BN365) -> 1
A366: 2025-07-10 | B366: =投資後權重!B366/投資後權重!$BT366 -> 0.0046115797 | C366: =投資後權重!C366/投資後權重!$BT366 -> 0.011358662 | D366: =投資後權重!D366/投資後權重!$BT366 -> 0.0052264489 | E366: =投資後權重!E366/投資後權重!$BT366 -> 0.005152544 | F366: =投資後權重!F366/投資後權重!$BT366 -> 0.003738218 | G366: =投資後權重!G366/投資後權重!$BT366 -> 0 | H366: =投資後權重!H366/投資後權重!$BT366 -> 0.007113231 | I366: =投資後權重!I366/投資後權重!$BT366 -> 0 | ... BN366: =投資後權重!BN366/投資後權重!$BT366 -> 0 | BO366: =SUM(B366:BN366) -> 1
A367: 2025-07-11 | B367: =投資後權重!B367/投資後權重!$BT367 -> 0.0046042029 | C367: =投資後權重!C367/投資後權重!$BT367 -> 0.011461998 | D367: =投資後權重!D367/投資後權重!$BT367 -> 0.0051424641 | E367: =投資後權重!E367/投資後權重!$BT367 -> 0.0050218185 | F367: =投資後權重!F367/投資後權重!$BT367 -> 0.0037322383 | G367: =投資後權重!G367/投資後權重!$BT367 -> 0 | H367: =投資後權重!H367/投資後權重!$BT367 -> 0.0070456374 | I367: =投資後權重!I367/投資後權重!$BT367 -> 0 | ... BN367: =投資後權重!BN367/投資後權重!$BT367 -> 0 | BO367: =SUM(B367:BN367) -> 1
A368: 2025-07-14 | B368: =投資後權重!B368/投資後權重!$BT368 -> 0.0046306921 | C368: =投資後權重!C368/投資後權重!$BT368 -> 0.011582255 | D368: =投資後權重!D368/投資後權重!$BT368 -> 0.0054306525 | E368: =投資後權重!E368/投資後權重!$BT368 -> 0.0051833744 | F368: =投資後權重!F368/投資後權重!$BT368 -> 0.0037537108 | G368: =投資後權重!G368/投資後權重!$BT368 -> 0 | H368: =投資後權重!H368/投資後權重!$BT368 -> 0.007105019 | I368: =投資後權重!I368/投資後權重!$BT368 -> 0 | ... BN368: =投資後權重!BN368/投資後權重!$BT368 -> 0 | BO368: =SUM(B368:BN368) -> 1
A369: 2025-07-15 | B369: =投資後權重!B369/投資後權重!$BT369 -> 0.0045875861 | C369: =投資後權重!C369/投資後權重!$BT369 -> 0.011380275 | D369: =投資後權重!D369/投資後權重!$BT369 -> 0.0054177757 | E369: =投資後權重!E369/投資後權重!$BT369 -> 0.0051914505 | F369: =投資後權重!F369/投資後權重!$BT369 -> 0.0037187685 | G369: =投資後權重!G369/投資後權重!$BT369 -> 0 | H369: =投資後權重!H369/投資後權重!$BT369 -> 0.0070575509 | I369: =投資後權重!I369/投資後權重!$BT369 -> 0 | ... BN369: =投資後權重!BN369/投資後權重!$BT369 -> 0 | BO369: =SUM(B369:BN369) -> 1
A370: 2025-07-16 | B370: =投資後權重!B370/投資後權重!$BT370 -> 0.0045430765 | C370: =投資後權重!C370/投資後權重!$BT370 -> 0.011389754 | D370: =投資後權重!D370/投資後權重!$BT370 -> 0.0052831289 | E370: =投資後權重!E370/投資後權重!$BT370 -> 0.0051596754 | F370: =投資後權重!F370/投資後權重!$BT370 -> 0.0036826883 | G370: =投資後權重!G370/投資後權重!$BT370 -> 0 | H370: =投資後權重!H370/投資後權重!$BT370 -> 0.0069520979 | I370: =投資後權重!I370/投資後權重!$BT370 -> 0 | ... BN370: =投資後權重!BN370/投資後權重!$BT370 -> 0 | BO370: =SUM(B370:BN370) -> 1
A371: 2025-07-17 | B371: =投資後權重!B371/投資後權重!$BT371 -> 0.0045399289 | C371: =投資後權重!C371/投資後權重!$BT371 -> 0.011435111 | D371: =投資後權重!D371/投資後權重!$BT371 -> 0.0056299417 | E371: =投資後權重!E371/投資後權重!$BT371 -> 0.0054348088 | F371: =投資後權重!F371/投資後權重!$BT371 -> 0.0036801368 | G371: =投資後權重!G371/投資後權重!$BT371 -> 0 | H371: =投資後權重!H371/投資後權重!$BT371 -> 0.0071135725 | I371: =投資後權重!I371/投資後權重!$BT371 -> 0 | ... BN371: =投資後權重!BN371/投資後權重!$BT371 -> 0 | BO371: =SUM(B371:BN371) -> 1
A372: 2025-07-18 | B372: =投資後權重!B372/投資後權重!$BT372 -> 0.0044829593 | C372: =投資後權重!C372/投資後權重!$BT372 -> 0.011317907 | D372: =投資後權重!D372/投資後權重!$BT372 -> 0.0057139234 | E372: =投資後權重!E372/投資後權重!$BT372 -> 0.0053941308 | F372: =投資後權重!F372/投資後權重!$BT372 -> 0.0036339563 | G372: =投資後權重!G372/投資後權重!$BT372 -> 0 | H372: =投資後權重!H372/投資後權重!$BT372 -> 0.0069330827 | I372: =投資後權重!I372/投資後權重!$BT372 -> 0 | ... BN372: =投資後權重!BN372/投資後權重!$BT372 -> 0 | BO372: =SUM(B372:BN372) -> 1
A373: 2025-07-21 | B373: =投資後權重!B373/投資後權重!$BT373 -> 0.004495112 | C373: =投資後權重!C373/投資後權重!$BT373 -> 0.011414492 | D373: =投資後權重!D373/投資後權重!$BT373 -> 0.0057441797 | E373: =投資後權重!E373/投資後權重!$BT373 -> 0.0054823421 | F373: =投資後權重!F373/投資後權重!$BT373 -> 0.0036438075 | G373: =投資後權重!G373/投資後權重!$BT373 -> 0 | H373: =投資後權重!H373/投資後權重!$BT373 -> 0.007025055 | I373: =投資後權重!I373/投資後權重!$BT373 -> 0 | ... BN373: =投資後權重!BN373/投資後權重!$BT373 -> 0 | BO373: =SUM(B373:BN373) -> 1
A374: 2025-07-22 | B374: =投資後權重!B374/投資後權重!$BT374 -> 0.0045501644 | C374: =投資後權重!C374/投資後權重!$BT374 -> 0.011607656 | D374: =投資後權重!D374/投資後權重!$BT374 -> 0.0058220034 | E374: =投資後權重!E374/投資後權重!$BT374 -> 0.005363261 | F374: =投資後權重!F374/投資後權重!$BT374 -> 0.0036884339 | G374: =投資後權重!G374/投資後權重!$BT374 -> 0 | H374: =投資後權重!H374/投資後權重!$BT374 -> 0.0071296106 | I374: =投資後權重!I374/投資後權重!$BT374 -> 0 | ... BN374: =投資後權重!BN374/投資後權重!$BT374 -> 0 | BO374: =SUM(B374:BN374) -> 1
A375: 2025-07-23 | B375: =投資後權重!B375/投資後權重!$BT375 -> 0.0044965993 | C375: =投資後權重!C375/投資後權重!$BT375 -> 0.011378713 | D375: =投資後權重!D375/投資後權重!$BT375 -> 0.0059381086 | E375: =投資後權重!E375/投資後權重!$BT375 -> 0.0058246154 | F375: =投資後權重!F375/投資後權重!$BT375 -> 0.0036450132 | G375: =投資後權重!G375/投資後權重!$BT375 -> 0 | H375: =投資後權重!H375/投資後權重!$BT375 -> 0.0073201869 | I375: =投資後權重!I375/投資後權重!$BT375 -> 0 | ... BN375: =投資後權重!BN375/投資後權重!$BT375 -> 0 | BO375: =SUM(B375:BN375) -> 1
... A427: 2025-10-07 | B427: =投資後權重!B427/投資後權重!$BT427 -> 0.0038305918 | C427: =投資後權重!C427/投資後權重!$BT427 -> 0.0087723324 | D427: =投資後權重!D427/投資後權重!$BT427 -> 0.0047188377 | E427: =投資後權重!E427/投資後權重!$BT427 -> 0.0064983 | F427: =投資後權重!F427/投資後權重!$BT427 -> 0.0031051371 | G427: =投資後權重!G427/投資後權重!$BT427 -> 0 | H427: =投資後權重!H427/投資後權重!$BT427 -> 0.0059085793 | I427: =投資後權重!I427/投資後權重!$BT427 -> 0 | ... BN427: =投資後權重!BN427/投資後權重!$BT427 -> 0 | BO427: =SUM(B427:BN427) -> 1
A428: 2025-10-08 | C428: 0.010292984 | D428: 0.0057512113 | E428: 0.0076698929 | H428: 0.0069067311 | I428: 0.0083975304 | J428: 0.0075810706 | K428: 0.0097641577 | L428: 0.013312573 | M428: 0.059598021 | N428: 0.07180629 | O428: 0.009145161 | P428: 0.30942183 | Q428: 0.014461802 | R428: 0.011814522 | S428: 0.0064085311 | T428: 0.0066731509 | U428: 0.027931678 | V428: 0.0099218055 | W428: 0.0065961107 | Y428: 0.023872588 | Z428: 0.049918048 | AA428: 0.0090762252 | AE428: 0.0055892014 | AF428: 0.0095507005 | AG428: 0.03252401 | AH428: 0.024760574 | AI428: 0.0065302115 | AJ428: 0.012489158 | AK428: 0.010789818 | AL428: 0.014623689 | AM428: 0.012720856 | AO428: 0.0080987858 | AP428: 0.020028731 | AQ428: 0.0099346395 | AR428: 0.005880148 | AS428: 0.0078043859 | AT428: 0.010761675 | AU428: 0.0058956405 | AV428: 0.0057795994 | AW428: 0.0097336927 | AX428: 0.012202044 | BB428: 0.0085661531 | BC428: 0.0068567481 | BD428: 0.017759203 | BE428: 0.0077509963 | BI428: 0.0089212806 | BK428: 0.009396142 | BL428: 0.01611026 | BM428: 0.0058995472 | BN428: 0.0067201968
...

Sheet 驗證
A1: date | B1: 1101 | C1: 1216 | D1: 1301 | E1: 1303 | F1: 1326 | G1: 1590 | H1: 2002 | I1: 2059 | J1: 2207 | K1: 2301 | L1: 2303 | M1: 2308 | N1: 2317 | O1: 2327 | P1: 2330 | Q1: 2345 | R1: 2357 | S1: 2360 | T1: 2379 | U1: 2382 | V1: 2383 | W1: 2395 | X1: 2408 | Y1: 2412 | Z1: 2454 | AA1: 2603 | AB1: 2609 | AC1: 2615 | AD1: 2618 | AE1: 2801 | AF1: 2880 | AG1: 2881 | AH1: 2882 | AI1: 2883 | AJ1: 2884 | AK1: 2885 | AL1: 2886 | AM1: 2887 | AN1: 2888 | AO1: 2890 | AP1: 2891 | AQ1: 2892 | AR1: 2912 | AS1: 3008 | AT1: 3017 | AU1: 3034 | AV1: 3037 | AW1: 3045 | AX1: 3231 | AY1: 3293 | AZ1: 3443 | BA1: 3529 | BB1: 3653 | BC1: 3661 | BD1: 3711 | BE1: 4904 | BF1: 4938 | BG1: 5871 | BH1: 5876 | BI1: 5880 | BJ1: 6488 | BK1: 6505 | BL1: 6669 | BM1: 6919 | BN1: 8069
A2: 2024-01-03
A3: 2024-01-04 | B3: =每日權重!B3-標準化後權重!B3 -> 5.4837829e-07 | C3: =每日權重!C3-標準化後權重!C3 -> 8.5217802e-07 | D3: =每日權重!D3-標準化後權重!D3 -> 1.0310834e-06 | E3: =每日權重!E3-標準化後權重!E3 -> 1.0762356e-06 | F3: =每日權重!F3-標準化後權重!F3 -> 7.4082475e-07 | G3: =每日權重!G3-標準化後權重!G3 -> 0 | H3: =每日權重!H3-標準化後權重!H3 -> 8.7119104e-07 | I3: =每日權重!I3-標準化後權重!I3 -> 0 | ... BN3: =每日權重!BN3-標準化後權重!BN3 -> 0
A4: 2024-01-05 | B4: =每日權重!B4-標準化後權重!B4 -> 5.505152e-07 | C4: =每日權重!C4-標準化後權重!C4 -> 8.5528751e-07 | D4: =每日權重!D4-標準化後權重!D4 -> 1.0279489e-06 | E4: =每日權重!E4-標準化後權重!E4 -> 1.0724318e-06 | F4: =每日權重!F4-標準化後權重!F4 -> 7.3925204e-07 | G4: =每日權重!G4-標準化後權重!G4 -> 0 | H4: =每日權重!H4-標準化後權重!H4 -> 8.7076673e-07 | I4: =每日權重!I4-標準化後權重!I4 -> 0 | ... BN4: =每日權重!BN4-標準化後權重!BN4 -> 0
A5: 2024-01-08 | B5: =每日權重!B5-標準化後權重!B5 -> 5.4365636e-07 | C5: =每日權重!C5-標準化後權重!C5 -> 8.494248e-07 | D5: =每日權重!D5-標準化後權重!D5 -> 1.0181056e-06 | E5: =每日權重!E5-標準化後權重!E5 -> 1.068659e-06 | F5: =每日權重!F5-標準化後權重!F5 -> 7.3217325e-07 | G5: =每日權重!G5-標準化後權重!G5 -> 0 | H5: =每日權重!H5-標準化後權重!H5 -> 8.5596846e-07 | I5: =每日權重!I5-標準化後權重!I5 -> 0 | ... BN5: =每日權重!BN5-標準化後權重!BN5 -> 0
A6: 2024-01-09 | B6: =每日權重!B6-標準化後權重!B6 -> 5.4624042e-07 | C6: =每日權重!C6-標準化後權重!C6 -> 8.5259524e-07 | D6: =每日權重!D6-標準化後權重!D6 -> 1.0223659e-06 | E6: =每日權重!E6-標準化後權重!E6 -> 1.0685555e-06 | F6: =每日權重!F6-標準化後權重!F6 -> 7.3754823e-07 | G6: =每日權重!G6-標準化後權重!G6 -> 0 | H6: =每日權重!H6-標準化後權重!H6 -> 8.4876617e-07 | I6: =每日權重!I6-標準化後權重!I6 -> 0 | ... BN6: =每日權重!BN6-標準化後權重!BN6 -> 0
A7: 2024-01-10 | B7: =每日權重!B7-標準化後權重!B7 -> 5.4217334e-07 | C7: =每日權重!C7-標準化後權重!C7 -> 8.5503608e-07 | D7: =每日權重!D7-標準化後權重!D7 -> 1.0173652e-06 | E7: =每日權重!E7-標準化後權重!E7 -> 1.0617379e-06 | F7: =每日權重!F7-標準化後權重!F7 -> 7.3357698e-07 | G7: =每日權重!G7-標準化後權重!G7 -> 0 | H7: =每日權重!H7-標準化後權重!H7 -> 8.462853e-07 | I7: =每日權重!I7-標準化後權重!I7 -> 0 | ... BN7: =每日權重!BN7-標準化後權重!BN7 -> 0
A8: 2024-01-11 | B8: =每日權重!B8-標準化後權重!B8 -> 5.3533877e-07 | C8: =每日權重!C8-標準化後權重!C8 -> 8.4192862e-07 | D8: =每日權重!D8-標準化後權重!D8 -> 9.9018987e-07 | E8: =每日權重!E8-標準化後權重!E8 -> 1.0321002e-06 | F8: =每日權重!F8-標準化後權重!F8 -> 7.243296e-07 | G8: =每日權重!G8-標準化後權重!G8 -> 0 | H8: =每日權重!H8-標準化後權重!H8 -> 8.3400085e-07 | I8: =每日權重!I8-標準化後權重!I8 -> 0 | ... BN8: =每日權重!BN8-標準化後權重!BN8 -> 0
A9: 2024-01-12 | B9: =每日權重!B9-標準化後權重!B9 -> 5.4035874e-07 | C9: =每日權重!C9-標準化後權重!C9 -> 8.5208555e-07 | D9: =每日權重!D9-標準化後權重!D9 -> 9.9930923e-07 | E9: =每日權重!E9-標準化後權重!E9 -> 1.0484259e-06 | F9: =每日權重!F9-標準化後權重!F9 -> 7.2761727e-07 | G9: =每日權重!G9-標準化後權重!G9 -> 0 | H9: =每日權重!H9-標準化後權重!H9 -> 8.4057428e-07 | I9: =每日權重!I9-標準化後權重!I9 -> 0 | ... BN9: =每日權重!BN9-標準化後權重!BN9 -> 0
A10: 2024-01-15 | B10: =每日權重!B10-標準化後權重!B10 -> 5.361627e-07 | C10: =每日權重!C10-標準化後權重!C10 -> 8.4330934e-07 | D10: =每日權重!D10-標準化後權重!D10 -> 9.8795324e-07 | E10: =每日權重!E10-標準化後權重!E10 -> 1.036855e-06 | F10: =每日權重!F10-標準化後權重!F10 -> 7.1929326e-07 | G10: =每日權重!G10-標準化後權重!G10 -> 0 | H10: =每日權重!H10-標準化後權重!H10 -> 8.3652559e-07 | I10: =每日權重!I10-標準化後權重!I10 -> 0 | ... BN10: =每日權重!BN10-標準化後權重!BN10 -> 0
A11: 2024-01-16 | B11: =每日權重!B11-標準化後權重!B11 -> 5.2248126e-07 | C11: =每日權重!C11-標準化後權重!C11 -> 8.2888253e-07 | D11: =每日權重!D11-標準化後權重!D11 -> 9.5991005e-07 | E11: =每日權重!E11-標準化後權重!E11 -> 1.0041825e-06 | F11: =每日權重!F11-標準化後權重!F11 -> 6.8449424e-07 | G11: =每日權重!G11-標準化後權重!G11 -> 0 | H11: =每日權重!H11-標準化後權重!H11 -> 8.1437297e-07 | I11: =每日權重!I11-標準化後權重!I11 -> 0 | ... BN11: =每日權重!BN11-標準化後權重!BN11 -> 0
A12: 2024-01-17 | B12: =每日權重!B12-標準化後權重!B12 -> 5.1403033e-07 | C12: =每日權重!C12-標準化後權重!C12 -> 8.2267136e-07 | D12: =每日權重!D12-標準化後權重!D12 -> 9.4131553e-07 | E12: =每日權重!E12-標準化後權重!E12 -> 9.8165007e-07 | F12: =每日權重!F12-標準化後權重!F12 -> 6.7357692e-07 | G12: =每日權重!G12-標準化後權重!G12 -> 0 | H12: =每日權重!H12-標準化後權重!H12 -> 8.0562428e-07 | I12: =每日權重!I12-標準化後權重!I12 -> 0 | ... BN12: =每日權重!BN12-標準化後權重!BN12 -> 0
A13: 2024-01-18 | B13: =每日權重!B13-標準化後權重!B13 -> 5.1641154e-07 | C13: =每日權重!C13-標準化後權重!C13 -> 8.3979964e-07 | D13: =每日權重!D13-標準化後權重!D13 -> 9.4083921e-07 | E13: =每日權重!E13-標準化後權重!E13 -> 9.9081308e-07 | F13: =每日權重!F13-標準化後權重!F13 -> 6.7986429e-07 | G13: =每日權重!G13-標準化後權重!G13 -> 0 | H13: =每日權重!H13-標準化後權重!H13 -> 8.1314421e-07 | I13: =每日權重!I13-標準化後權重!I13 -> 0 | ... BN13: =每日權重!BN13-標準化後權重!BN13 -> 0
A14: 2024-01-19 | B14: =每日權重!B14-標準化後權重!B14 -> 1.3922568e-06 | C14: =每日權重!C14-標準化後權重!C14 -> 2.2522601e-06 | D14: =每日權重!D14-標準化後權重!D14 -> 2.5126513e-06 | E14: =每日權重!E14-標準化後權重!E14 -> 2.6380009e-06 | F14: =每日權重!F14-標準化後權重!F14 -> 1.8163781e-06 | G14: =每日權重!G14-標準化後權重!G14 -> 0 | H14: =每日權重!H14-標準化後權重!H14 -> 2.1554564e-06 | I14: =每日權重!I14-標準化後權重!I14 -> 0 | ... BN14: =每日權重!BN14-標準化後權重!BN14 -> 0
... A479: 2025-12-22 | B479: =每日權重!B479-標準化後權重!B479 -> -0.0037074935 | C479: =每日權重!C479-標準化後權重!C479 -> 0.0013369495 | D479: =每日權重!D479-標準化後權重!D479 -> 0.00079519261 | E479: =每日權重!E479-標準化後權重!E479 -> 0.0014085951 | F479: =每日權重!F479-標準化後權重!F479 -> -0.0030053518 | G479: =每日權重!G479-標準化後權重!G479 -> 0 | H479: =每日權重!H479-標準化後權重!H479 -> 0.00084651661 | I479: =每日權重!I479-標準化後權重!I479 -> 0.0083589568 | ... BN479: =每日權重!BN479-標準化後權重!BN479 -> 0.0050088697

Sheet 每日權重
A1: date | B1: 1101 | C1: 1216 | D1: 1301 | E1: 1303 | F1: 1326 | G1: 1590 | H1: 2002 | I1: 2059 | J1: 2207 | K1: 2301 | L1: 2303 | M1: 2308 | N1: 2317 | O1: 2327 | P1: 2330 | Q1: 2345 | R1: 2357 | S1: 2360 | T1: 2379 | U1: 2382 | V1: 2383 | W1: 2395 | X1: 2408 | Y1: 2412 | Z1: 2454 | AA1: 2603 | AB1: 2609 | AC1: 2615 | AD1: 2618 | AE1: 2801 | AF1: 2880 | AG1: 2881 | AH1: 2882 | AI1: 2883 | AJ1: 2884 | AK1: 2885 | AL1: 2886 | AM1: 2887 | AN1: 2888 | AO1: 2890 | AP1: 2891 | AQ1: 2892 | AR1: 2912 | AS1: 3008 | AT1: 3017 | AU1: 3034 | AV1: 3037 | AW1: 3045 | AX1: 3231 | AY1: 3293 | AZ1: 3443 | BA1: 3529 | BB1: 3653 | BC1: 3661 | BD1: 3711 | BE1: 4904 | BF1: 4938 | BG1: 5871 | BH1: 5876 | BI1: 5880 | BJ1: 6488 | BK1: 6505 | BL1: 6669 | BM1: 6919 | BN1: 8069
A2: 2024-01-03 | B2: 0.0085195677 | C2: 0.013330686 | D2: 0.015977926 | E2: 0.016720322 | F2: 0.011509403 | H2: 0.013534765 | J2: 0.012264334 | K2: 0.0085076765 | L2: 0.020376065 | M2: 0.025419544 | N2: 0.046558253 | O2: 0.007859445 | P2: 0.3 | Q2: 0.0088252038 | R2: 0.011100602 | T2: 0.0074506446 | U2: 0.026565599 | W2: 0.0099233729 | X2: 0.0072787042 | Y2: 0.029917312 | Z2: 0.048995308 | AA2: 0.010596994 | AF2: 0.0096460185 | AG2: 0.029920205 | AH2: 0.023406395 | AI2: 0.0072803111 | AJ2: 0.012887497 | AK2: 0.010990368 | AL2: 0.017888553 | AM2: 0.0077887405 | AO2: 0.0076765775 | AP2: 0.018237576 | AQ2: 0.011818574 | AR2: 0.0089206549 | AS2: 0.011520008 | AU2: 0.0097684658 | AV2: 0.0083325222 | AW2: 0.011834001 | AX2: 0.0087136836 | AZ2: 0.0070627342 | BC2: 0.0082261441 | BD2: 0.017807886 | BE2: 0.0092009017 | BF2: 0.0073548722 | BG2: 0.010888489 | BH2: 0.0071871097 | BI2: 0.012456521 | BJ2: 0.0080310641 | BK2: 0.024400114 | BL2: 0.0095222857
A3: 2024-01-04 | B3: 0.0085330496 | C3: 0.013260331 | D3: 0.016044191 | E3: 0.016746782 | F3: 0.011527616 | H3: 0.013556183 | J3: 0.012158214 | K3: 0.008596883 | L3: 0.020488975 | M3: 0.025417963 | N3: 0.046408811 | O3: 0.0078582631 | P3: 0.30151444 | Q3: 0.0088572085 | R3: 0.010855158 | T3: 0.0075284742 | U3: 0.027229312 | W3: 0.0099390762 | X3: 0.0074198707 | Y3: 0.02971495 | Z3: 0.046518788 | AA3: 0.011024618 | AF3: 0.009661283 | AG3: 0.029873463 | AH3: 0.023313048 | AI3: 0.0072918319 | AJ3: 0.012958313 | AK3: 0.011109872 | AL3: 0.017963218 | AM3: 0.0078010659 | AO3: 0.0077285634 | AP3: 0.018234049 | AQ3: 0.011837277 | AR3: 0.0089515033 | AS3: 0.011387833 | AU3: 0.0096957806 | AV3: 0.0080756999 | AW3: 0.011852727 | AX3: 0.0087928121 | AZ3: 0.0070307771 | BC3: 0.0080478314 | BD3: 0.017906564 | BE3: 0.0092154618 | BF3: 0.0072550271 | BG3: 0.011104522 | BH3: 0.0072297808 | BI3: 0.012547256 | BJ3: 0.0081280009 | BK3: 0.024438726 | BL3: 0.0093685516
A4: 2024-01-05 | B4: 0.0086008869 | C4: 0.013362449 | D4: 0.016059996 | E4: 0.016754968 | F4: 0.011549587 | H4: 0.013604286 | J4: 0.012147368 | K4: 0.0087034006 | L4: 0.020561678 | M4: 0.025550111 | N4: 0.046573488 | O4: 0.00781781 | P4: 0.30049755 | Q4: 0.0088071735 | R4: 0.010893677 | T4: 0.0074640622 | U4: 0.026889217 | W4: 0.0099327845 | X4: 0.0074762245 | Y4: 0.029945687 | Z4: 0.046331715 | AA4: 0.011166817 | AF4: 0.0097176006 | AG4: 0.029837831 | AH4: 0.023474282 | AI4: 0.0073474532 | AJ4: 0.012978994 | AK4: 0.01104682 | AL4: 0.018120001 | AM4: 0.0078287474 | AO4: 0.0077959669 | AP4: 0.018266249 | AQ4: 0.01187928 | AR4: 0.0089832669 | AS4: 0.011191052 | AU4: 0.0096319006 | AV4: 0.0078826562 | AW4: 0.011846678 | AX4: 0.0087678087 | AZ4: 0.0071639418 | BC4: 0.0081363913 | BD4: 0.017899356 | BE4: 0.0092132194 | BF4: 0.0072205282 | BG4: 0.010830413 | BH4: 0.0072789917 | BI4: 0.012591778 | BJ4: 0.0082272815 | BK4: 0.024494673 | BL4: 0.0096558977
A5: 2024-01-08 | B5: 0.0085393253 | C5: 0.013342095 | D5: 0.0159916 | E5: 0.016785653 | F5: 0.0115004 | H5: 0.013444878 | J5: 0.012256911 | K5: 0.0086663348 | L5: 0.020353201 | M5: 0.025566626 | N5: 0.045260356 | O5: 0.0077845158 | P5: 0.30285413 | Q5: 0.0089499261 | R5: 0.010835337 | T5: 0.0074322745 | U5: 0.026588335 | W5: 0.0099594543 | X5: 0.0072849337 | Y5: 0.030067679 | Z5: 0.046084307 | AA5: 0.010982407 | AF5: 0.0097420402 | AG5: 0.030133855 | AH5: 0.023504602 | AI5: 0.0073754022 | AJ5: 0.012999297 | AK5: 0.010979366 | AL5: 0.018274448 | AM5: 0.0078390783 | AO5: 0.0077229566 | AP5: 0.01838264 | AQ5: 0.011938214 | AR5: 0.0089617289 | AS5: 0.011078979 | AU5: 0.0097866128 | AV5: 0.0078981425 | AW5: 0.011856105 | AX5: 0.008805088 | AZ5: 0.0071765346 | BC5: 0.0082570834 | BD5: 0.01775268 | BE5: 0.0092435702 | BF5: 0.0071897776 | BG5: 0.010557251 | BH5: 0.0072401734 | BI5: 0.012538153 | BJ5: 0.008220299 | BK5: 0.02451292 | BL5: 0.009502322
A6: 2024-01-09 | B6: 0.0084977034 | C6: 0.013263576 | D6: 0.015904649 | E6: 0.016623207 | F6: 0.011473823 | H6: 0.013204008 | J6: 0.012250875 | K6: 0.0086747493 | L6: 0.020211592 | M6: 0.024713311 | N6: 0.045081127 | O6: 0.0076967165 | P6: 0.30470812 | Q6: 0.0093104649 | R6: 0.010881731 | T6: 0.0074560046 | U6: 0.026862881 | W6: 0.0099415091 | X6: 0.00724213 | Y6: 0.02997199 | Z6: 0.046530174 | AA6: 0.010376637 | AF6: 0.009641685 | AG6: 0.030116057 | AH6: 0.023344838 | AI6: 0.0072936168 | AJ6: 0.012860617 | AK6: 0.010949171 | AL6: 0.018292191 | AM6: 0.0078029754 | AO6: 0.0077304551 | AP6: 0.018206117 | AQ6: 0.0118621 | AR6: 0.009003902 | AS6: 0.011068244 | AU6: 0.009796115 | AV6: 0.0079794678 | AW6: 0.011879604 | AX6: 0.0087762913 | AZ6: 0.007291363 | BC6: 0.0085880495 | BD6: 0.017840432 | BE6: 0.0092873728 | BF6: 0.0071881807 | BG6: 0.010368651 | BH6: 0.0072315505 | BI6: 0.012479287 | BJ6: 0.0082704048 | BK6: 0.024322024 | BL6: 0.0096522515
A7: 2024-01-10 | B7: 0.008440596 | C7: 0.013311267 | D7: 0.01583842 | E7: 0.016529217 | F7: 0.011420383 | H7: 0.013175034 | J7: 0.012168915 | K7: 0.0081356824 | L7: 0.020284266 | M7: 0.024424473 | N7: 0.044795269 | O7: 0.0075876762 | P7: 0.30476004 | Q7: 0.0091990746 | R7: 0.011064869 | T7: 0.0075573932 | U7: 0.027209095 | W7: 0.009977255 | X7: 0.0071580462 | Y7: 0.030079758 | Z7: 0.046496197 | AA7: 0.010173361 | AF7: 0.0096763529 | AG7: 0.030224343 | AH7: 0.0234026 | AI7: 0.0072900864 | AJ7: 0.012856244 | AK7: 0.010865534 | AL7: 0.018311428 | AM7: 0.0078090964 | AO7: 0.00771826 | AP7: 0.018239068 | AQ7: 0.011838737 | AR7: 0.0090026846 | AS7: 0.010892352 | AU7: 0.0098706635 | AV7: 0.008008159 | AW7: 0.011886227 | AX7: 0.0088546979 | AZ7: 0.0077505729 | BC7: 0.0087629779 | BD7: 0.01790458 | BE7: 0.0093324177 | BF7: 0.0071365491 | BG7: 0.010434442 | BH7: 0.0070611901 | BI7: 0.012452863 | BJ7: 0.0082860501 | BK7: 0.024347915 | BL7: 0.0099976179
A8: 2024-01-11 | B8: 0.0084054378 | C8: 0.013219253 | D8: 0.015547126 | E8: 0.016205167 | F8: 0.011372812 | H8: 0.013094778 | J8: 0.012136153 | K8: 0.0082153708 | L8: 0.020199774 | M8: 0.024489903 | N8: 0.044831724 | O8: 0.0075424561 | P8: 0.30452996 | Q8: 0.0093771529 | R8: 0.01101878 | T8: 0.0074351408 | U8: 0.027841514 | W8: 0.0099080969 | X8: 0.0069188697 | Y8: 0.030079275 | Z8: 0.046102079 | AA8: 0.010199438 | AF8: 0.0097018972 | AG8: 0.030051418 | AH8: 0.023252983 | AI8: 0.0072597205 | AJ8: 0.012802693 | AK8: 0.010942769 | AL8: 0.018165643 | AM8: 0.0077765686 | AO8: 0.0077060228 | AP8: 0.018357353 | AQ8: 0.011855164 | AR8: 0.0090320894 | AS8: 0.010954377 | AU8: 0.0098295485 | AV8: 0.0078766506 | AW8: 0.01194454 | AX8: 0.0091070764 | AZ8: 0.0080201214 | BC8: 0.0091568236 | BD8: 0.017689052 | BE8: 0.0094327738 | BF8: 0.0070725317 | BG8: 0.010561323 | BH8: 0.0071256389 | BI8: 0.01235366 | BJ8: 0.0084339676 | BK8: 0.024123885 | BL8: 0.010743452
A9: 2024-01-12 | B9: 0.0084235962 | C9: 0.013283073 | D9: 0.015578128 | E9: 0.016343802 | F9: 0.01134275 | H9: 0.013103625 | J9: 0.012108476 | K9: 0.008107268 | L9: 0.020213422 | M9: 0.024548269 | N9: 0.044862013 | O9: 0.0076292945 | P9: 0.30369565 | Q9: 0.0092030366 | R9: 0.010727249 | T9: 0.0073823604 | U9: 0.028730959 | W9: 0.009790511 | X9: 0.0068636865 | Y9: 0.029974703 | Z9: 0.046434096 | AA9: 0.01072007 | AF9: 0.0096645225 | AG9: 0.030165843 | AH9: 0.023216521 | AI9: 0.0072646254 | AJ9: 0.012786123 | AK9: 0.010888874 | AL9: 0.018108358 | AM9: 0.0077162455 | AO9: 0.0076315266 | AP9: 0.018175367 | AQ9: 0.011797389 | AR9: 0.0089712422 | AS9: 0.011176715 | AU9: 0.0099929417 | AV9: 0.007808309 | AW9: 0.011964599 | AX9: 0.0092906386 | AZ9: 0.0078097997 | BC9: 0.0089357293 | BD9: 0.017771525 | BE9: 0.0094275366 | BF9: 0.0071202029 | BG9: 0.010483229 | BH9: 0.007099145 | BI9: 0.012314643 | BJ9: 0.0083975377 | BK9: 0.024232205 | BL9: 0.010722568
A10: 2024-01-15 | B10: 0.0083965401 | C10: 0.013206589 | D10: 0.015471775 | E10: 0.016237597 | F10: 0.011264444 | H10: 0.013100353 | J10: 0.01205165 | K10: 0.0081052435 | L10: 0.020490727 | M10: 0.024709376 | N10: 0.044627672 | O10: 0.0078453147 | P10: 0.30465961 | Q10: 0.0093089824 | R10: 0.010688702 | T10: 0.0075126067 | U10: 0.028164231 | W10: 0.0097742606 | X10: 0.007131265 | Y10: 0.030092081 | Z10: 0.046221971 | AA10: 0.010854357 | AF10: 0.009596231 | AG10: 0.03015831 | AH10: 0.023184644 | AI10: 0.007203523 | AJ10: 0.012808143 | AK10: 0.010906579 | AL10: 0.018034295 | AM10: 0.007692465 | AO10: 0.0076097001 | AP10: 0.018235608 | AQ10: 0.011750598 | AR10: 0.0089690019 | AS10: 0.011152435 | AU10: 0.010460585 | AV10: 0.0078309074 | AW10: 0.011877712 | AX10: 0.0092043036 | AZ10: 0.007592163 | BC10: 0.0088497837 | BD10: 0.017696583 | BE10: 0.0094251824 | BF10: 0.0070669663 | BG10: 0.010452208 | BH10: 0.0070738969 | BI10: 0.012311567 | BJ10: 0.0084656366 | BK10: 0.023980825 | BL10: 0.0104948
A11: 2024-01-16 | B11: 0.0083185293 | C11: 0.013196806 | D11: 0.015282921 | E11: 0.015987792 | F11: 0.010897971 | H11: 0.012965796 | J11: 0.011684861 | K11: 0.008174614 | L11: 0.020763125 | M11: 0.024529473 | N11: 0.04522094 | O11: 0.0077839914 | P11: 0.30554882 | Q11: 0.0093778921 | R11: 0.0106733 | T11: 0.0075790159 | U11: 0.028727636 | W11: 0.0095264946 | X11: 0.0070138321 | Y11: 0.030112547 | Z11: 0.045464868 | AA11: 0.010651691 | AF11: 0.0095457907 | AG11: 0.030130158 | AH11: 0.023255019 | AI11: 0.0071490937 | AJ11: 0.012774027 | AK11: 0.010865306 | AL11: 0.018133107 | AM11: 0.0076618619 | AO11: 0.0075897485 | AP11: 0.018346745 | AQ11: 0.011773522 | AR11: 0.0089864995 | AS11: 0.011235371 | AU11: 0.010579796 | AV11: 0.0080593826 | AW11: 0.011902017 | AX11: 0.0093266632 | AZ11: 0.0075838143 | BC11: 0.0088947215 | BD11: 0.017931836 | BE11: 0.0093740532 | BF11: 0.0071087701 | BG11: 0.010476036 | BH11: 0.0070569275 | BI11: 0.012235326 | BJ11: 0.0084074666 | BK11: 0.023243115 | BL11: 0.010890908
A12: 2024-01-17 | B12: 0.0082366867 | C12: 0.013182269 | D12: 0.015083392 | E12: 0.015729702 | F12: 0.010793219 | H12: 0.012909111 | J12: 0.011472107 | K12: 0.0083478019 | L12: 0.020096077 | M12: 0.023958934 | N12: 0.04510893 | O12: 0.0078051467 | P12: 0.30965263 | Q12: 0.0094135118 | R12: 0.010761265 | T12: 0.0074221587 | U12: 0.029127101 | W12: 0.0093830832 | X12: 0.0069322084 | Y12: 0.03033646 | Z12: 0.045173922 | AA12: 0.010705971 | AF12: 0.0094772587 | AG12: 0.030048196 | AH12: 0.023152503 | AI12: 0.0071414749 | AJ12: 0.01271654 | AK12: 0.010803846 | AL12: 0.017727185 | AM12: 0.0076169861 | AO12: 0.0075967616 | AP12: 0.018295523 | AQ12: 0.011731325 | AR12: 0.0090229063 | AS12: 0.010970163 | AU12: 0.010261645 | AV12: 0.0079774125 | AW12: 0.011942817 | AX12: 0.0093686732 | AZ12: 0.0074292251 | BC12: 0.0087412159 | BD12: 0.018069123 | BE12: 0.0094003106 | BF12: 0.007103928 | BG12: 0.010394649 | BH12: 0.0070431379 | BI12: 0.012208417 | BJ12: 0.0083042326 | BK12: 0.022948886 | BL12: 0.010873969
A13: 2024-01-18 | B13: 0.0081534355 | C13: 0.013259294 | D13: 0.014854571 | E13: 0.01564359 | F13: 0.010734132 | H13: 0.012838441 | J13: 0.011336167 | K13: 0.0082248731 | L13: 0.019780444 | M13: 0.023614643 | N13: 0.045453469 | O13: 0.0077346451 | P13: 0.31166777 | Q13: 0.0092700133 | R13: 0.010848627 | T13: 0.0074067766 | U13: 0.028080234 | W13: 0.0093317157 | X13: 0.0069349323 | Y13: 0.030170384 | Z13: 0.045846617 | AA13: 0.011031364 | AF13: 0.0094477637 | AG13: 0.029883698 | AH13: 0.023025755 | AI13: 0.007132602 | AJ13: 0.012621218 | AK13: 0.0107447 | AL13: 0.017866467 | AM13: 0.007575287 | AO13: 0.0076567213 | AP13: 0.0183935 | AQ13: 0.011711803 | AR13: 0.0090246903 | AS13: 0.010932015 | AU13: 0.010245411 | AV13: 0.0078586576 | AW13: 0.011889656 | AX13: 0.0092983501 | AZ13: 0.0075864616 | BC13: 0.0089981786 | BD13: 0.018257727 | BE13: 0.0094080187 | BF13: 0.0070562938 | BG13: 0.010250872 | BH13: 0.0070604255 | BI13: 0.012165721 | BJ13: 0.0083017111 | BK13: 0.0226044 | BL13: 0.010785754
... A60: 2024-04-08 | B60: 0.0068863562 | C60: 0.011784102 | D60: 0.012326436 | E60: 0.012586707 | F60: 0.00888298 | H60: 0.010846134 | J60: 0.0097915118 | K60: 0.0066444575 | L60: 0.017955729 | M60: 0.023862856 | N60: 0.060246661 | O60: 0.0071803351 | P60: 0.3462236 | Q60: 0.0071830698 | R60: 0.0087035955 | T60: 0.0079989683 | U60: 0.030969907 | W60: 0.009177025 | X60: 0.0058033573 | Y60: 0.026991521 | Z60: 0.049259165 | AA60: 0.0098300509 | AF60: 0.0086682793 | AG60: 0.027617056 | AH60: 0.021547496 | AI60: 0.0070919941 | AJ60: 0.011697524 | AK60: 0.010575273 | AL60: 0.015844598 | AM60: 0.0067406492 | AO60: 0.0072678125 | AP60: 0.017739507 | AQ60: 0.010283458 | AR60: 0.0077776767 | AS60: 0.0085951959 | AU60: 0.0098917665 | AV60: 0.0083478789 | AW60: 0.010650356 | AX60: 0.010528333 | AZ60: 0.00479146 | BC60: 0.0064374393 | BD60: 0.018433541 | BE60: 0.0080828218 | BF60: 0.0074011438 | BG60: 0.0085422949 | BH60: 0.0062446605 | BI60: 0.010600173 | BJ60: 0.0065186022 | BK60: 0.019048617 | BL60: 0.01189987
A61: 2024-04-09 | B61: 0.0072467011 | C61: 0.012526012 | D61: 0.013081707 | E61: 0.013417859 | F61: 0.0093926758 | G61: 0.0066499733 | H61: 0.011721574 | J61: 0.010207682 | K61: 0.0066083935 | L61: 0.018721869 | M61: 0.024537704 | N61: 0.060022219 | O61: 0.0073615461 | P61: 0.31038466 | Q61: 0.0074754551 | R61: 0.0090950253 | T61: 0.0083204093 | U61: 0.033010142 | W61: 0.0095489591 | Y61: 0.027766589 | Z61: 0.054301986 | AA61: 0.010207572 | AF61: 0.0090895577 | AG61: 0.029230429 | AH61: 0.02294932 | AI61: 0.0074554494 | AJ61: 0.012192557 | AK61: 0.011249541 | AL61: 0.016651098 | AM61: 0.0070005865 | AO61: 0.0076118572 | AP61: 0.018746236 | AQ61: 0.010698261 | AR61: 0.0080926945 | AS61: 0.0090817807 | AU61: 0.010564784 | AV61: 0.0084273264 | AW61: 0.011107988 | AX61: 0.010756844 | BC61: 0.0071433209 | BD61: 0.020182121 | BE61: 0.0083375833 | BF61: 0.0077811782 | BG61: 0.0089739567 | BH61: 0.0064837742 | BI61: 0.011053333 | BJ61: 0.0071336697 | BK61: 0.020096206 | BL61: 0.012739126 | BN61: 0.007562708
A62: 2024-04-10 | B62: 0.0073190395 | C62: 0.012537918 | D62: 0.013202968 | E62: 0.013379345 | F62: 0.0094475909 | G62: 0.0067511921 | H62: 0.011545131 | J62: 0.010214994 | K62: 0.00659149 | L62: 0.019050669 | M62: 0.024151382 | N62: 0.058825298 | O62: 0.0074501706 | P62: 0.30956699 | Q62: 0.0076695932 | R62: 0.0093300706 | T62: 0.0083832642 | U62: 0.032508377 | W62: 0.0093158169 | Y62: 0.027940234 | Z62: 0.056066872 | AA62: 0.010110991 | AF62: 0.0090904725 | AG62: 0.028961693 | AH62: 0.022675603 | AI62: 0.0073930921 | AJ62: 0.012152977 | AK62: 0.011129018 | AL62: 0.01673005 | AM62: 0.0070164125 | AO62: 0.0077000332 | AP62: 0.018613294 | AQ62: 0.010702986 | AR62: 0.0082001212 | AS62: 0.0091023117 | AU62: 0.01076633 | AV62: 0.0083590768 | AW62: 0.0111331 | AX62: 0.010738379 | BC62: 0.0071594697 | BD62: 0.020551909 | BE62: 0.008459853 | BF62: 0.0078375688 | BG62: 0.008994244 | BH62: 0.0065816562 | BI62: 0.01105722 | BJ62: 0.0071757488 | BK62: 0.020333986 | BL62: 0.012148874 | BN62: 0.0078751219
A63: 2024-04-11 | B63: 0.0072592796 | C63: 0.01255069 | D63: 0.0130145 | E63: 0.013140276 | F63: 0.0093560681 | G63: 0.0066430383 | H63: 0.01142146 | J63: 0.01013072 | K63: 0.0066300799 | L63: 0.018819153 | M63: 0.023549472 | N63: 0.057170117 | O63: 0.0073136485 | P63: 0.31178345 | Q63: 0.0076290188 | R63: 0.009736775 | T63: 0.0083330172 | U63: 0.032829981 | W63: 0.0093738758 | Y63: 0.028079683 | Z63: 0.056358813 | AA63: 0.010480627 | AF63: 0.0091193864 | AG63: 0.028656036 | AH63: 0.023141035 | AI63: 0.0074006232 | AJ63: 0.012210165 | AK63: 0.011140355 | AL63: 0.016602364 | AM63: 0.0069847557 | AO63: 0.0077966773 | AP63: 0.018690754 | AQ63: 0.010694409 | AR63: 0.0082530856 | AS63: 0.008862738 | AU63: 0.010937356 | AV63: 0.0084112868 | AW63: 0.011144441 | AX63: 0.010535188 | BC63: 0.0071548972 | BD63: 0.020637743 | BE63: 0.0084684707 | BF63: 0.007884392 | BG63: 0.0088520883 | BH63: 0.0065953031 | BI63: 0.011026237 | BJ63: 0.0070791444 | BK63: 0.020162155 | BL63: 0.012006329 | BN63: 0.0079488369
A64: 2024-04-12 | B64: 0.0072605455 | C64: 0.012696977 | D64: 0.012875939 | E64: 0.013270437 | F64: 0.0093818912 | G64: 0.0066565237 | H64: 0.011289959 | J64: 0.010131899 | K64: 0.006608266 | L64: 0.019011495 | M64: 0.02351443 | N64: 0.057727027 | O64: 0.007469132 | P64: 0.3130094 | Q64: 0.0074017985 | R64: 0.0095828864 | T64: 0.0084158184 | U64: 0.030426677 | W64: 0.0092504454 | Y64: 0.028035627 | Z64: 0.055773445 | AA64: 0.010637971 | AF64: 0.0090985113 | AG64: 0.028586078 | AH64: 0.022984247 | AI64: 0.00734149 | AJ64: 0.012220506 | AK64: 0.011137986 | AL64: 0.016625168 | AM64: 0.0069903129 | AO64: 0.007810725 | AP64: 0.018692378 | AQ64: 0.010723502 | AR64: 0.0082309683 | AS64: 0.0090541909 | AU64: 0.011275678 | AV64: 0.0085309679 | AW64: 0.011269537 | AX64: 0.010559373 | BC64: 0.0069259436 | BD64: 0.020965488 | BE64: 0.0085017184 | BF64: 0.0076845874 | BG64: 0.0088578621 | BH64: 0.006637425 | BI64: 0.0110754 | BJ64: 0.0071243564 | BK64: 0.020069467 | BL64: 0.012498769 | BN64: 0.008098772
A65: 2024-04-15 | B65: 0.0074026341 | C65: 0.012868653 | D65: 0.013048301 | E65: 0.013420478 | F65: 0.0094694895 | G65: 0.0066084679 | H65: 0.011319209 | J65: 0.010233931 | K65: 0.0066412386 | L65: 0.018890957 | M65: 0.02318593 | N65: 0.05683216 | O65: 0.0073837463 | P65: 0.31299524 | Q65: 0.0070998358 | R65: 0.0096593353 | T65: 0.008420649 | U65: 0.029738862 | W65: 0.0092885345 | Y65: 0.028565097 | Z65: 0.053243556 | AA65: 0.010887613 | AF65: 0.0092134824 | AG65: 0.028839213 | AH65: 0.023277835 | AI65: 0.0073694723 | AJ65: 0.012379006 | AK65: 0.011396562 | AL65: 0.016808577 | AM65: 0.0070742503 | AO65: 0.0079085163 | AP65: 0.019089313 | AQ65: 0.010822979 | AR65: 0.0083683233 | AS65: 0.0089735253 | AU65: 0.011225074 | AV65: 0.0081443807 | AW65: 0.011382083 | AX65: 0.010453665 | BC65: 0.0066773043 | BD65: 0.021210384 | BE65: 0.0087019184 | BF65: 0.0078303794 | BG65: 0.0089120621 | BH65: 0.0067217596 | BI65: 0.011261359 | BJ65: 0.0072300992 | BK65: 0.020676369 | BL65: 0.012763393 | BN65: 0.0080847901
A66: 2024-04-16 | B66: 0.0076358426 | C66: 0.012853585 | D66: 0.013109433 | E66: 0.013390451 | F66: 0.0095429558 | G66: 0.0065238248 | H66: 0.011497584 | J66: 0.0101592 | K66: 0.0063807552 | L66: 0.018861328 | M66: 0.022681496 | N66: 0.056440479 | O66: 0.0073784716 | P66: 0.31467279 | Q66: 0.0070553134 | R66: 0.0095946948 | T66: 0.0085048092 | U66: 0.029233759 | W66: 0.0093093319 | Y66: 0.029024502 | Z66: 0.052038744 | AA66: 0.01072426 | AF66: 0.009247395 | AG66: 0.028908073 | AH66: 0.023399259 | AI66: 0.0073561384 | AJ66: 0.01237669 | AK66: 0.011489199 | AL66: 0.016980673 | AM66: 0.0070912324 | AO66: 0.0079273444 | AP66: 0.019015615 | AQ66: 0.010945409 | AR66: 0.008433559 | AS66: 0.008946243 | AU66: 0.011244172 | AV66: 0.0081226686 | AW66: 0.011479391 | AX66: 0.010255003 | BC66: 0.0070533637 | BD66: 0.020856924 | BE66: 0.0088287958 | BF66: 0.007782951 | BG66: 0.0090055718 | BH66: 0.0067225777 | BI66: 0.011402858 | BJ66: 0.0072984696 | BK66: 0.020539806 | BL66: 0.012501208 | BN66: 0.0081758012
A67: 2024-04-17 | B67: 0.0075907537 | C67: 0.012852831 | D67: 0.0129141 | E67: 0.013110654 | F67: 0.009376017 | G67: 0.0066544604 | H67: 0.011453366 | J67: 0.0099227286 | K67: 0.0063703738 | L67: 0.018709491 | M67: 0.022983068 | N67: 0.057938688 | O67: 0.0073896639 | P67: 0.31721117 | Q67: 0.0068284309 | R67: 0.0095464494 | T67: 0.0086925516 | U67: 0.029461941 | W67: 0.0093488676 | Y67: 0.028446041 | Z67: 0.051170905 | AA67: 0.01059563 | AF67: 0.0091568729 | AG67: 0.028691758 | AH67: 0.023142758 | AI67: 0.0073227587 | AJ67: 0.012321231 | AK67: 0.011370345 | AL67: 0.016734094 | AM67: 0.0070665761 | AO67: 0.0079428346 | AP67: 0.019121402 | AQ67: 0.010874766 | AR67: 0.0084095562 | AS67: 0.0087396251 | AU67: 0.011459932 | AV67: 0.0081159235 | AW67: 0.011341704 | AX67: 0.01017644 | BC67: 0.0071411357 | BD67: 0.021010814 | BE67: 0.0086369607 | BF67: 0.0077702037 | BG67: 0.0089237255 | BH67: 0.0066851682 | BI67: 0.011266088 | BJ67: 0.0073322349 | BK67: 0.020065108 | BL67: 0.012806734 | BN67: 0.0078050719
A68: 2024-04-18 | B68: 0.007576161 | C68: 0.013046331 | D68: 0.01292651 | E68: 0.013255484 | F68: 0.0093436833 | G68: 0.0066017745 | H68: 0.011577258 | J68: 0.0098885096 | K68: 0.0065263979 | L68: 0.018607903 | M68: 0.023551671 | N68: 0.058330067 | O68: 0.0073641803 | P68: 0.31611725 | Q68: 0.0068215613 | R68: 0.0094802252 | T68: 0.008723365 | U68: 0.028898881 | W68: 0.0093417397 | Y68: 0.028462713 | Z68: 0.05099444 | AA68: 0.010404265 | AF68: 0.0092065893 | AG68: 0.02872278 | AH68: 0.023327764 | AI68: 0.0073795003 | AJ68: 0.012510415 | AK68: 0.011557756 | AL68: 0.016761905 | AM68: 0.0070622699 | AO68: 0.0079521739 | AP68: 0.019176448 | AQ68: 0.010837264 | AR68: 0.0083498011 | AS68: 0.0087094861 | AU68: 0.01131007 | AV68: 0.0080653434 | AW68: 0.011468806 | AX68: 0.010451344 | BC68: 0.0074477949 | BD68: 0.020267256 | BE68: 0.0086071757 | BF68: 0.007759473 | BG68: 0.0089711888 | BH68: 0.006611861 | BI68: 0.011292765 | BJ68: 0.0073472451 | BK68: 0.019995912 | BL68: 0.013349968 | BN68: 0.0076592756
A69: 2024-04-19 | B69: 0.0077156128 | C69: 0.013435684 | D69: 0.013254877 | E69: 0.013597 | F69: 0.009506127 | G69: 0.0065299397 | H69: 0.011878234 | J69: 0.010205909 | K69: 0.0065929646 | L69: 0.018940621 | M69: 0.023676995 | N69: 0.058652401 | O69: 0.007599168 | P69: 0.3068827 | Q69: 0.0069602342 | R69: 0.0095540012 | T69: 0.0087303213 | U69: 0.028994086 | W69: 0.0095388647 | Y69: 0.029381822 | Z69: 0.050188218 | AA69: 0.011117579 | AF69: 0.0093907989 | AG69: 0.029305242 | AH69: 0.023775768 | AI69: 0.0075090694 | AJ69: 0.012802402 | AK69: 0.011752826 | AL69: 0.017221354 | AM69: 0.0072451958 | AO69: 0.0081036902 | AP69: 0.019515945 | AQ69: 0.011173355 | AR69: 0.0086414986 | AS69: 0.0087342318 | AU69: 0.011253471 | AV69: 0.0079937869 | AW69: 0.01176243 | AX69: 0.010600027 | BC69: 0.0073038871 | BD69: 0.02039341 | BE69: 0.0089350706 | BF69: 0.0079246928 | BG69: 0.0091190549 | BH69: 0.0067239674 | BI69: 0.011638546 | BJ69: 0.0072687468 | BK69: 0.020513423 | BL69: 0.012865013 | BN69: 0.0075997379
A70: 2024-04-22 | B70: 0.0078707948 | C70: 0.013967019 | D70: 0.013786896 | E70: 0.01418455 | F70: 0.010009318 | G70: 0.0066936193 | H70: 0.01201574 | J70: 0.010389603 | K70: 0.0066498716 | L70: 0.018888702 | M70: 0.023827806 | N70: 0.058730857 | O70: 0.0077516845 | P70: 0.30401541 | Q70: 0.0066827678 | R70: 0.0095667811 | T70: 0.0079818256 | U70: 0.027650352 | W70: 0.0096432153 | Y70: 0.030019115 | Z70: 0.048888892 | AA70: 0.011229255 | AF70: 0.0096363266 | AG70: 0.029886185 | AH70: 0.024284224 | AI70: 0.0076900028 | AJ70: 0.01306095 | AK70: 0.011768547 | AL70: 0.017600863 | AM70: 0.007380332 | AO70: 0.0083059105 | AP70: 0.019762687 | AQ70: 0.011377221 | AR70: 0.0088934205 | AS70: 0.0087046608 | AU70: 0.011000226 | AV70: 0.0078867668 | AW70: 0.012066844 | AX70: 0.010014273 | BC70: 0.0070707209 | BD70: 0.020210888 | BE70: 0.0090362697 | BF70: 0.0079101816 | BG70: 0.0093758401 | BH70: 0.0068152534 | BI70: 0.011881734 | BJ70: 0.0070405199 | BK70: 0.02154864 | BL70: 0.012019697 | BN70: 0.0073267444
A71: 2024-04-23 | B71: 0.0077531077 | C71: 0.01377664 | D71: 0.01356789 | E71: 0.013932997 | F71: 0.0098997849 | G71: 0.0066444885 | H71: 0.01199998 | J71: 0.010296465 | K71: 0.0064510378 | L71: 0.018673373 | M71: 0.023455803 | N71: 0.058707467 | O71: 0.007797556 | P71: 0.30666455 | Q71: 0.0069873998 | R71: 0.0094046963 | T71: 0.0080175637 | U71: 0.028282756 | W71: 0.0095204811 | Y71: 0.029680056 | Z71: 0.048831479 | AA71: 0.011114801 | AF71: 0.0096496897 | AG71: 0.029711636 | AH71: 0.0242803 | AI71: 0.0076618311 | AJ71: 0.013036978 | AK71: 0.011643096 | AL71: 0.017692834 | AM71: 0.0073469148 | AO71: 0.0082829407 | AP71: 0.019742782 | AQ71: 0.01131455 | AR71: 0.0087804236 | AS71: 0.0087431478 | AU71: 0.011090696 | AV71: 0.0079457273 | AW71: 0.011806337 | AX71: 0.010169818 | BC71: 0.0072599752 | BD71: 0.020131962 | BE71: 0.0088924259 | BF71: 0.0078687395 | BG71: 0.0093339988 | BH71: 0.0068097868 | BI71: 0.011817117 | BJ71: 0.0070027372 | BK71: 0.02144932 | BL71: 0.011765758 | BN71: 0.0073081016
A72: 2024-04-24 | B72: 0.0074946408 | C72: 0.013160921 | D72: 0.013139869 | E72: 0.01348059 | F72: 0.0096117459 | G72: 0.0067920671 | H72: 0.011625125 | J72: 0.010047963 | K72: 0.0065268233 | L72: 0.018722586 | M72: 0.02331338 | N72: 0.061861971 | O72: 0.0077969134 | P72: 0.30975784 | Q72: 0.0069139478 | R72: 0.0093934511 | T72: 0.0082266463 | U72: 0.030237746 | W72: 0.0094372146 | Y72: 0.028753609 | Z72: 0.049354107 | AA72: 0.01121613 | AF72: 0.0093451262 | AG72: 0.02911775 | AH72: 0.023859095 | AI72: 0.0075349809 | AJ72: 0.012610828 | AK72: 0.01153398 | AL72: 0.016929747 | AM72: 0.0071259826 | AO72: 0.0079272703 | AP72: 0.019142469 | AQ72: 0.011025662 | AR72: 0.0085405095 | AS72: 0.0087432475 | AU72: 0.011120723 | AV72: 0.0085014822 | AW72: 0.011372251 | AX72: 0.010292965 | BC72: 0.0073455511 | BD72: 0.019987023 | BE72: 0.0086709943 | BF72: 0.0078153777 | BG72: 0.0091051987 | BH72: 0.0066092713 | BI72: 0.011472252 | BJ72: 0.0070952042 | BK72: 0.020863244 | BL72: 0.012303937 | BN72: 0.0071425919
... A121: 2024-07-04 | B121: 0.0066177782 | C121: 0.012331072 | D121: 0.0094258007 | E121: 0.010127198 | F121: 0.0074240666 | G121: 0.0052043361 | H121: 0.0094576551 | J121: 0.0084220923 | K121: 0.0063368702 | L121: 0.016273981 | M121: 0.024637049 | N121: 0.070957383 | O121: 0.0078446973 | P121: 0.33936162 | Q121: 0.0082102839 | R121: 0.0088986173 | T121: 0.007206036 | U121: 0.030732179 | W121: 0.0080319375 | Y121: 0.022508008 | Z121: 0.056297162 | AA121: 0.009548477 | AF121: 0.0094964535 | AG121: 0.031260793 | AH121: 0.024328556 | AI121: 0.00728672 | AJ121: 0.011684104 | AK121: 0.010404673 | AL121: 0.015464322 | AM121: 0.006676526 | AO121: 0.0084230852 | AP121: 0.020730397 | AQ121: 0.0099333329 | AR121: 0.0073442534 | AS121: 0.0096928117 | AU121: 0.009829772 | AV121: 0.0070700561 | AW121: 0.010603822 | AX121: 0.0081226729 | BC121: 0.0055322563 | BD121: 0.018600787 | BE121: 0.0084078428 | BF121: 0.0070872228 | BG121: 0.0071046097 | BH121: 0.0057310825 | BI121: 0.0099992142 | BJ121: 0.0067278286 | BK121: 0.016184207 | BL121: 0.012365707 | BN121: 0.0080525871
A122: 2024-07-05 | B122: 0.0068137234 | C122: 0.012509133 | D122: 0.0096917117 | E122: 0.010256364 | F122: 0.0077101065 | H122: 0.0098051607 | J122: 0.0092313148 | K122: 0.0064925371 | L122: 0.016442934 | M122: 0.026545581 | N122: 0.076792897 | O122: 0.0082667184 | P122: 0.3088774 | Q122: 0.0085319311 | R122: 0.0090240685 | T122: 0.0077100644 | U122: 0.032470778 | W122: 0.0084757623 | Y122: 0.023440966 | Z122: 0.055809774 | AA122: 0.010346192 | AB122: 0.0065970366 | AC122: 0.0061447003 | AF122: 0.0097571526 | AG122: 0.033057337 | AH122: 0.025217321 | AI122: 0.0075245991 | AJ122: 0.012046902 | AK122: 0.011133655 | AL122: 0.016028816 | AM122: 0.0069207745 | AO122: 0.0086571285 | AP122: 0.021309867 | AQ122: 0.010296585 | AR122: 0.0076118212 | AS122: 0.010311216 | AT122: 0.0080170238 | AU122: 0.0099049416 | AV122: 0.0072306615 | AW122: 0.011483244 | AX122: 0.008277595 | BD122: 0.018494342 | BE122: 0.0086630328 | BF122: 0.0074036001 | BG122: 0.00734505 | BI122: 0.010286284 | BJ122: 0.0073427572 | BK122: 0.016485582 | BL122: 0.012988246 | BN122: 0.0082176151
A123: 2024-07-08 | B123: 0.0067193874 | C123: 0.012209528 | D123: 0.009632348 | E123: 0.01016338 | F123: 0.007562704 | H123: 0.0096070482 | J123: 0.0090201828 | K123: 0.0064046799 | L123: 0.01668818 | M123: 0.027074823 | N123: 0.079619651 | O123: 0.0081276886 | P123: 0.31233361 | Q123: 0.008467571 | R123: 0.0089155846 | T123: 0.0075566912 | U123: 0.032648803 | W123: 0.0083444313 | Y123: 0.022824408 | Z123: 0.057639891 | AA123: 0.0096894276 | AB123: 0.0060474554 | AC123: 0.005622483 | AF123: 0.0097397279 | AG123: 0.032878873 | AH123: 0.025164298 | AI123: 0.007434428 | AJ123: 0.011828609 | AK123: 0.010998164 | AL123: 0.015738369 | AM123: 0.0068836199 | AO123: 0.008596853 | AP123: 0.020949849 | AQ123: 0.010127683 | AR123: 0.0075006813 | AS123: 0.010596496 | AT123: 0.0076759898 | AU123: 0.0096310396 | AV123: 0.0071990748 | AW123: 0.0095450102 | AX123: 0.0082767333 | BD123: 0.0185903 | BE123: 0.0084593199 | BF123: 0.0074450355 | BG123: 0.0072808599 | BI123: 0.010137935 | BJ123: 0.0073459705 | BK123: 0.016261111 | BL123: 0.012963494 | BN123: 0.0078305192
A124: 2024-07-09 | B124: 0.0065874758 | C124: 0.012326602 | D124: 0.0094442084 | E124: 0.0099852786 | F124: 0.0074452941 | H124: 0.0094622981 | J124: 0.0090574993 | K124: 0.0063600316 | L124: 0.016649282 | M124: 0.027549261 | N124: 0.079083365 | O124: 0.0080013435 | P124: 0.31311094 | Q124: 0.0085078543 | R124: 0.0089039546 | T124: 0.0078117386 | U124: 0.034254861 | W124: 0.0082916816 | Y124: 0.022771208 | Z124: 0.059125414 | AA124: 0.0098045471 | AB124: 0.0056490122 | AC124: 0.0055518457 | AF124: 0.009611022 | AG124: 0.032802237 | AH124: 0.025025047 | AI124: 0.0074631683 | AJ124: 0.011801038 | AK124: 0.010906429 | AL124: 0.015533853 | AM124: 0.0069027934 | AO124: 0.008544692 | AP124: 0.020822834 | AQ124: 0.010104077 | AR124: 0.0075500124 | AS124: 0.010868365 | AT124: 0.0074730702 | AU124: 0.0094829885 | AV124: 0.00702357 | AW124: 0.0093834045 | AX124: 0.0080714629 | BD124: 0.019353358 | BE124: 0.0080665813 | BF124: 0.0073225734 | BG124: 0.0072180602 | BI124: 0.010019424 | BJ124: 0.0071681819 | BK124: 0.015260187 | BL124: 0.012466372 | BN124: 0.0080201984
A125: 2024-07-10 | B125: 0.0065514114 | C125: 0.012313441 | D125: 0.0093513699 | E125: 0.0098717869 | F125: 0.0070233074 | H125: 0.0093910825 | J125: 0.0090186897 | K125: 0.0064719936 | L125: 0.016451056 | M125: 0.028224626 | N125: 0.078298277 | O125: 0.0081966442 | P125: 0.31428039 | Q125: 0.0086186832 | R125: 0.0092875227 | T125: 0.007762543 | U125: 0.03472749 | W125: 0.0082606528 | Y125: 0.022651321 | Z125: 0.058050949 | AA125: 0.0097390566 | AB125: 0.0056343263 | AC125: 0.0054668962 | AF125: 0.0095831125 | AG125: 0.03394836 | AH125: 0.025602154 | AI125: 0.0076622893 | AJ125: 0.011929497 | AK125: 0.011076365 | AL125: 0.015517268 | AM125: 0.0069481948 | AO125: 0.0084713922 | AP125: 0.021269202 | AQ125: 0.010128519 | AR125: 0.0074618603 | AS125: 0.010839335 | AT125: 0.0074548234 | AU125: 0.0084377498 | AV125: 0.0069566132 | AW125: 0.0094661923 | AX125: 0.0080256896 | BD125: 0.019278994 | BE125: 0.0071031231 | BF125: 0.0073847532 | BG125: 0.007233244 | BI125: 0.0099708153 | BJ125: 0.0072592948 | BK125: 0.015220001 | BL125: 0.012219859 | BN125: 0.0079077812
A126: 2024-07-11 | B126: 0.0064824329 | C126: 0.012226632 | D126: 0.0092799654 | E126: 0.0098520862 | F126: 0.0070039839 | H126: 0.0092376258 | J126: 0.0089573083 | K126: 0.0063954398 | L126: 0.016182235 | M126: 0.02865475 | N126: 0.077708037 | O126: 0.0084109637 | P126: 0.31949897 | Q126: 0.0085220802 | R126: 0.0092256771 | T126: 0.0077830533 | U126: 0.033308523 | W126: 0.0082565514 | Y126: 0.022281183 | Z126: 0.056505468 | AA126: 0.0095257899 | AB126: 0.0055422575 | AC126: 0.0054623607 | AF126: 0.0095480383 | AG126: 0.034630421 | AH126: 0.025936143 | AI126: 0.0076049839 | AJ126: 0.011833671 | AK126: 0.010927844 | AL126: 0.015300353 | AM126: 0.0069038683 | AO126: 0.0083803102 | AP126: 0.020614354 | AQ126: 0.0099976659 | AR126: 0.0073793198 | AS126: 0.010970766 | AT126: 0.0072117998 | AU126: 0.0084309218 | AV126: 0.0072718393 | AW126: 0.0092202189 | AX126: 0.0078945443 | BD126: 0.020443045 | BE126: 0.0070134194 | BF126: 0.0072640813 | BG126: 0.0072276277 | BI126: 0.0098638239 | BJ126: 0.0071285289 | BK126: 0.014971296 | BL126: 0.011584332 | BN126: 0.0081434108
A127: 2024-07-12 | B127: 0.0066696304 | C127: 0.012535505 | D127: 0.0096420714 | E127: 0.010367099 | F127: 0.0073068448 | H127: 0.0094693833 | J127: 0.0091621585 | K127: 0.0065118303 | L127: 0.016037893 | M127: 0.028499657 | N127: 0.07613659 | O127: 0.0083118642 | P127: 0.31470187 | Q127: 0.008611408 | R127: 0.0093630846 | T127: 0.0078240256 | U127: 0.033404241 | W127: 0.0083895937 | Y127: 0.022790745 | Z127: 0.055355569 | AA127: 0.0096052371 | AB127: 0.0055732172 | AC127: 0.0055222304 | AF127: 0.0097663983 | AG127: 0.035230726 | AH127: 0.026610299 | AI127: 0.0077326039 | AJ127: 0.012124578 | AK127: 0.011210978 | AL127: 0.015762723 | AM127: 0.0070971544 | AO127: 0.0087495384 | AP127: 0.021059603 | AQ127: 0.010244032 | AR127: 0.0075749435 | AS127: 0.010748249 | AT127: 0.0073250731 | AU127: 0.0084450036 | AV127: 0.0074577692 | AW127: 0.0094310818 | AX127: 0.0079255508 | BD127: 0.019181531 | BE127: 0.0071198752 | BF127: 0.0075358509 | BG127: 0.0075311062 | BI127: 0.010127551 | BJ127: 0.0073039774 | BK127: 0.015385805 | BL127: 0.011450376 | BN127: 0.0080758769
A128: 2024-07-15 | B128: 0.0066700202 | C128: 0.012708922 | D128: 0.009584688 | E128: 0.010319778 | F128: 0.0072866138 | H128: 0.0096351206 | J128: 0.0091293752 | K128: 0.006540857 | L128: 0.016230963 | M128: 0.028151845 | N128: 0.076652999 | O128: 0.0083706001 | P128: 0.31610466 | Q128: 0.0082104872 | R128: 0.0092108118 | T128: 0.0078176112 | U128: 0.033244371 | W128: 0.0083933723 | Y128: 0.02308552 | Z128: 0.055397898 | AA128: 0.0096480528 | AB128: 0.0055193373 | AC128: 0.0056557499 | AF128: 0.0098634411 | AG128: 0.0350027 | AH128: 0.026444132 | AI128: 0.0076042894 | AJ128: 0.012219354 | AK128: 0.010977342 | AL128: 0.015795333 | AM128: 0.0071110127 | AO128: 0.0088371848 | AP128: 0.01886441 | AQ128: 0.0103253 | AR128: 0.0076356903 | AS128: 0.010989892 | AT128: 0.0072850816 | AU128: 0.0084228051 | AV128: 0.0075304389 | AW128: 0.0094731212 | AX128: 0.0079984306 | BD128: 0.019484126 | BE128: 0.0072419104 | BF128: 0.0074986997 | BG128: 0.0076109435 | BI128: 0.010191853 | BJ128: 0.0073365352 | BK128: 0.015454387 | BL128: 0.011195026 | BN128: 0.0080369043
A129: 2024-07-16 | B129: 0.006654826 | C129: 0.012427207 | D129: 0.0095321884 | E129: 0.01012589 | F129: 0.0072744006 | H129: 0.0094760317 | J129: 0.0094326466 | K129: 0.0066359692 | L129: 0.016049154 | M129: 0.027877636 | N129: 0.07513185 | O129: 0.008684975 | P129: 0.31946497 | Q129: 0.0082099737 | R129: 0.0092408026 | T129: 0.0076649755 | U129: 0.033068808 | W129: 0.0084847976 | Y129: 0.022999209 | Z129: 0.054783466 | AA129: 0.00950118 | AB129: 0.0054377019 | AC129: 0.0054320769 | AF129: 0.0097554857 | AG129: 0.035178736 | AH129: 0.026507388 | AI129: 0.0075990264 | AJ129: 0.012173669 | AK129: 0.010969541 | AL129: 0.015698766 | AM129: 0.0070844262 | AO129: 0.0087072182 | AP129: 0.018644128 | AQ129: 0.010286696 | AR129: 0.0075399413 | AS129: 0.010966349 | AT129: 0.0071441174 | AU129: 0.0083167909 | AV129: 0.0077772371 | AW129: 0.0094377033 | AX129: 0.0084922791 | BD129: 0.019357209 | BE129: 0.0072418227 | BF129: 0.0075059028 | BG129: 0.0075363938 | BI129: 0.010153748 | BJ129: 0.0072593837 | BK129: 0.015396607 | BL129: 0.011552336 | BN129: 0.0081263614
A130: 2024-07-17 | B130: 0.0067919928 | C130: 0.012539892 | D130: 0.010118198 | E130: 0.010397115 | F130: 0.0075540013 | H130: 0.0096768393 | J130: 0.0092478186 | K130: 0.006522848 | L130: 0.016213779 | M130: 0.02806118 | N130: 0.075546171 | O130: 0.0087085838 | P130: 0.315094 | Q130: 0.0080197482 | R130: 0.0091775181 | T130: 0.0076881892 | U130: 0.032527493 | W130: 0.0084477652 | Y130: 0.023235125 | Z130: 0.054522432 | AA130: 0.0096266235 | AB130: 0.0054494613 | AC130: 0.0053708797 | AF130: 0.0097837461 | AG130: 0.03526829 | AH130: 0.026738343 | AI130: 0.007676974 | AJ130: 0.012319039 | AK130: 0.011132435 | AL130: 0.015878746 | AM130: 0.0071213099 | AO130: 0.008747573 | AP130: 0.018658869 | AQ130: 0.010392212 | AR130: 0.0075901268 | AS130: 0.010866124 | AT130: 0.007206954 | AU130: 0.008341871 | AV130: 0.0085514457 | AW130: 0.0096289125 | AX130: 0.0082392374 | BD130: 0.019938143 | BE130: 0.0073979013 | BF130: 0.0076184956 | BG130: 0.0075438485 | BI130: 0.010238619 | BJ130: 0.0072333838 | BK130: 0.015773275 | BL130: 0.011291296 | BN130: 0.0082851752
A131: 2024-07-18 | B131: 0.0069661916 | C131: 0.013141576 | D131: 0.010408073 | E131: 0.010634775 | F131: 0.00790482 | H131: 0.0099026758 | J131: 0.0096443451 | K131: 0.0067245879 | L131: 0.016392948 | M131: 0.027873257 | N131: 0.073917083 | O131: 0.0088216501 | P131: 0.31261299 | Q131: 0.0077979605 | R131: 0.0093506639 | T131: 0.0076624567 | U131: 0.031388839 | W131: 0.0082812852 | Y131: 0.023823316 | Z131: 0.053555905 | AA131: 0.0098453169 | AB131: 0.0055320927 | AC131: 0.0054982928 | AF131: 0.010075945 | AG131: 0.035427521 | AH131: 0.026729719 | AI131: 0.0077583949 | AJ131: 0.012692808 | AK131: 0.011353672 | AL131: 0.016473139 | AM131: 0.0072591833 | AO131: 0.0089277725 | AP131: 0.018972448 | AQ131: 0.010712612 | AR131: 0.0077729106 | AS131: 0.010850474 | AT131: 0.0071687673 | AU131: 0.0084820636 | AV131: 0.0082714983 | AW131: 0.0099827102 | AX131: 0.0082239858 | BD131: 0.019551161 | BE131: 0.0078549081 | BF131: 0.0077103325 | BG131: 0.0070077357 | BI131: 0.010508717 | BJ131: 0.0070740291 | BK131: 0.016384332 | BL131: 0.010974539 | BN131: 0.0081175146
A132: 2024-07-19 | B132: 0.0070789081 | C132: 0.013354566 | D132: 0.010515144 | E132: 0.010805003 | F132: 0.0079686986 | H132: 0.010056471 | J132: 0.0097030287 | K132: 0.0068728945 | L132: 0.016500146 | M132: 0.028310599 | N132: 0.075547278 | O132: 0.008687313 | P132: 0.30838035 | Q132: 0.0082551461 | R132: 0.0093056441 | T132: 0.007687487 | U132: 0.031973446 | W132: 0.0083953899 | Y132: 0.024449756 | Z132: 0.053881781 | AA132: 0.0097134624 | AB132: 0.0055077151 | AC132: 0.0053993284 | AF132: 0.01022354 | AG132: 0.033671413 | AH132: 0.026638373 | AI132: 0.0077349125 | AJ132: 0.012887533 | AK132: 0.011377224 | AL132: 0.016639526 | AM132: 0.0073449012 | AO132: 0.0090229068 | AP132: 0.018840592 | AQ132: 0.01085577 | AR132: 0.0079584479 | AS132: 0.0106845 | AT132: 0.0074571254 | AU132: 0.0084969994 | AV132: 0.007938438 | AW132: 0.01015382 | AX132: 0.0082875285 | BD132: 0.019414669 | BE132: 0.0080281431 | BF132: 0.007843382 | BG132: 0.0069768555 | BI132: 0.010680365 | BJ132: 0.0069613151 | BK132: 0.016442589 | BL132: 0.01087145 | BN132: 0.0082181241
A133: 2024-07-22 | B133: 0.0072284692 | C133: 0.013957259 | D133: 0.010833447 | E133: 0.011091538 | F133: 0.0081962807 | H133: 0.010232932 | J133: 0.010122716 | K133: 0.0068432254 | L133: 0.01641548 | M133: 0.027258138 | N133: 0.073324449 | O133: 0.0086554574 | P133: 0.30705062 | Q133: 0.0083279357 | R133: 0.0093030515 | T133: 0.0075960869 | U133: 0.031890028 | W133: 0.0087643918 | Y133: 0.025044112 | Z133: 0.053881156 | AA133: 0.0096917462 | AB133: 0.0055144476 | AC133: 0.0055457197 | AF133: 0.010457952 | AG133: 0.033225205 | AH133: 0.026261168 | AI133: 0.0077306531 | AJ133: 0.013014584 | AK133: 0.01143293 | AL133: 0.017195759 | AM133: 0.0074972908 | AO133: 0.0091759282 | AP133: 0.0191361 | AQ133: 0.011108348 | AR133: 0.0081857373 | AS133: 0.010724377 | AT133: 0.0070783721 | AU133: 0.0084338616 | AV133: 0.0080803231 | AW133: 0.010443808 | AX133: 0.0081202249 | BD133: 0.019151692 | BE133: 0.0081991353 | BF133: 0.0078771166 | BG133: 0.0070092248 | BI133: 0.010882339 | BJ133: 0.0068310769 | BK133: 0.017120012 | BL133: 0.010953731 | BN133: 0.0079043636
... A184: 2024-10-08 | B184: 0.0068940439 | C184: 0.013164859 | D184: 0.0089077372 | E184: 0.0097595149 | F184: 0.0067731475 | H184: 0.010247797 | J184: 0.010301086 | K184: 0.0062631153 | L184: 0.017049773 | M184: 0.027634521 | N184: 0.073249184 | O184: 0.0070880959 | P184: 0.3259843 | Q184: 0.0082348382 | R184: 0.011369422 | T184: 0.0067364402 | U184: 0.029141368 | W184: 0.0073135054 | Y184: 0.025236996 | Z184: 0.05340967 | AA184: 0.011208095 | AB184: 0.0059232643 | AC184: 0.0066198579 | AF184: 0.0091635617 | AG184: 0.036443225 | AH184: 0.029372062 | AI184: 0.0081837929 | AJ184: 0.011600977 | AK184: 0.011297305 | AL184: 0.014985588 | AM184: 0.0066649246 | AO184: 0.0080298646 | AP184: 0.018808351 | AQ184: 0.0099033065 | AR184: 0.0082500705 | AS184: 0.0091600488 | AT184: 0.0066826935 | AU184: 0.0081207465 | AV184: 0.0057601965 | AW184: 0.01125263 | AX184: 0.0081693058 | BD184: 0.017710781 | BE184: 0.0085029436 | BF184: 0.0075290547 | BG184: 0.0077041237 | BI184: 0.010177291 | BJ184: 0.005747126 | BK184: 0.013957284 | BL184: 0.0087717599 | BN184: 0.0095403587
A185: 2024-10-09 | B185: 0.007189813 | C185: 0.013796082 | D185: 0.0088827191 | E185: 0.0096540504 | F185: 0.0066782155 | H185: 0.010105262 | J185: 0.010015739 | K185: 0.0066101049 | L185: 0.017912092 | M185: 0.026546528 | N185: 0.076267621 | O185: 0.0085809787 | P185: 0.30855903 | Q185: 0.0082515141 | R185: 0.011751373 | T185: 0.0066105513 | U185: 0.028354708 | W185: 0.0073646047 | Y185: 0.026550105 | Z185: 0.052369791 | AA185: 0.010564563 | AB185: 0.0058175729 | AC185: 0.0059794982 | AF185: 0.0097797094 | AG185: 0.038566055 | AH185: 0.030478495 | AI185: 0.0085457377 | AJ185: 0.012524072 | AK185: 0.011518166 | AL185: 0.01608408 | AM185: 0.0071750169 | AO185: 0.0085190636 | AP185: 0.019661288 | AQ185: 0.01043577 | AR185: 0.0086077185 | AS185: 0.0089274354 | AT185: 0.0061748981 | AU185: 0.0088766403 | AV185: 0.0059148417 | AW185: 0.011696106 | AX185: 0.0083188446 | AY185: 0.0078651679 | BD185: 0.018149946 | BE185: 0.0088970157 | BF185: 0.0074651197 | BG185: 0.008107613 | BI185: 0.010848764 | BK185: 0.013951126 | BL185: 0.008875456 | BN185: 0.0096233353
A186: 2024-10-11 | B186: 0.0071082329 | C186: 0.013447744 | D186: 0.0087772676 | E186: 0.0094970396 | F186: 0.0065842921 | H186: 0.0099752317 | J186: 0.0099176608 | K186: 0.0065250485 | L186: 0.017647537 | M186: 0.026101904 | N186: 0.075664561 | O186: 0.0083735177 | P186: 0.31205401 | Q186: 0.0082218906 | R186: 0.011760995 | T186: 0.0065730709 | U186: 0.028859735 | W186: 0.0072470144 | Y186: 0.026208468 | Z186: 0.053979671 | AA186: 0.010570701 | AB186: 0.0057702796 | AC186: 0.0059025562 | AF186: 0.0096729465 | AG186: 0.038111821 | AH186: 0.03017506 | AI186: 0.0086415249 | AJ186: 0.012406991 | AK186: 0.01133403 | AL186: 0.015938734 | AM186: 0.0069457334 | AO186: 0.0083559936 | AP186: 0.019547322 | AQ186: 0.010320705 | AR186: 0.0084111297 | AS186: 0.0088125605 | AT186: 0.0063372444 | AU186: 0.0087796002 | AV186: 0.0057772713 | AW186: 0.011443432 | AX186: 0.0084855275 | AY186: 0.008369774 | BD186: 0.018032739 | BE186: 0.0087027817 | BF186: 0.0075157093 | BG186: 0.0077238073 | BI186: 0.010730206 | BK186: 0.013692612 | BL186: 0.0091980989 | BN186: 0.0097682106
A187: 2024-10-14 | B187: 0.0071007535 | C187: 0.013629797 | D187: 0.0088251648 | E187: 0.0093961706 | F187: 0.0063680111 | H187: 0.0097960235 | J187: 0.0099841684 | K187: 0.006572928 | L187: 0.017839752 | M187: 0.026548222 | N187: 0.075091495 | O187: 0.0085454441 | P187: 0.31124683 | Q187: 0.0084907754 | R187: 0.011690468 | T187: 0.0065764077 | U187: 0.028938196 | W187: 0.0073648658 | Y187: 0.026140674 | Z187: 0.053425888 | AA187: 0.010600043 | AB187: 0.0058011765 | AC187: 0.0058163569 | AF187: 0.0097621021 | AG187: 0.037929415 | AH187: 0.029964225 | AI187: 0.0085935195 | AJ187: 0.012440839 | AK187: 0.01139429 | AL187: 0.015938479 | AM187: 0.0068106778 | AO187: 0.0084765434 | AP187: 0.019746362 | AQ187: 0.010313178 | AR187: 0.0084179079 | AS187: 0.0089158477 | AT187: 0.0065017347 | AU187: 0.0088939842 | AV187: 0.0058644962 | AW187: 0.011464786 | AX187: 0.0085025806 | AY187: 0.0085866417 | BD187: 0.018334212 | BE187: 0.0086504411 | BF187: 0.0074597013 | BG187: 0.007931902 | BI187: 0.01070245 | BK187: 0.013394555 | BL187: 0.0096342319 | BN187: 0.0095852904
A188: 2024-10-15 | B188: 0.0069696394 | C188: 0.013474836 | D188: 0.0083892435 | E188: 0.0091404202 | F188: 0.0062365384 | H188: 0.0096299342 | J188: 0.0099205879 | K188: 0.0064614856 | L188: 0.017570687 | M188: 0.026838953 | N188: 0.076785908 | O188: 0.00849571 | P188: 0.31328956 | Q188: 0.0083768408 | R188: 0.011807655 | T188: 0.0065248899 | U188: 0.029651685 | W188: 0.0073183269 | Y188: 0.025907241 | Z188: 0.052927197 | AA188: 0.010448183 | AB188: 0.0056848005 | AC188: 0.0056549862 | AF188: 0.0097462424 | AG188: 0.037863136 | AH188: 0.029934797 | AI188: 0.0087504268 | AJ188: 0.012381161 | AK188: 0.011482892 | AL188: 0.015829359 | AM188: 0.0067335723 | AO188: 0.0083328256 | AP188: 0.019820518 | AQ188: 0.010307921 | AR188: 0.0082471328 | AS188: 0.0088886266 | AT188: 0.0067076168 | AU188: 0.0086421115 | AV188: 0.005825327 | AW188: 0.011270403 | AX188: 0.0083584213 | AY188: 0.0082847414 | BD188: 0.019221115 | BE188: 0.0085330982 | BF188: 0.0074770125 | BG188: 0.007697771 | BI188: 0.010541622 | BK188: 0.012780175 | BL188: 0.0093519047 | BN188: 0.009484766
A189: 2024-10-16 | B189: 0.0069908616 | C189: 0.013632129 | D189: 0.0084360221 | E189: 0.0091811401 | F189: 0.0061965208 | H189: 0.0096770347 | J189: 0.0099672605 | K189: 0.0065517174 | L189: 0.017511217 | M189: 0.026564988 | N189: 0.077105936 | O189: 0.0085592171 | P189: 0.31024244 | Q189: 0.0084329322 | R189: 0.011812644 | T189: 0.006453817 | U189: 0.030014885 | W189: 0.0072957141 | Y189: 0.026056319 | Z189: 0.052634258 | AA189: 0.010707091 | AB189: 0.0058189963 | AC189: 0.0058117281 | AF189: 0.0096926641 | AG189: 0.037723467 | AH189: 0.029911649 | AI189: 0.0087703447 | AJ189: 0.012422602 | AK189: 0.011518241 | AL189: 0.015968727 | AM189: 0.0067497963 | AO189: 0.008360624 | AP189: 0.020069659 | AQ189: 0.010337221 | AR189: 0.0083480788 | AS189: 0.0090127524 | AT189: 0.0067712359 | AU189: 0.0088994466 | AV189: 0.005804836 | AW189: 0.011427789 | AX189: 0.0085140199 | AY189: 0.0085589329 | BD189: 0.019084702 | BE189: 0.0086621702 | BF189: 0.0076178749 | BG189: 0.0078305267 | BI189: 0.010626079 | BK189: 0.012762302 | BL189: 0.0093136005 | BN189: 0.0095857878
A190: 2024-10-17 | B190: 0.0070387555 | C190: 0.013792984 | D190: 0.008481199 | E190: 0.0092851727 | F190: 0.0063775099 | H190: 0.0097689459 | J190: 0.0099427199 | K190: 0.0067184362 | L190: 0.017441311 | M190: 0.026662992 | N190: 0.078109311 | O190: 0.0084975921 | P190: 0.30604695 | Q190: 0.0082324948 | R190: 0.011865026 | T190: 0.006286703 | U190: 0.030452429 | W190: 0.0073456965 | Y190: 0.0259523 | Z190: 0.052424138 | AA190: 0.011058281 | AB190: 0.00595954 | AC190: 0.0060842914 | AF190: 0.0096917548 | AG190: 0.038113788 | AH190: 0.03014377 | AI190: 0.0089645397 | AJ190: 0.012329367 | AK190: 0.011614551 | AL190: 0.016047351 | AM190: 0.0067615989 | AO190: 0.0083096052 | AP190: 0.020099674 | AQ190: 0.010334017 | AR190: 0.0083997416 | AS190: 0.0091019469 | AT190: 0.0067741345 | AU190: 0.0088979458 | AV190: 0.0059642414 | AW190: 0.011533931 | AX190: 0.0085574744 | AY190: 0.008524765 | BD190: 0.019066116 | BE190: 0.0086966898 | BF190: 0.0076237674 | BG190: 0.0077992666 | BI190: 0.010708662 | BK190: 0.012946025 | BL190: 0.0093725486 | BN190: 0.0097979473
A191: 2024-10-18 | B191: 0.0069551535 | C191: 0.01352512 | D191: 0.0082821258 | E191: 0.0091791338 | F191: 0.0062226212 | H191: 0.0097925759 | J191: 0.0099589772 | K191: 0.0065879621 | L191: 0.01670563 | M191: 0.026812157 | N191: 0.076225054 | O191: 0.008399873 | P191: 0.31460118 | Q191: 0.0084591514 | R191: 0.011634603 | T191: 0.0061382124 | U191: 0.030506946 | W191: 0.0071919593 | Y191: 0.025759911 | Z191: 0.052615599 | AA191: 0.010843526 | AB191: 0.0058794913 | AC191: 0.0058901749 | AF191: 0.0096332159 | AG191: 0.038026421 | AH191: 0.030075425 | AI191: 0.0088653642 | AJ191: 0.012325306 | AK191: 0.01168549 | AL191: 0.015875313 | AM191: 0.0066682825 | AO191: 0.0083039288 | AP191: 0.019925325 | AQ191: 0.010301283 | AR191: 0.0082505058 | AS191: 0.0081536556 | AT191: 0.0066621445 | AU191: 0.008725145 | AV191: 0.0057489512 | AW191: 0.011359543 | AX191: 0.0082773768 | AY191: 0.0083592115 | BD191: 0.018469915 | BE191: 0.0086342739 | BF191: 0.0074045142 | BG191: 0.0077218135 | BI191: 0.010582414 | BK191: 0.012886371 | BL191: 0.0091198345 | BN191: 0.0097918407
A192: 2024-10-21 | B192: 0.0068697078 | C192: 0.013514875 | D192: 0.0081394725 | E192: 0.0088951113 | F192: 0.0060453149 | H192: 0.0096574624 | J192: 0.0098987943 | K192: 0.0066923863 | L192: 0.016862796 | M192: 0.026718128 | N192: 0.077257254 | O192: 0.0084661918 | P192: 0.31506538 | Q192: 0.0086056306 | R192: 0.01153447 | T192: 0.0062926887 | U192: 0.030750995 | W192: 0.0072802567 | Y192: 0.025485848 | Z192: 0.053702682 | AA192: 0.011274012 | AB192: 0.0061115415 | AC192: 0.0060786672 | AF192: 0.009554666 | AG192: 0.037142724 | AH192: 0.029472528 | AI192: 0.0085783287 | AJ192: 0.012064906 | AK192: 0.011423264 | AL192: 0.015699004 | AM192: 0.0066590957 | AO192: 0.0081949037 | AP192: 0.019522103 | AQ192: 0.010185657 | AR192: 0.0082209487 | AS192: 0.0084290956 | AT192: 0.0066327852 | AU192: 0.0089050939 | AV192: 0.0060363406 | AW192: 0.011276948 | AX192: 0.0084036671 | AY192: 0.0086040885 | BD192: 0.018270902 | BE192: 0.0085306863 | BF192: 0.0074154396 | BG192: 0.0077085004 | BI192: 0.010516191 | BK192: 0.012623719 | BL192: 0.0093220927 | BN192: 0.0094066594
A193: 2024-10-22 | B193: 0.0068166266 | C193: 0.01336764 | D193: 0.008011333 | E193: 0.0087616161 | F193: 0.0059878596 | H193: 0.009542351 | J193: 0.0099577096 | K193: 0.0066087179 | L193: 0.016744514 | M193: 0.026935023 | N193: 0.079035104 | O193: 0.0083324541 | P193: 0.3111947 | Q193: 0.0086977167 | R193: 0.011693639 | T193: 0.0063390934 | U193: 0.031647846 | W193: 0.0071138812 | Y193: 0.025510613 | Z193: 0.052731292 | AA193: 0.01134928 | AB193: 0.0060391684 | AC193: 0.0060391579 | AF193: 0.009617549 | AG193: 0.038005311 | AH193: 0.029811422 | AI193: 0.0085517592 | AJ193: 0.012048901 | AK193: 0.011596835 | AL193: 0.015690203 | AM193: 0.0066195035 | AO193: 0.0081695218 | AP193: 0.019731189 | AQ193: 0.010247266 | AR193: 0.0081954862 | AS193: 0.0084029884 | AT193: 0.0066708435 | AU193: 0.0087442664 | AV193: 0.0064942895 | AW193: 0.011291544 | AX193: 0.0085671779 | AY193: 0.0086547134 | BD193: 0.018496267 | BE193: 0.008571912 | BF193: 0.0075346349 | BG193: 0.0077092552 | BI193: 0.010504015 | BK193: 0.012495277 | BL193: 0.009528491 | BN193: 0.0095920429
A194: 2024-10-23 | B194: 0.0068942786 | C194: 0.013392515 | D194: 0.0080033961 | E194: 0.0087620765 | F194: 0.0059919105 | H194: 0.0095930491 | J194: 0.0099348993 | K194: 0.0066100644 | L194: 0.016742208 | M194: 0.026796099 | N194: 0.079996491 | O194: 0.0083328593 | P194: 0.30986607 | Q194: 0.0084683836 | R194: 0.011631356 | T194: 0.006301537 | U194: 0.031758294 | W194: 0.0070608526 | Y194: 0.025551714 | Z194: 0.052842688 | AA194: 0.011432925 | AB194: 0.0061614432 | AC194: 0.0061054306 | AF194: 0.0095439113 | AG194: 0.037884949 | AH194: 0.030060762 | AI194: 0.0085853925 | AJ194: 0.012037795 | AK194: 0.011499724 | AL194: 0.015643228 | AM194: 0.0065887475 | AO194: 0.0081451072 | AP194: 0.019679991 | AQ194: 0.010216205 | AR194: 0.0081079346 | AS194: 0.008503193 | AT194: 0.0067659471 | AU194: 0.0087124093 | AV194: 0.0067185126 | AW194: 0.01140244 | AX194: 0.0086513169 | AY194: 0.0084665961 | BD194: 0.018393196 | BE194: 0.008617062 | BF194: 0.0073932945 | BG194: 0.00768548 | BI194: 0.010504194 | BK194: 0.012527774 | BL194: 0.0097171039 | BN194: 0.0097171935
A195: 2024-10-24 | B195: 0.0069025933 | C195: 0.013752825 | D195: 0.0080631299 | E195: 0.008924478 | F195: 0.006076035 | H195: 0.0096429777 | J195: 0.0098723548 | K195: 0.0065953663 | L195: 0.016766365 | M195: 0.026657372 | N195: 0.078914517 | O195: 0.0083403611 | P195: 0.31217877 | Q195: 0.0086070887 | R195: 0.011579373 | T195: 0.0064759425 | U195: 0.030784145 | W195: 0.0071585742 | Y195: 0.025742421 | Z195: 0.052008535 | AA195: 0.01149023 | AB195: 0.0060986862 | AC195: 0.0060317663 | AF195: 0.0096339592 | AG195: 0.037836173 | AH195: 0.029847476 | AI195: 0.00859874 | AJ195: 0.012105906 | AK195: 0.011585553 | AL195: 0.015739725 | AM195: 0.006637923 | AO195: 0.0081883272 | AP195: 0.019689759 | AQ195: 0.010330364 | AR195: 0.0082672036 | AS195: 0.0084419863 | AT195: 0.0065183498 | AU195: 0.00876049 | AV195: 0.0065261972 | AW195: 0.011487542 | AX195: 0.0084459254 | AY195: 0.0082939403 | BD195: 0.018243625 | BE195: 0.0087501977 | BF195: 0.0074484747 | BG195: 0.007742841 | BI195: 0.010541092 | BK195: 0.012725154 | BL195: 0.0095024018 | BN195: 0.0094467664
A196: 2024-10-25 | B196: 0.0068527602 | C196: 0.01349561 | D196: 0.0081048778 | E196: 0.0088355419 | F196: 0.0060149471 | H196: 0.0096873032 | J196: 0.0099513971 | K196: 0.0066010076 | L196: 0.016586047 | M196: 0.026994411 | N196: 0.079886884 | O196: 0.0083349948 | P196: 0.31090113 | Q196: 0.008920781 | R196: 0.011615419 | T196: 0.0065055459 | U196: 0.031014454 | W196: 0.0070958059 | Y196: 0.025516705 | Z196: 0.053379174 | AA196: 0.011528377 | AB196: 0.0060901237 | AC196: 0.0060414478 | AF196: 0.009493532 | AG196: 0.037874119 | AH196: 0.029932812 | AI196: 0.0085484866 | AJ196: 0.011913584 | AK196: 0.011571766 | AL196: 0.015621794 | AM196: 0.0065797199 | AO196: 0.0081339472 | AP196: 0.019625844 | AQ196: 0.010277362 | AR196: 0.0082506512 | AS196: 0.0083679647 | AT196: 0.0065399903 | AU196: 0.0086332869 | AV196: 0.0066492238 | AW196: 0.011386817 | AX196: 0.0087923741 | AY196: 0.0081043275 | BD196: 0.018424862 | BE196: 0.0086344917 | BF196: 0.0073831645 | BG196: 0.0076252737 | BI196: 0.010489801 | BK196: 0.01252348 | BL196: 0.0093953565 | BN196: 0.0092712224
... A246: 2025-01-07 | B246: 0.0066843387 | C246: 0.011977558 | D246: 0.0059319205 | E246: 0.0063513332 | F246: 0.0041554329 | H246: 0.0080793413 | J246: 0.0092039384 | K246: 0.0063937158 | L246: 0.013998367 | M246: 0.028790018 | N246: 0.069740607 | O246: 0.0075726695 | P246: 0.32615177 | Q246: 0.011378782 | R246: 0.012639585 | T246: 0.0071621147 | U246: 0.02934069 | W246: 0.007972371 | Y246: 0.025531731 | Z246: 0.058737006 | AA246: 0.012599307 | AB246: 0.0070426143 | AC246: 0.0058164663 | AF246: 0.0098846589 | AG246: 0.037466017 | AH246: 0.029749993 | AI246: 0.0087085558 | AJ246: 0.011588493 | AK246: 0.012477789 | AL246: 0.015364417 | AM246: 0.0067009143 | AO246: 0.0079515665 | AP246: 0.021150352 | AQ246: 0.010274396 | AR246: 0.0072724023 | AS246: 0.0093385425 | AT246: 0.006226713 | AU246: 0.0083847754 | AV246: 0.0061220092 | AW246: 0.011053065 | AX246: 0.0081569382 | AY246: 0.0075791432 | BD246: 0.019753209 | BE246: 0.0085403202 | BF246: 0.0067654429 | BG246: 0.0057435892 | BI246: 0.0099615588 | BK246: 0.008992806 | BL246: 0.013044824 | BN246: 0.0084958319
A247: 2025-01-08 | B247: 0.0066687321 | C247: 0.012083592 | D247: 0.0057901838 | E247: 0.0063146121 | H247: 0.0080730562 | J247: 0.0094027041 | K247: 0.0064526618 | L247: 0.014655416 | M247: 0.030132856 | N247: 0.071058808 | O247: 0.0080792186 | P247: 0.30145781 | Q247: 0.011974436 | R247: 0.013105526 | T247: 0.007630604 | U247: 0.031063594 | W247: 0.0089549752 | Y247: 0.026102852 | Z247: 0.062805195 | AA247: 0.013533518 | AB247: 0.007462464 | AC247: 0.0064961713 | AD247: 0.0068044153 | AF247: 0.0099501526 | AG247: 0.037627925 | AH247: 0.030098429 | AI247: 0.0087281319 | AJ247: 0.011880107 | AK247: 0.012332926 | AL247: 0.015663471 | AM247: 0.0067001311 | AO247: 0.0078614856 | AP247: 0.02133062 | AQ247: 0.010572108 | AR247: 0.0073803549 | AS247: 0.0096217861 | AT247: 0.006407682 | AU247: 0.0084568403 | AW247: 0.011305906 | AX247: 0.0085184628 | AY247: 0.0076026636 | BA247: 0.0066794671 | BC247: 0.0069086457 | BD247: 0.02051 | BE247: 0.0085329228 | BF247: 0.0068970009 | BI247: 0.010265674 | BK247: 0.0089124643 | BL247: 0.014387689 | BN247: 0.0087635475
A248: 2025-01-09 | B248: 0.0066243521 | C248: 0.012240916 | D248: 0.005652242 | E248: 0.0062519452 | H248: 0.0080585923 | J248: 0.0094119588 | K248: 0.0067061964 | L248: 0.014482171 | M248: 0.029814194 | N248: 0.07015865 | O248: 0.0078751641 | P248: 0.30438765 | Q248: 0.011750402 | R248: 0.013025539 | T248: 0.0075821243 | U248: 0.030760419 | W248: 0.0086505786 | Y248: 0.026369154 | Z248: 0.062403765 | AA248: 0.012708115 | AB248: 0.0070815319 | AC248: 0.0062753541 | AD248: 0.0067116851 | AF248: 0.0102055 | AG248: 0.038166325 | AH248: 0.030307225 | AI248: 0.0088022849 | AJ248: 0.012072164 | AK248: 0.01228099 | AL248: 0.015846539 | AM248: 0.0067382436 | AO248: 0.0079565614 | AP248: 0.021552827 | AQ248: 0.010684666 | AR248: 0.0074715884 | AS248: 0.0097033706 | AT248: 0.0060660753 | AU248: 0.0083574657 | AW248: 0.011570989 | AX248: 0.0083992233 | AY248: 0.0076239067 | BA248: 0.0066591376 | BC248: 0.0070644696 | BD248: 0.020136301 | BE248: 0.0087049297 | BF248: 0.0069145131 | BI248: 0.010328418 | BK248: 0.0088552295 | BL248: 0.013851959 | BN248: 0.0086964006
A249: 2025-01-10 | B249: 0.0065351917 | C249: 0.012280083 | D249: 0.0055799677 | E249: 0.0062140655 | H249: 0.0079641163 | J249: 0.0094383714 | K249: 0.0066714528 | L249: 0.01444211 | M249: 0.030127018 | N249: 0.069895148 | O249: 0.0078228568 | P249: 0.30575058 | Q249: 0.011580618 | R249: 0.012939176 | T249: 0.0075584856 | U249: 0.030415368 | W249: 0.0087617236 | Y249: 0.026487224 | Z249: 0.063771435 | AA249: 0.012885442 | AB249: 0.0070740489 | AC249: 0.0063743666 | AD249: 0.0068445526 | AF249: 0.010175542 | AG249: 0.037832228 | AH249: 0.029016613 | AI249: 0.0086888157 | AJ249: 0.012126218 | AK249: 0.012141851 | AL249: 0.015855638 | AM249: 0.0067297383 | AO249: 0.0079222343 | AP249: 0.021427003 | AQ249: 0.010693622 | AR249: 0.0074906105 | AS249: 0.010328999 | AT249: 0.0058278519 | AU249: 0.0083097463 | AW249: 0.011519025 | AX249: 0.0083157289 | AY249: 0.0075541245 | BA249: 0.0066042844 | BC249: 0.0067412965 | BD249: 0.020531079 | BE249: 0.0086837426 | BF249: 0.0068120494 | BI249: 0.010247887 | BK249: 0.0087225498 | BL249: 0.013488316 | BN249: 0.0087998072
A250: 2025-01-13 | B250: 0.0067447356 | C250: 0.012489883 | D250: 0.0058751296 | E250: 0.0064506491 | H250: 0.0080630102 | J250: 0.0096611582 | K250: 0.006762628 | L250: 0.014639831 | M250: 0.029369664 | N250: 0.067603107 | O250: 0.0077087227 | P250: 0.30585473 | Q250: 0.011366153 | R250: 0.012884919 | T250: 0.0075895295 | U250: 0.029705675 | W250: 0.0088326516 | Y250: 0.027112439 | Z250: 0.061934909 | AA250: 0.012634892 | AB250: 0.0070103575 | AC250: 0.0062828704 | AD250: 0.0069083892 | AF250: 0.010377009 | AG250: 0.038682158 | AH250: 0.029290912 | AI250: 0.008685255 | AJ250: 0.012276299 | AK250: 0.012302 | AL250: 0.016229901 | AM250: 0.0068292051 | AO250: 0.0081092337 | AP250: 0.021790538 | AQ250: 0.010886333 | AR250: 0.0076821951 | AS250: 0.010207566 | AT250: 0.0056068379 | AU250: 0.0084361723 | AW250: 0.011844037 | AX250: 0.0085120165 | AY250: 0.0076096978 | BA250: 0.0065218349 | BC250: 0.0065489561 | BD250: 0.020267369 | BE250: 0.008991358 | BF250: 0.0069728436 | BI250: 0.010446525 | BK250: 0.0095390477 | BL250: 0.013207592 | BN250: 0.008661078
A251: 2025-01-14 | B251: 0.0066770263 | C251: 0.012482094 | D251: 0.006263065 | E251: 0.0067531344 | H251: 0.008065871 | J251: 0.009532916 | K251: 0.0068037013 | L251: 0.014922309 | M251: 0.029704307 | N251: 0.067872607 | O251: 0.0077243257 | P251: 0.3060059 | Q251: 0.011824979 | R251: 0.012693008 | T251: 0.0075469513 | U251: 0.029148822 | W251: 0.0087032176 | Y251: 0.026861298 | Z251: 0.061552445 | AA251: 0.012680031 | AB251: 0.0071251179 | AC251: 0.0062392628 | AD251: 0.0069131148 | AF251: 0.010468502 | AG251: 0.038593732 | AH251: 0.029487349 | AI251: 0.008775852 | AJ251: 0.01233725 | AK251: 0.012281302 | AL251: 0.01620189 | AM251: 0.0067776183 | AO251: 0.0080192552 | AP251: 0.021810056 | AQ251: 0.010840016 | AR251: 0.0075219122 | AS251: 0.010091038 | AT251: 0.0055752996 | AU251: 0.0086681653 | AW251: 0.011791633 | AX251: 0.0085213439 | AY251: 0.0075409821 | BA251: 0.0064673334 | BC251: 0.0065776249 | BD251: 0.019813739 | BE251: 0.0090137967 | BF251: 0.0070300202 | BI251: 0.010307858 | BK251: 0.0096668163 | BL251: 0.013112887 | BN251: 0.0086112241
A252: 2025-01-15 | B252: 0.0068010176 | C252: 0.012423469 | D252: 0.0064467506 | E252: 0.0069460878 | H252: 0.0083179889 | J252: 0.0096147328 | K252: 0.0066864376 | L252: 0.014814786 | M252: 0.029362945 | N252: 0.067306458 | O252: 0.0078017585 | P252: 0.30256204 | Q252: 0.01175528 | R252: 0.012485616 | T252: 0.0076666112 | U252: 0.028510418 | W252: 0.0087085902 | Y252: 0.027182445 | Z252: 0.063178184 | AA252: 0.012493146 | AB252: 0.0071001467 | AC252: 0.0062413774 | AD252: 0.0069207044 | AF252: 0.010593661 | AG252: 0.0388831 | AH252: 0.029475436 | AI252: 0.0088547306 | AJ252: 0.012439434 | AK252: 0.012410096 | AL252: 0.016395596 | AM252: 0.0068784154 | AO252: 0.0081508809 | AP252: 0.022014001 | AQ252: 0.010969617 | AR252: 0.007626594 | AS252: 0.010384438 | AT252: 0.005446658 | AU252: 0.0088240128 | AW252: 0.01177351 | AX252: 0.0083756664 | AY252: 0.0073696878 | BA252: 0.0066311962 | BC252: 0.0068317381 | BD252: 0.020112897 | BE252: 0.0090293229 | BF252: 0.0070837645 | BI252: 0.010517482 | BK252: 0.0098365864 | BL252: 0.012671439 | BN252: 0.009093055
A253: 2025-01-16 | B253: 0.0066928216 | C253: 0.012338816 | D253: 0.0062868043 | E253: 0.0069233388 | H253: 0.0082331106 | J253: 0.009431663 | K253: 0.0069695911 | L253: 0.014543445 | M253: 0.030048166 | N253: 0.066878345 | O253: 0.0076696498 | P253: 0.30743444 | Q253: 0.011623508 | R253: 0.012413641 | T253: 0.0075801339 | U253: 0.027920874 | W253: 0.0088063531 | Y253: 0.026728136 | Z253: 0.063614639 | AA253: 0.01217454 | AB253: 0.0068454487 | AC253: 0.0060255614 | AD253: 0.0068217024 | AF253: 0.010412466 | AG253: 0.038584541 | AH253: 0.029222857 | AI253: 0.0086461258 | AJ253: 0.012315348 | AK253: 0.012330127 | AL253: 0.016139117 | AM253: 0.0067555389 | AO253: 0.0080173455 | AP253: 0.021753515 | AQ253: 0.010840092 | AR253: 0.0074833362 | AS253: 0.010376485 | AT253: 0.0055996699 | AU253: 0.008607459 | AW253: 0.011530054 | AX253: 0.0084449102 | AY253: 0.0075773605 | BA253: 0.0069390196 | BC253: 0.00669047 | BD253: 0.020123868 | BE253: 0.0089128717 | BF253: 0.0069447045 | BI253: 0.010342299 | BK253: 0.0097127965 | BL253: 0.012755601 | BN253: 0.0089372915
A254: 2025-01-17 | B254: 0.0068281087 | C254: 0.012243611 | D254: 0.0065805499 | E254: 0.007213616 | H254: 0.0084828439 | J254: 0.0093946552 | K254: 0.0069099544 | L254: 0.014364352 | M254: 0.030180576 | N254: 0.066615929 | O254: 0.0075813496 | P254: 0.31038508 | Q254: 0.011625415 | R254: 0.012364932 | T254: 0.0077226433 | U254: 0.027864802 | W254: 0.0087838315 | Y254: 0.02662326 | Z254: 0.062063007 | AA254: 0.012156786 | AB254: 0.0067209011 | AC254: 0.0060176302 | AD254: 0.0069779887 | AF254: 0.010333895 | AG254: 0.038181398 | AH254: 0.029108193 | AI254: 0.0086630096 | AJ254: 0.012200716 | AK254: 0.012140981 | AL254: 0.015952447 | AM254: 0.0066711889 | AO254: 0.0079684507 | AP254: 0.02164045 | AQ254: 0.010720017 | AR254: 0.007482753 | AS254: 0.010223424 | AT254: 0.0056094495 | AU254: 0.0085906628 | AW254: 0.01158828 | AX254: 0.0084520218 | AY254: 0.0074838682 | BA254: 0.0068590306 | BC254: 0.006629984 | BD254: 0.02016639 | BE254: 0.0089078924 | BF254: 0.0069322358 | BI254: 0.010259584 | BK254: 0.0099786715 | BL254: 0.012811652 | BN254: 0.0087415335
A255: 2025-01-20 | B255: 0.0068249736 | C255: 0.012071739 | D255: 0.0064937563 | E255: 0.0070456694 | H255: 0.0084390168 | J255: 0.0093461171 | K255: 0.0069384991 | L255: 0.014827752 | M255: 0.030380388 | N255: 0.067990618 | O255: 0.0076290382 | P255: 0.30878145 | Q255: 0.011596865 | R255: 0.012506065 | T255: 0.0076827438 | U255: 0.028412527 | W255: 0.0087504198 | Y255: 0.026378912 | Z255: 0.062390002 | AA255: 0.011914808 | AB255: 0.0065209664 | AC255: 0.0058380485 | AD255: 0.0068836622 | AF255: 0.010224224 | AG255: 0.037775428 | AH255: 0.028780962 | AI255: 0.0085424313 | AJ255: 0.012115692 | AK255: 0.01199073 | AL255: 0.015829126 | AM255: 0.0066367218 | AO255: 0.0078578959 | AP255: 0.021335685 | AQ255: 0.010645347 | AR255: 0.0074297774 | AS255: 0.010263742 | AT255: 0.0059489895 | AU255: 0.0084449394 | AW255: 0.01137401 | AX255: 0.0090089507 | AY255: 0.0075324199 | BA255: 0.0072435065 | BC255: 0.0071860533 | BD255: 0.020787339 | BE255: 0.0087325715 | BF255: 0.0069919994 | BI255: 0.01018562 | BK255: 0.0097693342 | BL255: 0.012930176 | BN255: 0.0087922857
A256: 2025-01-21 | B256: 0.0067989478 | C256: 0.012137503 | D256: 0.0063211365 | E256: 0.0069646462 | H256: 0.0086569357 | J256: 0.009449659 | K256: 0.0068588074 | L256: 0.014863648 | M256: 0.029921687 | N256: 0.0680284 | O256: 0.0076407835 | P256: 0.30808763 | Q256: 0.011680855 | R256: 0.012252952 | T256: 0.007693977 | U256: 0.028561034 | W256: 0.0087665885 | Y256: 0.026319639 | Z256: 0.063111402 | AA256: 0.011977419 | AB256: 0.0064966175 | AC256: 0.0058483238 | AD256: 0.0068173191 | AF256: 0.010350994 | AG256: 0.038107017 | AH256: 0.02906918 | AI256: 0.0086241033 | AJ256: 0.012176225 | AK256: 0.01210351 | AL256: 0.015895584 | AM256: 0.0066600856 | AO256: 0.007874854 | AP256: 0.021452766 | AQ256: 0.010717635 | AR256: 0.007455933 | AS256: 0.01027785 | AT256: 0.0057990503 | AU256: 0.0087292984 | AW256: 0.011399803 | AX256: 0.0089088081 | AY256: 0.0074363842 | BA256: 0.0072062819 | BC256: 0.0070339839 | BD256: 0.02074063 | BE256: 0.0087129496 | BF256: 0.00699096 | BI256: 0.010246376 | BK256: 0.0095637172 | BL256: 0.012453532 | BN256: 0.0087565795
A257: 2025-01-22 | B257: 0.0067535595 | C257: 0.012037548 | D257: 0.0063126162 | E257: 0.006971946 | H257: 0.0086070018 | J257: 0.0094335979 | K257: 0.0069294702 | L257: 0.013797392 | M257: 0.03080174 | N257: 0.068035134 | O257: 0.0076924594 | P257: 0.30964267 | Q257: 0.011896496 | R257: 0.012314345 | T257: 0.0076588774 | U257: 0.02837848 | W257: 0.0089786795 | Y257: 0.026314252 | Z257: 0.062591669 | AA257: 0.012085627 | AB257: 0.0065200495 | AC257: 0.0058852309 | AD257: 0.0068765066 | AF257: 0.010395698 | AG257: 0.038330152 | AH257: 0.02922352 | AI257: 0.0086531184 | AJ257: 0.01209771 | AK257: 0.011986514 | AL257: 0.015663495 | AM257: 0.0066242192 | AO257: 0.0077928384 | AP257: 0.021330653 | AQ257: 0.010591207 | AR257: 0.0073662006 | AS257: 0.010137913 | AT257: 0.0060326075 | AU257: 0.0087576901 | AW257: 0.011204069 | AX257: 0.0087165801 | AY257: 0.0074222197 | BA257: 0.0070222811 | BC257: 0.0070322258 | BD257: 0.021167788 | BE257: 0.0086707227 | BF257: 0.0070352428 | BI257: 0.010120518 | BK257: 0.0095370021 | BL257: 0.011698175 | BN257: 0.008874292
A258: 2025-02-03 | B258: 0.0069728586 | C258: 0.012594792 | D258: 0.0062134733 | E258: 0.0069754718 | H258: 0.0088481132 | J258: 0.0098025814 | K258: 0.0070782489 | L258: 0.014396927 | M258: 0.029094703 | N258: 0.064789193 | O258: 0.007700202 | P258: 0.30233787 | Q258: 0.011530193 | R258: 0.013636758 | T258: 0.0077422169 | U258: 0.026502111 | W258: 0.0091890141 | Y258: 0.0274732 | Z258: 0.066376447 | AA258: 0.012394949 | AB258: 0.0065836463 | AC258: 0.0058631873 | AD258: 0.0069131235 | AF258: 0.010786296 | AG258: 0.039100526 | AH258: 0.029905002 | AI258: 0.0088068236 | AJ258: 0.012620026 | AK258: 0.012558237 | AL258: 0.016411691 | AM258: 0.0068215423 | AO258: 0.008089004 | AP258: 0.022036155 | AQ258: 0.011048622 | AR258: 0.0075706598 | AS258: 0.010805531 | AT258: 0.0056330142 | AU258: 0.0092436475 | AW258: 0.011762558 | AX258: 0.0082072427 | AY258: 0.0074354558 | BA258: 0.0066813919 | BC258: 0.0068645855 | BD258: 0.019942147 | BE258: 0.0091537608 | BF258: 0.007339313 | BI258: 0.010546498 | BK258: 0.0092578145 | BL258: 0.010926104 | BN258: 0.0094370699
... A301: 2025-04-08 | B301: 0.0078732703 | C301: 0.015055352 | D301: 0.0076435757 | E301: 0.0077863284 | H301: 0.010938993 | J301: 0.010962923 | K301: 0.0059724777 | L301: 0.017923143 | M301: 0.02689083 | N301: 0.059166779 | O301: 0.0076689202 | P301: 0.27748844 | Q301: 0.0093331791 | R301: 0.012448753 | T301: 0.0079720093 | U301: 0.025252612 | W301: 0.0098495983 | Y301: 0.033614958 | Z301: 0.067415013 | AA301: 0.014061662 | AB301: 0.007562894 | AC301: 0.0065662244 | AD301: 0.0066345887 | AF301: 0.012018862 | AG301: 0.040293704 | AH301: 0.029638792 | AI301: 0.0094582472 | AJ301: 0.014577711 | AK301: 0.01299334 | AL301: 0.019387255 | AM301: 0.0072496373 | AO301: 0.0087056663 | AP301: 0.02449197 | AQ301: 0.012307416 | AR301: 0.0090117904 | AS301: 0.0089531963 | AT301: 0.0049320274 | AU301: 0.0099416637 | AW301: 0.014413475 | AX301: 0.0081272667 | AY301: 0.0072806147 | BA301: 0.0050084047 | BC301: 0.0060772821 | BD301: 0.019094996 | BE301: 0.010882966 | BF301: 0.006732932 | BI301: 0.011894757 | BK301: 0.010981836 | BL301: 0.010725589 | BN301: 0.0087360803
A302: 2025-04-09 | B302: 0.0077875531 | C302: 0.015060697 | D302: 0.0071047464 | E302: 0.007445623 | H302: 0.010545847 | J302: 0.01070243 | K302: 0.0056180665 | L302: 0.018145397 | M302: 0.025171751 | N302: 0.053533783 | O302: 0.0068329302 | P302: 0.30216633 | Q302: 0.0083273119 | R302: 0.011227546 | T302: 0.0077821454 | U302: 0.02320614 | W302: 0.0092132082 | Y302: 0.03490887 | Z302: 0.065067423 | AA302: 0.01319685 | AB302: 0.0070654845 | AC302: 0.0058934918 | AD302: 0.0062076712 | AF302: 0.012338311 | AG302: 0.038460819 | AH302: 0.027710532 | AI302: 0.0090522422 | AJ302: 0.014514667 | AK302: 0.012253921 | AL302: 0.019553819 | AM302: 0.0070579064 | AN302: 0.0063383704 | AO302: 0.0087155073 | AP302: 0.02414584 | AQ302: 0.012187759 | AR302: 0.0090796735 | AS302: 0.0085373523 | AU302: 0.0098105333 | AW302: 0.015338997 | AX302: 0.0074079711 | AY302: 0.0069816286 | BC302: 0.0052807062 | BD302: 0.017430316 | BE302: 0.011064599 | BF302: 0.0063026397 | BH302: 0.0078435105 | BI302: 0.012138162 | BK302: 0.010452712 | BL302: 0.01003794 | BN302: 0.0077522673
A303: 2025-04-10 | B303: 0.0077121705 | C303: 0.014450245 | D303: 0.00717017 | E303: 0.007508516 | H303: 0.010647546 | J303: 0.010719662 | K303: 0.0056679229 | L303: 0.018303684 | M303: 0.025410375 | N303: 0.053940841 | O303: 0.0068963892 | P303: 0.3049036 | Q303: 0.0084076158 | R303: 0.011333482 | T303: 0.0078571921 | U303: 0.023388162 | W303: 0.0093006712 | Y303: 0.03229567 | Z303: 0.065518501 | AA303: 0.01331703 | AB303: 0.0071267454 | AC303: 0.00594944 | AD303: 0.0062675346 | AF303: 0.012048155 | AG303: 0.038826817 | AH303: 0.027952065 | AI303: 0.0091336443 | AJ303: 0.014299717 | AK303: 0.012359731 | AL303: 0.018532077 | AM303: 0.0071168448 | AN303: 0.0063831718 | AO303: 0.0087953665 | AP303: 0.024378689 | AQ303: 0.012034795 | AR303: 0.0085022085 | AS303: 0.0086196818 | AU303: 0.0098982668 | AW303: 0.014568721 | AX303: 0.0074730377 | AY303: 0.0070444743 | BC303: 0.0053204164 | BD303: 0.017598404 | BE303: 0.010789726 | BF303: 0.0063575244 | BH303: 0.0074951945 | BI303: 0.011892191 | BK303: 0.010539563 | BL303: 0.01013187 | BN303: 0.0078144797
A304: 2025-04-11 | B304: 0.0072936393 | C304: 0.01393623 | D304: 0.006950579 | E304: 0.0074266014 | H304: 0.010099225 | J304: 0.010515494 | K304: 0.0059760537 | L304: 0.01784428 | M304: 0.026748057 | N304: 0.056946176 | O304: 0.0068896708 | P304: 0.30447038 | Q304: 0.0086696233 | R304: 0.011598 | T304: 0.0080414513 | U304: 0.024927506 | W304: 0.0089353336 | Y304: 0.031676358 | Z304: 0.06766466 | AA304: 0.014179506 | AB304: 0.0075971113 | AC304: 0.0063422416 | AD304: 0.0066773754 | AF304: 0.011679172 | AG304: 0.038159808 | AH304: 0.026996398 | AI304: 0.0086825544 | AJ304: 0.013762054 | AK304: 0.012101018 | AL304: 0.01803534 | AM304: 0.0067883278 | AN304: 0.0060464118 | AO304: 0.0084245027 | AP304: 0.023537295 | AQ304: 0.011466229 | AR304: 0.0083234252 | AS304: 0.0085878012 | AU304: 0.0097093537 | AW304: 0.013885191 | AX304: 0.0079677059 | AY304: 0.0071501871 | BC304: 0.0051333184 | BD304: 0.0181383 | BE304: 0.010208898 | BF304: 0.0063750508 | BH304: 0.0074129784 | BI304: 0.011625063 | BK304: 0.010336979 | BL304: 0.0105728 | BN304: 0.0074882852
A305: 2025-04-14 | B305: 0.007271091 | C305: 0.013671541 | D305: 0.0070621431 | E305: 0.0076011569 | H305: 0.010447454 | J305: 0.010624468 | K305: 0.0060892327 | L305: 0.017929556 | M305: 0.026355226 | N305: 0.05865397 | O305: 0.0071116136 | P305: 0.29632258 | Q305: 0.0089443154 | R305: 0.012280549 | T305: 0.0078702567 | U305: 0.026379816 | W305: 0.009085118 | Y305: 0.031437475 | Z305: 0.068414085 | AA305: 0.014423336 | AB305: 0.0081766529 | AC305: 0.0069704326 | AD305: 0.0066625042 | AF305: 0.011638171 | AG305: 0.038406436 | AH305: 0.02715241 | AI305: 0.0089703407 | AJ305: 0.013740456 | AK305: 0.012243769 | AL305: 0.017850818 | AM305: 0.0069226779 | AN305: 0.0062174455 | AO305: 0.0085077665 | AP305: 0.023416601 | AQ305: 0.01126897 | AR305: 0.0081785251 | AS305: 0.0090330976 | AU305: 0.0095784115 | AW305: 0.013651149 | AX305: 0.0085874406 | AY305: 0.0068216995 | BC305: 0.0053882718 | BD305: 0.017872921 | BE305: 0.0099609289 | BF305: 0.0063684329 | BH305: 0.0073682408 | BI305: 0.011652159 | BK305: 0.010549884 | BL305: 0.010631025 | BN305: 0.0082373744
A306: 2025-04-15 | B306: 0.0071841938 | C306: 0.013349233 | D306: 0.0072146113 | E306: 0.0077663486 | H306: 0.010420209 | J306: 0.010427394 | K306: 0.0061820506 | L306: 0.017875236 | M306: 0.026079708 | N306: 0.058371427 | O306: 0.0071976243 | P306: 0.29684292 | Q306: 0.0091909183 | R306: 0.012603912 | T306: 0.0078384085 | U306: 0.026064549 | W306: 0.00918869 | Y306: 0.031427197 | Z306: 0.066872217 | AA306: 0.014522409 | AB306: 0.008035026 | AC306: 0.0072942495 | AD306: 0.0065502918 | AF306: 0.011564049 | AG306: 0.038697945 | AH306: 0.027566294 | AI306: 0.0091454012 | AJ306: 0.0136748 | AK306: 0.012432935 | AL306: 0.017590822 | AM306: 0.0070584732 | AN306: 0.0063944508 | AO306: 0.0084462143 | AP306: 0.023573879 | AQ306: 0.011222139 | AR306: 0.0080969124 | AS306: 0.0090085552 | AU306: 0.0094074945 | AW306: 0.01342936 | AX306: 0.0089382651 | AY306: 0.006903311 | BC306: 0.0056342368 | BD306: 0.018059154 | BE306: 0.0099881077 | BF306: 0.0063245918 | BH306: 0.0071499056 | BI306: 0.011488918 | BK306: 0.011062297 | BL306: 0.010229 | BN306: 0.0084136609
A307: 2025-04-16 | B307: 0.0072083831 | C307: 0.013791285 | D307: 0.0071865025 | E307: 0.0077245731 | H307: 0.010373704 | J307: 0.010426143 | K307: 0.0062308387 | L307: 0.018280285 | M307: 0.025719842 | N307: 0.057872735 | O307: 0.0071142593 | P307: 0.2943081 | Q307: 0.0089189347 | R307: 0.012590155 | T307: 0.0078923602 | U307: 0.026390658 | W307: 0.0091963128 | Y307: 0.031836701 | Z307: 0.06702512 | AA307: 0.014699869 | AB307: 0.0080932547 | AC307: 0.0071851553 | AD307: 0.0066283217 | AF307: 0.011738291 | AG307: 0.038209861 | AH307: 0.027433417 | AI307: 0.0090422665 | AJ307: 0.013957004 | AK307: 0.012503459 | AL307: 0.01779447 | AM307: 0.0070449272 | AN307: 0.006360991 | AO307: 0.0084875496 | AP307: 0.023973975 | AQ307: 0.011278598 | AR307: 0.0084147668 | AS307: 0.0092038625 | AU307: 0.0093949496 | AW307: 0.014074754 | AX307: 0.0088416541 | AY307: 0.0071077934 | BC307: 0.0052685587 | BD307: 0.018094574 | BE307: 0.010111871 | BF307: 0.0064729527 | BH307: 0.0073959484 | BI307: 0.011635124 | BK307: 0.010827225 | BL307: 0.010290751 | BN307: 0.0083469117
A308: 2025-04-17 | B308: 0.0072467587 | C308: 0.013717822 | D308: 0.0072008333 | E308: 0.0077051555 | H308: 0.010281614 | J308: 0.010607254 | K308: 0.0062463929 | L308: 0.018122233 | M308: 0.025583471 | N308: 0.057833201 | O308: 0.0073005104 | P308: 0.29460449 | Q308: 0.0090468377 | R308: 0.012491817 | T308: 0.0081187639 | U308: 0.027019173 | W308: 0.0088292581 | Y308: 0.032044592 | Z308: 0.066485906 | AA308: 0.014435242 | AB308: 0.0080087253 | AC308: 0.0069116891 | AD308: 0.0065637118 | AF308: 0.0119056 | AG308: 0.038368592 | AH308: 0.027265154 | AI308: 0.0090208401 | AJ308: 0.01397642 | AK308: 0.012269231 | AL308: 0.017884733 | AM308: 0.007028804 | AN308: 0.0064275376 | AO308: 0.0085969598 | AP308: 0.023871839 | AQ308: 0.011328888 | AR308: 0.0084199261 | AS308: 0.0092787214 | AU308: 0.0094932366 | AW308: 0.013800161 | AX308: 0.009005841 | AY308: 0.0073233253 | BC308: 0.0054340755 | BD308: 0.017736043 | BE308: 0.010032723 | BF308: 0.006524091 | BH308: 0.0073866981 | BI308: 0.011781494 | BK308: 0.010833685 | BL308: 0.010624462 | BN308: 0.0079754685
A309: 2025-04-18 | B309: 0.0071226549 | C309: 0.013542624 | D309: 0.0071651995 | E309: 0.0076528713 | H309: 0.010195188 | J309: 0.01053376 | K309: 0.0062878336 | L309: 0.018139883 | M309: 0.02581598 | N309: 0.058056638 | O309: 0.0072427928 | P309: 0.29459985 | Q309: 0.0090492389 | R309: 0.012447532 | T309: 0.0080422065 | U309: 0.026981916 | W309: 0.0089744597 | Y309: 0.03193099 | Z309: 0.067486218 | AA309: 0.014418812 | AB309: 0.0081039725 | AC309: 0.0072259005 | AD309: 0.0066071819 | AF309: 0.011819045 | AG309: 0.03818454 | AH309: 0.02701728 | AI309: 0.0090177633 | AJ309: 0.013952102 | AK309: 0.012225735 | AL309: 0.017940776 | AM309: 0.0070262627 | AN309: 0.006433344 | AO309: 0.0086075689 | AP309: 0.023499463 | AQ309: 0.011266239 | AR309: 0.0084561401 | AS309: 0.0092031214 | AU309: 0.0096137096 | AW309: 0.01363114 | AX309: 0.0093757313 | AY309: 0.0072358193 | BC309: 0.005390365 | BD309: 0.01760493 | BE309: 0.0099165336 | BF309: 0.0065340041 | BH309: 0.0073605114 | BI309: 0.011690607 | BK309: 0.010916916 | BL309: 0.010614953 | BN309: 0.0078417008
A310: 2025-04-21 | B310: 0.0071378863 | C310: 0.013653248 | D310: 0.0070693997 | E310: 0.007584602 | H310: 0.010103909 | J310: 0.01077522 | K310: 0.0063418854 | L310: 0.018067971 | M310: 0.025483949 | N310: 0.059120708 | O310: 0.0071123206 | P310: 0.2925462 | Q310: 0.0088165294 | R310: 0.012304737 | T310: 0.0081618046 | U310: 0.027452647 | W310: 0.0089210218 | Y310: 0.03202584 | Z310: 0.067220094 | AA310: 0.014154053 | AB310: 0.0079420801 | AC310: 0.0072078576 | AD310: 0.0064850274 | AF310: 0.012081986 | AG310: 0.03835676 | AH310: 0.027565666 | AI310: 0.0091449843 | AJ310: 0.014052723 | AK310: 0.01237903 | AL310: 0.0182082 | AM310: 0.0070800034 | AN310: 0.0064743573 | AO310: 0.0086388157 | AP310: 0.023463976 | AQ310: 0.011343215 | AR310: 0.0084979541 | AS310: 0.0091304596 | AU310: 0.0096208135 | AW310: 0.013779281 | AX310: 0.0092970993 | AY310: 0.0071722564 | BC310: 0.005201829 | BD310: 0.017727281 | BE310: 0.010012663 | BF310: 0.006571614 | BH310: 0.0074960306 | BI310: 0.011916967 | BK310: 0.010820381 | BL310: 0.010474154 | BN310: 0.0078025098
A311: 2025-04-22 | B311: 0.0072463529 | C311: 0.014039526 | D311: 0.0072123268 | E311: 0.0078296317 | H311: 0.010396246 | J311: 0.011032648 | K311: 0.0064607675 | L311: 0.018680762 | M311: 0.025795239 | N311: 0.058243388 | O311: 0.0071472877 | P311: 0.29124861 | Q311: 0.0085912869 | R311: 0.012086861 | T311: 0.008134402 | U311: 0.026942599 | W311: 0.0089624138 | Y311: 0.032883081 | Z311: 0.066189012 | AA311: 0.014312038 | AB311: 0.0080446584 | AC311: 0.0071909258 | AD311: 0.0064691344 | AF311: 0.012285633 | AG311: 0.038234907 | AH311: 0.027251866 | AI311: 0.0091080577 | AJ311: 0.014134274 | AK311: 0.012402978 | AL311: 0.018549523 | AM311: 0.0071205465 | AN311: 0.006507387 | AO311: 0.0086315096 | AP311: 0.023508716 | AQ311: 0.011416901 | AR311: 0.0086402445 | AS311: 0.0092136565 | AU311: 0.0094837143 | AW311: 0.013975741 | AX311: 0.0090851669 | AY311: 0.0071075127 | BC311: 0.0050224149 | BD311: 0.017919046 | BE311: 0.010105468 | BF311: 0.0065586946 | BH311: 0.0076688717 | BI311: 0.012089772 | BK311: 0.011023215 | BL311: 0.010264555 | BN311: 0.0075504281
A312: 2025-04-23 | B312: 0.0071060717 | C312: 0.013836718 | D312: 0.0071151156 | E312: 0.0077046751 | H312: 0.0101905 | J312: 0.01082672 | K312: 0.0062716398 | L312: 0.0182355 | M312: 0.026289574 | N312: 0.058808184 | O312: 0.0071439587 | P312: 0.29877085 | Q312: 0.008629211 | R312: 0.012291182 | T312: 0.0081141667 | U312: 0.027163148 | W312: 0.0088885467 | Y312: 0.031406749 | Z312: 0.066882636 | AA312: 0.014100469 | AB312: 0.0079244893 | AC312: 0.0069979234 | AD312: 0.0065324283 | AF312: 0.01171438 | AG312: 0.037610058 | AH312: 0.026677922 | AI312: 0.0089615734 | AJ312: 0.013851591 | AK312: 0.012012308 | AL312: 0.017856961 | AM312: 0.006960103 | AN312: 0.0063243027 | AO312: 0.0084183109 | AP312: 0.022888587 | AQ312: 0.011035906 | AR312: 0.0083988499 | AS312: 0.0091929469 | AU312: 0.0092932026 | AW312: 0.013578512 | AX312: 0.0090375372 | AY312: 0.0069886636 | BC312: 0.0050329894 | BD312: 0.018529243 | BE312: 0.0098715839 | BF312: 0.0064927154 | BH312: 0.0072293154 | BI312: 0.011616519 | BK312: 0.010869873 | BL312: 0.010565029 | BN312: 0.0077605645
A313: 2025-04-24 | B313: 0.0071889911 | C313: 0.013817554 | D313: 0.0068750823 | E313: 0.0075700956 | H313: 0.010234524 | J313: 0.010863422 | K313: 0.0063448223 | L313: 0.017752897 | M313: 0.02635419 | N313: 0.058424362 | O313: 0.0070842049 | P313: 0.29914109 | Q313: 0.0088848723 | R313: 0.012457505 | T313: 0.0080497631 | U313: 0.026895426 | W313: 0.0088837615 | Y313: 0.031648627 | Z313: 0.065687513 | AA313: 0.014230297 | AB313: 0.0079608175 | AC313: 0.0070969328 | AD313: 0.0065003153 | AF313: 0.011673861 | AG313: 0.037569113 | AH313: 0.026938869 | AI313: 0.008950652 | AJ313: 0.013811594 | AK313: 0.011970796 | AL313: 0.017946008 | AM313: 0.0070636725 | AN313: 0.0063980998 | AO313: 0.0084139336 | AP313: 0.023219547 | AQ313: 0.011142218 | AR313: 0.0085463507 | AS313: 0.0091295714 | AU313: 0.0092765445 | AW313: 0.01367697 | AX313: 0.0090091946 | AY313: 0.0071756075 | BC313: 0.0051527702 | BD313: 0.018063804 | BE313: 0.0099407515 | BF313: 0.0065437221 | BH313: 0.007305834 | BI313: 0.011703001 | BK313: 0.010525858 | BL313: 0.010491421 | BN313: 0.00841317
... A362: 2025-07-04 | B362: 0.0052463163 | C362: 0.013247859 | D362: 0.0065161254 | E362: 0.0064307658 | H362: 0.0085441046 | J362: 0.0086858549 | K362: 0.0071216014 | L362: 0.014910408 | M362: 0.032213606 | N362: 0.059071131 | O362: 0.0066064189 | P362: 0.33253693 | Q362: 0.011756681 | R362: 0.012049385 | T362: 0.0082314737 | U362: 0.027532571 | W362: 0.0082959486 | Y362: 0.027808845 | Z362: 0.055527544 | AA362: 0.010481178 | AB362: 0.0073270561 | AC362: 0.0066925472 | AD362: 0.0061346838 | AF362: 0.011008743 | AG362: 0.032787253 | AH362: 0.025996673 | AI362: 0.0072145406 | AJ362: 0.014945522 | AK362: 0.010856114 | AL362: 0.017503544 | AM362: 0.0063395172 | AN362: 0.0057135698 | AO362: 0.0089764032 | AP362: 0.02527152 | AQ362: 0.011803192 | AR362: 0.007744741 | AS362: 0.0085527384 | AU362: 0.0092738594 | AW362: 0.012426047 | AX362: 0.0091095606 | AY362: 0.0066761296 | BC362: 0.0069258172 | BD362: 0.017150064 | BE362: 0.0092980395 | BF362: 0.0053764072 | BH362: 0.0061949751 | BI362: 0.010884323 | BK362: 0.0099956183 | BL362: 0.011916776 | BN362: 0.0070892784
A363: 2025-07-07 | C363: 0.013730373 | D363: 0.0064010079 | E363: 0.0063340119 | H363: 0.008523419 | J363: 0.0086352124 | K363: 0.0076421895 | L363: 0.015729105 | M363: 0.032898663 | N363: 0.06080139 | O363: 0.0071733838 | P363: 0.30587717 | Q363: 0.011932466 | R363: 0.013671103 | T363: 0.0084774935 | U363: 0.028317084 | V363: 0.0093441719 | W363: 0.0084902622 | Y363: 0.027719493 | Z363: 0.056492349 | AA363: 0.011843387 | AB363: 0.0072040232 | AC363: 0.0070593994 | AF363: 0.011203727 | AG363: 0.034801413 | AH363: 0.025268628 | AI363: 0.0070968966 | AJ363: 0.015643344 | AK363: 0.011372035 | AL363: 0.017957982 | AM363: 0.0064462183 | AO363: 0.0089620748 | AP363: 0.025701504 | AQ363: 0.012060864 | AR363: 0.0077940869 | AS363: 0.0085000724 | AT363: 0.0086169362 | AU363: 0.0096180554 | AW363: 0.012052352 | AX363: 0.01085417 | AY363: 0.0067619398 | BB363: 0.0060479458 | BC363: 0.0077656276 | BD363: 0.01740378 | BE363: 0.0092097119 | BG363: 0.0067870609 | BH363: 0.0061972298 | BI363: 0.010931244 | BK363: 0.010124723 | BL363: 0.013180093 | BN363: 0.0073431247
A364: 2025-07-08 | C364: 0.013940264 | D364: 0.0063042287 | E364: 0.0062571942 | H364: 0.0084502245 | J364: 0.008590879 | K364: 0.0076907483 | L364: 0.015850604 | M364: 0.033073004 | N364: 0.060163753 | O364: 0.0071429357 | P364: 0.30647654 | Q364: 0.012312255 | R364: 0.013697891 | T364: 0.0083896081 | U364: 0.027860431 | V364: 0.0099028247 | W364: 0.0085319559 | Y364: 0.027560165 | Z364: 0.056160834 | AA364: 0.011836245 | AB364: 0.007138928 | AC364: 0.0069946408 | AF364: 0.011205952 | AG364: 0.034529414 | AH364: 0.025236206 | AI364: 0.0069476041 | AJ364: 0.015673997 | AK364: 0.011520922 | AL364: 0.018143113 | AM364: 0.0065192127 | AO364: 0.0090345013 | AP364: 0.025436771 | AQ364: 0.012023258 | AR364: 0.007824206 | AS364: 0.0084192828 | AT364: 0.0090077267 | AU364: 0.00951221 | AW364: 0.012075968 | AX364: 0.010921521 | AY364: 0.0067912447 | BB364: 0.0061222688 | BC364: 0.0077687623 | BD364: 0.017316786 | BE364: 0.0091858615 | BG364: 0.0068003601 | BH364: 0.0061960053 | BI364: 0.011061754 | BK364: 0.0099422103 | BL364: 0.013017648 | BN364: 0.0074390823
A365: 2025-07-09 | C365: 0.013828892 | D365: 0.0062037732 | E365: 0.006096254 | H365: 0.0084575805 | J365: 0.0085681093 | K365: 0.0077904578 | L365: 0.015852686 | M365: 0.032890189 | N365: 0.060650951 | O365: 0.0072442495 | P365: 0.30794554 | Q365: 0.012838403 | R365: 0.013809628 | T365: 0.0085308281 | U365: 0.028145045 | V365: 0.0099003847 | W365: 0.0085316205 | Y365: 0.027225509 | Z365: 0.05965448 | AA365: 0.011965158 | AB365: 0.0056286959 | AC365: 0.0071514737 | AF365: 0.010999233 | AG365: 0.033995597 | AH365: 0.024920601 | AI365: 0.0068936494 | AJ365: 0.01569643 | AK365: 0.011307885 | AL365: 0.017892223 | AM365: 0.0065103965 | AO365: 0.0089763152 | AP365: 0.025039028 | AQ365: 0.011949731 | AR365: 0.0077304591 | AS365: 0.0084790409 | AT365: 0.0091483519 | AU365: 0.0085301995 | AW365: 0.010852196 | AX365: 0.011056706 | AY365: 0.006729225 | BB365: 0.0060744453 | BC365: 0.0080952425 | BD365: 0.01766212 | BE365: 0.0080440336 | BG365: 0.0067702678 | BH365: 0.0061153525 | BI365: 0.01094764 | BK365: 0.0098176326 | BL365: 0.013709798 | BN365: 0.0071462983
A366: 2025-07-10 | C366: 0.013760175 | D366: 0.0061900284 | E366: 0.005996904 | H366: 0.008387592 | J366: 0.0084446266 | K366: 0.0077717472 | L366: 0.015608584 | M366: 0.034804139 | N366: 0.06017665 | O366: 0.007187258 | P366: 0.30738583 | Q366: 0.012969769 | R366: 0.013680524 | T366: 0.0084820115 | U366: 0.027535899 | V366: 0.0097925504 | W366: 0.0085250556 | Y366: 0.027349736 | Z366: 0.060964294 | AA366: 0.011655519 | AB366: 0.0054036418 | AC366: 0.0069033191 | AF366: 0.010995995 | AG366: 0.034462811 | AH366: 0.025294645 | AI366: 0.0069103967 | AJ366: 0.015752446 | AK366: 0.011291581 | AL366: 0.017844996 | AM366: 0.0066970651 | AO366: 0.0089685919 | AP366: 0.024879135 | AQ366: 0.011920082 | AR366: 0.0077047395 | AS366: 0.0084058793 | AT366: 0.0094280627 | AU366: 0.0082217985 | AW366: 0.010784389 | AX366: 0.010890898 | AY366: 0.0065768817 | BB366: 0.0058647402 | BC366: 0.0082331236 | BD366: 0.017887111 | BE366: 0.0081240259 | BG366: 0.0067486396 | BH366: 0.0060421627 | BI366: 0.010871369 | BK366: 0.0096974155 | BL366: 0.013745869 | BN366: 0.006779297
A367: 2025-07-11 | C367: 0.013887239 | D367: 0.0060913845 | E367: 0.0058455478 | H367: 0.0083090139 | J367: 0.0084322603 | K367: 0.007793389 | L367: 0.015425233 | M367: 0.034789185 | N367: 0.060088527 | O367: 0.0071037987 | P367: 0.30693569 | Q367: 0.012695902 | R367: 0.01366049 | T367: 0.0084842691 | U367: 0.027495575 | V367: 0.0096147291 | W367: 0.0085864867 | Y367: 0.027414722 | Z367: 0.061744661 | AA367: 0.011727977 | AB367: 0.0053785174 | AC367: 0.0068777542 | AF367: 0.010979893 | AG367: 0.034537784 | AH367: 0.025177037 | AI367: 0.0069919752 | AJ367: 0.015774708 | AK367: 0.011524021 | AL367: 0.017903113 | AM367: 0.007241232 | AO367: 0.0090453725 | AP367: 0.02470187 | AQ367: 0.011962842 | AR367: 0.0077372524 | AS367: 0.0087576743 | AT367: 0.0092137159 | AU367: 0.0082097585 | AW367: 0.010768596 | AX367: 0.010829637 | AY367: 0.0065356771 | BB367: 0.0057947237 | BC367: 0.0081497861 | BD367: 0.017860917 | BE367: 0.0081416635 | BG367: 0.006608665 | BH367: 0.0060333145 | BI367: 0.010984169 | BK367: 0.0095240384 | BL367: 0.013778632 | BN367: 0.0068495751
A368: 2025-07-14 | C368: 0.014057238 | D368: 0.0064438894 | E368: 0.0060440507 | H368: 0.0083935514 | J368: 0.008480287 | K368: 0.0076854464 | L368: 0.015504908 | M368: 0.034324248 | N368: 0.060164018 | O368: 0.0071790837 | P368: 0.30783046 | Q368: 0.01221329 | R368: 0.013527059 | T368: 0.0085774334 | U368: 0.027346497 | V368: 0.0095529646 | W368: 0.0084894898 | Y368: 0.027620187 | Z368: 0.060674136 | AA368: 0.012116533 | AB368: 0.0054274978 | AC368: 0.0070071581 | AF368: 0.01121854 | AG368: 0.034796634 | AH368: 0.025649827 | AI368: 0.0070905705 | AJ368: 0.016052777 | AK368: 0.011574555 | AL368: 0.018037292 | AM368: 0.0074151011 | AO368: 0.0092218705 | AP368: 0.022474689 | AQ368: 0.0120525 | AR368: 0.0078981967 | AS368: 0.0086688541 | AT368: 0.0093052191 | AU368: 0.0082546121 | AW368: 0.010950699 | AX368: 0.010682542 | AY368: 0.0065289926 | BB368: 0.0057350058 | BC368: 0.0079236056 | BD368: 0.017814831 | BE368: 0.0082721129 | BG368: 0.0067106216 | BH368: 0.0060652893 | BI368: 0.011131335 | BK368: 0.009729059 | BL368: 0.013135847 | BN368: 0.0069493947
A369: 2025-07-15 | C369: 0.013810917 | D369: 0.0063386573 | E369: 0.0060529498 | H369: 0.0083367614 | J369: 0.0082954316 | K369: 0.0077121265 | L369: 0.015501642 | M369: 0.035511417 | N369: 0.060527198 | O369: 0.0072790654 | P369: 0.3091161 | Q369: 0.012337037 | R369: 0.013591117 | T369: 0.0083943128 | U369: 0.027190135 | V369: 0.0098915214 | W369: 0.0082990891 | Y369: 0.027151075 | Z369: 0.060538158 | AA369: 0.011883583 | AB369: 0.0053593372 | AC369: 0.0069413363 | AF369: 0.011016354 | AG369: 0.03484535 | AH369: 0.025368681 | AI369: 0.006955327 | AJ369: 0.015969846 | AK369: 0.011448081 | AL369: 0.017657648 | AM369: 0.0071677348 | AO369: 0.0091711396 | AP369: 0.022794922 | AQ369: 0.011919252 | AR369: 0.007722016 | AS369: 0.0086448001 | AT369: 0.009484671 | AU369: 0.0082266303 | AW369: 0.01074739 | AX369: 0.010853534 | AY369: 0.0064203957 | BB369: 0.0059467984 | BC369: 0.0079914562 | BD369: 0.017885164 | BE369: 0.0081059798 | BG369: 0.0067514538 | BH369: 0.0059230441 | BI369: 0.01098395 | BK369: 0.0096244304 | BL369: 0.013302794 | BN369: 0.007012192
A370: 2025-07-16 | C370: 0.013834652 | D370: 0.006186594 | E370: 0.0060212256 | H370: 0.008219462 | J370: 0.0081924269 | K370: 0.0076440606 | L370: 0.015329547 | M370: 0.035625506 | N370: 0.059808968 | O370: 0.0072436809 | P370: 0.31190839 | Q370: 0.012117847 | R370: 0.013365921 | T370: 0.0084363898 | U370: 0.027149422 | V370: 0.0099356173 | W370: 0.0082258428 | Y370: 0.027119255 | Z370: 0.060649062 | AA370: 0.011867262 | AB370: 0.0054227041 | AC370: 0.0071323426 | AF370: 0.010957505 | AG370: 0.034910074 | AH370: 0.025304178 | AI370: 0.0069846502 | AJ370: 0.015806478 | AK370: 0.011399819 | AL370: 0.017585147 | AM370: 0.0071240452 | AO370: 0.0091257747 | AP370: 0.022646404 | AQ370: 0.01183391 | AR370: 0.0076105391 | AS370: 0.0087201575 | AT370: 0.0093458556 | AU370: 0.0081785838 | AW370: 0.010602758 | AX370: 0.010578447 | AY370: 0.0063793469 | BB370: 0.0060158453 | BC370: 0.0084615222 | BD370: 0.017786208 | BE370: 0.0080344378 | BG370: 0.0066918667 | BH370: 0.0058642669 | BI370: 0.01090823 | BK370: 0.0095394868 | BL370: 0.013106901 | BN370: 0.0070613816
A371: 2025-07-17 | C371: 0.013897695 | D371: 0.0065964884 | E371: 0.00634593 | H371: 0.008415187 | J371: 0.008176543 | K371: 0.0075124846 | L371: 0.01536297 | M371: 0.035549957 | N371: 0.060353754 | O371: 0.0073582284 | P371: 0.31187069 | Q371: 0.012037602 | R371: 0.013469536 | T371: 0.0084789261 | U371: 0.026996711 | V371: 0.009833354 | W371: 0.0078619225 | Y371: 0.027115976 | Z371: 0.059781563 | AA371: 0.011924861 | AB371: 0.005396513 | AC371: 0.0070550444 | AF371: 0.01112887 | AG371: 0.034781781 | AH371: 0.025141742 | AI371: 0.0070064805 | AJ371: 0.015804567 | AK371: 0.011275309 | AL371: 0.017520522 | AM371: 0.0072014607 | AO371: 0.0090890978 | AP371: 0.022538347 | AQ371: 0.011872186 | AR371: 0.0076529375 | AS371: 0.0088707399 | AT371: 0.0093006469 | AU371: 0.008177595 | AW371: 0.010601476 | AX371: 0.010577168 | AY371: 0.0061209343 | BB371: 0.0058551199 | BC371: 0.0088247708 | BD371: 0.017842945 | BE371: 0.0080042539 | BG371: 0.0067167925 | BH371: 0.0057985518 | BI371: 0.010928131 | BK371: 0.010023778 | BL371: 0.012843733 | BN371: 0.007108127
A372: 2025-07-18 | C372: 0.013769001 | D372: 0.0067015805 | E372: 0.0063047288 | H372: 0.0082098705 | J372: 0.0081703382 | K372: 0.0074901999 | L372: 0.015150483 | M372: 0.035843135 | N372: 0.06020161 | O372: 0.0073016787 | P372: 0.31508503 | Q372: 0.012427941 | R372: 0.013293005 | T372: 0.0083952481 | U372: 0.026930757 | V372: 0.010239114 | W372: 0.0078414594 | Y372: 0.026494402 | Z372: 0.059940623 | AA372: 0.011670289 | AB372: 0.0052920542 | AC372: 0.0069432568 | AF372: 0.010943306 | AG372: 0.034216135 | AH372: 0.024654148 | AI372: 0.0069254754 | AJ372: 0.01551105 | AK372: 0.011127564 | AL372: 0.017379735 | AM372: 0.0069634578 | AO372: 0.0090015957 | AP372: 0.02222572 | AQ372: 0.011695679 | AR372: 0.0075216407 | AS372: 0.0091241543 | AT372: 0.0097050568 | AU372: 0.0080264121 | AW372: 0.010429711 | AX372: 0.010543481 | AY372: 0.0059757495 | BB372: 0.0058865259 | BC372: 0.0091292629 | BD372: 0.017927688 | BE372: 0.0079309629 | BG372: 0.0065882619 | BH372: 0.0057700648 | BI372: 0.010780811 | BK372: 0.010089447 | BL372: 0.01339335 | BN372: 0.0068377516
A373: 2025-07-21 | C373: 0.013894433 | D373: 0.0067409139 | E373: 0.0064114905 | H373: 0.0083235309 | J373: 0.0081528563 | K373: 0.0075147939 | L373: 0.015217721 | M373: 0.036384725 | N373: 0.060216806 | O373: 0.0073399615 | P373: 0.31475112 | Q373: 0.012390623 | R373: 0.013357524 | T373: 0.00830763 | U373: 0.027019184 | V373: 0.010172512 | W373: 0.008020311 | Y373: 0.026581395 | Z373: 0.060777197 | AA373: 0.011562251 | AB373: 0.0052503431 | AC373: 0.0069205746 | AF373: 0.010979238 | AG373: 0.034082401 | AH373: 0.024616561 | AI373: 0.0069032428 | AJ373: 0.015206278 | AK373: 0.011059437 | AL373: 0.017457461 | AM373: 0.0068310706 | AO373: 0.0090311523 | AP373: 0.022194254 | AQ373: 0.011694706 | AR373: 0.0076036156 | AS373: 0.0092293011 | AT373: 0.0095292896 | AU373: 0.0080040604 | AW373: 0.010513315 | AX373: 0.010533655 | AY373: 0.0059207087 | BB373: 0.0056473488 | BC373: 0.0088096494 | BD373: 0.01781136 | BE373: 0.0079473476 | BG373: 0.0066098944 | BH373: 0.0056987589 | BI373: 0.010732037 | BK373: 0.010148598 | BL373: 0.013100097 | BN373: 0.0067972656
A374: 2025-07-22 | C374: 0.01414083 | D374: 0.0068376891 | E374: 0.0061246569 | H374: 0.0084541473 | J374: 0.008169511 | K374: 0.0075472656 | L374: 0.015239177 | M374: 0.036716556 | N374: 0.059893748 | O374: 0.0073198217 | P374: 0.31331457 | Q374: 0.012172478 | R374: 0.013172455 | T374: 0.0084890096 | U374: 0.026271019 | V374: 0.010051481 | W374: 0.0079818383 | Y374: 0.027241517 | Z374: 0.061786635 | AA374: 0.011624227 | AB374: 0.0052333698 | AC374: 0.0068726958 | AF374: 0.011141841 | AG374: 0.034278026 | AH374: 0.024697739 | AI374: 0.0069250205 | AJ374: 0.014413834 | AK374: 0.011168467 | AL374: 0.01787372 | AM374: 0.0068022864 | AO374: 0.0091311781 | AP374: 0.022563339 | AQ374: 0.011827426 | AR374: 0.0077028752 | AS374: 0.0092736135 | AT374: 0.0094322726 | AU374: 0.0080674291 | AW374: 0.010600556 | AX374: 0.010310956 | AY374: 0.0058769802 | BB374: 0.00549948 | BC374: 0.0087829917 | BD374: 0.017866393 | BE374: 0.0079728334 | BG374: 0.0066444737 | BH374: 0.0057862134 | BI374: 0.010850818 | BK374: 0.010241537 | BL374: 0.012982035 | BN374: 0.0066309619
... A427: 2025-10-07 | C427: 0.010429203 | D427: 0.0056214428 | E427: 0.0075271133 | H427: 0.0069872696 | J427: 0.0074104751 | K427: 0.0095430253 | L427: 0.013406377 | M427: 0.060322088 | N427: 0.072138535 | O427: 0.0087192021 | P427: 0.33843004 | Q427: 0.013673728 | R427: 0.012475885 | T427: 0.0064604821 | U427: 0.026364371 | V427: 0.010565232 | W427: 0.0065814861 | Y427: 0.023707571 | Z427: 0.048886509 | AA427: 0.0091158075 | AB427: 0.0037824605 | AC427: 0.0048195453 | AF427: 0.0091170562 | AG427: 0.030831615 | AH427: 0.02228611 | AI427: 0.0057966674 | AJ427: 0.012122824 | AK427: 0.010366875 | AL427: 0.014369305 | AM427: 0.0058293092 | AO427: 0.0075321962 | AP427: 0.019086473 | AQ427: 0.0095471927 | AR427: 0.0058921919 | AS427: 0.0080834247 | AT427: 0.010770599 | AU427: 0.0059689744 | AW427: 0.0093935572 | AX427: 0.011995896 | AY427: 0.0051928276 | BB427: 0.0079816302 | BC427: 0.0069090907 | BD427: 0.017529683 | BE427: 0.0075682927 | BG427: 0.0045012035 | BH427: 0.0046286406 | BI427: 0.008524505 | BK427: 0.0091393394 | BL427: 0.015753156 | BN427: 0.0063135156
A428: 2025-10-08 | C428: 0.010292984 | D428: 0.0057512113 | E428: 0.0076698929 | H428: 0.0069067311 | I428: 0.0083975304 | J428: 0.0075810706 | K428: 0.0097641577 | L428: 0.013312573 | M428: 0.059598021 | N428: 0.07180629 | O428: 0.009145161 | P428: 0.30942183 | Q428: 0.014461802 | R428: 0.011814522 | S428: 0.0064085311 | T428: 0.0066731509 | U428: 0.027931678 | V428: 0.0099218055 | W428: 0.0065961107 | Y428: 0.023872588 | Z428: 0.049918048 | AA428: 0.0090762252 | AE428: 0.0055892014 | AF428: 0.0095507005 | AG428: 0.03252401 | AH428: 0.024760574 | AI428: 0.0065302115 | AJ428: 0.012489158 | AK428: 0.010789818 | AL428: 0.014623689 | AM428: 0.012720856 | AO428: 0.0080987858 | AP428: 0.020028731 | AQ428: 0.0099346395 | AR428: 0.005880148 | AS428: 0.0078043859 | AT428: 0.010761675 | AU428: 0.0058956405 | AV428: 0.0057795994 | AW428: 0.0097336927 | AX428: 0.012202044 | BB428: 0.0085661531 | BC428: 0.0068567481 | BD428: 0.017759203 | BE428: 0.0077509963 | BI428: 0.0089212806 | BK428: 0.009396142 | BL428: 0.01611026 | BM428: 0.0058995472 | BN428: 0.0067201968
A429: 2025-10-09 | C429: 0.010165687 | D429: 0.0057682983 | E429: 0.0077598075 | H429: 0.0068564747 | I429: 0.0087328438 | J429: 0.0075518142 | K429: 0.0096367542 | L429: 0.013421511 | M429: 0.060249945 | N429: 0.070174937 | O429: 0.0089807342 | P429: 0.31259738 | Q429: 0.014425263 | R429: 0.011474322 | S429: 0.0062612368 | T429: 0.0066969941 | U429: 0.027003509 | V429: 0.010179304 | W429: 0.0065581577 | Y429: 0.02361012 | Z429: 0.04992602 | AA429: 0.0089599867 | AE429: 0.0055894302 | AF429: 0.0094974404 | AG429: 0.032985257 | AH429: 0.02499447 | AI429: 0.0065475217 | AJ429: 0.012473881 | AK429: 0.010711307 | AL429: 0.014534584 | AM429: 0.012867854 | AO429: 0.0081326231 | AP429: 0.019929777 | AQ429: 0.0097611984 | AR429: 0.0058729552 | AS429: 0.0077008316 | AT429: 0.01091663 | AU429: 0.0058389701 | AV429: 0.0057734042 | AW429: 0.0096628661 | AX429: 0.0121535 | BB429: 0.0084305133 | BC429: 0.006945166 | BD429: 0.01808462 | BE429: 0.0076777226 | BI429: 0.0088563655 | BK429: 0.0093499806 | BL429: 0.015690401 | BM429: 0.0054973177 | BN429: 0.0065323123
A430: 2025-10-13 | C430: 0.01030246 | D430: 0.0057040524 | E430: 0.0077349867 | H430: 0.0069487242 | I430: 0.0087912577 | J430: 0.0075483979 | K430: 0.0095950701 | L430: 0.013542496 | M430: 0.062955342 | N430: 0.068389921 | O430: 0.0088287654 | P430: 0.31130313 | Q430: 0.014410498 | R430: 0.011972238 | S430: 0.006569916 | T430: 0.0066525789 | U430: 0.027045402 | V430: 0.010023897 | W430: 0.0065242546 | Y430: 0.023837826 | Z430: 0.049469169 | AA430: 0.0091059734 | AE430: 0.0055817354 | AF430: 0.0096252225 | AG430: 0.032684531 | AH430: 0.024911119 | AI430: 0.0066137148 | AJ430: 0.012450168 | AK430: 0.010839666 | AL430: 0.014607386 | AM430: 0.012867566 | AO430: 0.0081950346 | AP430: 0.019984561 | AQ430: 0.0099267003 | AR430: 0.005879827 | AS430: 0.0073304876 | AT430: 0.010968947 | AU430: 0.0057779654 | AV430: 0.0055785158 | AW430: 0.0097928739 | AX430: 0.011868384 | BB430: 0.0082653338 | BC430: 0.0067482537 | BD430: 0.017713593 | BE430: 0.0077981227 | BI430: 0.0089008818 | BK430: 0.0091831775 | BL430: 0.016184618 | BM430: 0.0059718302 | BN430: 0.0064934307
A431: 2025-10-14 | C431: 0.010422706 | D431: 0.0056132894 | E431: 0.0074692722 | H431: 0.0069385627 | I431: 0.0090266486 | J431: 0.0075841256 | K431: 0.0091974098 | L431: 0.013450362 | M431: 0.061025834 | N431: 0.066571203 | O431: 0.0085864789 | P431: 0.31553576 | Q431: 0.014013458 | R431: 0.011876979 | S431: 0.006807602 | T431: 0.0066587864 | U431: 0.026250233 | V431: 0.009836665 | W431: 0.0065255781 | Y431: 0.02399238 | Z431: 0.049411275 | AA431: 0.0096770243 | AE431: 0.0056179249 | AF431: 0.0097704284 | AG431: 0.033046313 | AH431: 0.025149424 | AI431: 0.0067447621 | AJ431: 0.012646559 | AK431: 0.01094166 | AL431: 0.01486094 | AM431: 0.013265169 | AO431: 0.0082797093 | AP431: 0.020209573 | AQ431: 0.010094239 | AR431: 0.0058816428 | AS431: 0.0071236009 | AT431: 0.010992478 | AU431: 0.0057241222 | AV431: 0.0053403513 | AW431: 0.0098563665 | AX431: 0.011329595 | BB431: 0.0082067573 | BC431: 0.0061974539 | BD431: 0.017467749 | BE431: 0.0078831063 | BI431: 0.0089961534 | BK431: 0.0092427171 | BL431: 0.016669483 | BM431: 0.0058089756 | BN431: 0.0061811098
A432: 2025-10-15 | C432: 0.010183573 | D432: 0.005468159 | E432: 0.0073997975 | H432: 0.0067688104 | I432: 0.0091688191 | J432: 0.0073799691 | K432: 0.0091291568 | L432: 0.013123332 | M432: 0.061401739 | N432: 0.065622357 | O432: 0.0085908728 | P432: 0.31899504 | Q432: 0.014055881 | R432: 0.011628346 | S432: 0.0069366527 | T432: 0.0064148465 | U432: 0.025995216 | V432: 0.0094249587 | W432: 0.0065177308 | Y432: 0.023415087 | Z432: 0.048961406 | AA432: 0.0092642536 | AE432: 0.0056201638 | AF432: 0.0096567029 | AG432: 0.033012242 | AH432: 0.025070755 | AI432: 0.0068492792 | AJ432: 0.012492994 | AK432: 0.010790779 | AL432: 0.014578944 | AM432: 0.013593677 | AO432: 0.0082039696 | AP432: 0.019990604 | AQ432: 0.0099093613 | AR432: 0.0057123682 | AS432: 0.0069425196 | AT432: 0.011417895 | AU432: 0.0056150602 | AV432: 0.0057011021 | AW432: 0.0095607871 | AX432: 0.011141071 | BB432: 0.00878714 | BC432: 0.0061042384 | BD432: 0.018038476 | BE432: 0.0077688578 | BI432: 0.0088464583 | BK432: 0.0091668879 | BL432: 0.017723087 | BM432: 0.0057663746 | BN432: 0.0060921977
A433: 2025-10-16 | C433: 0.010052776 | D433: 0.0054565363 | E433: 0.0074664673 | H433: 0.0067089477 | I433: 0.0090624517 | J433: 0.0073398409 | K433: 0.0094182597 | L433: 0.01305438 | M433: 0.061131396 | N433: 0.069865448 | O433: 0.0086873938 | P433: 0.31878551 | Q433: 0.013585753 | R433: 0.011480961 | S433: 0.0069084163 | T433: 0.0063839577 | U433: 0.026121119 | V433: 0.0092919159 | W433: 0.0064853159 | Y433: 0.023172334 | Z433: 0.048820878 | AA433: 0.009207937 | AE433: 0.0055003855 | AF433: 0.0095685527 | AG433: 0.032618889 | AH433: 0.024493511 | AI433: 0.0067525948 | AJ433: 0.012111054 | AK433: 0.010592336 | AL433: 0.014321815 | AM433: 0.01330026 | AO433: 0.007935267 | AP433: 0.019708416 | AQ433: 0.0098028236 | AR433: 0.0056199996 | AS433: 0.0069215969 | AT433: 0.011026049 | AU433: 0.0055902707 | AV433: 0.0058688548 | AW433: 0.0095123025 | AX433: 0.011103193 | BB433: 0.0084818643 | BC433: 0.0060473797 | BD433: 0.019132619 | BE433: 0.0077259393 | BI433: 0.0087762054 | BK433: 0.0094218284 | BL433: 0.017772181 | BM433: 0.0058271009 | BN433: 0.0059787119
A434: 2025-10-17 | C434: 0.010240334 | D434: 0.0057292518 | E434: 0.0076384577 | H434: 0.006871865 | I434: 0.0087644382 | J434: 0.007484158 | K434: 0.0093232007 | L434: 0.013445721 | M434: 0.060226693 | N434: 0.071731328 | O434: 0.0090261908 | P434: 0.31464672 | Q434: 0.01312879 | R434: 0.011605432 | S434: 0.006661317 | T434: 0.0064290456 | U434: 0.02613257 | V434: 0.0091042836 | W434: 0.006525509 | Y434: 0.023601009 | Z434: 0.049350172 | AA434: 0.0093579419 | AE434: 0.0055327632 | AF434: 0.0096560619 | AG434: 0.032862374 | AH434: 0.024533291 | AI434: 0.0068042027 | AJ434: 0.012299034 | AK434: 0.010551772 | AL434: 0.014373307 | AM434: 0.013273406 | AO434: 0.0080676634 | AP434: 0.01987532 | AQ434: 0.009807988 | AR434: 0.005716509 | AS434: 0.0068875587 | AT434: 0.01072588 | AU434: 0.0055820487 | AV434: 0.0057532532 | AW434: 0.00974655 | AX434: 0.010982202 | BB434: 0.0081890981 | BC434: 0.0060931916 | BD434: 0.019794512 | BE434: 0.0078012666 | BI434: 0.0088897583 | BK434: 0.009712679 | BL434: 0.0176158 | BM434: 0.005818443 | BN434: 0.0060296372
A435: 2025-10-20 | C435: 0.010155003 | D435: 0.0056381586 | E435: 0.0075446251 | H435: 0.0067179907 | I435: 0.0086132183 | J435: 0.0072725701 | K435: 0.0091312638 | L435: 0.013350326 | M435: 0.060295864 | N435: 0.074426398 | O435: 0.0094484847 | P435: 0.31645712 | Q435: 0.013247913 | R435: 0.011452303 | S435: 0.00650435 | T435: 0.0063111975 | U435: 0.026464211 | V435: 0.0091334315 | W435: 0.0063706663 | Y435: 0.023255652 | Z435: 0.048993648 | AA435: 0.0091221211 | AE435: 0.0054115173 | AF435: 0.0094987722 | AG435: 0.032236773 | AH435: 0.02421137 | AI435: 0.0066833513 | AJ435: 0.01202598 | AK435: 0.010427992 | AL435: 0.014231153 | AM435: 0.013315139 | AO435: 0.007934379 | AP435: 0.019538401 | AQ435: 0.0095980439 | AR435: 0.0057029771 | AS435: 0.0067867721 | AT435: 0.010477023 | AU435: 0.0056156632 | AV435: 0.0056514044 | AW435: 0.0096039274 | AX435: 0.011257529 | BB435: 0.0081775782 | BC435: 0.0062959592 | BD435: 0.019902914 | BE435: 0.0077120408 | BI435: 0.0087052653 | BK435: 0.0095924276 | BL435: 0.017793696 | BM435: 0.0056271287 | BN435: 0.0060783034
...

Sheet 每日收盤價
A1: date | B1: 1101 | C1: 1216 | D1: 1301 | E1: 1303 | F1: 1326 | G1: 1590 | H1: 2002 | I1: 2059 | J1: 2207 | K1: 2301 | L1: 2303 | M1: 2308 | N1: 2317 | O1: 2327 | P1: 2330 | Q1: 2345 | R1: 2357 | S1: 2360 | T1: 2379 | U1: 2382 | V1: 2383 | W1: 2395 | X1: 2408 | Y1: 2412 | Z1: 2454 | AA1: 2603 | AB1: 2609 | AC1: 2615 | AD1: 2618 | AE1: 2801 | AF1: 2880 | AG1: 2881 | AH1: 2882 | AI1: 2883 | AJ1: 2884 | AK1: 2885 | AL1: 2886 | AM1: 2887 | AN1: 2888 | AO1: 2890 | AP1: 2891 | AQ1: 2892 | AR1: 2912 | AS1: 3008 | AT1: 3017 | AU1: 3034 | AV1: 3037 | AW1: 3045 | AX1: 3231 | AY1: 3293 | AZ1: 3443 | BA1: 3529 | BB1: 3653 | BC1: 3661 | BD1: 3711 | BE1: 4904 | BF1: 4938 | BG1: 5871 | BH1: 5876 | BI1: 5880 | BJ1: 6488 | BK1: 6505 | BL1: 6669 | BM1: 6919 | BN1: 8069
A2: 2024-01-03 | B2: 34.2 | C2: 73 | D2: 78.1 | E2: 65.6 | F2: 61.1 | H2: 26.7 | J2: 685 | K2: 112.5 | L2: 50.6 | M2: 304.5 | N2: 104.5 | O2: 578 | P2: 578 | Q2: 490 | R2: 465 | T2: 452 | U2: 214 | W2: 360 | X2: 73.1 | Y2: 120 | Z2: 953 | AA2: 155 | AF2: 22 | AG2: 63.7 | AH2: 44.95 | AI2: 12.3 | AJ2: 25.6 | AK2: 26.95 | AL2: 38.65 | AM2: 17.85 | AO2: 19.3 | AP2: 28.2 | AQ2: 27 | AR2: 267 | AS2: 2685 | AU2: 499.5 | AV2: 170 | AW2: 98.9 | AX2: 93.5 | AZ2: 1640 | BC2: 3445 | BD2: 126.5 | BE2: 79.4 | BF2: 85.9 | BG2: 192 | BH2: 46 | BI2: 26.35 | BJ2: 573 | BK2: 79.7 | BL2: 1695
A3: 2024-01-04 | B3: 34.2 | C3: 72.5 | D3: 78.3 | E3: 65.6 | F3: 61.1 | H3: 26.7 | J3: 678 | K3: 113.5 | L3: 50.8 | M3: 304 | N3: 104 | O3: 577 | P3: 580 | Q3: 491 | R3: 454 | T3: 456 | U3: 219 | W3: 360 | X3: 74.4 | Y3: 119 | Z3: 928 | AA3: 161 | AF3: 22 | AG3: 63.5 | AH3: 44.7 | AI3: 12.3 | AJ3: 25.7 | AK3: 27.2 | AL3: 38.75 | AM3: 17.85 | AO3: 19.4 | AP3: 28.15 | AQ3: 27 | AR3: 267.5 | AS3: 2650 | AU3: 495 | AV3: 164.5 | AW3: 98.9 | AX3: 94.2 | AZ3: 1630 | BC3: 3365 | BD3: 127 | BE3: 79.4 | BF3: 84.6 | BG3: 195.5 | BH3: 46.2 | BI3: 26.5 | BJ3: 579 | BK3: 79.7 | BL3: 1665
A4: 2024-01-05 | B4: 34.35 | C4: 72.8 | D4: 78.1 | E4: 65.4 | F4: 61 | H4: 26.7 | J4: 675 | K4: 114.5 | L4: 50.8 | M4: 304.5 | N4: 104 | O4: 572 | P4: 576 | Q4: 486.5 | R4: 454 | T4: 450.5 | U4: 215.5 | W4: 358.5 | X4: 74.7 | Y4: 119.5 | Z4: 921 | AA4: 162.5 | AF4: 22.05 | AG4: 63.2 | AH4: 44.85 | AI4: 12.35 | AJ4: 25.65 | AK4: 26.95 | AL4: 38.95 | AM4: 17.85 | AO4: 19.5 | AP4: 28.1 | AQ4: 27 | AR4: 267.5 | AS4: 2595 | AU4: 490 | AV4: 160 | AW4: 98.5 | AX4: 93.6 | AZ4: 1655 | BC4: 3390 | BD4: 126.5 | BE4: 79.1 | BF4: 83.9 | BG4: 190 | BH4: 46.35 | BI4: 26.5 | BJ4: 584 | BK4: 79.6 | BL4: 1710
A5: 2024-01-08 | B5: 34.25 | C5: 73 | D5: 78.1 | E5: 65.8 | F5: 61 | H5: 26.5 | J5: 684 | K5: 114.5 | L5: 50.5 | M5: 306 | N5: 101.5 | O5: 572 | P5: 583 | Q5: 496.5 | R5: 453.5 | T5: 450.5 | U5: 214 | W5: 361 | X5: 73.1 | Y5: 120.5 | Z5: 920 | AA5: 160.5 | AF5: 22.2 | AG5: 64.1 | AH5: 45.1 | AI5: 12.45 | AJ5: 25.8 | AK5: 26.9 | AL5: 39.45 | AM5: 17.95 | AO5: 19.4 | AP5: 28.4 | AQ5: 27.25 | AR5: 268 | AS5: 2580 | AU5: 500 | AV5: 161 | AW5: 99 | AX5: 94.4 | AZ5: 1665 | BC5: 3455 | BD5: 126 | BE5: 79.7 | BF5: 83.9 | BG5: 186 | BH5: 46.3 | BI5: 26.5 | BJ5: 586 | BK5: 80 | BL5: 1690
A6: 2024-01-09 | B6: 34.05 | C6: 72.5 | D6: 77.6 | E6: 65.1 | F6: 60.8 | H6: 26 | J6: 683 | K6: 114.5 | L6: 50.1 | M6: 295.5 | N6: 101 | O6: 565 | P6: 586 | Q6: 516 | R6: 455 | T6: 451.5 | U6: 216 | W6: 360 | X6: 72.6 | Y6: 120 | Z6: 928 | AA6: 151.5 | AF6: 21.95 | AG6: 64 | AH6: 44.75 | AI6: 12.3 | AJ6: 25.5 | AK6: 26.8 | AL6: 39.45 | AM6: 17.85 | AO6: 19.4 | AP6: 28.1 | AQ6: 27.05 | AR6: 269 | AS6: 2575 | AU6: 500 | AV6: 162.5 | AW6: 99.1 | AX6: 94 | AZ6: 1690 | BC6: 3590 | BD6: 126.5 | BE6: 80 | BF6: 83.8 | BG6: 182.5 | BH6: 46.2 | BI6: 26.35 | BJ6: 589 | BK6: 79.3 | BL6: 1715
A7: 2024-01-10 | B7: 33.7 | C7: 72.5 | D7: 77 | E7: 64.5 | F7: 60.3 | H7: 25.85 | J7: 676 | K7: 107 | L7: 50.1 | M7: 291 | N7: 100 | O7: 555 | P7: 584 | Q7: 508 | R7: 461 | T7: 456 | U7: 218 | W7: 360 | X7: 71.5 | Y7: 120 | Z7: 924 | AA7: 148 | AF7: 21.95 | AG7: 64 | AH7: 44.7 | AI7: 12.25 | AJ7: 25.4 | AK7: 26.5 | AL7: 39.35 | AM7: 17.8 | AO7: 19.3 | AP7: 28.05 | AQ7: 26.9 | AR7: 268 | AS7: 2525 | AU7: 502 | AV7: 162.5 | AW7: 98.8 | AX7: 94.5 | AZ7: 1790 | BC7: 3650 | BD7: 126.5 | BE7: 80.1 | BF7: 82.9 | BG7: 183 | BH7: 44.95 | BI7: 26.2 | BJ7: 588 | BK7: 79.1 | BL7: 1770
A8: 2024-01-11 | B8: 33.7 | C8: 72.3 | D8: 75.9 | E8: 63.5 | F8: 60.3 | H8: 25.8 | J8: 677 | K8: 108.5 | L8: 50.1 | M8: 293 | N8: 100.5 | O8: 554 | P8: 586 | Q8: 520 | R8: 461 | T8: 450.5 | U8: 224 | W8: 359 | X8: 69.4 | Y8: 120.5 | Z8: 920 | AA8: 149 | AF8: 22.1 | AG8: 63.9 | AH8: 44.6 | AI8: 12.25 | AJ8: 25.4 | AK8: 26.8 | AL8: 39.2 | AM8: 17.8 | AO8: 19.35 | AP8: 28.35 | AQ8: 27.05 | AR8: 270 | AS8: 2550 | AU8: 502 | AV8: 160.5 | AW8: 99.7 | AX8: 97.6 | AZ8: 1860 | BC8: 3830 | BD8: 125.5 | BE8: 81.3 | BF8: 82.5 | BG8: 186 | BH8: 45.55 | BI8: 26.1 | BJ8: 601 | BK8: 78.7 | BL8: 1910
A9: 2024-01-12 | B9: 33.75 | C9: 72.6 | D9: 76 | E9: 64 | F9: 60.1 | H9: 25.8 | J9: 675 | K9: 107 | L9: 50.1 | M9: 293.5 | N9: 100.5 | O9: 560 | P9: 584 | Q9: 510 | R9: 448.5 | T9: 447 | U9: 231 | W9: 354.5 | X9: 68.8 | Y9: 120 | Z9: 926 | AA9: 156.5 | AF9: 22 | AG9: 64.1 | AH9: 44.5 | AI9: 12.25 | AJ9: 25.35 | AK9: 26.65 | AL9: 39.05 | AM9: 17.65 | AO9: 19.15 | AP9: 28.05 | AQ9: 26.9 | AR9: 268 | AS9: 2600 | AU9: 510 | AV9: 159 | AW9: 99.8 | AX9: 99.5 | AZ9: 1810 | BC9: 3735 | BD9: 126 | BE9: 81.2 | BF9: 83 | BG9: 184.5 | BH9: 45.35 | BI9: 26 | BJ9: 598 | BK9: 79 | BL9: 1905
A10: 2024-01-15 | B10: 33.65 | C10: 72.2 | D10: 75.5 | E10: 63.6 | F10: 59.7 | H10: 25.8 | J10: 672 | K10: 107 | L10: 50.8 | M10: 295.5 | N10: 100 | O10: 576 | P10: 586 | Q10: 516 | R10: 447 | T10: 455 | U10: 226.5 | W10: 354 | X10: 71.5 | Y10: 120.5 | Z10: 922 | AA10: 158.5 | AF10: 21.85 | AG10: 64.1 | AH10: 44.45 | AI10: 12.15 | AJ10: 25.4 | AK10: 26.7 | AL10: 38.9 | AM10: 17.6 | AO10: 19.1 | AP10: 28.15 | AQ10: 26.8 | AR10: 268 | AS10: 2595 | AU10: 534 | AV10: 159.5 | AW10: 99.1 | AX10: 98.6 | AZ10: 1760 | BC10: 3700 | BD10: 125.5 | BE10: 81.2 | BF10: 82.4 | BG10: 184 | BH10: 45.2 | BI10: 26 | BJ10: 603 | BK10: 78.2 | BL10: 1865
A11: 2024-01-16 | B11: 32.9 | C11: 71.2 | D11: 73.6 | E11: 61.8 | F11: 57 | H11: 25.2 | J11: 643 | K11: 106.5 | L11: 50.8 | M11: 289.5 | N11: 100 | O11: 564 | P11: 580 | Q11: 513 | R11: 440.5 | T11: 453 | U11: 228 | W11: 340.5 | X11: 69.4 | Y11: 119 | Z11: 895 | AA11: 153.5 | AF11: 21.45 | AG11: 63.2 | AH11: 44 | AI11: 11.9 | AJ11: 25 | AK11: 26.25 | AL11: 38.6 | AM11: 17.3 | AO11: 18.8 | AP11: 27.95 | AQ11: 26.5 | AR11: 265 | AS11: 2580 | AU11: 533 | AV11: 162 | AW11: 98 | AX11: 98.6 | AZ11: 1735 | BC11: 3670 | BD11: 125.5 | BE11: 79.7 | BF11: 81.8 | BG11: 182 | BH11: 44.5 | BI11: 25.5 | BJ11: 591 | BK11: 74.8 | BL11: 1910
A12: 2024-01-17 | B12: 32.2 | C12: 70.3 | D12: 71.8 | E12: 60.1 | F12: 55.8 | H12: 24.8 | J12: 624 | K12: 107.5 | L12: 48.6 | M12: 279.5 | N12: 98.6 | O12: 559 | P12: 581 | Q12: 509 | R12: 439 | T12: 438.5 | U12: 228.5 | W12: 331.5 | X12: 67.8 | Y12: 118.5 | Z12: 879 | AA12: 152.5 | AF12: 21.05 | AG12: 62.3 | AH12: 43.3 | AI12: 11.75 | AJ12: 24.6 | AK12: 25.8 | AL12: 37.3 | AM12: 17 | AO12: 18.6 | AP12: 27.55 | AQ12: 26.1 | AR12: 263 | AS12: 2490 | AU12: 511 | AV12: 158.5 | AW12: 97.2 | AX12: 97.9 | AZ12: 1680 | BC12: 3565 | BD12: 125 | BE12: 79 | BF12: 80.8 | BG12: 178.5 | BH12: 43.9 | BI12: 25.15 | BJ12: 577 | BK12: 73 | BL12: 1885
A13: 2024-01-18 | B13: 32.05 | C13: 71.1 | D13: 71.1 | E13: 60.1 | F13: 55.8 | H13: 24.8 | J13: 620 | K13: 106.5 | L13: 48.1 | M13: 277 | N13: 99.9 | O13: 557 | P13: 588 | Q13: 504 | R13: 445 | T13: 440 | U13: 221.5 | W13: 331.5 | X13: 68.2 | Y13: 118.5 | Z13: 897 | AA13: 158 | AF13: 21.1 | AG13: 62.3 | AH13: 43.3 | AI13: 11.8 | AJ13: 24.55 | AK13: 25.8 | AL13: 37.8 | AM13: 17 | AO13: 18.85 | AP13: 27.85 | AQ13: 26.2 | AR13: 264.5 | AS13: 2495 | AU13: 513 | AV13: 157 | AW13: 97.3 | AX13: 97.7 | AZ13: 1725 | BC13: 3690 | BD13: 127 | BE13: 79.5 | BF13: 80.7 | BG13: 177 | BH13: 44.25 | BI13: 25.2 | BJ13: 580 | BK13: 72.3 | BL13: 1880
... A60: 2024-04-08 | B60: 32.3 | C60: 75.4 | D60: 70.4 | E60: 57.7 | F60: 55.1 | H60: 25 | J60: 639 | K60: 105 | L60: 52.1 | M60: 334 | N60: 158 | O60: 617 | P60: 783 | Q60: 466 | R60: 426 | T60: 567 | U60: 291.5 | W60: 389 | X60: 68.1 | Y60: 126.5 | Z60: 1150 | AA60: 168 | AF60: 23.1 | AG60: 68.7 | AH60: 48.35 | AI60: 14 | AJ60: 27.15 | AK60: 30.3 | AL60: 40 | AM60: 18.05 | AO60: 21.35 | AP60: 32.05 | AQ60: 27.45 | AR60: 272 | AS60: 2380 | AU60: 591 | AV60: 199 | AW60: 104 | AX60: 132 | AZ60: 1300 | BC60: 3150 | BD60: 153 | BE60: 81.5 | BF60: 101 | BG60: 176 | BH60: 46.7 | BI60: 26.2 | BJ60: 551 | BK60: 72.7 | BL60: 2475
A61: 2024-04-09 | B61: 32.45 | C61: 76.5 | D61: 71.5 | E61: 58.6 | F61: 55.9 | G61: 1160 | H61: 26.05 | J61: 649 | K61: 104 | L61: 52.4 | M61: 334 | N61: 158 | O61: 615 | P61: 819 | Q61: 465 | R61: 425 | T61: 568 | U61: 287 | W61: 394.5 | Y61: 125.5 | Z61: 1160 | AA61: 171 | AF61: 23.2 | AG61: 70 | AH61: 49.45 | AI61: 14.15 | AJ61: 27.3 | AK61: 30.9 | AL61: 40.4 | AM61: 18.1 | AO61: 21.5 | AP61: 32.15 | AQ61: 27.55 | AR61: 273 | AS61: 2380 | AU61: 596 | AV61: 193.5 | AW61: 104 | AX61: 126 | BC61: 3020 | BD61: 156 | BE61: 80.8 | BF61: 100.5 | BG61: 178.5 | BH61: 46.85 | BI61: 26.25 | BJ61: 551 | BK61: 73.3 | BL61: 2475 | BN61: 231
A62: 2024-04-10 | B62: 32.7 | C62: 76.4 | D62: 72 | E62: 58.3 | F62: 56.1 | G62: 1175 | H62: 25.6 | J62: 648 | K62: 103.5 | L62: 53.2 | M62: 328 | N62: 154.5 | O62: 621 | P62: 815 | Q62: 476 | R62: 435 | T62: 571 | U62: 282 | W62: 384 | Y62: 126 | Z62: 1195 | AA62: 169 | AF62: 23.15 | AG62: 69.2 | AH62: 48.75 | AI62: 14 | AJ62: 27.15 | AK62: 30.5 | AL62: 40.5 | AM62: 18.1 | AO62: 21.7 | AP62: 31.85 | AQ62: 27.5 | AR62: 276 | AS62: 2380 | AU62: 606 | AV62: 191.5 | AW62: 104 | AX62: 125.5 | BC62: 3020 | BD62: 158.5 | BE62: 81.8 | BF62: 101 | BG62: 178.5 | BH62: 47.45 | BI62: 26.2 | BJ62: 553 | BK62: 74 | BL62: 2355 | BN62: 240
A63: 2024-04-11 | B63: 32.4 | C63: 76.4 | D63: 70.9 | E63: 57.2 | F63: 55.5 | G63: 1155 | H63: 25.3 | J63: 642 | K63: 104 | L63: 52.5 | M63: 319.5 | N63: 150 | O63: 609 | P63: 820 | Q63: 473 | R63: 453.5 | T63: 567 | U63: 284.5 | W63: 386 | Y63: 126.5 | Z63: 1200 | AA63: 175 | AF63: 23.2 | AG63: 68.4 | AH63: 49.7 | AI63: 14 | AJ63: 27.25 | AK63: 30.5 | AL63: 40.15 | AM63: 18 | AO63: 21.95 | AP63: 31.95 | AQ63: 27.45 | AR63: 277.5 | AS63: 2315 | AU63: 615 | AV63: 192.5 | AW63: 104 | AX63: 123 | BC63: 3015 | BD63: 159 | BE63: 81.8 | BF63: 101.5 | BG63: 175.5 | BH63: 47.5 | BI63: 26.1 | BJ63: 545 | BK63: 73.3 | BL63: 2325 | BN63: 242
A64: 2024-04-12 | B64: 32.2 | C64: 76.8 | D64: 69.7 | E64: 57.4 | F64: 55.3 | G64: 1150 | H64: 24.85 | J64: 638 | K64: 103 | L64: 52.7 | M64: 317 | N64: 150.5 | O64: 618 | P64: 818 | Q64: 456 | R64: 443.5 | T64: 569 | U64: 271 | W64: 378.5 | Y64: 125.5 | Z64: 1180 | AA64: 176.5 | AF64: 23 | AG64: 67.8 | AH64: 49.05 | AI64: 13.8 | AJ64: 27.1 | AK64: 30.3 | AL64: 39.95 | AM64: 17.9 | AO64: 21.85 | AP64: 31.75 | AQ64: 27.35 | AR64: 275 | AS64: 2350 | AU64: 630 | AV64: 194 | AW64: 104.5 | AX64: 122.5 | BC64: 2900 | BD64: 160.5 | BE64: 81.6 | BF64: 98.3 | BG64: 174.5 | BH64: 47.5 | BI64: 26.05 | BJ64: 545 | BK64: 72.5 | BL64: 2405 | BN64: 245
A65: 2024-04-15 | B65: 32.35 | C65: 76.7 | D65: 69.6 | E65: 57.2 | F65: 55 | G65: 1125 | H65: 24.55 | J65: 635 | K65: 102 | L65: 51.6 | M65: 308 | N65: 146 | O65: 602 | P65: 806 | Q65: 431 | R65: 440.5 | T65: 561 | U65: 261 | W65: 374.5 | Y65: 126 | Z65: 1110 | AA65: 178 | AF65: 22.95 | AG65: 67.4 | AH65: 48.95 | AI65: 13.65 | AJ65: 27.05 | AK65: 30.55 | AL65: 39.8 | AM65: 17.85 | AO65: 21.8 | AP65: 31.95 | AQ65: 27.2 | AR65: 275.5 | AS65: 2295 | AU65: 618 | AV65: 182.5 | AW65: 104 | AX65: 119.5 | BC65: 2755 | BD65: 160 | BE65: 82.3 | BF65: 98.7 | BG65: 173 | BH65: 47.4 | BI65: 26.1 | BJ65: 545 | BK65: 73.6 | BL65: 2420 | BN65: 241
A66: 2024-04-16 | B66: 32.45 | C66: 74.5 | D66: 68 | E66: 55.5 | F66: 53.9 | G66: 1080 | H66: 24.25 | J66: 613 | K66: 95.3 | L66: 50.1 | M66: 293 | N66: 141 | O66: 585 | P66: 788 | Q66: 416.5 | R66: 425.5 | T66: 551 | U66: 249.5 | W66: 365 | Y66: 124.5 | Z66: 1055 | AA66: 170.5 | AF66: 22.4 | AG66: 65.7 | AH66: 47.85 | AI66: 13.25 | AJ66: 26.3 | AK66: 29.95 | AL66: 39.1 | AM66: 17.4 | AO66: 21.25 | AP66: 30.95 | AQ66: 26.75 | AR66: 270 | AS66: 2225 | AU66: 602 | AV66: 177 | AW66: 102 | AX66: 114 | BC66: 2830 | BD66: 153 | BE66: 81.2 | BF66: 95.4 | BG66: 170 | BH66: 46.1 | BI66: 25.7 | BJ66: 535 | BK66: 71.1 | BL66: 2305 | BN66: 237
A67: 2024-04-17 | B67: 32.65 | C67: 75.4 | D67: 67.8 | E67: 55 | F67: 53.6 | G67: 1115 | H67: 24.45 | J67: 606 | K67: 96.3 | L67: 50.3 | M67: 300.5 | N67: 146.5 | O67: 593 | P67: 804 | Q67: 408 | R67: 428.5 | T67: 570 | U67: 254.5 | W67: 371 | Y67: 123.5 | Z67: 1050 | AA67: 170.5 | AF67: 22.45 | AG67: 66 | AH67: 47.9 | AI67: 13.35 | AJ67: 26.5 | AK67: 30 | AL67: 39 | AM67: 17.55 | AO67: 21.55 | AP67: 31.5 | AQ67: 26.9 | AR67: 272.5 | AS67: 2200 | AU67: 621 | AV67: 179 | AW67: 102 | AX67: 114.5 | BC67: 2900 | BD67: 156 | BE67: 80.4 | BF67: 96.4 | BG67: 170.5 | BH67: 46.4 | BI67: 25.7 | BJ67: 544 | BK67: 70.3 | BL67: 2390 | BN67: 229
A68: 2024-04-18 | B68: 32.7 | C68: 76.8 | D68: 68.1 | E68: 55.8 | F68: 53.6 | G68: 1110 | H68: 24.8 | J68: 606 | K68: 99 | L68: 50.2 | M68: 309 | N68: 148 | O68: 593 | P68: 804 | Q68: 409 | R68: 427 | T68: 574 | U68: 250.5 | W68: 372 | Y68: 124 | Z68: 1050 | AA68: 168 | AF68: 22.65 | AG68: 66.3 | AH68: 48.45 | AI68: 13.5 | AJ68: 27 | AK68: 30.6 | AL68: 39.2 | AM68: 17.6 | AO68: 21.65 | AP68: 31.7 | AQ68: 26.9 | AR68: 271.5 | AS68: 2200 | AU68: 615 | AV68: 178.5 | AW68: 103.5 | AX68: 118 | BC68: 3035 | BD68: 151 | BE68: 80.4 | BF68: 96.6 | BG68: 172 | BH68: 46.05 | BI68: 25.85 | BJ68: 547 | BK68: 70.3 | BL68: 2500 | BN68: 225.5
A69: 2024-04-19 | B69: 32 | C69: 76 | D69: 67.1 | E69: 55 | F69: 52.4 | G69: 1055 | H69: 24.45 | J69: 601 | K69: 96.1 | L69: 49.1 | M69: 298.5 | N69: 143 | O69: 588 | P69: 750 | Q69: 401 | R69: 413.5 | T69: 552 | U69: 241.5 | W69: 365 | Y69: 123 | Z69: 993 | AA69: 172.5 | AF69: 22.2 | AG69: 65 | AH69: 47.45 | AI69: 13.2 | AJ69: 26.55 | AK69: 29.9 | AL69: 38.7 | AM69: 17.35 | AO69: 21.2 | AP69: 31 | AQ69: 26.65 | AR69: 270 | AS69: 2120 | AU69: 588 | AV69: 170 | AW69: 102 | AX69: 115 | BC69: 2860 | BD69: 146 | BE69: 80.2 | BF69: 94.8 | BG69: 168 | BH69: 45 | BI69: 25.6 | BJ69: 520 | BK69: 69.3 | BL69: 2315 | BN69: 215
A70: 2024-04-22 | B70: 32.6 | C70: 78.9 | D70: 69.7 | E70: 57.3 | F70: 55.1 | G70: 1080 | H70: 24.7 | J70: 611 | K70: 96.8 | L70: 48.9 | M70: 300 | N70: 143 | O70: 599 | P70: 742 | Q70: 384.5 | R70: 413.5 | T70: 504 | U70: 230 | W70: 368.5 | Y70: 125.5 | Z70: 966 | AA70: 174 | AF70: 22.75 | AG70: 66.2 | AH70: 48.4 | AI70: 13.5 | AJ70: 27.05 | AK70: 29.9 | AL70: 39.5 | AM70: 17.65 | AO70: 21.7 | AP70: 31.35 | AQ70: 27.1 | AR70: 277.5 | AS70: 2110 | AU70: 574 | AV70: 167.5 | AW70: 104.5 | AX70: 108.5 | BC70: 2765 | BD70: 144.5 | BE70: 81 | BF70: 94.5 | BG70: 172.5 | BH70: 45.55 | BI70: 26.1 | BJ70: 503 | BK70: 72.7 | BL70: 2160 | BN70: 207
A71: 2024-04-23 | B71: 32.35 | C71: 78.4 | D71: 69.1 | E71: 56.7 | F71: 54.9 | G71: 1080 | H71: 24.85 | J71: 610 | K71: 94.6 | L71: 48.7 | M71: 297.5 | N71: 144 | O71: 607 | P71: 754 | Q71: 405 | R71: 409.5 | T71: 510 | U71: 237 | W71: 366.5 | Y71: 125 | Z71: 972 | AA71: 173.5 | AF71: 22.95 | AG71: 66.3 | AH71: 48.75 | AI71: 13.55 | AJ71: 27.2 | AK71: 29.8 | AL71: 40 | AM71: 17.7 | AO71: 21.8 | AP71: 31.55 | AQ71: 27.15 | AR71: 276 | AS71: 2135 | AU71: 583 | AV71: 170 | AW71: 103 | AX71: 111 | BC71: 2860 | BD71: 145 | BE71: 80.3 | BF71: 94.7 | BG71: 173 | BH71: 45.85 | BI71: 26.15 | BJ71: 504 | BK71: 72.9 | BL71: 2130 | BN71: 208
A72: 2024-04-24 | B72: 32.15 | C72: 77 | D72: 68.8 | E72: 56.4 | F72: 54.8 | G72: 1135 | H72: 24.75 | J72: 612 | K72: 98.4 | L72: 50.2 | M72: 304 | N72: 156 | O72: 624 | P72: 783 | Q72: 412 | R72: 420.5 | T72: 538 | U72: 260.5 | W72: 373.5 | Y72: 124.5 | Z72: 1010 | AA72: 180 | AF72: 22.85 | AG72: 66.8 | AH72: 49.25 | AI72: 13.7 | AJ72: 27.05 | AK72: 30.35 | AL72: 39.35 | AM72: 17.65 | AO72: 21.45 | AP72: 31.45 | AQ72: 27.2 | AR72: 276 | AS72: 2195 | AU72: 601 | AV72: 187 | AW72: 102 | AX72: 115.5 | BC72: 2975 | BD72: 148 | BE72: 80.5 | BF72: 96.7 | BG72: 173.5 | BH72: 45.75 | BI72: 26.1 | BJ72: 525 | BK72: 72.9 | BL72: 2290 | BN72: 209
... A121: 2024-07-04 | B121: 34.15 | C121: 84.2 | D121: 57.6 | E121: 49.45 | F121: 49.4 | G121: 1015 | H121: 23.5 | J121: 618 | K121: 111.5 | L121: 54 | M121: 382 | N121: 214.5 | O121: 753 | P121: 1005 | Q121: 571 | R121: 482 | T121: 550 | U121: 309 | W121: 371 | Y121: 118.5 | Z121: 1375 | AA121: 188.5 | AF121: 27.1 | AG121: 83.7 | AH121: 60.7 | AI121: 16 | AJ121: 29.25 | AK121: 33.1 | AL121: 41.95 | AM121: 19.3 | AO121: 26.6 | AP121: 39.75 | AQ121: 28.6 | AR121: 277 | AS121: 2840 | AU121: 620 | AV121: 181.5 | AW121: 111 | AX121: 109 | BC121: 2615 | BD121: 166 | BE121: 91.1 | BF121: 106.5 | BG121: 158 | BH121: 46.3 | BI121: 26.55 | BJ121: 581 | BK121: 66 | BL121: 2730 | BN121: 275
A122: 2024-07-05 | B122: 34.45 | C122: 84.2 | D122: 57.3 | E122: 48.8 | F122: 49.2 | H122: 23.55 | J122: 620 | K122: 107 | L122: 53.5 | M122: 387 | N122: 214.5 | O122: 754 | P122: 1005 | Q122: 557 | R122: 483 | T122: 554 | U122: 312 | W122: 374 | Y122: 120 | Z122: 1350 | AA122: 184 | AB122: 72.3 | AC122: 83.7 | AF122: 27.05 | AG122: 84.9 | AH122: 61.3 | AI122: 16 | AJ122: 29.25 | AK122: 33 | AL122: 42.1 | AM122: 19.25 | AO122: 26.4 | AP122: 40.05 | AQ122: 28.6 | AR122: 279 | AS122: 2895 | AT122: 764 | AU122: 618 | AV122: 178.5 | AW122: 116 | AX122: 109 | BD122: 168.5 | BE122: 91 | BF122: 103.5 | BG122: 157 | BI122: 26.55 | BJ122: 582 | BK122: 65.4 | BL122: 2725 | BN122: 271
A123: 2024-07-08 | B123: 34.6 | C123: 83.7 | D123: 58 | E123: 49.25 | F123: 49.15 | H123: 23.5 | J123: 617 | K123: 107.5 | L123: 55.3 | M123: 402 | N123: 226.5 | O123: 755 | P123: 1035 | Q123: 563 | R123: 486 | T123: 553 | U123: 319.5 | W123: 375 | Y123: 119 | Z123: 1420 | AA123: 175.5 | AB123: 67.5 | AC123: 78 | AF123: 27.5 | AG123: 86 | AH123: 62.3 | AI123: 16.1 | AJ123: 29.25 | AK123: 33.2 | AL123: 42.1 | AM123: 19.5 | AO123: 26.7 | AP123: 40.1 | AQ123: 28.65 | AR123: 280 | AS123: 3030 | AT123: 745 | AU123: 612 | AV123: 181 | AW123: 102.5 | AX123: 111 | BD123: 172.5 | BE123: 90.5 | BF123: 106 | BG123: 158.5 | BI123: 26.65 | BJ123: 593 | BK123: 65.7 | BL123: 2770 | BN123: 263
A124: 2024-07-09 | B124: 34 | C124: 84.7 | D124: 57 | E124: 48.5 | F124: 48.5 | H124: 23.2 | J124: 621 | K124: 107 | L124: 55.3 | M124: 410 | N124: 225.5 | O124: 745 | P124: 1040 | Q124: 567 | R124: 486.5 | T124: 573 | U124: 336 | W124: 373.5 | Y124: 119 | Z124: 1460 | AA124: 178 | AB124: 65.2 | AC124: 77.2 | AF124: 27.2 | AG124: 86 | AH124: 62.1 | AI124: 16.2 | AJ124: 29.25 | AK124: 33 | AL124: 41.65 | AM124: 19.6 | AO124: 26.6 | AP124: 39.95 | AQ124: 28.65 | AR124: 282.5 | AS124: 3115 | AT124: 727 | AU124: 604 | AV124: 177 | AW124: 101 | AX124: 108.5 | BD124: 180 | BE124: 86.5 | BF124: 104.5 | BG124: 157.5 | BI124: 26.4 | BJ124: 580 | BK124: 63.8 | BL124: 2670 | BN124: 270
A125: 2024-07-10 | B125: 33.85 | C125: 84.7 | D125: 56.5 | E125: 48 | F125: 47.05 | H125: 23.05 | J125: 619 | K125: 109 | L125: 54.7 | M125: 420.5 | N125: 223.5 | O125: 764 | P125: 1045 | Q125: 575 | R125: 508 | T125: 570 | U125: 341 | W125: 372.5 | Y125: 118.5 | Z125: 1435 | AA125: 177 | AB125: 65.1 | AC125: 76.1 | AF125: 27.15 | AG125: 89.1 | AH125: 63.6 | AI125: 16.65 | AJ125: 29.6 | AK125: 33.55 | AL125: 41.65 | AM125: 19.75 | AO125: 26.4 | AP125: 40.85 | AQ125: 28.75 | AR125: 279.5 | AS125: 3110 | AT125: 726 | AU125: 570 | AV125: 175.5 | AW125: 102 | AX125: 108 | BD125: 179.5 | BE125: 79.5 | BF125: 105.5 | BG125: 158 | BI125: 26.3 | BJ125: 588 | BK125: 63.7 | BL125: 2620 | BN125: 266.5
A126: 2024-07-11 | B126: 34.05 | C126: 85.5 | D126: 57 | E126: 48.7 | F126: 47.7 | H126: 23.05 | J126: 625 | K126: 109.5 | L126: 54.7 | M126: 434 | N126: 225.5 | O126: 797 | P126: 1080 | Q126: 578 | R126: 513 | T126: 581 | U126: 332.5 | W126: 378.5 | Y126: 118.5 | Z126: 1420 | AA126: 176 | AB126: 65.1 | AC126: 77.3 | AF126: 27.5 | AG126: 92.4 | AH126: 65.5 | AI126: 16.8 | AJ126: 29.85 | AK126: 33.65 | AL126: 41.75 | AM126: 19.95 | AO126: 26.55 | AP126: 40.25 | AQ126: 28.85 | AR126: 281 | AS126: 3200 | AT126: 714 | AU126: 579 | AV126: 189.5 | AW126: 101 | AX126: 108 | BD126: 193.5 | BE126: 79.8 | BF126: 105.5 | BG126: 160.5 | BI126: 26.45 | BJ126: 587 | BK126: 63.7 | BL126: 2525 | BN126: 279
A127: 2024-07-12 | B127: 34.25 | C127: 85.7 | D127: 57.9 | E127: 50.1 | F127: 48.65 | H127: 23.1 | J127: 625 | K127: 109 | L127: 53 | M127: 422 | N127: 216 | O127: 770 | P127: 1040 | Q127: 571 | R127: 509 | T127: 571 | U127: 326 | W127: 376 | Y127: 118.5 | Z127: 1360 | AA127: 173.5 | AB127: 64 | AC127: 76.4 | AF127: 27.5 | AG127: 91.9 | AH127: 65.7 | AI127: 16.7 | AJ127: 29.9 | AK127: 33.75 | AL127: 42.05 | AM127: 20.05 | AO127: 27.1 | AP127: 40.2 | AQ127: 28.9 | AR127: 282 | AS127: 3065 | AT127: 709 | AU127: 567 | AV127: 190 | AW127: 101 | AX127: 106 | BD127: 177.5 | BE127: 79.2 | BF127: 107 | BG127: 163.5 | BI127: 26.55 | BJ127: 588 | BK127: 64 | BL127: 2440 | BN127: 270.5
A128: 2024-07-15 | B128: 34.1 | C128: 86.5 | D128: 57.3 | E128: 49.65 | F128: 48.3 | H128: 23.4 | J128: 620 | K128: 109 | L128: 53.4 | M128: 415 | N128: 216.5 | O128: 772 | P128: 1040 | Q128: 542 | R128: 498.5 | T128: 568 | U128: 323 | W128: 374.5 | Y128: 119.5 | Z128: 1355 | AA128: 173.5 | AB128: 63.1 | AC128: 77.9 | AF128: 27.65 | AG128: 90.9 | AH128: 65 | AI128: 16.35 | AJ128: 30 | AK128: 32.9 | AL128: 41.95 | AM128: 20 | AO128: 27.25 | AP128: 37.65 | AQ128: 29 | AR128: 283 | AS128: 3120 | AT128: 702 | AU128: 563 | AV128: 191 | AW128: 101 | AX128: 106.5 | BD128: 179.5 | BE128: 80.2 | BF128: 106 | BG128: 164.5 | BI128: 26.6 | BJ128: 588 | BK128: 64 | BL128: 2375 | BN128: 268
A129: 2024-07-16 | B129: 34.15 | C129: 84.9 | D129: 57.2 | E129: 48.9 | F129: 48.4 | H129: 23.1 | J129: 643 | K129: 111 | L129: 53 | M129: 412.5 | N129: 213 | O129: 804 | P129: 1055 | Q129: 544 | R129: 502 | T129: 559 | U129: 322.5 | W129: 380 | Y129: 119.5 | Z129: 1345 | AA129: 171.5 | AB129: 62.4 | AC129: 75.1 | AF129: 27.45 | AG129: 91.7 | AH129: 65.4 | AI129: 16.4 | AJ129: 30 | AK129: 33 | AL129: 41.85 | AM129: 20 | AO129: 26.95 | AP129: 37.35 | AQ129: 29 | AR129: 280.5 | AS129: 3125 | AT129: 691 | AU129: 558 | AV129: 198 | AW129: 101 | AX129: 113.5 | BD129: 179 | BE129: 80.5 | BF129: 106.5 | BG129: 163.5 | BI129: 26.6 | BJ129: 584 | BK129: 64 | BL129: 2460 | BN129: 272
A130: 2024-07-17 | B130: 34.5 | C130: 84.8 | D130: 60.1 | E130: 50.4 | F130: 49.75 | H130: 23.35 | J130: 624 | K130: 108 | L130: 53 | M130: 411 | N130: 212 | O130: 798 | P130: 1030 | Q130: 526 | R130: 493.5 | T130: 555 | U130: 314 | W130: 374.5 | Y130: 119.5 | Z130: 1325 | AA130: 172 | AB130: 61.9 | AC130: 73.5 | AF130: 27.25 | AG130: 91 | AH130: 65.3 | AI130: 16.4 | AJ130: 30.05 | AK130: 33.15 | AL130: 41.9 | AM130: 19.9 | AO130: 26.8 | AP130: 37 | AQ130: 29 | AR130: 279.5 | AS130: 3065 | AT130: 690 | AU130: 554 | AV130: 215.5 | AW130: 102 | AX130: 109 | BD130: 182.5 | BE130: 81.4 | BF130: 107 | BG130: 162 | BI130: 26.55 | BJ130: 576 | BK130: 64.9 | BL130: 2380 | BN130: 274.5
A131: 2024-07-18 | B131: 34.8 | C131: 87.4 | D131: 60.8 | E131: 50.7 | F131: 51.2 | H131: 23.5 | J131: 640 | K131: 109.5 | L131: 52.7 | M131: 401.5 | N131: 204 | O131: 795 | P131: 1005 | Q131: 503 | R131: 494.5 | T131: 544 | U131: 298 | W131: 370.5 | Y131: 120.5 | Z131: 1280 | AA131: 173 | AB131: 61.8 | AC131: 74 | AF131: 27.6 | AG131: 89.9 | AH131: 64.2 | AI131: 16.3 | AJ131: 30.45 | AK131: 33.25 | AL131: 42.75 | AM131: 19.95 | AO131: 26.9 | AP131: 37 | AQ131: 29.4 | AR131: 281.5 | AS131: 3010 | AT131: 675 | AU131: 554 | AV131: 205 | AW131: 104 | AX131: 107 | BD131: 176 | BE131: 85 | BF131: 106.5 | BG131: 154.5 | BI131: 26.8 | BJ131: 565 | BK131: 66.3 | BL131: 2275 | BN131: 264.5
A132: 2024-07-19 | B132: 34.6 | C132: 86.9 | D132: 60.1 | E132: 50.4 | F132: 50.5 | H132: 23.35 | J132: 630 | K132: 109.5 | L132: 51.9 | M132: 399 | N132: 204 | O132: 766 | P132: 970 | Q132: 521 | R132: 481.5 | T132: 534 | U132: 297 | W132: 367.5 | Y132: 121 | Z132: 1260 | AA132: 167 | AB132: 60.2 | AC132: 71.1 | AF132: 27.4 | AG132: 86.1 | AH132: 62.6 | AI132: 15.9 | AJ132: 30.25 | AK132: 32.6 | AL132: 42.25 | AM132: 19.75 | AO132: 26.6 | AP132: 35.95 | AQ132: 29.15 | AR132: 282 | AS132: 2900 | AT132: 687 | AU132: 543 | AV132: 192.5 | AW132: 103.5 | AX132: 105.5 | BD132: 171 | BE132: 85 | BF132: 106 | BG132: 150.5 | BI132: 26.65 | BJ132: 544 | BK132: 65.1 | BL132: 2205 | BN132: 262
A133: 2024-07-22 | B133: 34.35 | C133: 88.3 | D133: 60.2 | E133: 50.3 | F133: 50.5 | H133: 23.1 | J133: 639 | K133: 106 | L133: 50.2 | M133: 373.5 | N133: 192.5 | O133: 742 | P133: 939 | Q133: 511 | R133: 468 | T133: 513 | U133: 288 | W133: 373 | Y133: 120.5 | Z133: 1225 | AA133: 162 | AB133: 58.6 | AC133: 71 | AF133: 27.25 | AG133: 82.6 | AH133: 60 | AI133: 15.45 | AJ133: 29.7 | AK133: 31.85 | AL133: 42.45 | AM133: 19.6 | AO133: 26.3 | AP133: 35.5 | AQ133: 29 | AR133: 282 | AS133: 2830 | AT133: 634 | AU133: 524 | AV133: 190.5 | AW133: 103.5 | AX133: 100.5 | BD133: 164 | BE133: 84.4 | BF133: 103.5 | BG133: 147 | BI133: 26.4 | BJ133: 519 | BK133: 65.9 | BL133: 2160 | BN133: 245
... A184: 2024-10-08 | B184: 33.05 | C184: 87.3 | D184: 50.8 | E184: 44.65 | F184: 42.1 | H184: 23.7 | J184: 656 | K184: 99.7 | L184: 52.6 | M184: 382 | N184: 194 | O184: 613 | P184: 1010 | Q184: 520 | R184: 577 | T184: 474 | U184: 265.5 | W184: 314 | Y184: 122.5 | Z184: 1225 | AA184: 189 | AB184: 63.5 | AC184: 85.5 | AF184: 25.3 | AG184: 91.4 | AH184: 67.7 | AI184: 16.5 | AJ184: 27.95 | AK184: 31.75 | AL184: 38.85 | AM184: 18.2 | AO184: 23.95 | AP184: 35.2 | AQ184: 26.95 | AR184: 296.5 | AS184: 2475 | AT184: 611 | AU184: 509 | AV184: 137 | AW184: 112.5 | AX184: 102 | BD184: 153 | BE184: 88.3 | BF184: 99.8 | BG184: 163 | BI184: 25.55 | BJ184: 440.5 | BK184: 54.2 | BL184: 1745 | BN184: 303.5
A185: 2024-10-09 | B185: 32.45 | C185: 87.7 | D185: 49.55 | E185: 43.6 | F185: 41.25 | H185: 22.7 | J185: 642 | K185: 100.5 | L185: 51.9 | M185: 381.5 | N185: 199 | O185: 611 | P185: 1020 | Q185: 532 | R185: 577 | T185: 480 | U185: 273.5 | W185: 318.5 | Y185: 122.5 | Z185: 1245 | AA185: 183.5 | AB185: 62.5 | AC185: 83 | AF185: 25.3 | AG185: 90.6 | AH185: 67.8 | AI185: 16.4 | AJ185: 28.05 | AK185: 31.65 | AL185: 38.65 | AM185: 18.1 | AO185: 23.6 | AP185: 34.9 | AQ185: 26.8 | AR185: 297 | AS185: 2440 | AT185: 605 | AU185: 510 | AV185: 142.5 | AW185: 113 | AX185: 105 | AY185: 974 | BD185: 154 | BE185: 88.1 | BF185: 100.5 | BG185: 157.5 | BI185: 25.45 | BK185: 52.3 | BL185: 1805 | BN185: 300.5
